Workbook

Sheet Cover
A1: CITY OF SEALY
A2: ESD #2 Development-Scenario Fiscal Model
A3: Council edition · June 2026 · Independent planning analysis (not a certified forecast) · Prepared by Councilmember Bobby Necker, Place 1
A5: 30-YEAR 1.5% SALES-TAX POOL · current INPUTS scenario
A6: =Results!F10 -> 98603635
A8: How to use this model
A9: 1. On TYPICAL INPUTS: set a scenario Active = Yes, choose a Development Type, enter a quantity (and lot size / gross-up for subdivisions).
A10: 2. Read the RESULTS block on that same page — the 1.5% sales-tax pool and the City / EDC / ESD shares by horizon.
A11: 3. Enter your City / ESD split at the top of Typical Inputs; it is yours to set and everything updates live.
A12: 4. Advanced Inputs holds every deeper assumption; Capital Items the infrastructure detail; Sources & Assumptions the citations.
A14: Go to
A15: ▸ Typical Inputs — set scenario, read results
A16: ▸ Advanced Inputs — all assumptions
A17: ▸ Results — full sales-tax & fiscal detail
A18: ▸ Capital Items — infrastructure detail

Sheet Typical Inputs
A1: TYPICAL INPUTS
A2: Set your split and scenarios here — results update live below. Everything for a meeting on one page.
A4: 1 · SALES-TAX ALLOCATION (City + ESD must total 100%)
A5: City General Fund share of pool
A6: EDC retention (% of City share) | C6: 0
A7: ESD #2 share of pool
A8: Sales-tax pool rate | C8: 0.015
A9: Split check (City + ESD) | C9: =C5+C7 -> 0 | D9: ← must equal 100%
A11: 2 · DEVELOPMENT SCENARIOS (Active = Yes, pick a type, enter quantity)
A12: Development Type | B12: Active? | C12: Quantity | D12: Lot size (ac/unit) | E12: Gross-up % (non-lot) | F12: Final Acres (computed)
A13: Big-Box / Anchor Retail | B13: Yes | C13: 10 | F13: ='Advanced Inputs'!J55 -> 10
A14: Retail Center / Strip | B14: No | C14: 10 | F14: ='Advanced Inputs'!J56 -> 10
A15: Office / Business Park | B15: No | C15: 10 | F15: ='Advanced Inputs'!J57 -> 10
A16: Light Industrial / Flex | B16: No | C16: 15 | F16: ='Advanced Inputs'!J58 -> 15
A17: Mixed-Use Pad / Vertical | B17: No | C17: 10 | F17: ='Advanced Inputs'!J59 -> 10
A18: Gas / Convenience Store | B18: No | C18: 1.5 | F18: ='Advanced Inputs'!J60 -> 1.5
A19: Large Travel Center (C-store) | B19: No | C19: 15 | F19: ='Advanced Inputs'!J61 -> 15
A20: Fast Food / QSR | B20: No | C20: 1 | F20: ='Advanced Inputs'!J62 -> 1
A21: Restaurant (Full-Service) | B21: No | C21: 1.5 | F21: ='Advanced Inputs'!J63 -> 1.5
A22: Grocery / Supermarket | B22: No | C22: 4 | F22: ='Advanced Inputs'!J64 -> 4
A23: Auto Parts / Service | B23: No | C23: 1.5 | F23: ='Advanced Inputs'!J65 -> 1.5
A24: Car Wash | B24: No | C24: 1 | F24: ='Advanced Inputs'!J66 -> 1
A25: Single-Family Subdivision | B25: Yes | C25: 100 | D25: 0.125 | E25: 0.5 | F25: ='Advanced Inputs'!J67 -> 18.75
A26: Single-Family Urban / Patio | B26: No | C26: 100 | E26: 0.5 | F26: ='Advanced Inputs'!J68 -> 27
A27: Townhome / Condo | B27: No | C27: 250 | E27: 0.5 | F27: ='Advanced Inputs'!J69 -> 37.5
A28: Multifamily Apartments | B28: No | C28: 250 | E28: 0.5 | F28: ='Advanced Inputs'!J70 -> 15
A29: Hotel | B29: No | C29: 100 | F29: ='Advanced Inputs'!J71 -> 2
A30: Manufacturing | B30: No | C30: 20 | F30: ='Advanced Inputs'!J72 -> 20
A31: Industrial / Logistics | B31: No | C31: 40 | F31: ='Advanced Inputs'!J73 -> 40
A32: Civic / Institutional | B32: No | C32: 10 | F32: ='Advanced Inputs'!J74 -> 10
A33: Parks / Open Space | B33: No | C33: 10 | F33: ='Advanced Inputs'!J75 -> 10
A34: Vacant / Holding Land | B34: No | C34: 10 | F34: ='Advanced Inputs'!J76 -> 10
A35: Gross-up % adds non-lot land (streets, detention, open space) for infrastructure sizing only — value & tax stay per-home. Sealy newer subdivisions (Westward Pointe / BSR): ~0.24-ac lots, ~50% gross-up (~2.6 homes per gross acre).
A36: 3 · RESULTS (live from your scenario — by horizon)
B37: 5-Year | C37: 10-Year | D37: 15-Year | E37: 20-Year | F37: 30-Year
A38: 1.5% sales-tax pool (the pie) | B38: =Results!B10 -> 1558728.3 | C38: =Results!C10 -> 10949246 | D38: =Results!D10 -> 23810531 | E38: =Results!E10 -> 41426083 | F38: =Results!F10 -> 98603635
A39: → City General Fund | B39: =Results!B11 -> 0 | C39: =Results!C11 -> 0 | D39: =Results!D11 -> 0 | E39: =Results!E11 -> 0 | F39: =Results!F11 -> 0
A40: → Sealy EDC (carve-out) | B40: =Results!B12 -> 0 | C40: =Results!C12 -> 0 | D40: =Results!D12 -> 0 | E40: =Results!E12 -> 0 | F40: =Results!F12 -> 0
A41: → ESD #2 share | B41: =Results!B13 -> 0 | C41: =Results!C13 -> 0 | D41: =Results!D13 -> 0 | E41: =Results!E13 -> 0 | F41: =Results!F13 -> 0
A43: City NET fiscal position | B43: =Results!B25 -> -3183421.2 | C43: =Results!C25 -> -8116362.7 | D43: =Results!D25 -> -12914101 | E43: =Results!E25 -> -17489434 | F43: =Results!F25 -> -17285751
A44: ESD #2 NET fiscal position | B44: =Results!B26 -> -292071.62 | C44: =Results!C26 -> -642050.92 | D44: =Results!D26 -> -963648.17 | E44: =Results!E26 -> -1236199.4 | F44: =Results!F26 -> -1506245.6
A45: Combined NET fiscal position | B45: =Results!B27 -> -3475492.8 | C45: =Results!C27 -> -8758413.6 | D45: =Results!D27 -> -13877750 | E45: =Results!E27 -> -18725633 | F45: =Results!F27 -> -18791996
A47: 4 · CAPITAL & PROPERTY-TAX CONTEXT (assumes full city funding)
A48: City property tax | B48: =Results!B18 -> 480191.29 | C48: =Results!C18 -> 1472843.4 | D48: =Results!D18 -> 2801235.8 | E48: =Results!E18 -> 4578924.4 | F48: =Results!F18 -> 10141443
A49: ESD #2 property tax | B49: =Results!B19 -> 117160.85 | C49: =Results!C19 -> 359250.09 | D49: =Results!D19 -> 683220.11 | E49: =Results!E19 -> 1116765.1 | F49: =Results!F19 -> 2473359
A50: Impact fees (one-time) | B50: =Results!B20 -> 1576300 | C50: =Results!C20 -> 1576300 | D50: =Results!D20 -> 1576300 | E50: =Results!E20 -> 1576300 | F50: =Results!F20 -> 1576300
A51: City capital / debt service | B51: =Results!B22 -> 4399527.6 | C51: =Results!C22 -> 8799055.3 | D51: =Results!D22 -> 13198583 | E51: =Results!E22 -> 17598111 | F51: =Results!F22 -> 18246111
A52: ESD capital / debt service | B52: =Results!B24 -> 188325 | C52: =Results!C24 -> 373275 | D52: =Results!D24 -> 558225 | E52: =Results!E24 -> 743175 | F52: =Results!F24 -> 1113075

Sheet Advanced Inputs
A1: INPUTS
A2: All user-editable assumptions · edit the "Your input" column · Section F holds the development scenarios
A4: Assumption | B4: Recommended | D4: Your input
A5: A. ALLOCATION & TAX RATES
A6: City General Fund share of sales-tax pool | B6: (enter) | D6: ='Typical Inputs'!C5 -> 0
A7: EDC retention of sales tax (%) | B7: 0 | D7: ='Typical Inputs'!C6 -> 0 | E7: EDC basis: | F7: 1 | G7: =IF($F$7="","",IF($F$7=2,IF($D$7>$D$6,"WARNING: EDC % ("&TEXT($D$7,"0%")&") exceeds City pool share ("&TEXT($D$6,"0%")&") - General Fund goes NEGATIVE",""),IF($D$7>1,"WARNING: EDC % over 100% - General Fund negative",""))) | H7: (1 = % of City share | 2 = % of total 1.5% pool)
A8: ESD #2 share of sales-tax pool | B8: (enter) | D8: ='Typical Inputs'!C7 -> 0
A9: Sales-tax pool rate | B9: 0.015 | D9: ='Typical Inputs'!C8 -> 0.015
A10: City property tax rate (per $1 AV) | B10: 0.0037731 | D10: 0.0037731
A11: ESD #2 property tax rate (per $1 AV) | B11: 0.000931 | D11: 0.000931
A12: B. GROWTH & FINANCIAL
A13: Sealy current population | B13: 7937 | D13: 7937
A14: Population CAGR | B14: 0.032 | D14: 0.032
A15: Current annual sales-tax pool ($) | B15: 3700000 | D15: 3700000
A16: Sales-tax pool CAGR | B16: 0.065 | D16: 0.065
A17: Property AV growth CAGR | B17: 0.06 | D17: 0.06
A18: Annexation capture rate | B18: 0.8 | D18: 0.8
A19: General opex inflation CAGR | B19: 0.025 | D19: 0.025
A20: Capital construction inflation CAGR | B20: 0.045 | D20: 0.045
A21: City reserve % (opex+capital basis) | B21: 0.025 | D21: 0.025
A22: ESD reserve % (opex+capital basis) | B22: 0.025 | D22: 0.025
A23: Reserve basis includes capital? (1=Yes,0=No) | B23: 1 | D23: 0
A24: Property tax collection rate | B24: 0.95 | D24: 1
A25: C. RESIDENT ONLINE / DELIVERY USE-TAX
A26: SFR occupancy rate | B26: 0.95 | D26: 0.95
A27: MFR occupancy rate | B27: 0.92 | D27: 0.92
A28: SFR household size | B28: 2.7 | D28: 2.7
A29: MFR household size | B29: 2.1 | D29: 2.1
A30: Online spend per occupied household ($) | B30: 6000 | D30: 6000
A31: Taxable share of online spending | B31: 0.7 | D31: 0.7
A32: Local address capture factor | B32: 0.75 | D32: 0.75
A33: Online spend growth (CAGR) | B33: 0.04 | D33: 0.04
A34: Include online use-tax? (1=Yes,0=No) | B34: 1 | D34: 1
A36: D. EXEMPTION ADJUSTMENT — effective taxable-value factor (edit % cells; factor = 1 − sum)
A37: Category | B37: Homestead% | D37: DisVet% | E37: Freeport% | F37: Pollution% | G37: Other% | H37: Haircut | I37: Factor | J37: ESD Hmstd% | K37: ESD Ov65% | L37: ESD DVet% | M37: ESD Free% | N37: ESD Poll% | O37: ESD Other% | P37: ESD Haircut | Q37: ESD Factor
A38: Residential | B38: 0 | C38: 0.005 | D38: 0.015 | E38: 0 | F38: 0 | G38: 0 | H38: =SUM(B38:G38) -> 0.02 | I38: =MAX(0,1-H38) -> 0.98 | J38: 0.015 | K38: 0.005 | L38: 0.015 | M38: 0 | N38: 0 | O38: 0 | P38: =SUM(J38:O38) -> 0.035 | Q38: =MAX(0,1-P38) -> 0.965
A39: Commercial | B39: 0 | C39: 0 | D39: 0 | E39: 0 | F39: 0 | G39: 0.01 | H39: =SUM(B39:G39) -> 0.01 | I39: =MAX(0,1-H39) -> 0.99 | J39: 0 | K39: 0 | L39: 0 | M39: 0 | N39: 0 | O39: 0.01 | P39: =SUM(J39:O39) -> 0.01 | Q39: =MAX(0,1-P39) -> 0.99
A40: Industrial | B40: 0 | C40: 0 | D40: 0 | E40: 0.05 | F40: 0.02 | G40: 0.01 | H40: =SUM(B40:G40) -> 0.08 | I40: =MAX(0,1-H40) -> 0.92 | J40: 0 | K40: 0 | L40: 0 | M40: 0.05 | N40: 0.02 | O40: 0.01 | P40: =SUM(J40:O40) -> 0.08 | Q40: =MAX(0,1-P40) -> 0.92
A41: Civic | B41: 0 | C41: 0 | D41: 0 | E41: 0 | F41: 0 | G41: 1 | H41: =SUM(B41:G41) -> 1 | I41: =MAX(0,1-H41) -> 0 | J41: 0 | K41: 0 | L41: 0 | M41: 0 | N41: 0 | O41: 1 | P41: =SUM(J41:O41) -> 1 | Q41: =MAX(0,1-P41) -> 0
A42: Vacant | B42: 0 | C42: 0 | D42: 0 | E42: 0 | F42: 0 | G42: 0 | H42: =SUM(B42:G42) -> 0 | I42: =MAX(0,1-H42) -> 1 | J42: 0 | K42: 0 | L42: 0 | M42: 0 | N42: 0 | O42: 0 | P42: =SUM(J42:O42) -> 0 | Q42: =MAX(0,1-P42) -> 1
A44: Factors flow to Type coefficients → property tax. City of Sealy: no general homestead. ESD #2: 1% homestead. Confirm vs Austin CAD certified roll.
A46: E. DEVELOPMENT GEOMETRY & INCENTIVES
A47: Floor-Area-Ratio (FAR) for sqft-entered projects | B47: 0.3 | D47: 0.3
A48: New industrial tax abatement % | B48: 0 | D48: 0
A49: Industrial abatement term (years) | B49: 10 (max) | D49: 10
A50: Water + sewer impact fee per LUE ($) | B50: 7165 | D50: 7165
A53: F. SCENARIO PROJECTS — set Active=Yes to include a project. Type & Quantity Type are dropdowns. Manual Acres only to override the lookup.
A54: Development Type | B54: Active? | D54: Quantity Type | E54: Quantity | F54: Manual Acres (opt.) | G54: Start Year | H54: Buildout Yrs | I54: Capture % | J54: Final Acres (computed) | K54: Sales-tax driver? | N54: Lot size (acres/unit, opt.)
A55: ='Typical Inputs'!A13 -> Big-Box / Anchor Retail | B55: ='Typical Inputs'!B13 -> Yes | D55: =IFERROR(VLOOKUP(A55,'02_Type_Assumptions'!$A$4:$B$25,2,FALSE()),"") -> acres | E55: ='Typical Inputs'!C13 -> 10 | G55: 1 | H55: 4 | I55: 1 | J55: =Scenarios!I3 -> 10 | K55: =IF(A55="","",IF(IFERROR(VLOOKUP(A55,'02_Type_Assumptions'!$A$4:$H$25,7,FALSE()),0)+IFERROR(VLOOKUP(A55,'02_Type_Assumptions'!$A$4:$H$25,8,FALSE()),0)>0,"Yes - retail sales",IF(IFERROR(VLOOKUP(A55,'02_Type_Assumptions'!$A$4:$AA$25,27,FALSE()),"")="Residential","Yes - online use-tax","No"))) -> Yes - retail sales | N55: ='Typical Inputs'!D13 -> 0
A56: ='Typical Inputs'!A14 -> Retail Center / Strip | B56: ='Typical Inputs'!B14 -> No | D56: =IFERROR(VLOOKUP(A56,'02_Type_Assumptions'!$A$4:$B$25,2,FALSE()),"") -> acres | E56: ='Typical Inputs'!C14 -> 10 | G56: 1 | H56: 2 | I56: 1 | J56: =Scenarios!I4 -> 10 | K56: =IF(A56="","",IF(IFERROR(VLOOKUP(A56,'02_Type_Assumptions'!$A$4:$H$25,7,FALSE()),0)+IFERROR(VLOOKUP(A56,'02_Type_Assumptions'!$A$4:$H$25,8,FALSE()),0)>0,"Yes - retail sales",IF(IFERROR(VLOOKUP(A56,'02_Type_Assumptions'!$A$4:$AA$25,27,FALSE()),"")="Residential","Yes - online use-tax","No"))) -> Yes - retail sales | N56: ='Typical Inputs'!D14 -> 0
A57: ='Typical Inputs'!A15 -> Office / Business Park | B57: ='Typical Inputs'!B15 -> No | D57: =IFERROR(VLOOKUP(A57,'02_Type_Assumptions'!$A$4:$B$25,2,FALSE()),"") -> acres | E57: ='Typical Inputs'!C15 -> 10 | G57: 1 | H57: 3 | I57: 1 | J57: =Scenarios!I5 -> 10 | K57: =IF(A57="","",IF(IFERROR(VLOOKUP(A57,'02_Type_Assumptions'!$A$4:$H$25,7,FALSE()),0)+IFERROR(VLOOKUP(A57,'02_Type_Assumptions'!$A$4:$H$25,8,FALSE()),0)>0,"Yes - retail sales",IF(IFERROR(VLOOKUP(A57,'02_Type_Assumptions'!$A$4:$AA$25,27,FALSE()),"")="Residential","Yes - online use-tax","No"))) -> Yes - retail sales | N57: ='Typical Inputs'!D15 -> 0
A58: ='Typical Inputs'!A16 -> Light Industrial / Flex | B58: ='Typical Inputs'!B16 -> No | D58: =IFERROR(VLOOKUP(A58,'02_Type_Assumptions'!$A$4:$B$25,2,FALSE()),"") -> acres | E58: ='Typical Inputs'!C16 -> 15 | G58: 1 | H58: 2 | I58: 1 | J58: =Scenarios!I6 -> 15 | K58: =IF(A58="","",IF(IFERROR(VLOOKUP(A58,'02_Type_Assumptions'!$A$4:$H$25,7,FALSE()),0)+IFERROR(VLOOKUP(A58,'02_Type_Assumptions'!$A$4:$H$25,8,FALSE()),0)>0,"Yes - retail sales",IF(IFERROR(VLOOKUP(A58,'02_Type_Assumptions'!$A$4:$AA$25,27,FALSE()),"")="Residential","Yes - online use-tax","No"))) -> Yes - retail sales | N58: ='Typical Inputs'!D16 -> 0
A59: ='Typical Inputs'!A17 -> Mixed-Use Pad / Vertical | B59: ='Typical Inputs'!B17 -> No | D59: =IFERROR(VLOOKUP(A59,'02_Type_Assumptions'!$A$4:$B$25,2,FALSE()),"") -> acres | E59: ='Typical Inputs'!C17 -> 10 | G59: 1 | H59: 2 | I59: 1 | J59: =Scenarios!I7 -> 10 | K59: =IF(A59="","",IF(IFERROR(VLOOKUP(A59,'02_Type_Assumptions'!$A$4:$H$25,7,FALSE()),0)+IFERROR(VLOOKUP(A59,'02_Type_Assumptions'!$A$4:$H$25,8,FALSE()),0)>0,"Yes - retail sales",IF(IFERROR(VLOOKUP(A59,'02_Type_Assumptions'!$A$4:$AA$25,27,FALSE()),"")="Residential","Yes - online use-tax","No"))) -> Yes - retail sales | N59: ='Typical Inputs'!D17 -> 0
A60: ='Typical Inputs'!A18 -> Gas / Convenience Store | B60: ='Typical Inputs'!B18 -> No | D60: =IFERROR(VLOOKUP(A60,'02_Type_Assumptions'!$A$4:$B$25,2,FALSE()),"") -> acres | E60: ='Typical Inputs'!C18 -> 1.5 | G60: 1 | H60: 2 | I60: 1 | J60: =Scenarios!I8 -> 1.5 | K60: =IF(A60="","",IF(IFERROR(VLOOKUP(A60,'02_Type_Assumptions'!$A$4:$H$25,7,FALSE()),0)+IFERROR(VLOOKUP(A60,'02_Type_Assumptions'!$A$4:$H$25,8,FALSE()),0)>0,"Yes - retail sales",IF(IFERROR(VLOOKUP(A60,'02_Type_Assumptions'!$A$4:$AA$25,27,FALSE()),"")="Residential","Yes - online use-tax","No"))) -> Yes - retail sales | N60: ='Typical Inputs'!D18 -> 0
A61: ='Typical Inputs'!A19 -> Large Travel Center (C-store) | B61: ='Typical Inputs'!B19 -> No | D61: =IFERROR(VLOOKUP(A61,'02_Type_Assumptions'!$A$4:$B$25,2,FALSE()),"") -> acres | E61: ='Typical Inputs'!C19 -> 15 | G61: 1 | H61: 2 | I61: 1 | J61: =Scenarios!I9 -> 15 | K61: =IF(A61="","",IF(IFERROR(VLOOKUP(A61,'02_Type_Assumptions'!$A$4:$H$25,7,FALSE()),0)+IFERROR(VLOOKUP(A61,'02_Type_Assumptions'!$A$4:$H$25,8,FALSE()),0)>0,"Yes - retail sales",IF(IFERROR(VLOOKUP(A61,'02_Type_Assumptions'!$A$4:$AA$25,27,FALSE()),"")="Residential","Yes - online use-tax","No"))) -> Yes - retail sales | N61: ='Typical Inputs'!D19 -> 0
A62: ='Typical Inputs'!A20 -> Fast Food / QSR | B62: ='Typical Inputs'!B20 -> No | D62: =IFERROR(VLOOKUP(A62,'02_Type_Assumptions'!$A$4:$B$25,2,FALSE()),"") -> acres | E62: ='Typical Inputs'!C20 -> 1 | G62: 1 | H62: 2 | I62: 1 | J62: =Scenarios!I10 -> 1 | K62: =IF(A62="","",IF(IFERROR(VLOOKUP(A62,'02_Type_Assumptions'!$A$4:$H$25,7,FALSE()),0)+IFERROR(VLOOKUP(A62,'02_Type_Assumptions'!$A$4:$H$25,8,FALSE()),0)>0,"Yes - retail sales",IF(IFERROR(VLOOKUP(A62,'02_Type_Assumptions'!$A$4:$AA$25,27,FALSE()),"")="Residential","Yes - online use-tax","No"))) -> Yes - retail sales | N62: ='Typical Inputs'!D20 -> 0
A63: ='Typical Inputs'!A21 -> Restaurant (Full-Service) | B63: ='Typical Inputs'!B21 -> No | D63: =IFERROR(VLOOKUP(A63,'02_Type_Assumptions'!$A$4:$B$25,2,FALSE()),"") -> acres | E63: ='Typical Inputs'!C21 -> 1.5 | G63: 1 | H63: 2 | I63: 1 | J63: =Scenarios!I11 -> 1.5 | K63: =IF(A63="","",IF(IFERROR(VLOOKUP(A63,'02_Type_Assumptions'!$A$4:$H$25,7,FALSE()),0)+IFERROR(VLOOKUP(A63,'02_Type_Assumptions'!$A$4:$H$25,8,FALSE()),0)>0,"Yes - retail sales",IF(IFERROR(VLOOKUP(A63,'02_Type_Assumptions'!$A$4:$AA$25,27,FALSE()),"")="Residential","Yes - online use-tax","No"))) -> Yes - retail sales | N63: ='Typical Inputs'!D21 -> 0
A64: ='Typical Inputs'!A22 -> Grocery / Supermarket | B64: ='Typical Inputs'!B22 -> No | D64: =IFERROR(VLOOKUP(A64,'02_Type_Assumptions'!$A$4:$B$25,2,FALSE()),"") -> acres | E64: ='Typical Inputs'!C22 -> 4 | G64: 1 | H64: 2 | I64: 1 | J64: =Scenarios!I12 -> 4 | K64: =IF(A64="","",IF(IFERROR(VLOOKUP(A64,'02_Type_Assumptions'!$A$4:$H$25,7,FALSE()),0)+IFERROR(VLOOKUP(A64,'02_Type_Assumptions'!$A$4:$H$25,8,FALSE()),0)>0,"Yes - retail sales",IF(IFERROR(VLOOKUP(A64,'02_Type_Assumptions'!$A$4:$AA$25,27,FALSE()),"")="Residential","Yes - online use-tax","No"))) -> Yes - retail sales | N64: ='Typical Inputs'!D22 -> 0
A65: ='Typical Inputs'!A23 -> Auto Parts / Service | B65: ='Typical Inputs'!B23 -> No | D65: =IFERROR(VLOOKUP(A65,'02_Type_Assumptions'!$A$4:$B$25,2,FALSE()),"") -> acres | E65: ='Typical Inputs'!C23 -> 1.5 | G65: 1 | H65: 2 | I65: 1 | J65: =Scenarios!I13 -> 1.5 | K65: =IF(A65="","",IF(IFERROR(VLOOKUP(A65,'02_Type_Assumptions'!$A$4:$H$25,7,FALSE()),0)+IFERROR(VLOOKUP(A65,'02_Type_Assumptions'!$A$4:$H$25,8,FALSE()),0)>0,"Yes - retail sales",IF(IFERROR(VLOOKUP(A65,'02_Type_Assumptions'!$A$4:$AA$25,27,FALSE()),"")="Residential","Yes - online use-tax","No"))) -> Yes - retail sales | N65: ='Typical Inputs'!D23 -> 0
A66: ='Typical Inputs'!A24 -> Car Wash | B66: ='Typical Inputs'!B24 -> No | D66: =IFERROR(VLOOKUP(A66,'02_Type_Assumptions'!$A$4:$B$25,2,FALSE()),"") -> acres | E66: ='Typical Inputs'!C24 -> 1 | G66: 1 | H66: 2 | I66: 1 | J66: =Scenarios!I14 -> 1 | K66: =IF(A66="","",IF(IFERROR(VLOOKUP(A66,'02_Type_Assumptions'!$A$4:$H$25,7,FALSE()),0)+IFERROR(VLOOKUP(A66,'02_Type_Assumptions'!$A$4:$H$25,8,FALSE()),0)>0,"Yes - retail sales",IF(IFERROR(VLOOKUP(A66,'02_Type_Assumptions'!$A$4:$AA$25,27,FALSE()),"")="Residential","Yes - online use-tax","No"))) -> Yes - retail sales | N66: ='Typical Inputs'!D24 -> 0
... A76: ='Typical Inputs'!A34 -> Vacant / Holding Land | B76: ='Typical Inputs'!B34 -> No | D76: =IFERROR(VLOOKUP(A76,'02_Type_Assumptions'!$A$4:$B$25,2,FALSE()),"") -> acres | E76: ='Typical Inputs'!C34 -> 10 | G76: 1 | H76: 2 | I76: 1 | J76: =Scenarios!I24 -> 10 | K76: =IF(A76="","",IF(IFERROR(VLOOKUP(A76,'02_Type_Assumptions'!$A$4:$H$25,7,FALSE()),0)+IFERROR(VLOOKUP(A76,'02_Type_Assumptions'!$A$4:$H$25,8,FALSE()),0)>0,"Yes - retail sales",IF(IFERROR(VLOOKUP(A76,'02_Type_Assumptions'!$A$4:$AA$25,27,FALSE()),"")="Residential","Yes - online use-tax","No"))) -> No | N76: ='Typical Inputs'!D34 -> 0

Sheet Capital Items
A1: CAPITAL ITEMS
A2: Infrastructure & service capital (supporting detail) · auto-sized by development · feeds the Fiscal Context section of RESULTS
A3: Item | B3: Entity | C3: Driver (what triggers qty) | D3: Unit | E3: Typical factor | F3: 5-year auto qty | G3: 10-year auto qty | H3: 15-year auto qty | I3: 20-year auto qty | J3: 30-year auto qty | K3: Manual qty +/- | L3: Cumulative quantity (at buildout) | M3: Unit cost ($) | N3: Unit cost override | O3: Manual Total Cost Override | P3: Total cost (today's $) | Q3: Who pays | R3: Include in net? | S3: How it's paid | T3: Year incurred (build yr) | U3: Debt term (yrs) | V3: Debt rate | W3: Annual Debt Service | X3: City 5-year impact | Y3: City 10-year impact | Z3: City 15-year impact | AA3: City 20-year impact | AB3: City 30-year impact | AC3: ESD 5-year impact | AD3: ESD 10-year impact | AE3: ESD 15-year impact | AF3: ESD 20-year impact | AG3: ESD 30-year impact | AH3: Source / Note | AI3: DS @5yr-qty | AJ3: DS @10yr-qty | AK3: DS @15yr-qty | AL3: DS @20yr-qty | AM3: DS @30yr-qty
A4: 12-inch water main, transmission | B4: City | C4: captured acres | D4: linear ft | E4: 60 LF/ac | F4: ='03_Multi_Horizon_Results'!$B$5*'12_Takeoff_Assumptions'!$B$3 -> 1725 | G4: ='03_Multi_Horizon_Results'!$C$5*'12_Takeoff_Assumptions'!$B$3 -> 1725 | H4: ='03_Multi_Horizon_Results'!$D$5*'12_Takeoff_Assumptions'!$B$3 -> 1725 | I4: ='03_Multi_Horizon_Results'!$E$5*'12_Takeoff_Assumptions'!$B$3 -> 1725 | J4: ='03_Multi_Horizon_Results'!$F$5*'12_Takeoff_Assumptions'!$B$3 -> 1725 | L4: =MAX(0,N(G4)+N(K4)) -> 1725 | M4: 600 | P4: =IFERROR(IF(O4<>"",O4,L4*IF(N4<>"",N4,M4)),0) -> 1035000 | Q4: City | R4: Yes | S4: Debt service | T4: 1 | U4: 20 | V4: 0.045 | W4: =IFERROR(IF(AND(R4="Yes",S4="Debt service",U4>0),IF(V4=0,P4/U4,P4*V4/(1-(1+V4)^(-U4))),0),0) -> 79566.809 | X4: =IFERROR(IF(OR(R4<>"Yes",Q4<>"City"),0,IF(S4="Cash capital",IF(T4<=5,IF(O4<>"",O4,MAX(0,N(F4)+N(K4))*IF(N4<>"",N4,M4)),0),IF(S4="Debt service",IF(T4>5,0,AI4*MAX(0,MIN(5-T4+1,U4))),IF(OR(S4="Annual O&M",S4="Maintenance-only"),IF(T4>5,0,IF(O4<>"",O4,MAX(0,N(F4)+N(K4))*IF(N4<>"",N4,M4))*MAX(0,5-T4+1)),0)))),0) -> 397834.05 | Y4: =IFERROR(IF(OR(R4<>"Yes",Q4<>"City"),0,IF(S4="Cash capital",IF(T4<=10,IF(O4<>"",O4,MAX(0,N(G4)+N(K4))*IF(N4<>"",N4,M4)),0),IF(S4="Debt service",IF(T4>10,0,AJ4*MAX(0,MIN(10-T4+1,U4))),IF(OR(S4="Annual O&M",S4="Maintenance-only"),IF(T4>10,0,IF(O4<>"",O4,MAX(0,N(G4)+N(K4))*IF(N4<>"",N4,M4))*MAX(0,10-T4+1)),0)))),0) -> 795668.09 | Z4: =IFERROR(IF(OR(R4<>"Yes",Q4<>"City"),0,IF(S4="Cash capital",IF(T4<=15,IF(O4<>"",O4,MAX(0,N(H4)+N(K4))*IF(N4<>"",N4,M4)),0),IF(S4="Debt service",IF(T4>15,0,AK4*MAX(0,MIN(15-T4+1,U4))),IF(OR(S4="Annual O&M",S4="Maintenance-only"),IF(T4>15,0,IF(O4<>"",O4,MAX(0,N(H4)+N(K4))*IF(N4<>"",N4,M4))*MAX(0,15-T4+1)),0)))),0) -> 1193502.1 | AA4: =IFERROR(IF(OR(R4<>"Yes",Q4<>"City"),0,IF(S4="Cash capital",IF(T4<=20,IF(O4<>"",O4,MAX(0,N(I4)+N(K4))*IF(N4<>"",N4,M4)),0),IF(S4="Debt service",IF(T4>20,0,AL4*MAX(0,MIN(20-T4+1,U4))),IF(OR(S4="Annual O&M",S4="Maintenance-only"),IF(T4>20,0,IF(O4<>"",O4,MAX(0,N(I4)+N(K4))*IF(N4<>"",N4,M4))*MAX(0,20-T4+1)),0)))),0) -> 1591336.2 | AB4: =IFERROR(IF(OR(R4<>"Yes",Q4<>"City"),0,IF(S4="Cash capital",IF(T4<=30,IF(O4<>"",O4,MAX(0,N(J4)+N(K4))*IF(N4<>"",N4,M4)),0),IF(S4="Debt service",IF(T4>30,0,AM4*MAX(0,MIN(30-T4+1,U4))),IF(OR(S4="Annual O&M",S4="Maintenance-only"),IF(T4>30,0,IF(O4<>"",O4,MAX(0,N(J4)+N(K4))*IF(N4<>"",N4,M4))*MAX(0,30-T4+1)),0)))),0) -> 1591336.2 | AC4: =IFERROR(IF(OR(R4<>"Yes",Q4<>"ESD"),0,IF(S4="Cash capital",IF(T4<=5,IF(O4<>"",O4,MAX(0,N(F4)+N(K4))*IF(N4<>"",N4,M4)),0),IF(S4="Debt service",IF(T4>5,0,AI4*MAX(0,MIN(5-T4+1,U4))),IF(OR(S4="Annual O&M",S4="Maintenance-only"),IF(T4>5,0,IF(O4<>"",O4,MAX(0,N(F4)+N(K4))*IF(N4<>"",N4,M4))*MAX(0,5-T4+1)),0)))),0) -> 0 | AD4: =IFERROR(IF(OR(R4<>"Yes",Q4<>"ESD"),0,IF(S4="Cash capital",IF(T4<=10,IF(O4<>"",O4,MAX(0,N(G4)+N(K4))*IF(N4<>"",N4,M4)),0),IF(S4="Debt service",IF(T4>10,0,AJ4*MAX(0,MIN(10-T4+1,U4))),IF(OR(S4="Annual O&M",S4="Maintenance-only"),IF(T4>10,0,IF(O4<>"",O4,MAX(0,N(G4)+N(K4))*IF(N4<>"",N4,M4))*MAX(0,10-T4+1)),0)))),0) -> 0 | AE4: =IFERROR(IF(OR(R4<>"Yes",Q4<>"ESD"),0,IF(S4="Cash capital",IF(T4<=15,IF(O4<>"",O4,MAX(0,N(H4)+N(K4))*IF(N4<>"",N4,M4)),0),IF(S4="Debt service",IF(T4>15,0,AK4*MAX(0,MIN(15-T4+1,U4))),IF(OR(S4="Annual O&M",S4="Maintenance-only"),IF(T4>15,0,IF(O4<>"",O4,MAX(0,N(H4)+N(K4))*IF(N4<>"",N4,M4))*MAX(0,15-T4+1)),0)))),0) -> 0 | AF4: =IFERROR(IF(OR(R4<>"Yes",Q4<>"ESD"),0,IF(S4="Cash capital",IF(T4<=20,IF(O4<>"",O4,MAX(0,N(I4)+N(K4))*IF(N4<>"",N4,M4)),0),IF(S4="Debt service",IF(T4>20,0,AL4*MAX(0,MIN(20-T4+1,U4))),IF(OR(S4="Annual O&M",S4="Maintenance-only"),IF(T4>20,0,IF(O4<>"",O4,MAX(0,N(I4)+N(K4))*IF(N4<>"",N4,M4))*MAX(0,20-T4+1)),0)))),0) -> 0 | AG4: =IFERROR(IF(OR(R4<>"Yes",Q4<>"ESD"),0,IF(S4="Cash capital",IF(T4<=30,IF(O4<>"",O4,MAX(0,N(J4)+N(K4))*IF(N4<>"",N4,M4)),0),IF(S4="Debt service",IF(T4>30,0,AM4*MAX(0,MIN(30-T4+1,U4))),IF(OR(S4="Annual O&M",S4="Maintenance-only"),IF(T4>30,0,IF(O4<>"",O4,MAX(0,N(J4)+N(K4))*IF(N4<>"",N4,M4))*MAX(0,30-T4+1)),0)))),0) -> 0 | AH4: Planning allowance for trunk/looping needs; engineer/Public Works validation required. | Takeoff factor: 60 LF per developed acre; confidence Low; validate w/ Engineer/Public Works. | AI4: =IFERROR(IF(U4>0,IF(O4<>"",O4,MAX(0,N(F4)+N(K4))*IF(N4<>"",N4,M4))*IF(V4=0,1/U4,V4/(1-(1+V4)^(-U4))),0),0) -> 79566.809 | AJ4: =IFERROR(IF(U4>0,IF(O4<>"",O4,MAX(0,N(G4)+N(K4))*IF(N4<>"",N4,M4))*IF(V4=0,1/U4,V4/(1-(1+V4)^(-U4))),0),0) -> 79566.809 | AK4: =IFERROR(IF(U4>0,IF(O4<>"",O4,MAX(0,N(H4)+N(K4))*IF(N4<>"",N4,M4))*IF(V4=0,1/U4,V4/(1-(1+V4)^(-U4))),0),0) -> 79566.809 | AL4: =IFERROR(IF(U4>0,IF(O4<>"",O4,MAX(0,N(I4)+N(K4))*IF(N4<>"",N4,M4))*IF(V4=0,1/U4,V4/(1-(1+V4)^(-U4))),0),0) -> 79566.809 | AM4: =IFERROR(IF(U4>0,IF(O4<>"",O4,MAX(0,N(J4)+N(K4))*IF(N4<>"",N4,M4))*IF(V4=0,1/U4,V4/(1-(1+V4)^(-U4))),0),0) -> 79566.809
A5: 8-inch water main, distribution | B5: City | C5: captured acres | D5: linear ft | E5: 400 LF/ac | F5: ='03_Multi_Horizon_Results'!$B$5*'12_Takeoff_Assumptions'!$B$2 -> 11500 | G5: ='03_Multi_Horizon_Results'!$C$5*'12_Takeoff_Assumptions'!$B$2 -> 11500 | H5: ='03_Multi_Horizon_Results'!$D$5*'12_Takeoff_Assumptions'!$B$2 -> 11500 | I5: ='03_Multi_Horizon_Results'!$E$5*'12_Takeoff_Assumptions'!$B$2 -> 11500 | J5: ='03_Multi_Horizon_Results'!$F$5*'12_Takeoff_Assumptions'!$B$2 -> 11500 | L5: =MAX(0,N(G5)+N(K5)) -> 11500 | M5: 250 | P5: =IFERROR(IF(O5<>"",O5,L5*IF(N5<>"",N5,M5)),0) -> 2875000 | Q5: City | R5: Yes | S5: Debt service | T5: 1 | U5: 20 | V5: 0.045 | W5: =IFERROR(IF(AND(R5="Yes",S5="Debt service",U5>0),IF(V5=0,P5/U5,P5*V5/(1-(1+V5)^(-U5))),0),0) -> 221018.91 | X5: =IFERROR(IF(OR(R5<>"Yes",Q5<>"City"),0,IF(S5="Cash capital",IF(T5<=5,IF(O5<>"",O5,MAX(0,N(F5)+N(K5))*IF(N5<>"",N5,M5)),0),IF(S5="Debt service",IF(T5>5,0,AI5*MAX(0,MIN(5-T5+1,U5))),IF(OR(S5="Annual O&M",S5="Maintenance-only"),IF(T5>5,0,IF(O5<>"",O5,MAX(0,N(F5)+N(K5))*IF(N5<>"",N5,M5))*MAX(0,5-T5+1)),0)))),0) -> 1105094.6 | Y5: =IFERROR(IF(OR(R5<>"Yes",Q5<>"City"),0,IF(S5="Cash capital",IF(T5<=10,IF(O5<>"",O5,MAX(0,N(G5)+N(K5))*IF(N5<>"",N5,M5)),0),IF(S5="Debt service",IF(T5>10,0,AJ5*MAX(0,MIN(10-T5+1,U5))),IF(OR(S5="Annual O&M",S5="Maintenance-only"),IF(T5>10,0,IF(O5<>"",O5,MAX(0,N(G5)+N(K5))*IF(N5<>"",N5,M5))*MAX(0,10-T5+1)),0)))),0) -> 2210189.1 | Z5: =IFERROR(IF(OR(R5<>"Yes",Q5<>"City"),0,IF(S5="Cash capital",IF(T5<=15,IF(O5<>"",O5,MAX(0,N(H5)+N(K5))*IF(N5<>"",N5,M5)),0),IF(S5="Debt service",IF(T5>15,0,AK5*MAX(0,MIN(15-T5+1,U5))),IF(OR(S5="Annual O&M",S5="Maintenance-only"),IF(T5>15,0,IF(O5<>"",O5,MAX(0,N(H5)+N(K5))*IF(N5<>"",N5,M5))*MAX(0,15-T5+1)),0)))),0) -> 3315283.7 | AA5: =IFERROR(IF(OR(R5<>"Yes",Q5<>"City"),0,IF(S5="Cash capital",IF(T5<=20,IF(O5<>"",O5,MAX(0,N(I5)+N(K5))*IF(N5<>"",N5,M5)),0),IF(S5="Debt service",IF(T5>20,0,AL5*MAX(0,MIN(20-T5+1,U5))),IF(OR(S5="Annual O&M",S5="Maintenance-only"),IF(T5>20,0,IF(O5<>"",O5,MAX(0,N(I5)+N(K5))*IF(N5<>"",N5,M5))*MAX(0,20-T5+1)),0)))),0) -> 4420378.3 | AB5: =IFERROR(IF(OR(R5<>"Yes",Q5<>"City"),0,IF(S5="Cash capital",IF(T5<=30,IF(O5<>"",O5,MAX(0,N(J5)+N(K5))*IF(N5<>"",N5,M5)),0),IF(S5="Debt service",IF(T5>30,0,AM5*MAX(0,MIN(30-T5+1,U5))),IF(OR(S5="Annual O&M",S5="Maintenance-only"),IF(T5>30,0,IF(O5<>"",O5,MAX(0,N(J5)+N(K5))*IF(N5<>"",N5,M5))*MAX(0,30-T5+1)),0)))),0) -> 4420378.3 | AC5: =IFERROR(IF(OR(R5<>"Yes",Q5<>"ESD"),0,IF(S5="Cash capital",IF(T5<=5,IF(O5<>"",O5,MAX(0,N(F5)+N(K5))*IF(N5<>"",N5,M5)),0),IF(S5="Debt service",IF(T5>5,0,AI5*MAX(0,MIN(5-T5+1,U5))),IF(OR(S5="Annual O&M",S5="Maintenance-only"),IF(T5>5,0,IF(O5<>"",O5,MAX(0,N(F5)+N(K5))*IF(N5<>"",N5,M5))*MAX(0,5-T5+1)),0)))),0) -> 0 | AD5: =IFERROR(IF(OR(R5<>"Yes",Q5<>"ESD"),0,IF(S5="Cash capital",IF(T5<=10,IF(O5<>"",O5,MAX(0,N(G5)+N(K5))*IF(N5<>"",N5,M5)),0),IF(S5="Debt service",IF(T5>10,0,AJ5*MAX(0,MIN(10-T5+1,U5))),IF(OR(S5="Annual O&M",S5="Maintenance-only"),IF(T5>10,0,IF(O5<>"",O5,MAX(0,N(G5)+N(K5))*IF(N5<>"",N5,M5))*MAX(0,10-T5+1)),0)))),0) -> 0 | AE5: =IFERROR(IF(OR(R5<>"Yes",Q5<>"ESD"),0,IF(S5="Cash capital",IF(T5<=15,IF(O5<>"",O5,MAX(0,N(H5)+N(K5))*IF(N5<>"",N5,M5)),0),IF(S5="Debt service",IF(T5>15,0,AK5*MAX(0,MIN(15-T5+1,U5))),IF(OR(S5="Annual O&M",S5="Maintenance-only"),IF(T5>15,0,IF(O5<>"",O5,MAX(0,N(H5)+N(K5))*IF(N5<>"",N5,M5))*MAX(0,15-T5+1)),0)))),0) -> 0 | AF5: =IFERROR(IF(OR(R5<>"Yes",Q5<>"ESD"),0,IF(S5="Cash capital",IF(T5<=20,IF(O5<>"",O5,MAX(0,N(I5)+N(K5))*IF(N5<>"",N5,M5)),0),IF(S5="Debt service",IF(T5>20,0,AL5*MAX(0,MIN(20-T5+1,U5))),IF(OR(S5="Annual O&M",S5="Maintenance-only"),IF(T5>20,0,IF(O5<>"",O5,MAX(0,N(I5)+N(K5))*IF(N5<>"",N5,M5))*MAX(0,20-T5+1)),0)))),0) -> 0 | AG5: =IFERROR(IF(OR(R5<>"Yes",Q5<>"ESD"),0,IF(S5="Cash capital",IF(T5<=30,IF(O5<>"",O5,MAX(0,N(J5)+N(K5))*IF(N5<>"",N5,M5)),0),IF(S5="Debt service",IF(T5>30,0,AM5*MAX(0,MIN(30-T5+1,U5))),IF(OR(S5="Annual O&M",S5="Maintenance-only"),IF(T5>30,0,IF(O5<>"",O5,MAX(0,N(J5)+N(K5))*IF(N5<>"",N5,M5))*MAX(0,30-T5+1)),0)))),0) -> 0 | AH5: Subdivision/internal water distribution planning allowance; actual plat should override. | Takeoff factor: 400 LF per developed acre; confidence Low; validate w/ Engineer/Public Works. | AI5: =IFERROR(IF(U5>0,IF(O5<>"",O5,MAX(0,N(F5)+N(K5))*IF(N5<>"",N5,M5))*IF(V5=0,1/U5,V5/(1-(1+V5)^(-U5))),0),0) -> 221018.91 | AJ5: =IFERROR(IF(U5>0,IF(O5<>"",O5,MAX(0,N(G5)+N(K5))*IF(N5<>"",N5,M5))*IF(V5=0,1/U5,V5/(1-(1+V5)^(-U5))),0),0) -> 221018.91 | AK5: =IFERROR(IF(U5>0,IF(O5<>"",O5,MAX(0,N(H5)+N(K5))*IF(N5<>"",N5,M5))*IF(V5=0,1/U5,V5/(1-(1+V5)^(-U5))),0),0) -> 221018.91 | AL5: =IFERROR(IF(U5>0,IF(O5<>"",O5,MAX(0,N(I5)+N(K5))*IF(N5<>"",N5,M5))*IF(V5=0,1/U5,V5/(1-(1+V5)^(-U5))),0),0) -> 221018.91 | AM5: =IFERROR(IF(U5>0,IF(O5<>"",O5,MAX(0,N(J5)+N(K5))*IF(N5<>"",N5,M5))*IF(V5=0,1/U5,V5/(1-(1+V5)^(-U5))),0),0) -> 221018.91
A6: Fire hydrants | B6: City | C6: water distribution LF | D6: each | E6: hydrant spacing 500 LF | F6: =IFERROR(ROUNDUP(('03_Multi_Horizon_Results'!$B$5*'12_Takeoff_Assumptions'!$B$2)/'12_Takeoff_Assumptions'!$B$9,0),0) -> 23 | G6: =IFERROR(ROUNDUP(('03_Multi_Horizon_Results'!$C$5*'12_Takeoff_Assumptions'!$B$2)/'12_Takeoff_Assumptions'!$B$9,0),0) -> 23 | H6: =IFERROR(ROUNDUP(('03_Multi_Horizon_Results'!$D$5*'12_Takeoff_Assumptions'!$B$2)/'12_Takeoff_Assumptions'!$B$9,0),0) -> 23 | I6: =IFERROR(ROUNDUP(('03_Multi_Horizon_Results'!$E$5*'12_Takeoff_Assumptions'!$B$2)/'12_Takeoff_Assumptions'!$B$9,0),0) -> 23 | J6: =IFERROR(ROUNDUP(('03_Multi_Horizon_Results'!$F$5*'12_Takeoff_Assumptions'!$B$2)/'12_Takeoff_Assumptions'!$B$9,0),0) -> 23 | L6: =MAX(0,N(G6)+N(K6)) -> 23 | M6: 7500 | P6: =IFERROR(IF(O6<>"",O6,L6*IF(N6<>"",N6,M6)),0) -> 172500 | Q6: City | R6: Yes | S6: Debt service | T6: 1 | U6: 20 | V6: 0.045 | W6: =IFERROR(IF(AND(R6="Yes",S6="Debt service",U6>0),IF(V6=0,P6/U6,P6*V6/(1-(1+V6)^(-U6))),0),0) -> 13261.135 | X6: =IFERROR(IF(OR(R6<>"Yes",Q6<>"City"),0,IF(S6="Cash capital",IF(T6<=5,IF(O6<>"",O6,MAX(0,N(F6)+N(K6))*IF(N6<>"",N6,M6)),0),IF(S6="Debt service",IF(T6>5,0,AI6*MAX(0,MIN(5-T6+1,U6))),IF(OR(S6="Annual O&M",S6="Maintenance-only"),IF(T6>5,0,IF(O6<>"",O6,MAX(0,N(F6)+N(K6))*IF(N6<>"",N6,M6))*MAX(0,5-T6+1)),0)))),0) -> 66305.674 | Y6: =IFERROR(IF(OR(R6<>"Yes",Q6<>"City"),0,IF(S6="Cash capital",IF(T6<=10,IF(O6<>"",O6,MAX(0,N(G6)+N(K6))*IF(N6<>"",N6,M6)),0),IF(S6="Debt service",IF(T6>10,0,AJ6*MAX(0,MIN(10-T6+1,U6))),IF(OR(S6="Annual O&M",S6="Maintenance-only"),IF(T6>10,0,IF(O6<>"",O6,MAX(0,N(G6)+N(K6))*IF(N6<>"",N6,M6))*MAX(0,10-T6+1)),0)))),0) -> 132611.35 | Z6: =IFERROR(IF(OR(R6<>"Yes",Q6<>"City"),0,IF(S6="Cash capital",IF(T6<=15,IF(O6<>"",O6,MAX(0,N(H6)+N(K6))*IF(N6<>"",N6,M6)),0),IF(S6="Debt service",IF(T6>15,0,AK6*MAX(0,MIN(15-T6+1,U6))),IF(OR(S6="Annual O&M",S6="Maintenance-only"),IF(T6>15,0,IF(O6<>"",O6,MAX(0,N(H6)+N(K6))*IF(N6<>"",N6,M6))*MAX(0,15-T6+1)),0)))),0) -> 198917.02 | AA6: =IFERROR(IF(OR(R6<>"Yes",Q6<>"City"),0,IF(S6="Cash capital",IF(T6<=20,IF(O6<>"",O6,MAX(0,N(I6)+N(K6))*IF(N6<>"",N6,M6)),0),IF(S6="Debt service",IF(T6>20,0,AL6*MAX(0,MIN(20-T6+1,U6))),IF(OR(S6="Annual O&M",S6="Maintenance-only"),IF(T6>20,0,IF(O6<>"",O6,MAX(0,N(I6)+N(K6))*IF(N6<>"",N6,M6))*MAX(0,20-T6+1)),0)))),0) -> 265222.7 | AB6: =IFERROR(IF(OR(R6<>"Yes",Q6<>"City"),0,IF(S6="Cash capital",IF(T6<=30,IF(O6<>"",O6,MAX(0,N(J6)+N(K6))*IF(N6<>"",N6,M6)),0),IF(S6="Debt service",IF(T6>30,0,AM6*MAX(0,MIN(30-T6+1,U6))),IF(OR(S6="Annual O&M",S6="Maintenance-only"),IF(T6>30,0,IF(O6<>"",O6,MAX(0,N(J6)+N(K6))*IF(N6<>"",N6,M6))*MAX(0,30-T6+1)),0)))),0) -> 265222.7 | AC6: =IFERROR(IF(OR(R6<>"Yes",Q6<>"ESD"),0,IF(S6="Cash capital",IF(T6<=5,IF(O6<>"",O6,MAX(0,N(F6)+N(K6))*IF(N6<>"",N6,M6)),0),IF(S6="Debt service",IF(T6>5,0,AI6*MAX(0,MIN(5-T6+1,U6))),IF(OR(S6="Annual O&M",S6="Maintenance-only"),IF(T6>5,0,IF(O6<>"",O6,MAX(0,N(F6)+N(K6))*IF(N6<>"",N6,M6))*MAX(0,5-T6+1)),0)))),0) -> 0 | AD6: =IFERROR(IF(OR(R6<>"Yes",Q6<>"ESD"),0,IF(S6="Cash capital",IF(T6<=10,IF(O6<>"",O6,MAX(0,N(G6)+N(K6))*IF(N6<>"",N6,M6)),0),IF(S6="Debt service",IF(T6>10,0,AJ6*MAX(0,MIN(10-T6+1,U6))),IF(OR(S6="Annual O&M",S6="Maintenance-only"),IF(T6>10,0,IF(O6<>"",O6,MAX(0,N(G6)+N(K6))*IF(N6<>"",N6,M6))*MAX(0,10-T6+1)),0)))),0) -> 0 | AE6: =IFERROR(IF(OR(R6<>"Yes",Q6<>"ESD"),0,IF(S6="Cash capital",IF(T6<=15,IF(O6<>"",O6,MAX(0,N(H6)+N(K6))*IF(N6<>"",N6,M6)),0),IF(S6="Debt service",IF(T6>15,0,AK6*MAX(0,MIN(15-T6+1,U6))),IF(OR(S6="Annual O&M",S6="Maintenance-only"),IF(T6>15,0,IF(O6<>"",O6,MAX(0,N(H6)+N(K6))*IF(N6<>"",N6,M6))*MAX(0,15-T6+1)),0)))),0) -> 0 | AF6: =IFERROR(IF(OR(R6<>"Yes",Q6<>"ESD"),0,IF(S6="Cash capital",IF(T6<=20,IF(O6<>"",O6,MAX(0,N(I6)+N(K6))*IF(N6<>"",N6,M6)),0),IF(S6="Debt service",IF(T6>20,0,AL6*MAX(0,MIN(20-T6+1,U6))),IF(OR(S6="Annual O&M",S6="Maintenance-only"),IF(T6>20,0,IF(O6<>"",O6,MAX(0,N(I6)+N(K6))*IF(N6<>"",N6,M6))*MAX(0,20-T6+1)),0)))),0) -> 0 | AG6: =IFERROR(IF(OR(R6<>"Yes",Q6<>"ESD"),0,IF(S6="Cash capital",IF(T6<=30,IF(O6<>"",O6,MAX(0,N(J6)+N(K6))*IF(N6<>"",N6,M6)),0),IF(S6="Debt service",IF(T6>30,0,AM6*MAX(0,MIN(30-T6+1,U6))),IF(OR(S6="Annual O&M",S6="Maintenance-only"),IF(T6>30,0,IF(O6<>"",O6,MAX(0,N(J6)+N(K6))*IF(N6<>"",N6,M6))*MAX(0,30-T6+1)),0)))),0) -> 0 | AH6: Hydrant count from distribution LF / spacing; verify fire code and utility standards. | Takeoff factor: 500 LF between hydrants; confidence Medium; validate w/ Fire/Public Works. | AI6: =IFERROR(IF(U6>0,IF(O6<>"",O6,MAX(0,N(F6)+N(K6))*IF(N6<>"",N6,M6))*IF(V6=0,1/U6,V6/(1-(1+V6)^(-U6))),0),0) -> 13261.135 | AJ6: =IFERROR(IF(U6>0,IF(O6<>"",O6,MAX(0,N(G6)+N(K6))*IF(N6<>"",N6,M6))*IF(V6=0,1/U6,V6/(1-(1+V6)^(-U6))),0),0) -> 13261.135 | AK6: =IFERROR(IF(U6>0,IF(O6<>"",O6,MAX(0,N(H6)+N(K6))*IF(N6<>"",N6,M6))*IF(V6=0,1/U6,V6/(1-(1+V6)^(-U6))),0),0) -> 13261.135 | AL6: =IFERROR(IF(U6>0,IF(O6<>"",O6,MAX(0,N(I6)+N(K6))*IF(N6<>"",N6,M6))*IF(V6=0,1/U6,V6/(1-(1+V6)^(-U6))),0),0) -> 13261.135 | AM6: =IFERROR(IF(U6>0,IF(O6<>"",O6,MAX(0,N(J6)+N(K6))*IF(N6<>"",N6,M6))*IF(V6=0,1/U6,V6/(1-(1+V6)^(-U6))),0),0) -> 13261.135
A7: Water wells, 1,500 gpm | B7: City | C7: water demand MGD | D7: each | E7: threshold 0.50 MGD | F7: =IF((('03_Multi_Horizon_Results'!$B$22/'Advanced Inputs'!$D$50)*'12_Takeoff_Assumptions'!$B$13/1000000)>'12_Takeoff_Assumptions'!$B$16,ROUNDUP((('03_Multi_Horizon_Results'!$B$22/'Advanced Inputs'!$D$50)*'12_Takeoff_Assumptions'!$B$13/1000000)/'12_Takeoff_Assumptions'!$B$16,0),0) -> 0 | G7: =IF((('03_Multi_Horizon_Results'!$C$22/'Advanced Inputs'!$D$50)*'12_Takeoff_Assumptions'!$B$13/1000000)>'12_Takeoff_Assumptions'!$B$16,ROUNDUP((('03_Multi_Horizon_Results'!$C$22/'Advanced Inputs'!$D$50)*'12_Takeoff_Assumptions'!$B$13/1000000)/'12_Takeoff_Assumptions'!$B$16,0),0) -> 0 | H7: =IF((('03_Multi_Horizon_Results'!$D$22/'Advanced Inputs'!$D$50)*'12_Takeoff_Assumptions'!$B$13/1000000)>'12_Takeoff_Assumptions'!$B$16,ROUNDUP((('03_Multi_Horizon_Results'!$D$22/'Advanced Inputs'!$D$50)*'12_Takeoff_Assumptions'!$B$13/1000000)/'12_Takeoff_Assumptions'!$B$16,0),0) -> 0 | I7: =IF((('03_Multi_Horizon_Results'!$E$22/'Advanced Inputs'!$D$50)*'12_Takeoff_Assumptions'!$B$13/1000000)>'12_Takeoff_Assumptions'!$B$16,ROUNDUP((('03_Multi_Horizon_Results'!$E$22/'Advanced Inputs'!$D$50)*'12_Takeoff_Assumptions'!$B$13/1000000)/'12_Takeoff_Assumptions'!$B$16,0),0) -> 0 | J7: =IF((('03_Multi_Horizon_Results'!$F$22/'Advanced Inputs'!$D$50)*'12_Takeoff_Assumptions'!$B$13/1000000)>'12_Takeoff_Assumptions'!$B$16,ROUNDUP((('03_Multi_Horizon_Results'!$F$22/'Advanced Inputs'!$D$50)*'12_Takeoff_Assumptions'!$B$13/1000000)/'12_Takeoff_Assumptions'!$B$16,0),0) -> 0 | L7: =MAX(0,N(G7)+N(K7)) -> 0 | M7: 1500000 | P7: =IFERROR(IF(O7<>"",O7,L7*IF(N7<>"",N7,M7)),0) -> 0 | Q7: City | R7: Yes | S7: Debt service | T7: 1 | U7: 20 | V7: 0.045 | W7: =IFERROR(IF(AND(R7="Yes",S7="Debt service",U7>0),IF(V7=0,P7/U7,P7*V7/(1-(1+V7)^(-U7))),0),0) -> 0 | X7: =IFERROR(IF(OR(R7<>"Yes",Q7<>"City"),0,IF(S7="Cash capital",IF(T7<=5,IF(O7<>"",O7,MAX(0,N(F7)+N(K7))*IF(N7<>"",N7,M7)),0),IF(S7="Debt service",IF(T7>5,0,AI7*MAX(0,MIN(5-T7+1,U7))),IF(OR(S7="Annual O&M",S7="Maintenance-only"),IF(T7>5,0,IF(O7<>"",O7,MAX(0,N(F7)+N(K7))*IF(N7<>"",N7,M7))*MAX(0,5-T7+1)),0)))),0) -> 0 | Y7: =IFERROR(IF(OR(R7<>"Yes",Q7<>"City"),0,IF(S7="Cash capital",IF(T7<=10,IF(O7<>"",O7,MAX(0,N(G7)+N(K7))*IF(N7<>"",N7,M7)),0),IF(S7="Debt service",IF(T7>10,0,AJ7*MAX(0,MIN(10-T7+1,U7))),IF(OR(S7="Annual O&M",S7="Maintenance-only"),IF(T7>10,0,IF(O7<>"",O7,MAX(0,N(G7)+N(K7))*IF(N7<>"",N7,M7))*MAX(0,10-T7+1)),0)))),0) -> 0 | Z7: =IFERROR(IF(OR(R7<>"Yes",Q7<>"City"),0,IF(S7="Cash capital",IF(T7<=15,IF(O7<>"",O7,MAX(0,N(H7)+N(K7))*IF(N7<>"",N7,M7)),0),IF(S7="Debt service",IF(T7>15,0,AK7*MAX(0,MIN(15-T7+1,U7))),IF(OR(S7="Annual O&M",S7="Maintenance-only"),IF(T7>15,0,IF(O7<>"",O7,MAX(0,N(H7)+N(K7))*IF(N7<>"",N7,M7))*MAX(0,15-T7+1)),0)))),0) -> 0 | AA7: =IFERROR(IF(OR(R7<>"Yes",Q7<>"City"),0,IF(S7="Cash capital",IF(T7<=20,IF(O7<>"",O7,MAX(0,N(I7)+N(K7))*IF(N7<>"",N7,M7)),0),IF(S7="Debt service",IF(T7>20,0,AL7*MAX(0,MIN(20-T7+1,U7))),IF(OR(S7="Annual O&M",S7="Maintenance-only"),IF(T7>20,0,IF(O7<>"",O7,MAX(0,N(I7)+N(K7))*IF(N7<>"",N7,M7))*MAX(0,20-T7+1)),0)))),0) -> 0 | AB7: =IFERROR(IF(OR(R7<>"Yes",Q7<>"City"),0,IF(S7="Cash capital",IF(T7<=30,IF(O7<>"",O7,MAX(0,N(J7)+N(K7))*IF(N7<>"",N7,M7)),0),IF(S7="Debt service",IF(T7>30,0,AM7*MAX(0,MIN(30-T7+1,U7))),IF(OR(S7="Annual O&M",S7="Maintenance-only"),IF(T7>30,0,IF(O7<>"",O7,MAX(0,N(J7)+N(K7))*IF(N7<>"",N7,M7))*MAX(0,30-T7+1)),0)))),0) -> 0 | AC7: =IFERROR(IF(OR(R7<>"Yes",Q7<>"ESD"),0,IF(S7="Cash capital",IF(T7<=5,IF(O7<>"",O7,MAX(0,N(F7)+N(K7))*IF(N7<>"",N7,M7)),0),IF(S7="Debt service",IF(T7>5,0,AI7*MAX(0,MIN(5-T7+1,U7))),IF(OR(S7="Annual O&M",S7="Maintenance-only"),IF(T7>5,0,IF(O7<>"",O7,MAX(0,N(F7)+N(K7))*IF(N7<>"",N7,M7))*MAX(0,5-T7+1)),0)))),0) -> 0 | AD7: =IFERROR(IF(OR(R7<>"Yes",Q7<>"ESD"),0,IF(S7="Cash capital",IF(T7<=10,IF(O7<>"",O7,MAX(0,N(G7)+N(K7))*IF(N7<>"",N7,M7)),0),IF(S7="Debt service",IF(T7>10,0,AJ7*MAX(0,MIN(10-T7+1,U7))),IF(OR(S7="Annual O&M",S7="Maintenance-only"),IF(T7>10,0,IF(O7<>"",O7,MAX(0,N(G7)+N(K7))*IF(N7<>"",N7,M7))*MAX(0,10-T7+1)),0)))),0) -> 0 | AE7: =IFERROR(IF(OR(R7<>"Yes",Q7<>"ESD"),0,IF(S7="Cash capital",IF(T7<=15,IF(O7<>"",O7,MAX(0,N(H7)+N(K7))*IF(N7<>"",N7,M7)),0),IF(S7="Debt service",IF(T7>15,0,AK7*MAX(0,MIN(15-T7+1,U7))),IF(OR(S7="Annual O&M",S7="Maintenance-only"),IF(T7>15,0,IF(O7<>"",O7,MAX(0,N(H7)+N(K7))*IF(N7<>"",N7,M7))*MAX(0,15-T7+1)),0)))),0) -> 0 | AF7: =IFERROR(IF(OR(R7<>"Yes",Q7<>"ESD"),0,IF(S7="Cash capital",IF(T7<=20,IF(O7<>"",O7,MAX(0,N(I7)+N(K7))*IF(N7<>"",N7,M7)),0),IF(S7="Debt service",IF(T7>20,0,AL7*MAX(0,MIN(20-T7+1,U7))),IF(OR(S7="Annual O&M",S7="Maintenance-only"),IF(T7>20,0,IF(O7<>"",O7,MAX(0,N(I7)+N(K7))*IF(N7<>"",N7,M7))*MAX(0,20-T7+1)),0)))),0) -> 0 | AG7: =IFERROR(IF(OR(R7<>"Yes",Q7<>"ESD"),0,IF(S7="Cash capital",IF(T7<=30,IF(O7<>"",O7,MAX(0,N(J7)+N(K7))*IF(N7<>"",N7,M7)),0),IF(S7="Debt service",IF(T7>30,0,AM7*MAX(0,MIN(30-T7+1,U7))),IF(OR(S7="Annual O&M",S7="Maintenance-only"),IF(T7>30,0,IF(O7<>"",O7,MAX(0,N(J7)+N(K7))*IF(N7<>"",N7,M7))*MAX(0,30-T7+1)),0)))),0) -> 0 | AH7: Demand-based planning trigger; validate with water master plan and TCEQ capacity review. | Takeoff factor: 0.5 MGD demand; confidence Low; validate w/ Engineer/Public Works. | AI7: =IFERROR(IF(U7>0,IF(O7<>"",O7,MAX(0,N(F7)+N(K7))*IF(N7<>"",N7,M7))*IF(V7=0,1/U7,V7/(1-(1+V7)^(-U7))),0),0) -> 0 | AJ7: =IFERROR(IF(U7>0,IF(O7<>"",O7,MAX(0,N(G7)+N(K7))*IF(N7<>"",N7,M7))*IF(V7=0,1/U7,V7/(1-(1+V7)^(-U7))),0),0) -> 0 | AK7: =IFERROR(IF(U7>0,IF(O7<>"",O7,MAX(0,N(H7)+N(K7))*IF(N7<>"",N7,M7))*IF(V7=0,1/U7,V7/(1-(1+V7)^(-U7))),0),0) -> 0 | AL7: =IFERROR(IF(U7>0,IF(O7<>"",O7,MAX(0,N(I7)+N(K7))*IF(N7<>"",N7,M7))*IF(V7=0,1/U7,V7/(1-(1+V7)^(-U7))),0),0) -> 0 | AM7: =IFERROR(IF(U7>0,IF(O7<>"",O7,MAX(0,N(J7)+N(K7))*IF(N7<>"",N7,M7))*IF(V7=0,1/U7,V7/(1-(1+V7)^(-U7))),0),0) -> 0
A8: Gravity sewer main, 10-inch | B8: City | C8: captured acres | D8: linear ft | E8: 300 LF/ac | F8: ='03_Multi_Horizon_Results'!$B$5*'12_Takeoff_Assumptions'!$B$4 -> 8625 | G8: ='03_Multi_Horizon_Results'!$C$5*'12_Takeoff_Assumptions'!$B$4 -> 8625 | H8: ='03_Multi_Horizon_Results'!$D$5*'12_Takeoff_Assumptions'!$B$4 -> 8625 | I8: ='03_Multi_Horizon_Results'!$E$5*'12_Takeoff_Assumptions'!$B$4 -> 8625 | J8: ='03_Multi_Horizon_Results'!$F$5*'12_Takeoff_Assumptions'!$B$4 -> 8625 | L8: =MAX(0,N(G8)+N(K8)) -> 8625 | M8: 325 | P8: =IFERROR(IF(O8<>"",O8,L8*IF(N8<>"",N8,M8)),0) -> 2803125 | Q8: City | R8: Yes | S8: Debt service | T8: 1 | U8: 20 | V8: 0.045 | W8: =IFERROR(IF(AND(R8="Yes",S8="Debt service",U8>0),IF(V8=0,P8/U8,P8*V8/(1-(1+V8)^(-U8))),0),0) -> 215493.44 | X8: =IFERROR(IF(OR(R8<>"Yes",Q8<>"City"),0,IF(S8="Cash capital",IF(T8<=5,IF(O8<>"",O8,MAX(0,N(F8)+N(K8))*IF(N8<>"",N8,M8)),0),IF(S8="Debt service",IF(T8>5,0,AI8*MAX(0,MIN(5-T8+1,U8))),IF(OR(S8="Annual O&M",S8="Maintenance-only"),IF(T8>5,0,IF(O8<>"",O8,MAX(0,N(F8)+N(K8))*IF(N8<>"",N8,M8))*MAX(0,5-T8+1)),0)))),0) -> 1077467.2 | Y8: =IFERROR(IF(OR(R8<>"Yes",Q8<>"City"),0,IF(S8="Cash capital",IF(T8<=10,IF(O8<>"",O8,MAX(0,N(G8)+N(K8))*IF(N8<>"",N8,M8)),0),IF(S8="Debt service",IF(T8>10,0,AJ8*MAX(0,MIN(10-T8+1,U8))),IF(OR(S8="Annual O&M",S8="Maintenance-only"),IF(T8>10,0,IF(O8<>"",O8,MAX(0,N(G8)+N(K8))*IF(N8<>"",N8,M8))*MAX(0,10-T8+1)),0)))),0) -> 2154934.4 | Z8: =IFERROR(IF(OR(R8<>"Yes",Q8<>"City"),0,IF(S8="Cash capital",IF(T8<=15,IF(O8<>"",O8,MAX(0,N(H8)+N(K8))*IF(N8<>"",N8,M8)),0),IF(S8="Debt service",IF(T8>15,0,AK8*MAX(0,MIN(15-T8+1,U8))),IF(OR(S8="Annual O&M",S8="Maintenance-only"),IF(T8>15,0,IF(O8<>"",O8,MAX(0,N(H8)+N(K8))*IF(N8<>"",N8,M8))*MAX(0,15-T8+1)),0)))),0) -> 3232401.6 | AA8: =IFERROR(IF(OR(R8<>"Yes",Q8<>"City"),0,IF(S8="Cash capital",IF(T8<=20,IF(O8<>"",O8,MAX(0,N(I8)+N(K8))*IF(N8<>"",N8,M8)),0),IF(S8="Debt service",IF(T8>20,0,AL8*MAX(0,MIN(20-T8+1,U8))),IF(OR(S8="Annual O&M",S8="Maintenance-only"),IF(T8>20,0,IF(O8<>"",O8,MAX(0,N(I8)+N(K8))*IF(N8<>"",N8,M8))*MAX(0,20-T8+1)),0)))),0) -> 4309868.8 | AB8: =IFERROR(IF(OR(R8<>"Yes",Q8<>"City"),0,IF(S8="Cash capital",IF(T8<=30,IF(O8<>"",O8,MAX(0,N(J8)+N(K8))*IF(N8<>"",N8,M8)),0),IF(S8="Debt service",IF(T8>30,0,AM8*MAX(0,MIN(30-T8+1,U8))),IF(OR(S8="Annual O&M",S8="Maintenance-only"),IF(T8>30,0,IF(O8<>"",O8,MAX(0,N(J8)+N(K8))*IF(N8<>"",N8,M8))*MAX(0,30-T8+1)),0)))),0) -> 4309868.8 | AC8: =IFERROR(IF(OR(R8<>"Yes",Q8<>"ESD"),0,IF(S8="Cash capital",IF(T8<=5,IF(O8<>"",O8,MAX(0,N(F8)+N(K8))*IF(N8<>"",N8,M8)),0),IF(S8="Debt service",IF(T8>5,0,AI8*MAX(0,MIN(5-T8+1,U8))),IF(OR(S8="Annual O&M",S8="Maintenance-only"),IF(T8>5,0,IF(O8<>"",O8,MAX(0,N(F8)+N(K8))*IF(N8<>"",N8,M8))*MAX(0,5-T8+1)),0)))),0) -> 0 | AD8: =IFERROR(IF(OR(R8<>"Yes",Q8<>"ESD"),0,IF(S8="Cash capital",IF(T8<=10,IF(O8<>"",O8,MAX(0,N(G8)+N(K8))*IF(N8<>"",N8,M8)),0),IF(S8="Debt service",IF(T8>10,0,AJ8*MAX(0,MIN(10-T8+1,U8))),IF(OR(S8="Annual O&M",S8="Maintenance-only"),IF(T8>10,0,IF(O8<>"",O8,MAX(0,N(G8)+N(K8))*IF(N8<>"",N8,M8))*MAX(0,10-T8+1)),0)))),0) -> 0 | AE8: =IFERROR(IF(OR(R8<>"Yes",Q8<>"ESD"),0,IF(S8="Cash capital",IF(T8<=15,IF(O8<>"",O8,MAX(0,N(H8)+N(K8))*IF(N8<>"",N8,M8)),0),IF(S8="Debt service",IF(T8>15,0,AK8*MAX(0,MIN(15-T8+1,U8))),IF(OR(S8="Annual O&M",S8="Maintenance-only"),IF(T8>15,0,IF(O8<>"",O8,MAX(0,N(H8)+N(K8))*IF(N8<>"",N8,M8))*MAX(0,15-T8+1)),0)))),0) -> 0 | AF8: =IFERROR(IF(OR(R8<>"Yes",Q8<>"ESD"),0,IF(S8="Cash capital",IF(T8<=20,IF(O8<>"",O8,MAX(0,N(I8)+N(K8))*IF(N8<>"",N8,M8)),0),IF(S8="Debt service",IF(T8>20,0,AL8*MAX(0,MIN(20-T8+1,U8))),IF(OR(S8="Annual O&M",S8="Maintenance-only"),IF(T8>20,0,IF(O8<>"",O8,MAX(0,N(I8)+N(K8))*IF(N8<>"",N8,M8))*MAX(0,20-T8+1)),0)))),0) -> 0 | AG8: =IFERROR(IF(OR(R8<>"Yes",Q8<>"ESD"),0,IF(S8="Cash capital",IF(T8<=30,IF(O8<>"",O8,MAX(0,N(J8)+N(K8))*IF(N8<>"",N8,M8)),0),IF(S8="Debt service",IF(T8>30,0,AM8*MAX(0,MIN(30-T8+1,U8))),IF(OR(S8="Annual O&M",S8="Maintenance-only"),IF(T8>30,0,IF(O8<>"",O8,MAX(0,N(J8)+N(K8))*IF(N8<>"",N8,M8))*MAX(0,30-T8+1)),0)))),0) -> 0 | AH8: Gravity sewer planning allowance; actual basin/topography should override. | Takeoff factor: 300 LF per developed acre; confidence Low; validate w/ Engineer/Public Works. | AI8: =IFERROR(IF(U8>0,IF(O8<>"",O8,MAX(0,N(F8)+N(K8))*IF(N8<>"",N8,M8))*IF(V8=0,1/U8,V8/(1-(1+V8)^(-U8))),0),0) -> 215493.44 | AJ8: =IFERROR(IF(U8>0,IF(O8<>"",O8,MAX(0,N(G8)+N(K8))*IF(N8<>"",N8,M8))*IF(V8=0,1/U8,V8/(1-(1+V8)^(-U8))),0),0) -> 215493.44 | AK8: =IFERROR(IF(U8>0,IF(O8<>"",O8,MAX(0,N(H8)+N(K8))*IF(N8<>"",N8,M8))*IF(V8=0,1/U8,V8/(1-(1+V8)^(-U8))),0),0) -> 215493.44 | AL8: =IFERROR(IF(U8>0,IF(O8<>"",O8,MAX(0,N(I8)+N(K8))*IF(N8<>"",N8,M8))*IF(V8=0,1/U8,V8/(1-(1+V8)^(-U8))),0),0) -> 215493.44 | AM8: =IFERROR(IF(U8>0,IF(O8<>"",O8,MAX(0,N(J8)+N(K8))*IF(N8<>"",N8,M8))*IF(V8=0,1/U8,V8/(1-(1+V8)^(-U8))),0),0) -> 215493.44
A9: Force main | B9: City | C9: captured acres | D9: linear ft | E9: 40 LF/ac | F9: ='03_Multi_Horizon_Results'!$B$5*'12_Takeoff_Assumptions'!$B$5 -> 1150 | G9: ='03_Multi_Horizon_Results'!$C$5*'12_Takeoff_Assumptions'!$B$5 -> 1150 | H9: ='03_Multi_Horizon_Results'!$D$5*'12_Takeoff_Assumptions'!$B$5 -> 1150 | I9: ='03_Multi_Horizon_Results'!$E$5*'12_Takeoff_Assumptions'!$B$5 -> 1150 | J9: ='03_Multi_Horizon_Results'!$F$5*'12_Takeoff_Assumptions'!$B$5 -> 1150 | L9: =MAX(0,N(G9)+N(K9)) -> 1150 | M9: 225 | P9: =IFERROR(IF(O9<>"",O9,L9*IF(N9<>"",N9,M9)),0) -> 258750 | Q9: City | R9: Yes | S9: Debt service | T9: 1 | U9: 20 | V9: 0.045 | W9: =IFERROR(IF(AND(R9="Yes",S9="Debt service",U9>0),IF(V9=0,P9/U9,P9*V9/(1-(1+V9)^(-U9))),0),0) -> 19891.702 | X9: =IFERROR(IF(OR(R9<>"Yes",Q9<>"City"),0,IF(S9="Cash capital",IF(T9<=5,IF(O9<>"",O9,MAX(0,N(F9)+N(K9))*IF(N9<>"",N9,M9)),0),IF(S9="Debt service",IF(T9>5,0,AI9*MAX(0,MIN(5-T9+1,U9))),IF(OR(S9="Annual O&M",S9="Maintenance-only"),IF(T9>5,0,IF(O9<>"",O9,MAX(0,N(F9)+N(K9))*IF(N9<>"",N9,M9))*MAX(0,5-T9+1)),0)))),0) -> 99458.512 | Y9: =IFERROR(IF(OR(R9<>"Yes",Q9<>"City"),0,IF(S9="Cash capital",IF(T9<=10,IF(O9<>"",O9,MAX(0,N(G9)+N(K9))*IF(N9<>"",N9,M9)),0),IF(S9="Debt service",IF(T9>10,0,AJ9*MAX(0,MIN(10-T9+1,U9))),IF(OR(S9="Annual O&M",S9="Maintenance-only"),IF(T9>10,0,IF(O9<>"",O9,MAX(0,N(G9)+N(K9))*IF(N9<>"",N9,M9))*MAX(0,10-T9+1)),0)))),0) -> 198917.02 | Z9: =IFERROR(IF(OR(R9<>"Yes",Q9<>"City"),0,IF(S9="Cash capital",IF(T9<=15,IF(O9<>"",O9,MAX(0,N(H9)+N(K9))*IF(N9<>"",N9,M9)),0),IF(S9="Debt service",IF(T9>15,0,AK9*MAX(0,MIN(15-T9+1,U9))),IF(OR(S9="Annual O&M",S9="Maintenance-only"),IF(T9>15,0,IF(O9<>"",O9,MAX(0,N(H9)+N(K9))*IF(N9<>"",N9,M9))*MAX(0,15-T9+1)),0)))),0) -> 298375.54 | AA9: =IFERROR(IF(OR(R9<>"Yes",Q9<>"City"),0,IF(S9="Cash capital",IF(T9<=20,IF(O9<>"",O9,MAX(0,N(I9)+N(K9))*IF(N9<>"",N9,M9)),0),IF(S9="Debt service",IF(T9>20,0,AL9*MAX(0,MIN(20-T9+1,U9))),IF(OR(S9="Annual O&M",S9="Maintenance-only"),IF(T9>20,0,IF(O9<>"",O9,MAX(0,N(I9)+N(K9))*IF(N9<>"",N9,M9))*MAX(0,20-T9+1)),0)))),0) -> 397834.05 | AB9: =IFERROR(IF(OR(R9<>"Yes",Q9<>"City"),0,IF(S9="Cash capital",IF(T9<=30,IF(O9<>"",O9,MAX(0,N(J9)+N(K9))*IF(N9<>"",N9,M9)),0),IF(S9="Debt service",IF(T9>30,0,AM9*MAX(0,MIN(30-T9+1,U9))),IF(OR(S9="Annual O&M",S9="Maintenance-only"),IF(T9>30,0,IF(O9<>"",O9,MAX(0,N(J9)+N(K9))*IF(N9<>"",N9,M9))*MAX(0,30-T9+1)),0)))),0) -> 397834.05 | AC9: =IFERROR(IF(OR(R9<>"Yes",Q9<>"ESD"),0,IF(S9="Cash capital",IF(T9<=5,IF(O9<>"",O9,MAX(0,N(F9)+N(K9))*IF(N9<>"",N9,M9)),0),IF(S9="Debt service",IF(T9>5,0,AI9*MAX(0,MIN(5-T9+1,U9))),IF(OR(S9="Annual O&M",S9="Maintenance-only"),IF(T9>5,0,IF(O9<>"",O9,MAX(0,N(F9)+N(K9))*IF(N9<>"",N9,M9))*MAX(0,5-T9+1)),0)))),0) -> 0 | AD9: =IFERROR(IF(OR(R9<>"Yes",Q9<>"ESD"),0,IF(S9="Cash capital",IF(T9<=10,IF(O9<>"",O9,MAX(0,N(G9)+N(K9))*IF(N9<>"",N9,M9)),0),IF(S9="Debt service",IF(T9>10,0,AJ9*MAX(0,MIN(10-T9+1,U9))),IF(OR(S9="Annual O&M",S9="Maintenance-only"),IF(T9>10,0,IF(O9<>"",O9,MAX(0,N(G9)+N(K9))*IF(N9<>"",N9,M9))*MAX(0,10-T9+1)),0)))),0) -> 0 | AE9: =IFERROR(IF(OR(R9<>"Yes",Q9<>"ESD"),0,IF(S9="Cash capital",IF(T9<=15,IF(O9<>"",O9,MAX(0,N(H9)+N(K9))*IF(N9<>"",N9,M9)),0),IF(S9="Debt service",IF(T9>15,0,AK9*MAX(0,MIN(15-T9+1,U9))),IF(OR(S9="Annual O&M",S9="Maintenance-only"),IF(T9>15,0,IF(O9<>"",O9,MAX(0,N(H9)+N(K9))*IF(N9<>"",N9,M9))*MAX(0,15-T9+1)),0)))),0) -> 0 | AF9: =IFERROR(IF(OR(R9<>"Yes",Q9<>"ESD"),0,IF(S9="Cash capital",IF(T9<=20,IF(O9<>"",O9,MAX(0,N(I9)+N(K9))*IF(N9<>"",N9,M9)),0),IF(S9="Debt service",IF(T9>20,0,AL9*MAX(0,MIN(20-T9+1,U9))),IF(OR(S9="Annual O&M",S9="Maintenance-only"),IF(T9>20,0,IF(O9<>"",O9,MAX(0,N(I9)+N(K9))*IF(N9<>"",N9,M9))*MAX(0,20-T9+1)),0)))),0) -> 0 | AG9: =IFERROR(IF(OR(R9<>"Yes",Q9<>"ESD"),0,IF(S9="Cash capital",IF(T9<=30,IF(O9<>"",O9,MAX(0,N(J9)+N(K9))*IF(N9<>"",N9,M9)),0),IF(S9="Debt service",IF(T9>30,0,AM9*MAX(0,MIN(30-T9+1,U9))),IF(OR(S9="Annual O&M",S9="Maintenance-only"),IF(T9>30,0,IF(O9<>"",O9,MAX(0,N(J9)+N(K9))*IF(N9<>"",N9,M9))*MAX(0,30-T9+1)),0)))),0) -> 0 | AH9: Force-main planning allowance; actual need depends on lift-station/basin design. | Takeoff factor: 40 LF per developed acre; confidence Low; validate w/ Engineer/Public Works. | AI9: =IFERROR(IF(U9>0,IF(O9<>"",O9,MAX(0,N(F9)+N(K9))*IF(N9<>"",N9,M9))*IF(V9=0,1/U9,V9/(1-(1+V9)^(-U9))),0),0) -> 19891.702 | AJ9: =IFERROR(IF(U9>0,IF(O9<>"",O9,MAX(0,N(G9)+N(K9))*IF(N9<>"",N9,M9))*IF(V9=0,1/U9,V9/(1-(1+V9)^(-U9))),0),0) -> 19891.702 | AK9: =IFERROR(IF(U9>0,IF(O9<>"",O9,MAX(0,N(H9)+N(K9))*IF(N9<>"",N9,M9))*IF(V9=0,1/U9,V9/(1-(1+V9)^(-U9))),0),0) -> 19891.702 | AL9: =IFERROR(IF(U9>0,IF(O9<>"",O9,MAX(0,N(I9)+N(K9))*IF(N9<>"",N9,M9))*IF(V9=0,1/U9,V9/(1-(1+V9)^(-U9))),0),0) -> 19891.702 | AM9: =IFERROR(IF(U9>0,IF(O9<>"",O9,MAX(0,N(J9)+N(K9))*IF(N9<>"",N9,M9))*IF(V9=0,1/U9,V9/(1-(1+V9)^(-U9))),0),0) -> 19891.702
A10: Lift stations | B10: City | C10: sewer demand MGD | D10: each | E10: threshold 0.25 MGD | F10: =IF((('03_Multi_Horizon_Results'!$B$22/'Advanced Inputs'!$D$50)*'12_Takeoff_Assumptions'!$B$14/1000000)>'12_Takeoff_Assumptions'!$B$15,ROUNDUP((('03_Multi_Horizon_Results'!$B$22/'Advanced Inputs'!$D$50)*'12_Takeoff_Assumptions'!$B$14/1000000)/'12_Takeoff_Assumptions'!$B$15,0),0) -> 0 | G10: =IF((('03_Multi_Horizon_Results'!$C$22/'Advanced Inputs'!$D$50)*'12_Takeoff_Assumptions'!$B$14/1000000)>'12_Takeoff_Assumptions'!$B$15,ROUNDUP((('03_Multi_Horizon_Results'!$C$22/'Advanced Inputs'!$D$50)*'12_Takeoff_Assumptions'!$B$14/1000000)/'12_Takeoff_Assumptions'!$B$15,0),0) -> 0 | H10: =IF((('03_Multi_Horizon_Results'!$D$22/'Advanced Inputs'!$D$50)*'12_Takeoff_Assumptions'!$B$14/1000000)>'12_Takeoff_Assumptions'!$B$15,ROUNDUP((('03_Multi_Horizon_Results'!$D$22/'Advanced Inputs'!$D$50)*'12_Takeoff_Assumptions'!$B$14/1000000)/'12_Takeoff_Assumptions'!$B$15,0),0) -> 0 | I10: =IF((('03_Multi_Horizon_Results'!$E$22/'Advanced Inputs'!$D$50)*'12_Takeoff_Assumptions'!$B$14/1000000)>'12_Takeoff_Assumptions'!$B$15,ROUNDUP((('03_Multi_Horizon_Results'!$E$22/'Advanced Inputs'!$D$50)*'12_Takeoff_Assumptions'!$B$14/1000000)/'12_Takeoff_Assumptions'!$B$15,0),0) -> 0 | J10: =IF((('03_Multi_Horizon_Results'!$F$22/'Advanced Inputs'!$D$50)*'12_Takeoff_Assumptions'!$B$14/1000000)>'12_Takeoff_Assumptions'!$B$15,ROUNDUP((('03_Multi_Horizon_Results'!$F$22/'Advanced Inputs'!$D$50)*'12_Takeoff_Assumptions'!$B$14/1000000)/'12_Takeoff_Assumptions'!$B$15,0),0) -> 0 | L10: =MAX(0,N(G10)+N(K10)) -> 0 | M10: 1250000 | P10: =IFERROR(IF(O10<>"",O10,L10*IF(N10<>"",N10,M10)),0) -> 0 | Q10: City | R10: Yes | S10: Debt service | T10: 1 | U10: 20 | V10: 0.045 | W10: =IFERROR(IF(AND(R10="Yes",S10="Debt service",U10>0),IF(V10=0,P10/U10,P10*V10/(1-(1+V10)^(-U10))),0),0) -> 0 | X10: =IFERROR(IF(OR(R10<>"Yes",Q10<>"City"),0,IF(S10="Cash capital",IF(T10<=5,IF(O10<>"",O10,MAX(0,N(F10)+N(K10))*IF(N10<>"",N10,M10)),0),IF(S10="Debt service",IF(T10>5,0,AI10*MAX(0,MIN(5-T10+1,U10))),IF(OR(S10="Annual O&M",S10="Maintenance-only"),IF(T10>5,0,IF(O10<>"",O10,MAX(0,N(F10)+N(K10))*IF(N10<>"",N10,M10))*MAX(0,5-T10+1)),0)))),0) -> 0 | Y10: =IFERROR(IF(OR(R10<>"Yes",Q10<>"City"),0,IF(S10="Cash capital",IF(T10<=10,IF(O10<>"",O10,MAX(0,N(G10)+N(K10))*IF(N10<>"",N10,M10)),0),IF(S10="Debt service",IF(T10>10,0,AJ10*MAX(0,MIN(10-T10+1,U10))),IF(OR(S10="Annual O&M",S10="Maintenance-only"),IF(T10>10,0,IF(O10<>"",O10,MAX(0,N(G10)+N(K10))*IF(N10<>"",N10,M10))*MAX(0,10-T10+1)),0)))),0) -> 0 | Z10: =IFERROR(IF(OR(R10<>"Yes",Q10<>"City"),0,IF(S10="Cash capital",IF(T10<=15,IF(O10<>"",O10,MAX(0,N(H10)+N(K10))*IF(N10<>"",N10,M10)),0),IF(S10="Debt service",IF(T10>15,0,AK10*MAX(0,MIN(15-T10+1,U10))),IF(OR(S10="Annual O&M",S10="Maintenance-only"),IF(T10>15,0,IF(O10<>"",O10,MAX(0,N(H10)+N(K10))*IF(N10<>"",N10,M10))*MAX(0,15-T10+1)),0)))),0) -> 0 | AA10: =IFERROR(IF(OR(R10<>"Yes",Q10<>"City"),0,IF(S10="Cash capital",IF(T10<=20,IF(O10<>"",O10,MAX(0,N(I10)+N(K10))*IF(N10<>"",N10,M10)),0),IF(S10="Debt service",IF(T10>20,0,AL10*MAX(0,MIN(20-T10+1,U10))),IF(OR(S10="Annual O&M",S10="Maintenance-only"),IF(T10>20,0,IF(O10<>"",O10,MAX(0,N(I10)+N(K10))*IF(N10<>"",N10,M10))*MAX(0,20-T10+1)),0)))),0) -> 0 | AB10: =IFERROR(IF(OR(R10<>"Yes",Q10<>"City"),0,IF(S10="Cash capital",IF(T10<=30,IF(O10<>"",O10,MAX(0,N(J10)+N(K10))*IF(N10<>"",N10,M10)),0),IF(S10="Debt service",IF(T10>30,0,AM10*MAX(0,MIN(30-T10+1,U10))),IF(OR(S10="Annual O&M",S10="Maintenance-only"),IF(T10>30,0,IF(O10<>"",O10,MAX(0,N(J10)+N(K10))*IF(N10<>"",N10,M10))*MAX(0,30-T10+1)),0)))),0) -> 0 | AC10: =IFERROR(IF(OR(R10<>"Yes",Q10<>"ESD"),0,IF(S10="Cash capital",IF(T10<=5,IF(O10<>"",O10,MAX(0,N(F10)+N(K10))*IF(N10<>"",N10,M10)),0),IF(S10="Debt service",IF(T10>5,0,AI10*MAX(0,MIN(5-T10+1,U10))),IF(OR(S10="Annual O&M",S10="Maintenance-only"),IF(T10>5,0,IF(O10<>"",O10,MAX(0,N(F10)+N(K10))*IF(N10<>"",N10,M10))*MAX(0,5-T10+1)),0)))),0) -> 0 | AD10: =IFERROR(IF(OR(R10<>"Yes",Q10<>"ESD"),0,IF(S10="Cash capital",IF(T10<=10,IF(O10<>"",O10,MAX(0,N(G10)+N(K10))*IF(N10<>"",N10,M10)),0),IF(S10="Debt service",IF(T10>10,0,AJ10*MAX(0,MIN(10-T10+1,U10))),IF(OR(S10="Annual O&M",S10="Maintenance-only"),IF(T10>10,0,IF(O10<>"",O10,MAX(0,N(G10)+N(K10))*IF(N10<>"",N10,M10))*MAX(0,10-T10+1)),0)))),0) -> 0 | AE10: =IFERROR(IF(OR(R10<>"Yes",Q10<>"ESD"),0,IF(S10="Cash capital",IF(T10<=15,IF(O10<>"",O10,MAX(0,N(H10)+N(K10))*IF(N10<>"",N10,M10)),0),IF(S10="Debt service",IF(T10>15,0,AK10*MAX(0,MIN(15-T10+1,U10))),IF(OR(S10="Annual O&M",S10="Maintenance-only"),IF(T10>15,0,IF(O10<>"",O10,MAX(0,N(H10)+N(K10))*IF(N10<>"",N10,M10))*MAX(0,15-T10+1)),0)))),0) -> 0 | AF10: =IFERROR(IF(OR(R10<>"Yes",Q10<>"ESD"),0,IF(S10="Cash capital",IF(T10<=20,IF(O10<>"",O10,MAX(0,N(I10)+N(K10))*IF(N10<>"",N10,M10)),0),IF(S10="Debt service",IF(T10>20,0,AL10*MAX(0,MIN(20-T10+1,U10))),IF(OR(S10="Annual O&M",S10="Maintenance-only"),IF(T10>20,0,IF(O10<>"",O10,MAX(0,N(I10)+N(K10))*IF(N10<>"",N10,M10))*MAX(0,20-T10+1)),0)))),0) -> 0 | AG10: =IFERROR(IF(OR(R10<>"Yes",Q10<>"ESD"),0,IF(S10="Cash capital",IF(T10<=30,IF(O10<>"",O10,MAX(0,N(J10)+N(K10))*IF(N10<>"",N10,M10)),0),IF(S10="Debt service",IF(T10>30,0,AM10*MAX(0,MIN(30-T10+1,U10))),IF(OR(S10="Annual O&M",S10="Maintenance-only"),IF(T10>30,0,IF(O10<>"",O10,MAX(0,N(J10)+N(K10))*IF(N10<>"",N10,M10))*MAX(0,30-T10+1)),0)))),0) -> 0 | AH10: Planning trigger only; topography and basin engineer review required. | Takeoff factor: 0.25 MGD; confidence Low; validate w/ Engineer/Public Works. | AI10: =IFERROR(IF(U10>0,IF(O10<>"",O10,MAX(0,N(F10)+N(K10))*IF(N10<>"",N10,M10))*IF(V10=0,1/U10,V10/(1-(1+V10)^(-U10))),0),0) -> 0 | AJ10: =IFERROR(IF(U10>0,IF(O10<>"",O10,MAX(0,N(G10)+N(K10))*IF(N10<>"",N10,M10))*IF(V10=0,1/U10,V10/(1-(1+V10)^(-U10))),0),0) -> 0 | AK10: =IFERROR(IF(U10>0,IF(O10<>"",O10,MAX(0,N(H10)+N(K10))*IF(N10<>"",N10,M10))*IF(V10=0,1/U10,V10/(1-(1+V10)^(-U10))),0),0) -> 0 | AL10: =IFERROR(IF(U10>0,IF(O10<>"",O10,MAX(0,N(I10)+N(K10))*IF(N10<>"",N10,M10))*IF(V10=0,1/U10,V10/(1-(1+V10)^(-U10))),0),0) -> 0 | AM10: =IFERROR(IF(U10>0,IF(O10<>"",O10,MAX(0,N(J10)+N(K10))*IF(N10<>"",N10,M10))*IF(V10=0,1/U10,V10/(1-(1+V10)^(-U10))),0),0) -> 0
A11: WWTP expansion capacity | B11: City | C11: sewer demand MGD | D11: MGD | E11: 250 gpd/LUE | F11: =(('03_Multi_Horizon_Results'!$B$22/'Advanced Inputs'!$D$50)*'12_Takeoff_Assumptions'!$B$14/1000000) -> 0.055 | G11: =(('03_Multi_Horizon_Results'!$C$22/'Advanced Inputs'!$D$50)*'12_Takeoff_Assumptions'!$B$14/1000000) -> 0.055 | H11: =(('03_Multi_Horizon_Results'!$D$22/'Advanced Inputs'!$D$50)*'12_Takeoff_Assumptions'!$B$14/1000000) -> 0.055 | I11: =(('03_Multi_Horizon_Results'!$E$22/'Advanced Inputs'!$D$50)*'12_Takeoff_Assumptions'!$B$14/1000000) -> 0.055 | J11: =(('03_Multi_Horizon_Results'!$F$22/'Advanced Inputs'!$D$50)*'12_Takeoff_Assumptions'!$B$14/1000000) -> 0.055 | L11: =MAX(0,N(G11)+N(K11)) -> 0.055 | M11: 6000000 | P11: =IFERROR(IF(O11<>"",O11,L11*IF(N11<>"",N11,M11)),0) -> 330000 | Q11: City | R11: Yes | S11: Debt service | T11: 1 | U11: 20 | V11: 0.045 | W11: =IFERROR(IF(AND(R11="Yes",S11="Debt service",U11>0),IF(V11=0,P11/U11,P11*V11/(1-(1+V11)^(-U11))),0),0) -> 25369.128 | X11: =IFERROR(IF(OR(R11<>"Yes",Q11<>"City"),0,IF(S11="Cash capital",IF(T11<=5,IF(O11<>"",O11,MAX(0,N(F11)+N(K11))*IF(N11<>"",N11,M11)),0),IF(S11="Debt service",IF(T11>5,0,AI11*MAX(0,MIN(5-T11+1,U11))),IF(OR(S11="Annual O&M",S11="Maintenance-only"),IF(T11>5,0,IF(O11<>"",O11,MAX(0,N(F11)+N(K11))*IF(N11<>"",N11,M11))*MAX(0,5-T11+1)),0)))),0) -> 126845.64 | Y11: =IFERROR(IF(OR(R11<>"Yes",Q11<>"City"),0,IF(S11="Cash capital",IF(T11<=10,IF(O11<>"",O11,MAX(0,N(G11)+N(K11))*IF(N11<>"",N11,M11)),0),IF(S11="Debt service",IF(T11>10,0,AJ11*MAX(0,MIN(10-T11+1,U11))),IF(OR(S11="Annual O&M",S11="Maintenance-only"),IF(T11>10,0,IF(O11<>"",O11,MAX(0,N(G11)+N(K11))*IF(N11<>"",N11,M11))*MAX(0,10-T11+1)),0)))),0) -> 253691.28 | Z11: =IFERROR(IF(OR(R11<>"Yes",Q11<>"City"),0,IF(S11="Cash capital",IF(T11<=15,IF(O11<>"",O11,MAX(0,N(H11)+N(K11))*IF(N11<>"",N11,M11)),0),IF(S11="Debt service",IF(T11>15,0,AK11*MAX(0,MIN(15-T11+1,U11))),IF(OR(S11="Annual O&M",S11="Maintenance-only"),IF(T11>15,0,IF(O11<>"",O11,MAX(0,N(H11)+N(K11))*IF(N11<>"",N11,M11))*MAX(0,15-T11+1)),0)))),0) -> 380536.91 | AA11: =IFERROR(IF(OR(R11<>"Yes",Q11<>"City"),0,IF(S11="Cash capital",IF(T11<=20,IF(O11<>"",O11,MAX(0,N(I11)+N(K11))*IF(N11<>"",N11,M11)),0),IF(S11="Debt service",IF(T11>20,0,AL11*MAX(0,MIN(20-T11+1,U11))),IF(OR(S11="Annual O&M",S11="Maintenance-only"),IF(T11>20,0,IF(O11<>"",O11,MAX(0,N(I11)+N(K11))*IF(N11<>"",N11,M11))*MAX(0,20-T11+1)),0)))),0) -> 507382.55 | AB11: =IFERROR(IF(OR(R11<>"Yes",Q11<>"City"),0,IF(S11="Cash capital",IF(T11<=30,IF(O11<>"",O11,MAX(0,N(J11)+N(K11))*IF(N11<>"",N11,M11)),0),IF(S11="Debt service",IF(T11>30,0,AM11*MAX(0,MIN(30-T11+1,U11))),IF(OR(S11="Annual O&M",S11="Maintenance-only"),IF(T11>30,0,IF(O11<>"",O11,MAX(0,N(J11)+N(K11))*IF(N11<>"",N11,M11))*MAX(0,30-T11+1)),0)))),0) -> 507382.55 | AC11: =IFERROR(IF(OR(R11<>"Yes",Q11<>"ESD"),0,IF(S11="Cash capital",IF(T11<=5,IF(O11<>"",O11,MAX(0,N(F11)+N(K11))*IF(N11<>"",N11,M11)),0),IF(S11="Debt service",IF(T11>5,0,AI11*MAX(0,MIN(5-T11+1,U11))),IF(OR(S11="Annual O&M",S11="Maintenance-only"),IF(T11>5,0,IF(O11<>"",O11,MAX(0,N(F11)+N(K11))*IF(N11<>"",N11,M11))*MAX(0,5-T11+1)),0)))),0) -> 0 | AD11: =IFERROR(IF(OR(R11<>"Yes",Q11<>"ESD"),0,IF(S11="Cash capital",IF(T11<=10,IF(O11<>"",O11,MAX(0,N(G11)+N(K11))*IF(N11<>"",N11,M11)),0),IF(S11="Debt service",IF(T11>10,0,AJ11*MAX(0,MIN(10-T11+1,U11))),IF(OR(S11="Annual O&M",S11="Maintenance-only"),IF(T11>10,0,IF(O11<>"",O11,MAX(0,N(G11)+N(K11))*IF(N11<>"",N11,M11))*MAX(0,10-T11+1)),0)))),0) -> 0 | AE11: =IFERROR(IF(OR(R11<>"Yes",Q11<>"ESD"),0,IF(S11="Cash capital",IF(T11<=15,IF(O11<>"",O11,MAX(0,N(H11)+N(K11))*IF(N11<>"",N11,M11)),0),IF(S11="Debt service",IF(T11>15,0,AK11*MAX(0,MIN(15-T11+1,U11))),IF(OR(S11="Annual O&M",S11="Maintenance-only"),IF(T11>15,0,IF(O11<>"",O11,MAX(0,N(H11)+N(K11))*IF(N11<>"",N11,M11))*MAX(0,15-T11+1)),0)))),0) -> 0 | AF11: =IFERROR(IF(OR(R11<>"Yes",Q11<>"ESD"),0,IF(S11="Cash capital",IF(T11<=20,IF(O11<>"",O11,MAX(0,N(I11)+N(K11))*IF(N11<>"",N11,M11)),0),IF(S11="Debt service",IF(T11>20,0,AL11*MAX(0,MIN(20-T11+1,U11))),IF(OR(S11="Annual O&M",S11="Maintenance-only"),IF(T11>20,0,IF(O11<>"",O11,MAX(0,N(I11)+N(K11))*IF(N11<>"",N11,M11))*MAX(0,20-T11+1)),0)))),0) -> 0 | AG11: =IFERROR(IF(OR(R11<>"Yes",Q11<>"ESD"),0,IF(S11="Cash capital",IF(T11<=30,IF(O11<>"",O11,MAX(0,N(J11)+N(K11))*IF(N11<>"",N11,M11)),0),IF(S11="Debt service",IF(T11>30,0,AM11*MAX(0,MIN(30-T11+1,U11))),IF(OR(S11="Annual O&M",S11="Maintenance-only"),IF(T11>30,0,IF(O11<>"",O11,MAX(0,N(J11)+N(K11))*IF(N11<>"",N11,M11))*MAX(0,30-T11+1)),0)))),0) -> 0 | AH11: Shows estimated sewer demand capacity exposure, not an engineering design directive. | Takeoff factor: 250 gpd per LUE; confidence Low; validate w/ Engineer/Public Works. | AI11: =IFERROR(IF(U11>0,IF(O11<>"",O11,MAX(0,N(F11)+N(K11))*IF(N11<>"",N11,M11))*IF(V11=0,1/U11,V11/(1-(1+V11)^(-U11))),0),0) -> 25369.128 | AJ11: =IFERROR(IF(U11>0,IF(O11<>"",O11,MAX(0,N(G11)+N(K11))*IF(N11<>"",N11,M11))*IF(V11=0,1/U11,V11/(1-(1+V11)^(-U11))),0),0) -> 25369.128 | AK11: =IFERROR(IF(U11>0,IF(O11<>"",O11,MAX(0,N(H11)+N(K11))*IF(N11<>"",N11,M11))*IF(V11=0,1/U11,V11/(1-(1+V11)^(-U11))),0),0) -> 25369.128 | AL11: =IFERROR(IF(U11>0,IF(O11<>"",O11,MAX(0,N(I11)+N(K11))*IF(N11<>"",N11,M11))*IF(V11=0,1/U11,V11/(1-(1+V11)^(-U11))),0),0) -> 25369.128 | AM11: =IFERROR(IF(U11>0,IF(O11<>"",O11,MAX(0,N(J11)+N(K11))*IF(N11<>"",N11,M11))*IF(V11=0,1/U11,V11/(1-(1+V11)^(-U11))),0),0) -> 25369.128
A12: Collector street | B12: City | C12: captured acres | D12: lane-miles | E12: 0.02 lane-mi/ac | F12: ='03_Multi_Horizon_Results'!$B$5*'12_Takeoff_Assumptions'!$B$7 -> 0.575 | G12: ='03_Multi_Horizon_Results'!$C$5*'12_Takeoff_Assumptions'!$B$7 -> 0.575 | H12: ='03_Multi_Horizon_Results'!$D$5*'12_Takeoff_Assumptions'!$B$7 -> 0.575 | I12: ='03_Multi_Horizon_Results'!$E$5*'12_Takeoff_Assumptions'!$B$7 -> 0.575 | J12: ='03_Multi_Horizon_Results'!$F$5*'12_Takeoff_Assumptions'!$B$7 -> 0.575 | L12: =MAX(0,N(G12)+N(K12)) -> 0.575 | M12: 750000 | P12: =IFERROR(IF(O12<>"",O12,L12*IF(N12<>"",N12,M12)),0) -> 431250 | Q12: City | R12: Yes | S12: Debt service | T12: 1 | U12: 20 | V12: 0.045 | W12: =IFERROR(IF(AND(R12="Yes",S12="Debt service",U12>0),IF(V12=0,P12/U12,P12*V12/(1-(1+V12)^(-U12))),0),0) -> 33152.837 | X12: =IFERROR(IF(OR(R12<>"Yes",Q12<>"City"),0,IF(S12="Cash capital",IF(T12<=5,IF(O12<>"",O12,MAX(0,N(F12)+N(K12))*IF(N12<>"",N12,M12)),0),IF(S12="Debt service",IF(T12>5,0,AI12*MAX(0,MIN(5-T12+1,U12))),IF(OR(S12="Annual O&M",S12="Maintenance-only"),IF(T12>5,0,IF(O12<>"",O12,MAX(0,N(F12)+N(K12))*IF(N12<>"",N12,M12))*MAX(0,5-T12+1)),0)))),0) -> 165764.19 | Y12: =IFERROR(IF(OR(R12<>"Yes",Q12<>"City"),0,IF(S12="Cash capital",IF(T12<=10,IF(O12<>"",O12,MAX(0,N(G12)+N(K12))*IF(N12<>"",N12,M12)),0),IF(S12="Debt service",IF(T12>10,0,AJ12*MAX(0,MIN(10-T12+1,U12))),IF(OR(S12="Annual O&M",S12="Maintenance-only"),IF(T12>10,0,IF(O12<>"",O12,MAX(0,N(G12)+N(K12))*IF(N12<>"",N12,M12))*MAX(0,10-T12+1)),0)))),0) -> 331528.37 | Z12: =IFERROR(IF(OR(R12<>"Yes",Q12<>"City"),0,IF(S12="Cash capital",IF(T12<=15,IF(O12<>"",O12,MAX(0,N(H12)+N(K12))*IF(N12<>"",N12,M12)),0),IF(S12="Debt service",IF(T12>15,0,AK12*MAX(0,MIN(15-T12+1,U12))),IF(OR(S12="Annual O&M",S12="Maintenance-only"),IF(T12>15,0,IF(O12<>"",O12,MAX(0,N(H12)+N(K12))*IF(N12<>"",N12,M12))*MAX(0,15-T12+1)),0)))),0) -> 497292.56 | AA12: =IFERROR(IF(OR(R12<>"Yes",Q12<>"City"),0,IF(S12="Cash capital",IF(T12<=20,IF(O12<>"",O12,MAX(0,N(I12)+N(K12))*IF(N12<>"",N12,M12)),0),IF(S12="Debt service",IF(T12>20,0,AL12*MAX(0,MIN(20-T12+1,U12))),IF(OR(S12="Annual O&M",S12="Maintenance-only"),IF(T12>20,0,IF(O12<>"",O12,MAX(0,N(I12)+N(K12))*IF(N12<>"",N12,M12))*MAX(0,20-T12+1)),0)))),0) -> 663056.74 | AB12: =IFERROR(IF(OR(R12<>"Yes",Q12<>"City"),0,IF(S12="Cash capital",IF(T12<=30,IF(O12<>"",O12,MAX(0,N(J12)+N(K12))*IF(N12<>"",N12,M12)),0),IF(S12="Debt service",IF(T12>30,0,AM12*MAX(0,MIN(30-T12+1,U12))),IF(OR(S12="Annual O&M",S12="Maintenance-only"),IF(T12>30,0,IF(O12<>"",O12,MAX(0,N(J12)+N(K12))*IF(N12<>"",N12,M12))*MAX(0,30-T12+1)),0)))),0) -> 663056.74 | AC12: =IFERROR(IF(OR(R12<>"Yes",Q12<>"ESD"),0,IF(S12="Cash capital",IF(T12<=5,IF(O12<>"",O12,MAX(0,N(F12)+N(K12))*IF(N12<>"",N12,M12)),0),IF(S12="Debt service",IF(T12>5,0,AI12*MAX(0,MIN(5-T12+1,U12))),IF(OR(S12="Annual O&M",S12="Maintenance-only"),IF(T12>5,0,IF(O12<>"",O12,MAX(0,N(F12)+N(K12))*IF(N12<>"",N12,M12))*MAX(0,5-T12+1)),0)))),0) -> 0 | AD12: =IFERROR(IF(OR(R12<>"Yes",Q12<>"ESD"),0,IF(S12="Cash capital",IF(T12<=10,IF(O12<>"",O12,MAX(0,N(G12)+N(K12))*IF(N12<>"",N12,M12)),0),IF(S12="Debt service",IF(T12>10,0,AJ12*MAX(0,MIN(10-T12+1,U12))),IF(OR(S12="Annual O&M",S12="Maintenance-only"),IF(T12>10,0,IF(O12<>"",O12,MAX(0,N(G12)+N(K12))*IF(N12<>"",N12,M12))*MAX(0,10-T12+1)),0)))),0) -> 0 | AE12: =IFERROR(IF(OR(R12<>"Yes",Q12<>"ESD"),0,IF(S12="Cash capital",IF(T12<=15,IF(O12<>"",O12,MAX(0,N(H12)+N(K12))*IF(N12<>"",N12,M12)),0),IF(S12="Debt service",IF(T12>15,0,AK12*MAX(0,MIN(15-T12+1,U12))),IF(OR(S12="Annual O&M",S12="Maintenance-only"),IF(T12>15,0,IF(O12<>"",O12,MAX(0,N(H12)+N(K12))*IF(N12<>"",N12,M12))*MAX(0,15-T12+1)),0)))),0) -> 0 | AF12: =IFERROR(IF(OR(R12<>"Yes",Q12<>"ESD"),0,IF(S12="Cash capital",IF(T12<=20,IF(O12<>"",O12,MAX(0,N(I12)+N(K12))*IF(N12<>"",N12,M12)),0),IF(S12="Debt service",IF(T12>20,0,AL12*MAX(0,MIN(20-T12+1,U12))),IF(OR(S12="Annual O&M",S12="Maintenance-only"),IF(T12>20,0,IF(O12<>"",O12,MAX(0,N(I12)+N(K12))*IF(N12<>"",N12,M12))*MAX(0,20-T12+1)),0)))),0) -> 0 | AG12: =IFERROR(IF(OR(R12<>"Yes",Q12<>"ESD"),0,IF(S12="Cash capital",IF(T12<=30,IF(O12<>"",O12,MAX(0,N(J12)+N(K12))*IF(N12<>"",N12,M12)),0),IF(S12="Debt service",IF(T12>30,0,AM12*MAX(0,MIN(30-T12+1,U12))),IF(OR(S12="Annual O&M",S12="Maintenance-only"),IF(T12>30,0,IF(O12<>"",O12,MAX(0,N(J12)+N(K12))*IF(N12<>"",N12,M12))*MAX(0,30-T12+1)),0)))),0) -> 0 | AH12: Thoroughfare planning allowance; actual route/section should override. | Takeoff factor: 0.02 lane-mile per developed acre; confidence Low; validate w/ Public Works/Engineer. | AI12: =IFERROR(IF(U12>0,IF(O12<>"",O12,MAX(0,N(F12)+N(K12))*IF(N12<>"",N12,M12))*IF(V12=0,1/U12,V12/(1-(1+V12)^(-U12))),0),0) -> 33152.837 | AJ12: =IFERROR(IF(U12>0,IF(O12<>"",O12,MAX(0,N(G12)+N(K12))*IF(N12<>"",N12,M12))*IF(V12=0,1/U12,V12/(1-(1+V12)^(-U12))),0),0) -> 33152.837 | AK12: =IFERROR(IF(U12>0,IF(O12<>"",O12,MAX(0,N(H12)+N(K12))*IF(N12<>"",N12,M12))*IF(V12=0,1/U12,V12/(1-(1+V12)^(-U12))),0),0) -> 33152.837 | AL12: =IFERROR(IF(U12>0,IF(O12<>"",O12,MAX(0,N(I12)+N(K12))*IF(N12<>"",N12,M12))*IF(V12=0,1/U12,V12/(1-(1+V12)^(-U12))),0),0) -> 33152.837 | AM12: =IFERROR(IF(U12>0,IF(O12<>"",O12,MAX(0,N(J12)+N(K12))*IF(N12<>"",N12,M12))*IF(V12=0,1/U12,V12/(1-(1+V12)^(-U12))),0),0) -> 33152.837
A13: Local street | B13: City | C13: captured acres | D13: lane-miles | E13: 120 centerline LF/ac × 2 lanes | F13: =('03_Multi_Horizon_Results'!$B$5*'12_Takeoff_Assumptions'!$B$6/5280)*'12_Takeoff_Assumptions'!$B$8 -> 1.3068182 | G13: =('03_Multi_Horizon_Results'!$C$5*'12_Takeoff_Assumptions'!$B$6/5280)*'12_Takeoff_Assumptions'!$B$8 -> 1.3068182 | H13: =('03_Multi_Horizon_Results'!$D$5*'12_Takeoff_Assumptions'!$B$6/5280)*'12_Takeoff_Assumptions'!$B$8 -> 1.3068182 | I13: =('03_Multi_Horizon_Results'!$E$5*'12_Takeoff_Assumptions'!$B$6/5280)*'12_Takeoff_Assumptions'!$B$8 -> 1.3068182 | J13: =('03_Multi_Horizon_Results'!$F$5*'12_Takeoff_Assumptions'!$B$6/5280)*'12_Takeoff_Assumptions'!$B$8 -> 1.3068182 | L13: =MAX(0,N(G13)+N(K13)) -> 1.3068182 | M13: 600000 | P13: =IFERROR(IF(O13<>"",O13,L13*IF(N13<>"",N13,M13)),0) -> 784090.91 | Q13: City | R13: Yes | S13: Debt service | T13: 1 | U13: 20 | V13: 0.045 | W13: =IFERROR(IF(AND(R13="Yes",S13="Debt service",U13>0),IF(V13=0,P13/U13,P13*V13/(1-(1+V13)^(-U13))),0),0) -> 60277.886 | X13: =IFERROR(IF(OR(R13<>"Yes",Q13<>"City"),0,IF(S13="Cash capital",IF(T13<=5,IF(O13<>"",O13,MAX(0,N(F13)+N(K13))*IF(N13<>"",N13,M13)),0),IF(S13="Debt service",IF(T13>5,0,AI13*MAX(0,MIN(5-T13+1,U13))),IF(OR(S13="Annual O&M",S13="Maintenance-only"),IF(T13>5,0,IF(O13<>"",O13,MAX(0,N(F13)+N(K13))*IF(N13<>"",N13,M13))*MAX(0,5-T13+1)),0)))),0) -> 301389.43 | Y13: =IFERROR(IF(OR(R13<>"Yes",Q13<>"City"),0,IF(S13="Cash capital",IF(T13<=10,IF(O13<>"",O13,MAX(0,N(G13)+N(K13))*IF(N13<>"",N13,M13)),0),IF(S13="Debt service",IF(T13>10,0,AJ13*MAX(0,MIN(10-T13+1,U13))),IF(OR(S13="Annual O&M",S13="Maintenance-only"),IF(T13>10,0,IF(O13<>"",O13,MAX(0,N(G13)+N(K13))*IF(N13<>"",N13,M13))*MAX(0,10-T13+1)),0)))),0) -> 602778.86 | Z13: =IFERROR(IF(OR(R13<>"Yes",Q13<>"City"),0,IF(S13="Cash capital",IF(T13<=15,IF(O13<>"",O13,MAX(0,N(H13)+N(K13))*IF(N13<>"",N13,M13)),0),IF(S13="Debt service",IF(T13>15,0,AK13*MAX(0,MIN(15-T13+1,U13))),IF(OR(S13="Annual O&M",S13="Maintenance-only"),IF(T13>15,0,IF(O13<>"",O13,MAX(0,N(H13)+N(K13))*IF(N13<>"",N13,M13))*MAX(0,15-T13+1)),0)))),0) -> 904168.29 | AA13: =IFERROR(IF(OR(R13<>"Yes",Q13<>"City"),0,IF(S13="Cash capital",IF(T13<=20,IF(O13<>"",O13,MAX(0,N(I13)+N(K13))*IF(N13<>"",N13,M13)),0),IF(S13="Debt service",IF(T13>20,0,AL13*MAX(0,MIN(20-T13+1,U13))),IF(OR(S13="Annual O&M",S13="Maintenance-only"),IF(T13>20,0,IF(O13<>"",O13,MAX(0,N(I13)+N(K13))*IF(N13<>"",N13,M13))*MAX(0,20-T13+1)),0)))),0) -> 1205557.7 | AB13: =IFERROR(IF(OR(R13<>"Yes",Q13<>"City"),0,IF(S13="Cash capital",IF(T13<=30,IF(O13<>"",O13,MAX(0,N(J13)+N(K13))*IF(N13<>"",N13,M13)),0),IF(S13="Debt service",IF(T13>30,0,AM13*MAX(0,MIN(30-T13+1,U13))),IF(OR(S13="Annual O&M",S13="Maintenance-only"),IF(T13>30,0,IF(O13<>"",O13,MAX(0,N(J13)+N(K13))*IF(N13<>"",N13,M13))*MAX(0,30-T13+1)),0)))),0) -> 1205557.7 | AC13: =IFERROR(IF(OR(R13<>"Yes",Q13<>"ESD"),0,IF(S13="Cash capital",IF(T13<=5,IF(O13<>"",O13,MAX(0,N(F13)+N(K13))*IF(N13<>"",N13,M13)),0),IF(S13="Debt service",IF(T13>5,0,AI13*MAX(0,MIN(5-T13+1,U13))),IF(OR(S13="Annual O&M",S13="Maintenance-only"),IF(T13>5,0,IF(O13<>"",O13,MAX(0,N(F13)+N(K13))*IF(N13<>"",N13,M13))*MAX(0,5-T13+1)),0)))),0) -> 0 | AD13: =IFERROR(IF(OR(R13<>"Yes",Q13<>"ESD"),0,IF(S13="Cash capital",IF(T13<=10,IF(O13<>"",O13,MAX(0,N(G13)+N(K13))*IF(N13<>"",N13,M13)),0),IF(S13="Debt service",IF(T13>10,0,AJ13*MAX(0,MIN(10-T13+1,U13))),IF(OR(S13="Annual O&M",S13="Maintenance-only"),IF(T13>10,0,IF(O13<>"",O13,MAX(0,N(G13)+N(K13))*IF(N13<>"",N13,M13))*MAX(0,10-T13+1)),0)))),0) -> 0 | AE13: =IFERROR(IF(OR(R13<>"Yes",Q13<>"ESD"),0,IF(S13="Cash capital",IF(T13<=15,IF(O13<>"",O13,MAX(0,N(H13)+N(K13))*IF(N13<>"",N13,M13)),0),IF(S13="Debt service",IF(T13>15,0,AK13*MAX(0,MIN(15-T13+1,U13))),IF(OR(S13="Annual O&M",S13="Maintenance-only"),IF(T13>15,0,IF(O13<>"",O13,MAX(0,N(H13)+N(K13))*IF(N13<>"",N13,M13))*MAX(0,15-T13+1)),0)))),0) -> 0 | AF13: =IFERROR(IF(OR(R13<>"Yes",Q13<>"ESD"),0,IF(S13="Cash capital",IF(T13<=20,IF(O13<>"",O13,MAX(0,N(I13)+N(K13))*IF(N13<>"",N13,M13)),0),IF(S13="Debt service",IF(T13>20,0,AL13*MAX(0,MIN(20-T13+1,U13))),IF(OR(S13="Annual O&M",S13="Maintenance-only"),IF(T13>20,0,IF(O13<>"",O13,MAX(0,N(I13)+N(K13))*IF(N13<>"",N13,M13))*MAX(0,20-T13+1)),0)))),0) -> 0 | AG13: =IFERROR(IF(OR(R13<>"Yes",Q13<>"ESD"),0,IF(S13="Cash capital",IF(T13<=30,IF(O13<>"",O13,MAX(0,N(J13)+N(K13))*IF(N13<>"",N13,M13)),0),IF(S13="Debt service",IF(T13>30,0,AM13*MAX(0,MIN(30-T13+1,U13))),IF(OR(S13="Annual O&M",S13="Maintenance-only"),IF(T13>30,0,IF(O13<>"",O13,MAX(0,N(J13)+N(K13))*IF(N13<>"",N13,M13))*MAX(0,30-T13+1)),0)))),0) -> 0 | AH13: Local street lane-mile takeoff; actual plat should override. | Takeoff factor: 120 centerline LF per developed acre; confidence Low; validate w/ Public Works/Engineer. | AI13: =IFERROR(IF(U13>0,IF(O13<>"",O13,MAX(0,N(F13)+N(K13))*IF(N13<>"",N13,M13))*IF(V13=0,1/U13,V13/(1-(1+V13)^(-U13))),0),0) -> 60277.886 | AJ13: =IFERROR(IF(U13>0,IF(O13<>"",O13,MAX(0,N(G13)+N(K13))*IF(N13<>"",N13,M13))*IF(V13=0,1/U13,V13/(1-(1+V13)^(-U13))),0),0) -> 60277.886 | AK13: =IFERROR(IF(U13>0,IF(O13<>"",O13,MAX(0,N(H13)+N(K13))*IF(N13<>"",N13,M13))*IF(V13=0,1/U13,V13/(1-(1+V13)^(-U13))),0),0) -> 60277.886 | AL13: =IFERROR(IF(U13>0,IF(O13<>"",O13,MAX(0,N(I13)+N(K13))*IF(N13<>"",N13,M13))*IF(V13=0,1/U13,V13/(1-(1+V13)^(-U13))),0),0) -> 60277.886 | AM13: =IFERROR(IF(U13>0,IF(O13<>"",O13,MAX(0,N(J13)+N(K13))*IF(N13<>"",N13,M13))*IF(V13=0,1/U13,V13/(1-(1+V13)^(-U13))),0),0) -> 60277.886
A14: Sidewalk / trail | B14: City | C14: captured acres | D14: linear ft | E14: 300 LF/ac | F14: ='03_Multi_Horizon_Results'!$B$5*'12_Takeoff_Assumptions'!$B$24 -> 8625 | G14: ='03_Multi_Horizon_Results'!$C$5*'12_Takeoff_Assumptions'!$B$24 -> 8625 | H14: ='03_Multi_Horizon_Results'!$D$5*'12_Takeoff_Assumptions'!$B$24 -> 8625 | I14: ='03_Multi_Horizon_Results'!$E$5*'12_Takeoff_Assumptions'!$B$24 -> 8625 | J14: ='03_Multi_Horizon_Results'!$F$5*'12_Takeoff_Assumptions'!$B$24 -> 8625 | L14: =MAX(0,N(G14)+N(K14)) -> 8625 | M14: 75 | P14: =IFERROR(IF(O14<>"",O14,L14*IF(N14<>"",N14,M14)),0) -> 646875 | Q14: City | R14: Yes | S14: Debt service | T14: 1 | U14: 20 | V14: 0.045 | W14: =IFERROR(IF(AND(R14="Yes",S14="Debt service",U14>0),IF(V14=0,P14/U14,P14*V14/(1-(1+V14)^(-U14))),0),0) -> 49729.256 | X14: =IFERROR(IF(OR(R14<>"Yes",Q14<>"City"),0,IF(S14="Cash capital",IF(T14<=5,IF(O14<>"",O14,MAX(0,N(F14)+N(K14))*IF(N14<>"",N14,M14)),0),IF(S14="Debt service",IF(T14>5,0,AI14*MAX(0,MIN(5-T14+1,U14))),IF(OR(S14="Annual O&M",S14="Maintenance-only"),IF(T14>5,0,IF(O14<>"",O14,MAX(0,N(F14)+N(K14))*IF(N14<>"",N14,M14))*MAX(0,5-T14+1)),0)))),0) -> 248646.28 | Y14: =IFERROR(IF(OR(R14<>"Yes",Q14<>"City"),0,IF(S14="Cash capital",IF(T14<=10,IF(O14<>"",O14,MAX(0,N(G14)+N(K14))*IF(N14<>"",N14,M14)),0),IF(S14="Debt service",IF(T14>10,0,AJ14*MAX(0,MIN(10-T14+1,U14))),IF(OR(S14="Annual O&M",S14="Maintenance-only"),IF(T14>10,0,IF(O14<>"",O14,MAX(0,N(G14)+N(K14))*IF(N14<>"",N14,M14))*MAX(0,10-T14+1)),0)))),0) -> 497292.56 | Z14: =IFERROR(IF(OR(R14<>"Yes",Q14<>"City"),0,IF(S14="Cash capital",IF(T14<=15,IF(O14<>"",O14,MAX(0,N(H14)+N(K14))*IF(N14<>"",N14,M14)),0),IF(S14="Debt service",IF(T14>15,0,AK14*MAX(0,MIN(15-T14+1,U14))),IF(OR(S14="Annual O&M",S14="Maintenance-only"),IF(T14>15,0,IF(O14<>"",O14,MAX(0,N(H14)+N(K14))*IF(N14<>"",N14,M14))*MAX(0,15-T14+1)),0)))),0) -> 745938.84 | AA14: =IFERROR(IF(OR(R14<>"Yes",Q14<>"City"),0,IF(S14="Cash capital",IF(T14<=20,IF(O14<>"",O14,MAX(0,N(I14)+N(K14))*IF(N14<>"",N14,M14)),0),IF(S14="Debt service",IF(T14>20,0,AL14*MAX(0,MIN(20-T14+1,U14))),IF(OR(S14="Annual O&M",S14="Maintenance-only"),IF(T14>20,0,IF(O14<>"",O14,MAX(0,N(I14)+N(K14))*IF(N14<>"",N14,M14))*MAX(0,20-T14+1)),0)))),0) -> 994585.12 | AB14: =IFERROR(IF(OR(R14<>"Yes",Q14<>"City"),0,IF(S14="Cash capital",IF(T14<=30,IF(O14<>"",O14,MAX(0,N(J14)+N(K14))*IF(N14<>"",N14,M14)),0),IF(S14="Debt service",IF(T14>30,0,AM14*MAX(0,MIN(30-T14+1,U14))),IF(OR(S14="Annual O&M",S14="Maintenance-only"),IF(T14>30,0,IF(O14<>"",O14,MAX(0,N(J14)+N(K14))*IF(N14<>"",N14,M14))*MAX(0,30-T14+1)),0)))),0) -> 994585.12 | AC14: =IFERROR(IF(OR(R14<>"Yes",Q14<>"ESD"),0,IF(S14="Cash capital",IF(T14<=5,IF(O14<>"",O14,MAX(0,N(F14)+N(K14))*IF(N14<>"",N14,M14)),0),IF(S14="Debt service",IF(T14>5,0,AI14*MAX(0,MIN(5-T14+1,U14))),IF(OR(S14="Annual O&M",S14="Maintenance-only"),IF(T14>5,0,IF(O14<>"",O14,MAX(0,N(F14)+N(K14))*IF(N14<>"",N14,M14))*MAX(0,5-T14+1)),0)))),0) -> 0 | AD14: =IFERROR(IF(OR(R14<>"Yes",Q14<>"ESD"),0,IF(S14="Cash capital",IF(T14<=10,IF(O14<>"",O14,MAX(0,N(G14)+N(K14))*IF(N14<>"",N14,M14)),0),IF(S14="Debt service",IF(T14>10,0,AJ14*MAX(0,MIN(10-T14+1,U14))),IF(OR(S14="Annual O&M",S14="Maintenance-only"),IF(T14>10,0,IF(O14<>"",O14,MAX(0,N(G14)+N(K14))*IF(N14<>"",N14,M14))*MAX(0,10-T14+1)),0)))),0) -> 0 | AE14: =IFERROR(IF(OR(R14<>"Yes",Q14<>"ESD"),0,IF(S14="Cash capital",IF(T14<=15,IF(O14<>"",O14,MAX(0,N(H14)+N(K14))*IF(N14<>"",N14,M14)),0),IF(S14="Debt service",IF(T14>15,0,AK14*MAX(0,MIN(15-T14+1,U14))),IF(OR(S14="Annual O&M",S14="Maintenance-only"),IF(T14>15,0,IF(O14<>"",O14,MAX(0,N(H14)+N(K14))*IF(N14<>"",N14,M14))*MAX(0,15-T14+1)),0)))),0) -> 0 | AF14: =IFERROR(IF(OR(R14<>"Yes",Q14<>"ESD"),0,IF(S14="Cash capital",IF(T14<=20,IF(O14<>"",O14,MAX(0,N(I14)+N(K14))*IF(N14<>"",N14,M14)),0),IF(S14="Debt service",IF(T14>20,0,AL14*MAX(0,MIN(20-T14+1,U14))),IF(OR(S14="Annual O&M",S14="Maintenance-only"),IF(T14>20,0,IF(O14<>"",O14,MAX(0,N(I14)+N(K14))*IF(N14<>"",N14,M14))*MAX(0,20-T14+1)),0)))),0) -> 0 | AG14: =IFERROR(IF(OR(R14<>"Yes",Q14<>"ESD"),0,IF(S14="Cash capital",IF(T14<=30,IF(O14<>"",O14,MAX(0,N(J14)+N(K14))*IF(N14<>"",N14,M14)),0),IF(S14="Debt service",IF(T14>30,0,AM14*MAX(0,MIN(30-T14+1,U14))),IF(OR(S14="Annual O&M",S14="Maintenance-only"),IF(T14>30,0,IF(O14<>"",O14,MAX(0,N(J14)+N(K14))*IF(N14<>"",N14,M14))*MAX(0,30-T14+1)),0)))),0) -> 0 | AH14: Planning benchmark; frontage/trail plans should override. | Takeoff factor: 300 LF per developed acre; confidence Low; validate w/ Planning/Public Works. | AI14: =IFERROR(IF(U14>0,IF(O14<>"",O14,MAX(0,N(F14)+N(K14))*IF(N14<>"",N14,M14))*IF(V14=0,1/U14,V14/(1-(1+V14)^(-U14))),0),0) -> 49729.256 | AJ14: =IFERROR(IF(U14>0,IF(O14<>"",O14,MAX(0,N(G14)+N(K14))*IF(N14<>"",N14,M14))*IF(V14=0,1/U14,V14/(1-(1+V14)^(-U14))),0),0) -> 49729.256 | AK14: =IFERROR(IF(U14>0,IF(O14<>"",O14,MAX(0,N(H14)+N(K14))*IF(N14<>"",N14,M14))*IF(V14=0,1/U14,V14/(1-(1+V14)^(-U14))),0),0) -> 49729.256 | AL14: =IFERROR(IF(U14>0,IF(O14<>"",O14,MAX(0,N(I14)+N(K14))*IF(N14<>"",N14,M14))*IF(V14=0,1/U14,V14/(1-(1+V14)^(-U14))),0),0) -> 49729.256 | AM14: =IFERROR(IF(U14>0,IF(O14<>"",O14,MAX(0,N(J14)+N(K14))*IF(N14<>"",N14,M14))*IF(V14=0,1/U14,V14/(1-(1+V14)^(-U14))),0),0) -> 49729.256
A15: Drainage / detention acreage | B15: City | C15: captured acres | D15: acres | E15: 0.10 ac/ac | F15: ='03_Multi_Horizon_Results'!$B$5*'12_Takeoff_Assumptions'!$B$25 -> 2.875 | G15: ='03_Multi_Horizon_Results'!$C$5*'12_Takeoff_Assumptions'!$B$25 -> 2.875 | H15: ='03_Multi_Horizon_Results'!$D$5*'12_Takeoff_Assumptions'!$B$25 -> 2.875 | I15: ='03_Multi_Horizon_Results'!$E$5*'12_Takeoff_Assumptions'!$B$25 -> 2.875 | J15: ='03_Multi_Horizon_Results'!$F$5*'12_Takeoff_Assumptions'!$B$25 -> 2.875 | L15: =MAX(0,N(G15)+N(K15)) -> 2.875 | M15: 150000 | P15: =IFERROR(IF(O15<>"",O15,L15*IF(N15<>"",N15,M15)),0) -> 431250 | Q15: City | R15: Yes | S15: Debt service | T15: 1 | U15: 20 | V15: 0.045 | W15: =IFERROR(IF(AND(R15="Yes",S15="Debt service",U15>0),IF(V15=0,P15/U15,P15*V15/(1-(1+V15)^(-U15))),0),0) -> 33152.837 | X15: =IFERROR(IF(OR(R15<>"Yes",Q15<>"City"),0,IF(S15="Cash capital",IF(T15<=5,IF(O15<>"",O15,MAX(0,N(F15)+N(K15))*IF(N15<>"",N15,M15)),0),IF(S15="Debt service",IF(T15>5,0,AI15*MAX(0,MIN(5-T15+1,U15))),IF(OR(S15="Annual O&M",S15="Maintenance-only"),IF(T15>5,0,IF(O15<>"",O15,MAX(0,N(F15)+N(K15))*IF(N15<>"",N15,M15))*MAX(0,5-T15+1)),0)))),0) -> 165764.19 | Y15: =IFERROR(IF(OR(R15<>"Yes",Q15<>"City"),0,IF(S15="Cash capital",IF(T15<=10,IF(O15<>"",O15,MAX(0,N(G15)+N(K15))*IF(N15<>"",N15,M15)),0),IF(S15="Debt service",IF(T15>10,0,AJ15*MAX(0,MIN(10-T15+1,U15))),IF(OR(S15="Annual O&M",S15="Maintenance-only"),IF(T15>10,0,IF(O15<>"",O15,MAX(0,N(G15)+N(K15))*IF(N15<>"",N15,M15))*MAX(0,10-T15+1)),0)))),0) -> 331528.37 | Z15: =IFERROR(IF(OR(R15<>"Yes",Q15<>"City"),0,IF(S15="Cash capital",IF(T15<=15,IF(O15<>"",O15,MAX(0,N(H15)+N(K15))*IF(N15<>"",N15,M15)),0),IF(S15="Debt service",IF(T15>15,0,AK15*MAX(0,MIN(15-T15+1,U15))),IF(OR(S15="Annual O&M",S15="Maintenance-only"),IF(T15>15,0,IF(O15<>"",O15,MAX(0,N(H15)+N(K15))*IF(N15<>"",N15,M15))*MAX(0,15-T15+1)),0)))),0) -> 497292.56 | AA15: =IFERROR(IF(OR(R15<>"Yes",Q15<>"City"),0,IF(S15="Cash capital",IF(T15<=20,IF(O15<>"",O15,MAX(0,N(I15)+N(K15))*IF(N15<>"",N15,M15)),0),IF(S15="Debt service",IF(T15>20,0,AL15*MAX(0,MIN(20-T15+1,U15))),IF(OR(S15="Annual O&M",S15="Maintenance-only"),IF(T15>20,0,IF(O15<>"",O15,MAX(0,N(I15)+N(K15))*IF(N15<>"",N15,M15))*MAX(0,20-T15+1)),0)))),0) -> 663056.74 | AB15: =IFERROR(IF(OR(R15<>"Yes",Q15<>"City"),0,IF(S15="Cash capital",IF(T15<=30,IF(O15<>"",O15,MAX(0,N(J15)+N(K15))*IF(N15<>"",N15,M15)),0),IF(S15="Debt service",IF(T15>30,0,AM15*MAX(0,MIN(30-T15+1,U15))),IF(OR(S15="Annual O&M",S15="Maintenance-only"),IF(T15>30,0,IF(O15<>"",O15,MAX(0,N(J15)+N(K15))*IF(N15<>"",N15,M15))*MAX(0,30-T15+1)),0)))),0) -> 663056.74 | AC15: =IFERROR(IF(OR(R15<>"Yes",Q15<>"ESD"),0,IF(S15="Cash capital",IF(T15<=5,IF(O15<>"",O15,MAX(0,N(F15)+N(K15))*IF(N15<>"",N15,M15)),0),IF(S15="Debt service",IF(T15>5,0,AI15*MAX(0,MIN(5-T15+1,U15))),IF(OR(S15="Annual O&M",S15="Maintenance-only"),IF(T15>5,0,IF(O15<>"",O15,MAX(0,N(F15)+N(K15))*IF(N15<>"",N15,M15))*MAX(0,5-T15+1)),0)))),0) -> 0 | AD15: =IFERROR(IF(OR(R15<>"Yes",Q15<>"ESD"),0,IF(S15="Cash capital",IF(T15<=10,IF(O15<>"",O15,MAX(0,N(G15)+N(K15))*IF(N15<>"",N15,M15)),0),IF(S15="Debt service",IF(T15>10,0,AJ15*MAX(0,MIN(10-T15+1,U15))),IF(OR(S15="Annual O&M",S15="Maintenance-only"),IF(T15>10,0,IF(O15<>"",O15,MAX(0,N(G15)+N(K15))*IF(N15<>"",N15,M15))*MAX(0,10-T15+1)),0)))),0) -> 0 | AE15: =IFERROR(IF(OR(R15<>"Yes",Q15<>"ESD"),0,IF(S15="Cash capital",IF(T15<=15,IF(O15<>"",O15,MAX(0,N(H15)+N(K15))*IF(N15<>"",N15,M15)),0),IF(S15="Debt service",IF(T15>15,0,AK15*MAX(0,MIN(15-T15+1,U15))),IF(OR(S15="Annual O&M",S15="Maintenance-only"),IF(T15>15,0,IF(O15<>"",O15,MAX(0,N(H15)+N(K15))*IF(N15<>"",N15,M15))*MAX(0,15-T15+1)),0)))),0) -> 0 | AF15: =IFERROR(IF(OR(R15<>"Yes",Q15<>"ESD"),0,IF(S15="Cash capital",IF(T15<=20,IF(O15<>"",O15,MAX(0,N(I15)+N(K15))*IF(N15<>"",N15,M15)),0),IF(S15="Debt service",IF(T15>20,0,AL15*MAX(0,MIN(20-T15+1,U15))),IF(OR(S15="Annual O&M",S15="Maintenance-only"),IF(T15>20,0,IF(O15<>"",O15,MAX(0,N(I15)+N(K15))*IF(N15<>"",N15,M15))*MAX(0,20-T15+1)),0)))),0) -> 0 | AG15: =IFERROR(IF(OR(R15<>"Yes",Q15<>"ESD"),0,IF(S15="Cash capital",IF(T15<=30,IF(O15<>"",O15,MAX(0,N(J15)+N(K15))*IF(N15<>"",N15,M15)),0),IF(S15="Debt service",IF(T15>30,0,AM15*MAX(0,MIN(30-T15+1,U15))),IF(OR(S15="Annual O&M",S15="Maintenance-only"),IF(T15>30,0,IF(O15<>"",O15,MAX(0,N(J15)+N(K15))*IF(N15<>"",N15,M15))*MAX(0,30-T15+1)),0)))),0) -> 0 | AH15: Drainage/detention planning share; drainage study should override. | Takeoff factor: 0.1 acres per developed acre; confidence Low; validate w/ Engineer/Public Works. | AI15: =IFERROR(IF(U15>0,IF(O15<>"",O15,MAX(0,N(F15)+N(K15))*IF(N15<>"",N15,M15))*IF(V15=0,1/U15,V15/(1-(1+V15)^(-U15))),0),0) -> 33152.837 | AJ15: =IFERROR(IF(U15>0,IF(O15<>"",O15,MAX(0,N(G15)+N(K15))*IF(N15<>"",N15,M15))*IF(V15=0,1/U15,V15/(1-(1+V15)^(-U15))),0),0) -> 33152.837 | AK15: =IFERROR(IF(U15>0,IF(O15<>"",O15,MAX(0,N(H15)+N(K15))*IF(N15<>"",N15,M15))*IF(V15=0,1/U15,V15/(1-(1+V15)^(-U15))),0),0) -> 33152.837 | AL15: =IFERROR(IF(U15>0,IF(O15<>"",O15,MAX(0,N(I15)+N(K15))*IF(N15<>"",N15,M15))*IF(V15=0,1/U15,V15/(1-(1+V15)^(-U15))),0),0) -> 33152.837 | AM15: =IFERROR(IF(U15>0,IF(O15<>"",O15,MAX(0,N(J15)+N(K15))*IF(N15<>"",N15,M15))*IF(V15=0,1/U15,V15/(1-(1+V15)^(-U15))),0),0) -> 33152.837
A16: Traffic signals | B16: City | C16: commercial/industrial sqft | D16: each | E16: threshold 150,000 sqft | F16: =IF('03_Multi_Horizon_Results'!$B$10>'12_Takeoff_Assumptions'!$B$26,ROUNDUP('03_Multi_Horizon_Results'!$B$10/'12_Takeoff_Assumptions'!$B$26,0),0) -> 2 | G16: =IF('03_Multi_Horizon_Results'!$C$10>'12_Takeoff_Assumptions'!$B$26,ROUNDUP('03_Multi_Horizon_Results'!$C$10/'12_Takeoff_Assumptions'!$B$26,0),0) -> 2 | H16: =IF('03_Multi_Horizon_Results'!$D$10>'12_Takeoff_Assumptions'!$B$26,ROUNDUP('03_Multi_Horizon_Results'!$D$10/'12_Takeoff_Assumptions'!$B$26,0),0) -> 2 | I16: =IF('03_Multi_Horizon_Results'!$E$10>'12_Takeoff_Assumptions'!$B$26,ROUNDUP('03_Multi_Horizon_Results'!$E$10/'12_Takeoff_Assumptions'!$B$26,0),0) -> 2 | J16: =IF('03_Multi_Horizon_Results'!$F$10>'12_Takeoff_Assumptions'!$B$26,ROUNDUP('03_Multi_Horizon_Results'!$F$10/'12_Takeoff_Assumptions'!$B$26,0),0) -> 2 | L16: =MAX(0,N(G16)+N(K16)) -> 2 | M16: 350000 | P16: =IFERROR(IF(O16<>"",O16,L16*IF(N16<>"",N16,M16)),0) -> 700000 | Q16: City | R16: Yes | S16: Debt service | T16: 1 | U16: 20 | V16: 0.045 | W16: =IFERROR(IF(AND(R16="Yes",S16="Debt service",U16>0),IF(V16=0,P16/U16,P16*V16/(1-(1+V16)^(-U16))),0),0) -> 53813.301 | X16: =IFERROR(IF(OR(R16<>"Yes",Q16<>"City"),0,IF(S16="Cash capital",IF(T16<=5,IF(O16<>"",O16,MAX(0,N(F16)+N(K16))*IF(N16<>"",N16,M16)),0),IF(S16="Debt service",IF(T16>5,0,AI16*MAX(0,MIN(5-T16+1,U16))),IF(OR(S16="Annual O&M",S16="Maintenance-only"),IF(T16>5,0,IF(O16<>"",O16,MAX(0,N(F16)+N(K16))*IF(N16<>"",N16,M16))*MAX(0,5-T16+1)),0)))),0) -> 269066.51 | Y16: =IFERROR(IF(OR(R16<>"Yes",Q16<>"City"),0,IF(S16="Cash capital",IF(T16<=10,IF(O16<>"",O16,MAX(0,N(G16)+N(K16))*IF(N16<>"",N16,M16)),0),IF(S16="Debt service",IF(T16>10,0,AJ16*MAX(0,MIN(10-T16+1,U16))),IF(OR(S16="Annual O&M",S16="Maintenance-only"),IF(T16>10,0,IF(O16<>"",O16,MAX(0,N(G16)+N(K16))*IF(N16<>"",N16,M16))*MAX(0,10-T16+1)),0)))),0) -> 538133.01 | Z16: =IFERROR(IF(OR(R16<>"Yes",Q16<>"City"),0,IF(S16="Cash capital",IF(T16<=15,IF(O16<>"",O16,MAX(0,N(H16)+N(K16))*IF(N16<>"",N16,M16)),0),IF(S16="Debt service",IF(T16>15,0,AK16*MAX(0,MIN(15-T16+1,U16))),IF(OR(S16="Annual O&M",S16="Maintenance-only"),IF(T16>15,0,IF(O16<>"",O16,MAX(0,N(H16)+N(K16))*IF(N16<>"",N16,M16))*MAX(0,15-T16+1)),0)))),0) -> 807199.52 | AA16: =IFERROR(IF(OR(R16<>"Yes",Q16<>"City"),0,IF(S16="Cash capital",IF(T16<=20,IF(O16<>"",O16,MAX(0,N(I16)+N(K16))*IF(N16<>"",N16,M16)),0),IF(S16="Debt service",IF(T16>20,0,AL16*MAX(0,MIN(20-T16+1,U16))),IF(OR(S16="Annual O&M",S16="Maintenance-only"),IF(T16>20,0,IF(O16<>"",O16,MAX(0,N(I16)+N(K16))*IF(N16<>"",N16,M16))*MAX(0,20-T16+1)),0)))),0) -> 1076266 | AB16: =IFERROR(IF(OR(R16<>"Yes",Q16<>"City"),0,IF(S16="Cash capital",IF(T16<=30,IF(O16<>"",O16,MAX(0,N(J16)+N(K16))*IF(N16<>"",N16,M16)),0),IF(S16="Debt service",IF(T16>30,0,AM16*MAX(0,MIN(30-T16+1,U16))),IF(OR(S16="Annual O&M",S16="Maintenance-only"),IF(T16>30,0,IF(O16<>"",O16,MAX(0,N(J16)+N(K16))*IF(N16<>"",N16,M16))*MAX(0,30-T16+1)),0)))),0) -> 1076266 | AC16: =IFERROR(IF(OR(R16<>"Yes",Q16<>"ESD"),0,IF(S16="Cash capital",IF(T16<=5,IF(O16<>"",O16,MAX(0,N(F16)+N(K16))*IF(N16<>"",N16,M16)),0),IF(S16="Debt service",IF(T16>5,0,AI16*MAX(0,MIN(5-T16+1,U16))),IF(OR(S16="Annual O&M",S16="Maintenance-only"),IF(T16>5,0,IF(O16<>"",O16,MAX(0,N(F16)+N(K16))*IF(N16<>"",N16,M16))*MAX(0,5-T16+1)),0)))),0) -> 0 | AD16: =IFERROR(IF(OR(R16<>"Yes",Q16<>"ESD"),0,IF(S16="Cash capital",IF(T16<=10,IF(O16<>"",O16,MAX(0,N(G16)+N(K16))*IF(N16<>"",N16,M16)),0),IF(S16="Debt service",IF(T16>10,0,AJ16*MAX(0,MIN(10-T16+1,U16))),IF(OR(S16="Annual O&M",S16="Maintenance-only"),IF(T16>10,0,IF(O16<>"",O16,MAX(0,N(G16)+N(K16))*IF(N16<>"",N16,M16))*MAX(0,10-T16+1)),0)))),0) -> 0 | AE16: =IFERROR(IF(OR(R16<>"Yes",Q16<>"ESD"),0,IF(S16="Cash capital",IF(T16<=15,IF(O16<>"",O16,MAX(0,N(H16)+N(K16))*IF(N16<>"",N16,M16)),0),IF(S16="Debt service",IF(T16>15,0,AK16*MAX(0,MIN(15-T16+1,U16))),IF(OR(S16="Annual O&M",S16="Maintenance-only"),IF(T16>15,0,IF(O16<>"",O16,MAX(0,N(H16)+N(K16))*IF(N16<>"",N16,M16))*MAX(0,15-T16+1)),0)))),0) -> 0 | AF16: =IFERROR(IF(OR(R16<>"Yes",Q16<>"ESD"),0,IF(S16="Cash capital",IF(T16<=20,IF(O16<>"",O16,MAX(0,N(I16)+N(K16))*IF(N16<>"",N16,M16)),0),IF(S16="Debt service",IF(T16>20,0,AL16*MAX(0,MIN(20-T16+1,U16))),IF(OR(S16="Annual O&M",S16="Maintenance-only"),IF(T16>20,0,IF(O16<>"",O16,MAX(0,N(I16)+N(K16))*IF(N16<>"",N16,M16))*MAX(0,20-T16+1)),0)))),0) -> 0 | AG16: =IFERROR(IF(OR(R16<>"Yes",Q16<>"ESD"),0,IF(S16="Cash capital",IF(T16<=30,IF(O16<>"",O16,MAX(0,N(J16)+N(K16))*IF(N16<>"",N16,M16)),0),IF(S16="Debt service",IF(T16>30,0,AM16*MAX(0,MIN(30-T16+1,U16))),IF(OR(S16="Annual O&M",S16="Maintenance-only"),IF(T16>30,0,IF(O16<>"",O16,MAX(0,N(J16)+N(K16))*IF(N16<>"",N16,M16))*MAX(0,30-T16+1)),0)))),0) -> 0 | AH16: Planning trigger; traffic impact analysis should override. | Takeoff factor: 150000 commercial/industrial sqft; confidence Low; validate w/ Engineer/Public Works. | AI16: =IFERROR(IF(U16>0,IF(O16<>"",O16,MAX(0,N(F16)+N(K16))*IF(N16<>"",N16,M16))*IF(V16=0,1/U16,V16/(1-(1+V16)^(-U16))),0),0) -> 53813.301 | AJ16: =IFERROR(IF(U16>0,IF(O16<>"",O16,MAX(0,N(G16)+N(K16))*IF(N16<>"",N16,M16))*IF(V16=0,1/U16,V16/(1-(1+V16)^(-U16))),0),0) -> 53813.301 | AK16: =IFERROR(IF(U16>0,IF(O16<>"",O16,MAX(0,N(H16)+N(K16))*IF(N16<>"",N16,M16))*IF(V16=0,1/U16,V16/(1-(1+V16)^(-U16))),0),0) -> 53813.301 | AL16: =IFERROR(IF(U16>0,IF(O16<>"",O16,MAX(0,N(I16)+N(K16))*IF(N16<>"",N16,M16))*IF(V16=0,1/U16,V16/(1-(1+V16)^(-U16))),0),0) -> 53813.301 | AM16: =IFERROR(IF(U16>0,IF(O16<>"",O16,MAX(0,N(J16)+N(K16))*IF(N16<>"",N16,M16))*IF(V16=0,1/U16,V16/(1-(1+V16)^(-U16))),0),0) -> 53813.301
A17: Police FTEs (sworn) | B17: City | C17: captured residents | D17: FTE | E17: 2.0 FTE/1,000 residents | F17: =('03_Multi_Horizon_Results'!$B$7/1000*'12_Takeoff_Assumptions'!$B$11) -> 0.54 | G17: =('03_Multi_Horizon_Results'!$C$7/1000*'12_Takeoff_Assumptions'!$B$11) -> 0.54 | H17: =('03_Multi_Horizon_Results'!$D$7/1000*'12_Takeoff_Assumptions'!$B$11) -> 0.54 | I17: =('03_Multi_Horizon_Results'!$E$7/1000*'12_Takeoff_Assumptions'!$B$11) -> 0.54 | J17: =('03_Multi_Horizon_Results'!$F$7/1000*'12_Takeoff_Assumptions'!$B$11) -> 0.54 | L17: =MAX(0,N(G17)+N(K17)) -> 0.54 | M17: 120000 | P17: =IFERROR(IF(O17<>"",O17,L17*IF(N17<>"",N17,M17)),0) -> 64800 | Q17: City | R17: Yes | S17: Annual O&M | T17: 1 | U17: 20 | V17: 0.045 | W17: =IFERROR(IF(AND(R17="Yes",S17="Debt service",U17>0),IF(V17=0,P17/U17,P17*V17/(1-(1+V17)^(-U17))),0),0) -> 0 | X17: =IFERROR(IF(OR(R17<>"Yes",Q17<>"City"),0,IF(S17="Cash capital",IF(T17<=5,IF(O17<>"",O17,MAX(0,N(F17)+N(K17))*IF(N17<>"",N17,M17)),0),IF(S17="Debt service",IF(T17>5,0,AI17*MAX(0,MIN(5-T17+1,U17))),IF(OR(S17="Annual O&M",S17="Maintenance-only"),IF(T17>5,0,IF(O17<>"",O17,MAX(0,N(F17)+N(K17))*IF(N17<>"",N17,M17))*MAX(0,5-T17+1)),0)))),0) -> 324000 | Y17: =IFERROR(IF(OR(R17<>"Yes",Q17<>"City"),0,IF(S17="Cash capital",IF(T17<=10,IF(O17<>"",O17,MAX(0,N(G17)+N(K17))*IF(N17<>"",N17,M17)),0),IF(S17="Debt service",IF(T17>10,0,AJ17*MAX(0,MIN(10-T17+1,U17))),IF(OR(S17="Annual O&M",S17="Maintenance-only"),IF(T17>10,0,IF(O17<>"",O17,MAX(0,N(G17)+N(K17))*IF(N17<>"",N17,M17))*MAX(0,10-T17+1)),0)))),0) -> 648000 | Z17: =IFERROR(IF(OR(R17<>"Yes",Q17<>"City"),0,IF(S17="Cash capital",IF(T17<=15,IF(O17<>"",O17,MAX(0,N(H17)+N(K17))*IF(N17<>"",N17,M17)),0),IF(S17="Debt service",IF(T17>15,0,AK17*MAX(0,MIN(15-T17+1,U17))),IF(OR(S17="Annual O&M",S17="Maintenance-only"),IF(T17>15,0,IF(O17<>"",O17,MAX(0,N(H17)+N(K17))*IF(N17<>"",N17,M17))*MAX(0,15-T17+1)),0)))),0) -> 972000 | AA17: =IFERROR(IF(OR(R17<>"Yes",Q17<>"City"),0,IF(S17="Cash capital",IF(T17<=20,IF(O17<>"",O17,MAX(0,N(I17)+N(K17))*IF(N17<>"",N17,M17)),0),IF(S17="Debt service",IF(T17>20,0,AL17*MAX(0,MIN(20-T17+1,U17))),IF(OR(S17="Annual O&M",S17="Maintenance-only"),IF(T17>20,0,IF(O17<>"",O17,MAX(0,N(I17)+N(K17))*IF(N17<>"",N17,M17))*MAX(0,20-T17+1)),0)))),0) -> 1296000 | AB17: =IFERROR(IF(OR(R17<>"Yes",Q17<>"City"),0,IF(S17="Cash capital",IF(T17<=30,IF(O17<>"",O17,MAX(0,N(J17)+N(K17))*IF(N17<>"",N17,M17)),0),IF(S17="Debt service",IF(T17>30,0,AM17*MAX(0,MIN(30-T17+1,U17))),IF(OR(S17="Annual O&M",S17="Maintenance-only"),IF(T17>30,0,IF(O17<>"",O17,MAX(0,N(J17)+N(K17))*IF(N17<>"",N17,M17))*MAX(0,30-T17+1)),0)))),0) -> 1944000 | AC17: =IFERROR(IF(OR(R17<>"Yes",Q17<>"ESD"),0,IF(S17="Cash capital",IF(T17<=5,IF(O17<>"",O17,MAX(0,N(F17)+N(K17))*IF(N17<>"",N17,M17)),0),IF(S17="Debt service",IF(T17>5,0,AI17*MAX(0,MIN(5-T17+1,U17))),IF(OR(S17="Annual O&M",S17="Maintenance-only"),IF(T17>5,0,IF(O17<>"",O17,MAX(0,N(F17)+N(K17))*IF(N17<>"",N17,M17))*MAX(0,5-T17+1)),0)))),0) -> 0 | AD17: =IFERROR(IF(OR(R17<>"Yes",Q17<>"ESD"),0,IF(S17="Cash capital",IF(T17<=10,IF(O17<>"",O17,MAX(0,N(G17)+N(K17))*IF(N17<>"",N17,M17)),0),IF(S17="Debt service",IF(T17>10,0,AJ17*MAX(0,MIN(10-T17+1,U17))),IF(OR(S17="Annual O&M",S17="Maintenance-only"),IF(T17>10,0,IF(O17<>"",O17,MAX(0,N(G17)+N(K17))*IF(N17<>"",N17,M17))*MAX(0,10-T17+1)),0)))),0) -> 0 | AE17: =IFERROR(IF(OR(R17<>"Yes",Q17<>"ESD"),0,IF(S17="Cash capital",IF(T17<=15,IF(O17<>"",O17,MAX(0,N(H17)+N(K17))*IF(N17<>"",N17,M17)),0),IF(S17="Debt service",IF(T17>15,0,AK17*MAX(0,MIN(15-T17+1,U17))),IF(OR(S17="Annual O&M",S17="Maintenance-only"),IF(T17>15,0,IF(O17<>"",O17,MAX(0,N(H17)+N(K17))*IF(N17<>"",N17,M17))*MAX(0,15-T17+1)),0)))),0) -> 0 | AF17: =IFERROR(IF(OR(R17<>"Yes",Q17<>"ESD"),0,IF(S17="Cash capital",IF(T17<=20,IF(O17<>"",O17,MAX(0,N(I17)+N(K17))*IF(N17<>"",N17,M17)),0),IF(S17="Debt service",IF(T17>20,0,AL17*MAX(0,MIN(20-T17+1,U17))),IF(OR(S17="Annual O&M",S17="Maintenance-only"),IF(T17>20,0,IF(O17<>"",O17,MAX(0,N(I17)+N(K17))*IF(N17<>"",N17,M17))*MAX(0,20-T17+1)),0)))),0) -> 0 | AG17: =IFERROR(IF(OR(R17<>"Yes",Q17<>"ESD"),0,IF(S17="Cash capital",IF(T17<=30,IF(O17<>"",O17,MAX(0,N(J17)+N(K17))*IF(N17<>"",N17,M17)),0),IF(S17="Debt service",IF(T17>30,0,AM17*MAX(0,MIN(30-T17+1,U17))),IF(OR(S17="Annual O&M",S17="Maintenance-only"),IF(T17>30,0,IF(O17<>"",O17,MAX(0,N(J17)+N(K17))*IF(N17<>"",N17,M17))*MAX(0,30-T17+1)),0)))),0) -> 0 | AH17: Planning benchmark only; workload-based police staffing should validate. | Takeoff factor: 2 FTE per 1,000 residents; confidence Low; validate w/ Police/HR. | AI17: =IFERROR(IF(U17>0,IF(O17<>"",O17,MAX(0,N(F17)+N(K17))*IF(N17<>"",N17,M17))*IF(V17=0,1/U17,V17/(1-(1+V17)^(-U17))),0),0) -> 4981.5742 | AJ17: =IFERROR(IF(U17>0,IF(O17<>"",O17,MAX(0,N(G17)+N(K17))*IF(N17<>"",N17,M17))*IF(V17=0,1/U17,V17/(1-(1+V17)^(-U17))),0),0) -> 4981.5742 | AK17: =IFERROR(IF(U17>0,IF(O17<>"",O17,MAX(0,N(H17)+N(K17))*IF(N17<>"",N17,M17))*IF(V17=0,1/U17,V17/(1-(1+V17)^(-U17))),0),0) -> 4981.5742 | AL17: =IFERROR(IF(U17>0,IF(O17<>"",O17,MAX(0,N(I17)+N(K17))*IF(N17<>"",N17,M17))*IF(V17=0,1/U17,V17/(1-(1+V17)^(-U17))),0),0) -> 4981.5742 | AM17: =IFERROR(IF(U17>0,IF(O17<>"",O17,MAX(0,N(J17)+N(K17))*IF(N17<>"",N17,M17))*IF(V17=0,1/U17,V17/(1-(1+V17)^(-U17))),0),0) -> 4981.5742
A18: Police vehicles | B18: City | C18: police FTE | D18: each | E18: 1 vehicle / 2 FTE | F18: =IF(('03_Multi_Horizon_Results'!$B$7/1000*'12_Takeoff_Assumptions'!$B$11)>=1,ROUNDUP(('03_Multi_Horizon_Results'!$B$7/1000*'12_Takeoff_Assumptions'!$B$11)/2,0),0) -> 0 | G18: =IF(('03_Multi_Horizon_Results'!$C$7/1000*'12_Takeoff_Assumptions'!$B$11)>=1,ROUNDUP(('03_Multi_Horizon_Results'!$C$7/1000*'12_Takeoff_Assumptions'!$B$11)/2,0),0) -> 0 | H18: =IF(('03_Multi_Horizon_Results'!$D$7/1000*'12_Takeoff_Assumptions'!$B$11)>=1,ROUNDUP(('03_Multi_Horizon_Results'!$D$7/1000*'12_Takeoff_Assumptions'!$B$11)/2,0),0) -> 0 | I18: =IF(('03_Multi_Horizon_Results'!$E$7/1000*'12_Takeoff_Assumptions'!$B$11)>=1,ROUNDUP(('03_Multi_Horizon_Results'!$E$7/1000*'12_Takeoff_Assumptions'!$B$11)/2,0),0) -> 0 | J18: =IF(('03_Multi_Horizon_Results'!$F$7/1000*'12_Takeoff_Assumptions'!$B$11)>=1,ROUNDUP(('03_Multi_Horizon_Results'!$F$7/1000*'12_Takeoff_Assumptions'!$B$11)/2,0),0) -> 0 | L18: =MAX(0,N(G18)+N(K18)) -> 0 | M18: 65000 | P18: =IFERROR(IF(O18<>"",O18,L18*IF(N18<>"",N18,M18)),0) -> 0 | Q18: City | R18: Yes | S18: Cash capital | T18: 1 | U18: 20 | V18: 0.045 | W18: =IFERROR(IF(AND(R18="Yes",S18="Debt service",U18>0),IF(V18=0,P18/U18,P18*V18/(1-(1+V18)^(-U18))),0),0) -> 0 | X18: =IFERROR(IF(OR(R18<>"Yes",Q18<>"City"),0,IF(S18="Cash capital",IF(T18<=5,IF(O18<>"",O18,MAX(0,N(F18)+N(K18))*IF(N18<>"",N18,M18)),0),IF(S18="Debt service",IF(T18>5,0,AI18*MAX(0,MIN(5-T18+1,U18))),IF(OR(S18="Annual O&M",S18="Maintenance-only"),IF(T18>5,0,IF(O18<>"",O18,MAX(0,N(F18)+N(K18))*IF(N18<>"",N18,M18))*MAX(0,5-T18+1)),0)))),0) -> 0 | Y18: =IFERROR(IF(OR(R18<>"Yes",Q18<>"City"),0,IF(S18="Cash capital",IF(T18<=10,IF(O18<>"",O18,MAX(0,N(G18)+N(K18))*IF(N18<>"",N18,M18)),0),IF(S18="Debt service",IF(T18>10,0,AJ18*MAX(0,MIN(10-T18+1,U18))),IF(OR(S18="Annual O&M",S18="Maintenance-only"),IF(T18>10,0,IF(O18<>"",O18,MAX(0,N(G18)+N(K18))*IF(N18<>"",N18,M18))*MAX(0,10-T18+1)),0)))),0) -> 0 | Z18: =IFERROR(IF(OR(R18<>"Yes",Q18<>"City"),0,IF(S18="Cash capital",IF(T18<=15,IF(O18<>"",O18,MAX(0,N(H18)+N(K18))*IF(N18<>"",N18,M18)),0),IF(S18="Debt service",IF(T18>15,0,AK18*MAX(0,MIN(15-T18+1,U18))),IF(OR(S18="Annual O&M",S18="Maintenance-only"),IF(T18>15,0,IF(O18<>"",O18,MAX(0,N(H18)+N(K18))*IF(N18<>"",N18,M18))*MAX(0,15-T18+1)),0)))),0) -> 0 | AA18: =IFERROR(IF(OR(R18<>"Yes",Q18<>"City"),0,IF(S18="Cash capital",IF(T18<=20,IF(O18<>"",O18,MAX(0,N(I18)+N(K18))*IF(N18<>"",N18,M18)),0),IF(S18="Debt service",IF(T18>20,0,AL18*MAX(0,MIN(20-T18+1,U18))),IF(OR(S18="Annual O&M",S18="Maintenance-only"),IF(T18>20,0,IF(O18<>"",O18,MAX(0,N(I18)+N(K18))*IF(N18<>"",N18,M18))*MAX(0,20-T18+1)),0)))),0) -> 0 | AB18: =IFERROR(IF(OR(R18<>"Yes",Q18<>"City"),0,IF(S18="Cash capital",IF(T18<=30,IF(O18<>"",O18,MAX(0,N(J18)+N(K18))*IF(N18<>"",N18,M18)),0),IF(S18="Debt service",IF(T18>30,0,AM18*MAX(0,MIN(30-T18+1,U18))),IF(OR(S18="Annual O&M",S18="Maintenance-only"),IF(T18>30,0,IF(O18<>"",O18,MAX(0,N(J18)+N(K18))*IF(N18<>"",N18,M18))*MAX(0,30-T18+1)),0)))),0) -> 0 | AC18: =IFERROR(IF(OR(R18<>"Yes",Q18<>"ESD"),0,IF(S18="Cash capital",IF(T18<=5,IF(O18<>"",O18,MAX(0,N(F18)+N(K18))*IF(N18<>"",N18,M18)),0),IF(S18="Debt service",IF(T18>5,0,AI18*MAX(0,MIN(5-T18+1,U18))),IF(OR(S18="Annual O&M",S18="Maintenance-only"),IF(T18>5,0,IF(O18<>"",O18,MAX(0,N(F18)+N(K18))*IF(N18<>"",N18,M18))*MAX(0,5-T18+1)),0)))),0) -> 0 | AD18: =IFERROR(IF(OR(R18<>"Yes",Q18<>"ESD"),0,IF(S18="Cash capital",IF(T18<=10,IF(O18<>"",O18,MAX(0,N(G18)+N(K18))*IF(N18<>"",N18,M18)),0),IF(S18="Debt service",IF(T18>10,0,AJ18*MAX(0,MIN(10-T18+1,U18))),IF(OR(S18="Annual O&M",S18="Maintenance-only"),IF(T18>10,0,IF(O18<>"",O18,MAX(0,N(G18)+N(K18))*IF(N18<>"",N18,M18))*MAX(0,10-T18+1)),0)))),0) -> 0 | AE18: =IFERROR(IF(OR(R18<>"Yes",Q18<>"ESD"),0,IF(S18="Cash capital",IF(T18<=15,IF(O18<>"",O18,MAX(0,N(H18)+N(K18))*IF(N18<>"",N18,M18)),0),IF(S18="Debt service",IF(T18>15,0,AK18*MAX(0,MIN(15-T18+1,U18))),IF(OR(S18="Annual O&M",S18="Maintenance-only"),IF(T18>15,0,IF(O18<>"",O18,MAX(0,N(H18)+N(K18))*IF(N18<>"",N18,M18))*MAX(0,15-T18+1)),0)))),0) -> 0 | AF18: =IFERROR(IF(OR(R18<>"Yes",Q18<>"ESD"),0,IF(S18="Cash capital",IF(T18<=20,IF(O18<>"",O18,MAX(0,N(I18)+N(K18))*IF(N18<>"",N18,M18)),0),IF(S18="Debt service",IF(T18>20,0,AL18*MAX(0,MIN(20-T18+1,U18))),IF(OR(S18="Annual O&M",S18="Maintenance-only"),IF(T18>20,0,IF(O18<>"",O18,MAX(0,N(I18)+N(K18))*IF(N18<>"",N18,M18))*MAX(0,20-T18+1)),0)))),0) -> 0 | AG18: =IFERROR(IF(OR(R18<>"Yes",Q18<>"ESD"),0,IF(S18="Cash capital",IF(T18<=30,IF(O18<>"",O18,MAX(0,N(J18)+N(K18))*IF(N18<>"",N18,M18)),0),IF(S18="Debt service",IF(T18>30,0,AM18*MAX(0,MIN(30-T18+1,U18))),IF(OR(S18="Annual O&M",S18="Maintenance-only"),IF(T18>30,0,IF(O18<>"",O18,MAX(0,N(J18)+N(K18))*IF(N18<>"",N18,M18))*MAX(0,30-T18+1)),0)))),0) -> 0 | AH18: Planning fleet benchmark; police/fleet plan should validate. | Takeoff factor: 1 vehicle per 2 police FTE; confidence Low; validate w/ Police/Fleet. | AI18: =IFERROR(IF(U18>0,IF(O18<>"",O18,MAX(0,N(F18)+N(K18))*IF(N18<>"",N18,M18))*IF(V18=0,1/U18,V18/(1-(1+V18)^(-U18))),0),0) -> 0 | AJ18: =IFERROR(IF(U18>0,IF(O18<>"",O18,MAX(0,N(G18)+N(K18))*IF(N18<>"",N18,M18))*IF(V18=0,1/U18,V18/(1-(1+V18)^(-U18))),0),0) -> 0 | AK18: =IFERROR(IF(U18>0,IF(O18<>"",O18,MAX(0,N(H18)+N(K18))*IF(N18<>"",N18,M18))*IF(V18=0,1/U18,V18/(1-(1+V18)^(-U18))),0),0) -> 0 | AL18: =IFERROR(IF(U18>0,IF(O18<>"",O18,MAX(0,N(I18)+N(K18))*IF(N18<>"",N18,M18))*IF(V18=0,1/U18,V18/(1-(1+V18)^(-U18))),0),0) -> 0 | AM18: =IFERROR(IF(U18>0,IF(O18<>"",O18,MAX(0,N(J18)+N(K18))*IF(N18<>"",N18,M18))*IF(V18=0,1/U18,V18/(1-(1+V18)^(-U18))),0),0) -> 0
A19: Park acreage | B19: City | C19: captured residents | D19: acres | E19: 5 ac/1,000 residents | F19: ='03_Multi_Horizon_Results'!$B$7/1000*'12_Takeoff_Assumptions'!$B$10 -> 1.35 | G19: ='03_Multi_Horizon_Results'!$C$7/1000*'12_Takeoff_Assumptions'!$B$10 -> 1.35 | H19: ='03_Multi_Horizon_Results'!$D$7/1000*'12_Takeoff_Assumptions'!$B$10 -> 1.35 | I19: ='03_Multi_Horizon_Results'!$E$7/1000*'12_Takeoff_Assumptions'!$B$10 -> 1.35 | J19: ='03_Multi_Horizon_Results'!$F$7/1000*'12_Takeoff_Assumptions'!$B$10 -> 1.35 | L19: =MAX(0,N(G19)+N(K19)) -> 1.35 | M19: 100000 | P19: =IFERROR(IF(O19<>"",O19,L19*IF(N19<>"",N19,M19)),0) -> 135000 | Q19: City | R19: Yes | S19: Debt service | T19: 1 | U19: 20 | V19: 0.045 | W19: =IFERROR(IF(AND(R19="Yes",S19="Debt service",U19>0),IF(V19=0,P19/U19,P19*V19/(1-(1+V19)^(-U19))),0),0) -> 10378.279 | X19: =IFERROR(IF(OR(R19<>"Yes",Q19<>"City"),0,IF(S19="Cash capital",IF(T19<=5,IF(O19<>"",O19,MAX(0,N(F19)+N(K19))*IF(N19<>"",N19,M19)),0),IF(S19="Debt service",IF(T19>5,0,AI19*MAX(0,MIN(5-T19+1,U19))),IF(OR(S19="Annual O&M",S19="Maintenance-only"),IF(T19>5,0,IF(O19<>"",O19,MAX(0,N(F19)+N(K19))*IF(N19<>"",N19,M19))*MAX(0,5-T19+1)),0)))),0) -> 51891.397 | Y19: =IFERROR(IF(OR(R19<>"Yes",Q19<>"City"),0,IF(S19="Cash capital",IF(T19<=10,IF(O19<>"",O19,MAX(0,N(G19)+N(K19))*IF(N19<>"",N19,M19)),0),IF(S19="Debt service",IF(T19>10,0,AJ19*MAX(0,MIN(10-T19+1,U19))),IF(OR(S19="Annual O&M",S19="Maintenance-only"),IF(T19>10,0,IF(O19<>"",O19,MAX(0,N(G19)+N(K19))*IF(N19<>"",N19,M19))*MAX(0,10-T19+1)),0)))),0) -> 103782.79 | Z19: =IFERROR(IF(OR(R19<>"Yes",Q19<>"City"),0,IF(S19="Cash capital",IF(T19<=15,IF(O19<>"",O19,MAX(0,N(H19)+N(K19))*IF(N19<>"",N19,M19)),0),IF(S19="Debt service",IF(T19>15,0,AK19*MAX(0,MIN(15-T19+1,U19))),IF(OR(S19="Annual O&M",S19="Maintenance-only"),IF(T19>15,0,IF(O19<>"",O19,MAX(0,N(H19)+N(K19))*IF(N19<>"",N19,M19))*MAX(0,15-T19+1)),0)))),0) -> 155674.19 | AA19: =IFERROR(IF(OR(R19<>"Yes",Q19<>"City"),0,IF(S19="Cash capital",IF(T19<=20,IF(O19<>"",O19,MAX(0,N(I19)+N(K19))*IF(N19<>"",N19,M19)),0),IF(S19="Debt service",IF(T19>20,0,AL19*MAX(0,MIN(20-T19+1,U19))),IF(OR(S19="Annual O&M",S19="Maintenance-only"),IF(T19>20,0,IF(O19<>"",O19,MAX(0,N(I19)+N(K19))*IF(N19<>"",N19,M19))*MAX(0,20-T19+1)),0)))),0) -> 207565.59 | AB19: =IFERROR(IF(OR(R19<>"Yes",Q19<>"City"),0,IF(S19="Cash capital",IF(T19<=30,IF(O19<>"",O19,MAX(0,N(J19)+N(K19))*IF(N19<>"",N19,M19)),0),IF(S19="Debt service",IF(T19>30,0,AM19*MAX(0,MIN(30-T19+1,U19))),IF(OR(S19="Annual O&M",S19="Maintenance-only"),IF(T19>30,0,IF(O19<>"",O19,MAX(0,N(J19)+N(K19))*IF(N19<>"",N19,M19))*MAX(0,30-T19+1)),0)))),0) -> 207565.59 | AC19: =IFERROR(IF(OR(R19<>"Yes",Q19<>"ESD"),0,IF(S19="Cash capital",IF(T19<=5,IF(O19<>"",O19,MAX(0,N(F19)+N(K19))*IF(N19<>"",N19,M19)),0),IF(S19="Debt service",IF(T19>5,0,AI19*MAX(0,MIN(5-T19+1,U19))),IF(OR(S19="Annual O&M",S19="Maintenance-only"),IF(T19>5,0,IF(O19<>"",O19,MAX(0,N(F19)+N(K19))*IF(N19<>"",N19,M19))*MAX(0,5-T19+1)),0)))),0) -> 0 | AD19: =IFERROR(IF(OR(R19<>"Yes",Q19<>"ESD"),0,IF(S19="Cash capital",IF(T19<=10,IF(O19<>"",O19,MAX(0,N(G19)+N(K19))*IF(N19<>"",N19,M19)),0),IF(S19="Debt service",IF(T19>10,0,AJ19*MAX(0,MIN(10-T19+1,U19))),IF(OR(S19="Annual O&M",S19="Maintenance-only"),IF(T19>10,0,IF(O19<>"",O19,MAX(0,N(G19)+N(K19))*IF(N19<>"",N19,M19))*MAX(0,10-T19+1)),0)))),0) -> 0 | AE19: =IFERROR(IF(OR(R19<>"Yes",Q19<>"ESD"),0,IF(S19="Cash capital",IF(T19<=15,IF(O19<>"",O19,MAX(0,N(H19)+N(K19))*IF(N19<>"",N19,M19)),0),IF(S19="Debt service",IF(T19>15,0,AK19*MAX(0,MIN(15-T19+1,U19))),IF(OR(S19="Annual O&M",S19="Maintenance-only"),IF(T19>15,0,IF(O19<>"",O19,MAX(0,N(H19)+N(K19))*IF(N19<>"",N19,M19))*MAX(0,15-T19+1)),0)))),0) -> 0 | AF19: =IFERROR(IF(OR(R19<>"Yes",Q19<>"ESD"),0,IF(S19="Cash capital",IF(T19<=20,IF(O19<>"",O19,MAX(0,N(I19)+N(K19))*IF(N19<>"",N19,M19)),0),IF(S19="Debt service",IF(T19>20,0,AL19*MAX(0,MIN(20-T19+1,U19))),IF(OR(S19="Annual O&M",S19="Maintenance-only"),IF(T19>20,0,IF(O19<>"",O19,MAX(0,N(I19)+N(K19))*IF(N19<>"",N19,M19))*MAX(0,20-T19+1)),0)))),0) -> 0 | AG19: =IFERROR(IF(OR(R19<>"Yes",Q19<>"ESD"),0,IF(S19="Cash capital",IF(T19<=30,IF(O19<>"",O19,MAX(0,N(J19)+N(K19))*IF(N19<>"",N19,M19)),0),IF(S19="Debt service",IF(T19>30,0,AM19*MAX(0,MIN(30-T19+1,U19))),IF(OR(S19="Annual O&M",S19="Maintenance-only"),IF(T19>30,0,IF(O19<>"",O19,MAX(0,N(J19)+N(K19))*IF(N19<>"",N19,M19))*MAX(0,30-T19+1)),0)))),0) -> 0 | AH19: Local planning target, not an NRPA universal standard. | Takeoff factor: 5 acres per 1,000 residents; confidence Low; validate w/ Parks/Planning. | AI19: =IFERROR(IF(U19>0,IF(O19<>"",O19,MAX(0,N(F19)+N(K19))*IF(N19<>"",N19,M19))*IF(V19=0,1/U19,V19/(1-(1+V19)^(-U19))),0),0) -> 10378.279 | AJ19: =IFERROR(IF(U19>0,IF(O19<>"",O19,MAX(0,N(G19)+N(K19))*IF(N19<>"",N19,M19))*IF(V19=0,1/U19,V19/(1-(1+V19)^(-U19))),0),0) -> 10378.279 | AK19: =IFERROR(IF(U19>0,IF(O19<>"",O19,MAX(0,N(H19)+N(K19))*IF(N19<>"",N19,M19))*IF(V19=0,1/U19,V19/(1-(1+V19)^(-U19))),0),0) -> 10378.279 | AL19: =IFERROR(IF(U19>0,IF(O19<>"",O19,MAX(0,N(I19)+N(K19))*IF(N19<>"",N19,M19))*IF(V19=0,1/U19,V19/(1-(1+V19)^(-U19))),0),0) -> 10378.279 | AM19: =IFERROR(IF(U19>0,IF(O19<>"",O19,MAX(0,N(J19)+N(K19))*IF(N19<>"",N19,M19))*IF(V19=0,1/U19,V19/(1-(1+V19)^(-U19))),0),0) -> 10378.279
A20: Public works vehicles | B20: City | C20: captured acres | D20: each | E20: threshold 500 ac | F20: =IF('03_Multi_Horizon_Results'!$B$5>='12_Takeoff_Assumptions'!$B$17,ROUNDUP('03_Multi_Horizon_Results'!$B$5/'12_Takeoff_Assumptions'!$B$17,0),0) -> 0 | G20: =IF('03_Multi_Horizon_Results'!$C$5>='12_Takeoff_Assumptions'!$B$17,ROUNDUP('03_Multi_Horizon_Results'!$C$5/'12_Takeoff_Assumptions'!$B$17,0),0) -> 0 | H20: =IF('03_Multi_Horizon_Results'!$D$5>='12_Takeoff_Assumptions'!$B$17,ROUNDUP('03_Multi_Horizon_Results'!$D$5/'12_Takeoff_Assumptions'!$B$17,0),0) -> 0 | I20: =IF('03_Multi_Horizon_Results'!$E$5>='12_Takeoff_Assumptions'!$B$17,ROUNDUP('03_Multi_Horizon_Results'!$E$5/'12_Takeoff_Assumptions'!$B$17,0),0) -> 0 | J20: =IF('03_Multi_Horizon_Results'!$F$5>='12_Takeoff_Assumptions'!$B$17,ROUNDUP('03_Multi_Horizon_Results'!$F$5/'12_Takeoff_Assumptions'!$B$17,0),0) -> 0 | L20: =MAX(0,N(G20)+N(K20)) -> 0 | M20: 150000 | P20: =IFERROR(IF(O20<>"",O20,L20*IF(N20<>"",N20,M20)),0) -> 0 | Q20: City | R20: Yes | S20: Cash capital | T20: 1 | U20: 20 | V20: 0.045 | W20: =IFERROR(IF(AND(R20="Yes",S20="Debt service",U20>0),IF(V20=0,P20/U20,P20*V20/(1-(1+V20)^(-U20))),0),0) -> 0 | X20: =IFERROR(IF(OR(R20<>"Yes",Q20<>"City"),0,IF(S20="Cash capital",IF(T20<=5,IF(O20<>"",O20,MAX(0,N(F20)+N(K20))*IF(N20<>"",N20,M20)),0),IF(S20="Debt service",IF(T20>5,0,AI20*MAX(0,MIN(5-T20+1,U20))),IF(OR(S20="Annual O&M",S20="Maintenance-only"),IF(T20>5,0,IF(O20<>"",O20,MAX(0,N(F20)+N(K20))*IF(N20<>"",N20,M20))*MAX(0,5-T20+1)),0)))),0) -> 0 | Y20: =IFERROR(IF(OR(R20<>"Yes",Q20<>"City"),0,IF(S20="Cash capital",IF(T20<=10,IF(O20<>"",O20,MAX(0,N(G20)+N(K20))*IF(N20<>"",N20,M20)),0),IF(S20="Debt service",IF(T20>10,0,AJ20*MAX(0,MIN(10-T20+1,U20))),IF(OR(S20="Annual O&M",S20="Maintenance-only"),IF(T20>10,0,IF(O20<>"",O20,MAX(0,N(G20)+N(K20))*IF(N20<>"",N20,M20))*MAX(0,10-T20+1)),0)))),0) -> 0 | Z20: =IFERROR(IF(OR(R20<>"Yes",Q20<>"City"),0,IF(S20="Cash capital",IF(T20<=15,IF(O20<>"",O20,MAX(0,N(H20)+N(K20))*IF(N20<>"",N20,M20)),0),IF(S20="Debt service",IF(T20>15,0,AK20*MAX(0,MIN(15-T20+1,U20))),IF(OR(S20="Annual O&M",S20="Maintenance-only"),IF(T20>15,0,IF(O20<>"",O20,MAX(0,N(H20)+N(K20))*IF(N20<>"",N20,M20))*MAX(0,15-T20+1)),0)))),0) -> 0 | AA20: =IFERROR(IF(OR(R20<>"Yes",Q20<>"City"),0,IF(S20="Cash capital",IF(T20<=20,IF(O20<>"",O20,MAX(0,N(I20)+N(K20))*IF(N20<>"",N20,M20)),0),IF(S20="Debt service",IF(T20>20,0,AL20*MAX(0,MIN(20-T20+1,U20))),IF(OR(S20="Annual O&M",S20="Maintenance-only"),IF(T20>20,0,IF(O20<>"",O20,MAX(0,N(I20)+N(K20))*IF(N20<>"",N20,M20))*MAX(0,20-T20+1)),0)))),0) -> 0 | AB20: =IFERROR(IF(OR(R20<>"Yes",Q20<>"City"),0,IF(S20="Cash capital",IF(T20<=30,IF(O20<>"",O20,MAX(0,N(J20)+N(K20))*IF(N20<>"",N20,M20)),0),IF(S20="Debt service",IF(T20>30,0,AM20*MAX(0,MIN(30-T20+1,U20))),IF(OR(S20="Annual O&M",S20="Maintenance-only"),IF(T20>30,0,IF(O20<>"",O20,MAX(0,N(J20)+N(K20))*IF(N20<>"",N20,M20))*MAX(0,30-T20+1)),0)))),0) -> 0 | AC20: =IFERROR(IF(OR(R20<>"Yes",Q20<>"ESD"),0,IF(S20="Cash capital",IF(T20<=5,IF(O20<>"",O20,MAX(0,N(F20)+N(K20))*IF(N20<>"",N20,M20)),0),IF(S20="Debt service",IF(T20>5,0,AI20*MAX(0,MIN(5-T20+1,U20))),IF(OR(S20="Annual O&M",S20="Maintenance-only"),IF(T20>5,0,IF(O20<>"",O20,MAX(0,N(F20)+N(K20))*IF(N20<>"",N20,M20))*MAX(0,5-T20+1)),0)))),0) -> 0 | AD20: =IFERROR(IF(OR(R20<>"Yes",Q20<>"ESD"),0,IF(S20="Cash capital",IF(T20<=10,IF(O20<>"",O20,MAX(0,N(G20)+N(K20))*IF(N20<>"",N20,M20)),0),IF(S20="Debt service",IF(T20>10,0,AJ20*MAX(0,MIN(10-T20+1,U20))),IF(OR(S20="Annual O&M",S20="Maintenance-only"),IF(T20>10,0,IF(O20<>"",O20,MAX(0,N(G20)+N(K20))*IF(N20<>"",N20,M20))*MAX(0,10-T20+1)),0)))),0) -> 0 | AE20: =IFERROR(IF(OR(R20<>"Yes",Q20<>"ESD"),0,IF(S20="Cash capital",IF(T20<=15,IF(O20<>"",O20,MAX(0,N(H20)+N(K20))*IF(N20<>"",N20,M20)),0),IF(S20="Debt service",IF(T20>15,0,AK20*MAX(0,MIN(15-T20+1,U20))),IF(OR(S20="Annual O&M",S20="Maintenance-only"),IF(T20>15,0,IF(O20<>"",O20,MAX(0,N(H20)+N(K20))*IF(N20<>"",N20,M20))*MAX(0,15-T20+1)),0)))),0) -> 0 | AF20: =IFERROR(IF(OR(R20<>"Yes",Q20<>"ESD"),0,IF(S20="Cash capital",IF(T20<=20,IF(O20<>"",O20,MAX(0,N(I20)+N(K20))*IF(N20<>"",N20,M20)),0),IF(S20="Debt service",IF(T20>20,0,AL20*MAX(0,MIN(20-T20+1,U20))),IF(OR(S20="Annual O&M",S20="Maintenance-only"),IF(T20>20,0,IF(O20<>"",O20,MAX(0,N(I20)+N(K20))*IF(N20<>"",N20,M20))*MAX(0,20-T20+1)),0)))),0) -> 0 | AG20: =IFERROR(IF(OR(R20<>"Yes",Q20<>"ESD"),0,IF(S20="Cash capital",IF(T20<=30,IF(O20<>"",O20,MAX(0,N(J20)+N(K20))*IF(N20<>"",N20,M20)),0),IF(S20="Debt service",IF(T20>30,0,AM20*MAX(0,MIN(30-T20+1,U20))),IF(OR(S20="Annual O&M",S20="Maintenance-only"),IF(T20>30,0,IF(O20<>"",O20,MAX(0,N(J20)+N(K20))*IF(N20<>"",N20,M20))*MAX(0,30-T20+1)),0)))),0) -> 0 | AH20: Fleet planning trigger; Public Works validation required. | AI20: =IFERROR(IF(U20>0,IF(O20<>"",O20,MAX(0,N(F20)+N(K20))*IF(N20<>"",N20,M20))*IF(V20=0,1/U20,V20/(1-(1+V20)^(-U20))),0),0) -> 0 | AJ20: =IFERROR(IF(U20>0,IF(O20<>"",O20,MAX(0,N(G20)+N(K20))*IF(N20<>"",N20,M20))*IF(V20=0,1/U20,V20/(1-(1+V20)^(-U20))),0),0) -> 0 | AK20: =IFERROR(IF(U20>0,IF(O20<>"",O20,MAX(0,N(H20)+N(K20))*IF(N20<>"",N20,M20))*IF(V20=0,1/U20,V20/(1-(1+V20)^(-U20))),0),0) -> 0 | AL20: =IFERROR(IF(U20>0,IF(O20<>"",O20,MAX(0,N(I20)+N(K20))*IF(N20<>"",N20,M20))*IF(V20=0,1/U20,V20/(1-(1+V20)^(-U20))),0),0) -> 0 | AM20: =IFERROR(IF(U20>0,IF(O20<>"",O20,MAX(0,N(J20)+N(K20))*IF(N20<>"",N20,M20))*IF(V20=0,1/U20,V20/(1-(1+V20)^(-U20))),0),0) -> 0
A21: Fire stations | B21: ESD | C21: captured residents | D21: each | E21: threshold 3,500 residents | F21: =IF('03_Multi_Horizon_Results'!$B$7>='12_Takeoff_Assumptions'!$B$18,INT('03_Multi_Horizon_Results'!$B$7/'12_Takeoff_Assumptions'!$B$18),0) -> 0 | G21: =IF('03_Multi_Horizon_Results'!$C$7>='12_Takeoff_Assumptions'!$B$18,INT('03_Multi_Horizon_Results'!$C$7/'12_Takeoff_Assumptions'!$B$18),0) -> 0 | H21: =IF('03_Multi_Horizon_Results'!$D$7>='12_Takeoff_Assumptions'!$B$18,INT('03_Multi_Horizon_Results'!$D$7/'12_Takeoff_Assumptions'!$B$18),0) -> 0 | I21: =IF('03_Multi_Horizon_Results'!$E$7>='12_Takeoff_Assumptions'!$B$18,INT('03_Multi_Horizon_Results'!$E$7/'12_Takeoff_Assumptions'!$B$18),0) -> 0 | J21: =IF('03_Multi_Horizon_Results'!$F$7>='12_Takeoff_Assumptions'!$B$18,INT('03_Multi_Horizon_Results'!$F$7/'12_Takeoff_Assumptions'!$B$18),0) -> 0 | L21: =MAX(0,N(G21)+N(K21)) -> 0 | M21: 5000000 | P21: =IFERROR(IF(O21<>"",O21,L21*IF(N21<>"",N21,M21)),0) -> 0 | Q21: ESD | R21: Yes | S21: Debt service | T21: 1 | U21: 20 | V21: 0.045 | W21: =IFERROR(IF(AND(R21="Yes",S21="Debt service",U21>0),IF(V21=0,P21/U21,P21*V21/(1-(1+V21)^(-U21))),0),0) -> 0 | X21: =IFERROR(IF(OR(R21<>"Yes",Q21<>"City"),0,IF(S21="Cash capital",IF(T21<=5,IF(O21<>"",O21,MAX(0,N(F21)+N(K21))*IF(N21<>"",N21,M21)),0),IF(S21="Debt service",IF(T21>5,0,AI21*MAX(0,MIN(5-T21+1,U21))),IF(OR(S21="Annual O&M",S21="Maintenance-only"),IF(T21>5,0,IF(O21<>"",O21,MAX(0,N(F21)+N(K21))*IF(N21<>"",N21,M21))*MAX(0,5-T21+1)),0)))),0) -> 0 | Y21: =IFERROR(IF(OR(R21<>"Yes",Q21<>"City"),0,IF(S21="Cash capital",IF(T21<=10,IF(O21<>"",O21,MAX(0,N(G21)+N(K21))*IF(N21<>"",N21,M21)),0),IF(S21="Debt service",IF(T21>10,0,AJ21*MAX(0,MIN(10-T21+1,U21))),IF(OR(S21="Annual O&M",S21="Maintenance-only"),IF(T21>10,0,IF(O21<>"",O21,MAX(0,N(G21)+N(K21))*IF(N21<>"",N21,M21))*MAX(0,10-T21+1)),0)))),0) -> 0 | Z21: =IFERROR(IF(OR(R21<>"Yes",Q21<>"City"),0,IF(S21="Cash capital",IF(T21<=15,IF(O21<>"",O21,MAX(0,N(H21)+N(K21))*IF(N21<>"",N21,M21)),0),IF(S21="Debt service",IF(T21>15,0,AK21*MAX(0,MIN(15-T21+1,U21))),IF(OR(S21="Annual O&M",S21="Maintenance-only"),IF(T21>15,0,IF(O21<>"",O21,MAX(0,N(H21)+N(K21))*IF(N21<>"",N21,M21))*MAX(0,15-T21+1)),0)))),0) -> 0 | AA21: =IFERROR(IF(OR(R21<>"Yes",Q21<>"City"),0,IF(S21="Cash capital",IF(T21<=20,IF(O21<>"",O21,MAX(0,N(I21)+N(K21))*IF(N21<>"",N21,M21)),0),IF(S21="Debt service",IF(T21>20,0,AL21*MAX(0,MIN(20-T21+1,U21))),IF(OR(S21="Annual O&M",S21="Maintenance-only"),IF(T21>20,0,IF(O21<>"",O21,MAX(0,N(I21)+N(K21))*IF(N21<>"",N21,M21))*MAX(0,20-T21+1)),0)))),0) -> 0 | AB21: =IFERROR(IF(OR(R21<>"Yes",Q21<>"City"),0,IF(S21="Cash capital",IF(T21<=30,IF(O21<>"",O21,MAX(0,N(J21)+N(K21))*IF(N21<>"",N21,M21)),0),IF(S21="Debt service",IF(T21>30,0,AM21*MAX(0,MIN(30-T21+1,U21))),IF(OR(S21="Annual O&M",S21="Maintenance-only"),IF(T21>30,0,IF(O21<>"",O21,MAX(0,N(J21)+N(K21))*IF(N21<>"",N21,M21))*MAX(0,30-T21+1)),0)))),0) -> 0 | AC21: =IFERROR(IF(OR(R21<>"Yes",Q21<>"ESD"),0,IF(S21="Cash capital",IF(T21<=5,IF(O21<>"",O21,MAX(0,N(F21)+N(K21))*IF(N21<>"",N21,M21)),0),IF(S21="Debt service",IF(T21>5,0,AI21*MAX(0,MIN(5-T21+1,U21))),IF(OR(S21="Annual O&M",S21="Maintenance-only"),IF(T21>5,0,IF(O21<>"",O21,MAX(0,N(F21)+N(K21))*IF(N21<>"",N21,M21))*MAX(0,5-T21+1)),0)))),0) -> 0 | AD21: =IFERROR(IF(OR(R21<>"Yes",Q21<>"ESD"),0,IF(S21="Cash capital",IF(T21<=10,IF(O21<>"",O21,MAX(0,N(G21)+N(K21))*IF(N21<>"",N21,M21)),0),IF(S21="Debt service",IF(T21>10,0,AJ21*MAX(0,MIN(10-T21+1,U21))),IF(OR(S21="Annual O&M",S21="Maintenance-only"),IF(T21>10,0,IF(O21<>"",O21,MAX(0,N(G21)+N(K21))*IF(N21<>"",N21,M21))*MAX(0,10-T21+1)),0)))),0) -> 0 | AE21: =IFERROR(IF(OR(R21<>"Yes",Q21<>"ESD"),0,IF(S21="Cash capital",IF(T21<=15,IF(O21<>"",O21,MAX(0,N(H21)+N(K21))*IF(N21<>"",N21,M21)),0),IF(S21="Debt service",IF(T21>15,0,AK21*MAX(0,MIN(15-T21+1,U21))),IF(OR(S21="Annual O&M",S21="Maintenance-only"),IF(T21>15,0,IF(O21<>"",O21,MAX(0,N(H21)+N(K21))*IF(N21<>"",N21,M21))*MAX(0,15-T21+1)),0)))),0) -> 0 | AF21: =IFERROR(IF(OR(R21<>"Yes",Q21<>"ESD"),0,IF(S21="Cash capital",IF(T21<=20,IF(O21<>"",O21,MAX(0,N(I21)+N(K21))*IF(N21<>"",N21,M21)),0),IF(S21="Debt service",IF(T21>20,0,AL21*MAX(0,MIN(20-T21+1,U21))),IF(OR(S21="Annual O&M",S21="Maintenance-only"),IF(T21>20,0,IF(O21<>"",O21,MAX(0,N(I21)+N(K21))*IF(N21<>"",N21,M21))*MAX(0,20-T21+1)),0)))),0) -> 0 | AG21: =IFERROR(IF(OR(R21<>"Yes",Q21<>"ESD"),0,IF(S21="Cash capital",IF(T21<=30,IF(O21<>"",O21,MAX(0,N(J21)+N(K21))*IF(N21<>"",N21,M21)),0),IF(S21="Debt service",IF(T21>30,0,AM21*MAX(0,MIN(30-T21+1,U21))),IF(OR(S21="Annual O&M",S21="Maintenance-only"),IF(T21>30,0,IF(O21<>"",O21,MAX(0,N(J21)+N(K21))*IF(N21<>"",N21,M21))*MAX(0,30-T21+1)),0)))),0) -> 0 | AH21: ESD fire/rescue and EMS-assist station trigger; call-volume validation required. | Takeoff factor: 3500 captured residents; confidence Low; validate w/ ESD #2. | AI21: =IFERROR(IF(U21>0,IF(O21<>"",O21,MAX(0,N(F21)+N(K21))*IF(N21<>"",N21,M21))*IF(V21=0,1/U21,V21/(1-(1+V21)^(-U21))),0),0) -> 0 | AJ21: =IFERROR(IF(U21>0,IF(O21<>"",O21,MAX(0,N(G21)+N(K21))*IF(N21<>"",N21,M21))*IF(V21=0,1/U21,V21/(1-(1+V21)^(-U21))),0),0) -> 0 | AK21: =IFERROR(IF(U21>0,IF(O21<>"",O21,MAX(0,N(H21)+N(K21))*IF(N21<>"",N21,M21))*IF(V21=0,1/U21,V21/(1-(1+V21)^(-U21))),0),0) -> 0 | AL21: =IFERROR(IF(U21>0,IF(O21<>"",O21,MAX(0,N(I21)+N(K21))*IF(N21<>"",N21,M21))*IF(V21=0,1/U21,V21/(1-(1+V21)^(-U21))),0),0) -> 0 | AM21: =IFERROR(IF(U21>0,IF(O21<>"",O21,MAX(0,N(J21)+N(K21))*IF(N21<>"",N21,M21))*IF(V21=0,1/U21,V21/(1-(1+V21)^(-U21))),0),0) -> 0
A22: Engine companies (Type I pumper) | B22: ESD | C22: captured residents | D22: each | E22: threshold 7,000 residents | F22: =IF('03_Multi_Horizon_Results'!$B$7>='12_Takeoff_Assumptions'!$B$19,INT('03_Multi_Horizon_Results'!$B$7/'12_Takeoff_Assumptions'!$B$19),0) -> 0 | G22: =IF('03_Multi_Horizon_Results'!$C$7>='12_Takeoff_Assumptions'!$B$19,INT('03_Multi_Horizon_Results'!$C$7/'12_Takeoff_Assumptions'!$B$19),0) -> 0 | H22: =IF('03_Multi_Horizon_Results'!$D$7>='12_Takeoff_Assumptions'!$B$19,INT('03_Multi_Horizon_Results'!$D$7/'12_Takeoff_Assumptions'!$B$19),0) -> 0 | I22: =IF('03_Multi_Horizon_Results'!$E$7>='12_Takeoff_Assumptions'!$B$19,INT('03_Multi_Horizon_Results'!$E$7/'12_Takeoff_Assumptions'!$B$19),0) -> 0 | J22: =IF('03_Multi_Horizon_Results'!$F$7>='12_Takeoff_Assumptions'!$B$19,INT('03_Multi_Horizon_Results'!$F$7/'12_Takeoff_Assumptions'!$B$19),0) -> 0 | L22: =MAX(0,N(G22)+N(K22)) -> 0 | M22: 1200000 | P22: =IFERROR(IF(O22<>"",O22,L22*IF(N22<>"",N22,M22)),0) -> 0 | Q22: ESD | R22: Yes | S22: Cash capital | T22: 1 | U22: 20 | V22: 0.045 | W22: =IFERROR(IF(AND(R22="Yes",S22="Debt service",U22>0),IF(V22=0,P22/U22,P22*V22/(1-(1+V22)^(-U22))),0),0) -> 0 | X22: =IFERROR(IF(OR(R22<>"Yes",Q22<>"City"),0,IF(S22="Cash capital",IF(T22<=5,IF(O22<>"",O22,MAX(0,N(F22)+N(K22))*IF(N22<>"",N22,M22)),0),IF(S22="Debt service",IF(T22>5,0,AI22*MAX(0,MIN(5-T22+1,U22))),IF(OR(S22="Annual O&M",S22="Maintenance-only"),IF(T22>5,0,IF(O22<>"",O22,MAX(0,N(F22)+N(K22))*IF(N22<>"",N22,M22))*MAX(0,5-T22+1)),0)))),0) -> 0 | Y22: =IFERROR(IF(OR(R22<>"Yes",Q22<>"City"),0,IF(S22="Cash capital",IF(T22<=10,IF(O22<>"",O22,MAX(0,N(G22)+N(K22))*IF(N22<>"",N22,M22)),0),IF(S22="Debt service",IF(T22>10,0,AJ22*MAX(0,MIN(10-T22+1,U22))),IF(OR(S22="Annual O&M",S22="Maintenance-only"),IF(T22>10,0,IF(O22<>"",O22,MAX(0,N(G22)+N(K22))*IF(N22<>"",N22,M22))*MAX(0,10-T22+1)),0)))),0) -> 0 | Z22: =IFERROR(IF(OR(R22<>"Yes",Q22<>"City"),0,IF(S22="Cash capital",IF(T22<=15,IF(O22<>"",O22,MAX(0,N(H22)+N(K22))*IF(N22<>"",N22,M22)),0),IF(S22="Debt service",IF(T22>15,0,AK22*MAX(0,MIN(15-T22+1,U22))),IF(OR(S22="Annual O&M",S22="Maintenance-only"),IF(T22>15,0,IF(O22<>"",O22,MAX(0,N(H22)+N(K22))*IF(N22<>"",N22,M22))*MAX(0,15-T22+1)),0)))),0) -> 0 | AA22: =IFERROR(IF(OR(R22<>"Yes",Q22<>"City"),0,IF(S22="Cash capital",IF(T22<=20,IF(O22<>"",O22,MAX(0,N(I22)+N(K22))*IF(N22<>"",N22,M22)),0),IF(S22="Debt service",IF(T22>20,0,AL22*MAX(0,MIN(20-T22+1,U22))),IF(OR(S22="Annual O&M",S22="Maintenance-only"),IF(T22>20,0,IF(O22<>"",O22,MAX(0,N(I22)+N(K22))*IF(N22<>"",N22,M22))*MAX(0,20-T22+1)),0)))),0) -> 0 | AB22: =IFERROR(IF(OR(R22<>"Yes",Q22<>"City"),0,IF(S22="Cash capital",IF(T22<=30,IF(O22<>"",O22,MAX(0,N(J22)+N(K22))*IF(N22<>"",N22,M22)),0),IF(S22="Debt service",IF(T22>30,0,AM22*MAX(0,MIN(30-T22+1,U22))),IF(OR(S22="Annual O&M",S22="Maintenance-only"),IF(T22>30,0,IF(O22<>"",O22,MAX(0,N(J22)+N(K22))*IF(N22<>"",N22,M22))*MAX(0,30-T22+1)),0)))),0) -> 0 | AC22: =IFERROR(IF(OR(R22<>"Yes",Q22<>"ESD"),0,IF(S22="Cash capital",IF(T22<=5,IF(O22<>"",O22,MAX(0,N(F22)+N(K22))*IF(N22<>"",N22,M22)),0),IF(S22="Debt service",IF(T22>5,0,AI22*MAX(0,MIN(5-T22+1,U22))),IF(OR(S22="Annual O&M",S22="Maintenance-only"),IF(T22>5,0,IF(O22<>"",O22,MAX(0,N(F22)+N(K22))*IF(N22<>"",N22,M22))*MAX(0,5-T22+1)),0)))),0) -> 0 | AD22: =IFERROR(IF(OR(R22<>"Yes",Q22<>"ESD"),0,IF(S22="Cash capital",IF(T22<=10,IF(O22<>"",O22,MAX(0,N(G22)+N(K22))*IF(N22<>"",N22,M22)),0),IF(S22="Debt service",IF(T22>10,0,AJ22*MAX(0,MIN(10-T22+1,U22))),IF(OR(S22="Annual O&M",S22="Maintenance-only"),IF(T22>10,0,IF(O22<>"",O22,MAX(0,N(G22)+N(K22))*IF(N22<>"",N22,M22))*MAX(0,10-T22+1)),0)))),0) -> 0 | AE22: =IFERROR(IF(OR(R22<>"Yes",Q22<>"ESD"),0,IF(S22="Cash capital",IF(T22<=15,IF(O22<>"",O22,MAX(0,N(H22)+N(K22))*IF(N22<>"",N22,M22)),0),IF(S22="Debt service",IF(T22>15,0,AK22*MAX(0,MIN(15-T22+1,U22))),IF(OR(S22="Annual O&M",S22="Maintenance-only"),IF(T22>15,0,IF(O22<>"",O22,MAX(0,N(H22)+N(K22))*IF(N22<>"",N22,M22))*MAX(0,15-T22+1)),0)))),0) -> 0 | AF22: =IFERROR(IF(OR(R22<>"Yes",Q22<>"ESD"),0,IF(S22="Cash capital",IF(T22<=20,IF(O22<>"",O22,MAX(0,N(I22)+N(K22))*IF(N22<>"",N22,M22)),0),IF(S22="Debt service",IF(T22>20,0,AL22*MAX(0,MIN(20-T22+1,U22))),IF(OR(S22="Annual O&M",S22="Maintenance-only"),IF(T22>20,0,IF(O22<>"",O22,MAX(0,N(I22)+N(K22))*IF(N22<>"",N22,M22))*MAX(0,20-T22+1)),0)))),0) -> 0 | AG22: =IFERROR(IF(OR(R22<>"Yes",Q22<>"ESD"),0,IF(S22="Cash capital",IF(T22<=30,IF(O22<>"",O22,MAX(0,N(J22)+N(K22))*IF(N22<>"",N22,M22)),0),IF(S22="Debt service",IF(T22>30,0,AM22*MAX(0,MIN(30-T22+1,U22))),IF(OR(S22="Annual O&M",S22="Maintenance-only"),IF(T22>30,0,IF(O22<>"",O22,MAX(0,N(J22)+N(K22))*IF(N22<>"",N22,M22))*MAX(0,30-T22+1)),0)))),0) -> 0 | AH22: Apparatus trigger; ESD capital plan should validate. | Takeoff factor: 7000 captured residents; confidence Low; validate w/ ESD #2. | AI22: =IFERROR(IF(U22>0,IF(O22<>"",O22,MAX(0,N(F22)+N(K22))*IF(N22<>"",N22,M22))*IF(V22=0,1/U22,V22/(1-(1+V22)^(-U22))),0),0) -> 0 | AJ22: =IFERROR(IF(U22>0,IF(O22<>"",O22,MAX(0,N(G22)+N(K22))*IF(N22<>"",N22,M22))*IF(V22=0,1/U22,V22/(1-(1+V22)^(-U22))),0),0) -> 0 | AK22: =IFERROR(IF(U22>0,IF(O22<>"",O22,MAX(0,N(H22)+N(K22))*IF(N22<>"",N22,M22))*IF(V22=0,1/U22,V22/(1-(1+V22)^(-U22))),0),0) -> 0 | AL22: =IFERROR(IF(U22>0,IF(O22<>"",O22,MAX(0,N(I22)+N(K22))*IF(N22<>"",N22,M22))*IF(V22=0,1/U22,V22/(1-(1+V22)^(-U22))),0),0) -> 0 | AM22: =IFERROR(IF(U22>0,IF(O22<>"",O22,MAX(0,N(J22)+N(K22))*IF(N22<>"",N22,M22))*IF(V22=0,1/U22,V22/(1-(1+V22)^(-U22))),0),0) -> 0
A23: Ladder trucks / quints | B23: ESD | C23: captured residents | D23: each | E23: threshold 14,000 residents | F23: =IF('03_Multi_Horizon_Results'!$B$7>='12_Takeoff_Assumptions'!$B$20,INT('03_Multi_Horizon_Results'!$B$7/'12_Takeoff_Assumptions'!$B$20),0) -> 0 | G23: =IF('03_Multi_Horizon_Results'!$C$7>='12_Takeoff_Assumptions'!$B$20,INT('03_Multi_Horizon_Results'!$C$7/'12_Takeoff_Assumptions'!$B$20),0) -> 0 | H23: =IF('03_Multi_Horizon_Results'!$D$7>='12_Takeoff_Assumptions'!$B$20,INT('03_Multi_Horizon_Results'!$D$7/'12_Takeoff_Assumptions'!$B$20),0) -> 0 | I23: =IF('03_Multi_Horizon_Results'!$E$7>='12_Takeoff_Assumptions'!$B$20,INT('03_Multi_Horizon_Results'!$E$7/'12_Takeoff_Assumptions'!$B$20),0) -> 0 | J23: =IF('03_Multi_Horizon_Results'!$F$7>='12_Takeoff_Assumptions'!$B$20,INT('03_Multi_Horizon_Results'!$F$7/'12_Takeoff_Assumptions'!$B$20),0) -> 0 | L23: =MAX(0,N(G23)+N(K23)) -> 0 | M23: 1500000 | P23: =IFERROR(IF(O23<>"",O23,L23*IF(N23<>"",N23,M23)),0) -> 0 | Q23: ESD | R23: Yes | S23: Cash capital | T23: 1 | U23: 20 | V23: 0.045 | W23: =IFERROR(IF(AND(R23="Yes",S23="Debt service",U23>0),IF(V23=0,P23/U23,P23*V23/(1-(1+V23)^(-U23))),0),0) -> 0 | X23: =IFERROR(IF(OR(R23<>"Yes",Q23<>"City"),0,IF(S23="Cash capital",IF(T23<=5,IF(O23<>"",O23,MAX(0,N(F23)+N(K23))*IF(N23<>"",N23,M23)),0),IF(S23="Debt service",IF(T23>5,0,AI23*MAX(0,MIN(5-T23+1,U23))),IF(OR(S23="Annual O&M",S23="Maintenance-only"),IF(T23>5,0,IF(O23<>"",O23,MAX(0,N(F23)+N(K23))*IF(N23<>"",N23,M23))*MAX(0,5-T23+1)),0)))),0) -> 0 | Y23: =IFERROR(IF(OR(R23<>"Yes",Q23<>"City"),0,IF(S23="Cash capital",IF(T23<=10,IF(O23<>"",O23,MAX(0,N(G23)+N(K23))*IF(N23<>"",N23,M23)),0),IF(S23="Debt service",IF(T23>10,0,AJ23*MAX(0,MIN(10-T23+1,U23))),IF(OR(S23="Annual O&M",S23="Maintenance-only"),IF(T23>10,0,IF(O23<>"",O23,MAX(0,N(G23)+N(K23))*IF(N23<>"",N23,M23))*MAX(0,10-T23+1)),0)))),0) -> 0 | Z23: =IFERROR(IF(OR(R23<>"Yes",Q23<>"City"),0,IF(S23="Cash capital",IF(T23<=15,IF(O23<>"",O23,MAX(0,N(H23)+N(K23))*IF(N23<>"",N23,M23)),0),IF(S23="Debt service",IF(T23>15,0,AK23*MAX(0,MIN(15-T23+1,U23))),IF(OR(S23="Annual O&M",S23="Maintenance-only"),IF(T23>15,0,IF(O23<>"",O23,MAX(0,N(H23)+N(K23))*IF(N23<>"",N23,M23))*MAX(0,15-T23+1)),0)))),0) -> 0 | AA23: =IFERROR(IF(OR(R23<>"Yes",Q23<>"City"),0,IF(S23="Cash capital",IF(T23<=20,IF(O23<>"",O23,MAX(0,N(I23)+N(K23))*IF(N23<>"",N23,M23)),0),IF(S23="Debt service",IF(T23>20,0,AL23*MAX(0,MIN(20-T23+1,U23))),IF(OR(S23="Annual O&M",S23="Maintenance-only"),IF(T23>20,0,IF(O23<>"",O23,MAX(0,N(I23)+N(K23))*IF(N23<>"",N23,M23))*MAX(0,20-T23+1)),0)))),0) -> 0 | AB23: =IFERROR(IF(OR(R23<>"Yes",Q23<>"City"),0,IF(S23="Cash capital",IF(T23<=30,IF(O23<>"",O23,MAX(0,N(J23)+N(K23))*IF(N23<>"",N23,M23)),0),IF(S23="Debt service",IF(T23>30,0,AM23*MAX(0,MIN(30-T23+1,U23))),IF(OR(S23="Annual O&M",S23="Maintenance-only"),IF(T23>30,0,IF(O23<>"",O23,MAX(0,N(J23)+N(K23))*IF(N23<>"",N23,M23))*MAX(0,30-T23+1)),0)))),0) -> 0 | AC23: =IFERROR(IF(OR(R23<>"Yes",Q23<>"ESD"),0,IF(S23="Cash capital",IF(T23<=5,IF(O23<>"",O23,MAX(0,N(F23)+N(K23))*IF(N23<>"",N23,M23)),0),IF(S23="Debt service",IF(T23>5,0,AI23*MAX(0,MIN(5-T23+1,U23))),IF(OR(S23="Annual O&M",S23="Maintenance-only"),IF(T23>5,0,IF(O23<>"",O23,MAX(0,N(F23)+N(K23))*IF(N23<>"",N23,M23))*MAX(0,5-T23+1)),0)))),0) -> 0 | AD23: =IFERROR(IF(OR(R23<>"Yes",Q23<>"ESD"),0,IF(S23="Cash capital",IF(T23<=10,IF(O23<>"",O23,MAX(0,N(G23)+N(K23))*IF(N23<>"",N23,M23)),0),IF(S23="Debt service",IF(T23>10,0,AJ23*MAX(0,MIN(10-T23+1,U23))),IF(OR(S23="Annual O&M",S23="Maintenance-only"),IF(T23>10,0,IF(O23<>"",O23,MAX(0,N(G23)+N(K23))*IF(N23<>"",N23,M23))*MAX(0,10-T23+1)),0)))),0) -> 0 | AE23: =IFERROR(IF(OR(R23<>"Yes",Q23<>"ESD"),0,IF(S23="Cash capital",IF(T23<=15,IF(O23<>"",O23,MAX(0,N(H23)+N(K23))*IF(N23<>"",N23,M23)),0),IF(S23="Debt service",IF(T23>15,0,AK23*MAX(0,MIN(15-T23+1,U23))),IF(OR(S23="Annual O&M",S23="Maintenance-only"),IF(T23>15,0,IF(O23<>"",O23,MAX(0,N(H23)+N(K23))*IF(N23<>"",N23,M23))*MAX(0,15-T23+1)),0)))),0) -> 0 | AF23: =IFERROR(IF(OR(R23<>"Yes",Q23<>"ESD"),0,IF(S23="Cash capital",IF(T23<=20,IF(O23<>"",O23,MAX(0,N(I23)+N(K23))*IF(N23<>"",N23,M23)),0),IF(S23="Debt service",IF(T23>20,0,AL23*MAX(0,MIN(20-T23+1,U23))),IF(OR(S23="Annual O&M",S23="Maintenance-only"),IF(T23>20,0,IF(O23<>"",O23,MAX(0,N(I23)+N(K23))*IF(N23<>"",N23,M23))*MAX(0,20-T23+1)),0)))),0) -> 0 | AG23: =IFERROR(IF(OR(R23<>"Yes",Q23<>"ESD"),0,IF(S23="Cash capital",IF(T23<=30,IF(O23<>"",O23,MAX(0,N(J23)+N(K23))*IF(N23<>"",N23,M23)),0),IF(S23="Debt service",IF(T23>30,0,AM23*MAX(0,MIN(30-T23+1,U23))),IF(OR(S23="Annual O&M",S23="Maintenance-only"),IF(T23>30,0,IF(O23<>"",O23,MAX(0,N(J23)+N(K23))*IF(N23<>"",N23,M23))*MAX(0,30-T23+1)),0)))),0) -> 0 | AH23: Apparatus trigger; may require manual override for tall/industrial risk. | Takeoff factor: 14000 captured residents; confidence Low; validate w/ ESD #2. | AI23: =IFERROR(IF(U23>0,IF(O23<>"",O23,MAX(0,N(F23)+N(K23))*IF(N23<>"",N23,M23))*IF(V23=0,1/U23,V23/(1-(1+V23)^(-U23))),0),0) -> 0 | AJ23: =IFERROR(IF(U23>0,IF(O23<>"",O23,MAX(0,N(G23)+N(K23))*IF(N23<>"",N23,M23))*IF(V23=0,1/U23,V23/(1-(1+V23)^(-U23))),0),0) -> 0 | AK23: =IFERROR(IF(U23>0,IF(O23<>"",O23,MAX(0,N(H23)+N(K23))*IF(N23<>"",N23,M23))*IF(V23=0,1/U23,V23/(1-(1+V23)^(-U23))),0),0) -> 0 | AL23: =IFERROR(IF(U23>0,IF(O23<>"",O23,MAX(0,N(I23)+N(K23))*IF(N23<>"",N23,M23))*IF(V23=0,1/U23,V23/(1-(1+V23)^(-U23))),0),0) -> 0 | AM23: =IFERROR(IF(U23>0,IF(O23<>"",O23,MAX(0,N(J23)+N(K23))*IF(N23<>"",N23,M23))*IF(V23=0,1/U23,V23/(1-(1+V23)^(-U23))),0),0) -> 0
A24: Brush trucks | B24: ESD | C24: captured acres | D24: each | E24: threshold 1,500 ac | F24: =IF('03_Multi_Horizon_Results'!$B$5>='12_Takeoff_Assumptions'!$B$21,INT('03_Multi_Horizon_Results'!$B$5/'12_Takeoff_Assumptions'!$B$21),0) -> 0 | G24: =IF('03_Multi_Horizon_Results'!$C$5>='12_Takeoff_Assumptions'!$B$21,INT('03_Multi_Horizon_Results'!$C$5/'12_Takeoff_Assumptions'!$B$21),0) -> 0 | H24: =IF('03_Multi_Horizon_Results'!$D$5>='12_Takeoff_Assumptions'!$B$21,INT('03_Multi_Horizon_Results'!$D$5/'12_Takeoff_Assumptions'!$B$21),0) -> 0 | I24: =IF('03_Multi_Horizon_Results'!$E$5>='12_Takeoff_Assumptions'!$B$21,INT('03_Multi_Horizon_Results'!$E$5/'12_Takeoff_Assumptions'!$B$21),0) -> 0 | J24: =IF('03_Multi_Horizon_Results'!$F$5>='12_Takeoff_Assumptions'!$B$21,INT('03_Multi_Horizon_Results'!$F$5/'12_Takeoff_Assumptions'!$B$21),0) -> 0 | L24: =MAX(0,N(G24)+N(K24)) -> 0 | M24: 400000 | P24: =IFERROR(IF(O24<>"",O24,L24*IF(N24<>"",N24,M24)),0) -> 0 | Q24: ESD | R24: Yes | S24: Cash capital | T24: 1 | U24: 20 | V24: 0.045 | W24: =IFERROR(IF(AND(R24="Yes",S24="Debt service",U24>0),IF(V24=0,P24/U24,P24*V24/(1-(1+V24)^(-U24))),0),0) -> 0 | X24: =IFERROR(IF(OR(R24<>"Yes",Q24<>"City"),0,IF(S24="Cash capital",IF(T24<=5,IF(O24<>"",O24,MAX(0,N(F24)+N(K24))*IF(N24<>"",N24,M24)),0),IF(S24="Debt service",IF(T24>5,0,AI24*MAX(0,MIN(5-T24+1,U24))),IF(OR(S24="Annual O&M",S24="Maintenance-only"),IF(T24>5,0,IF(O24<>"",O24,MAX(0,N(F24)+N(K24))*IF(N24<>"",N24,M24))*MAX(0,5-T24+1)),0)))),0) -> 0 | Y24: =IFERROR(IF(OR(R24<>"Yes",Q24<>"City"),0,IF(S24="Cash capital",IF(T24<=10,IF(O24<>"",O24,MAX(0,N(G24)+N(K24))*IF(N24<>"",N24,M24)),0),IF(S24="Debt service",IF(T24>10,0,AJ24*MAX(0,MIN(10-T24+1,U24))),IF(OR(S24="Annual O&M",S24="Maintenance-only"),IF(T24>10,0,IF(O24<>"",O24,MAX(0,N(G24)+N(K24))*IF(N24<>"",N24,M24))*MAX(0,10-T24+1)),0)))),0) -> 0 | Z24: =IFERROR(IF(OR(R24<>"Yes",Q24<>"City"),0,IF(S24="Cash capital",IF(T24<=15,IF(O24<>"",O24,MAX(0,N(H24)+N(K24))*IF(N24<>"",N24,M24)),0),IF(S24="Debt service",IF(T24>15,0,AK24*MAX(0,MIN(15-T24+1,U24))),IF(OR(S24="Annual O&M",S24="Maintenance-only"),IF(T24>15,0,IF(O24<>"",O24,MAX(0,N(H24)+N(K24))*IF(N24<>"",N24,M24))*MAX(0,15-T24+1)),0)))),0) -> 0 | AA24: =IFERROR(IF(OR(R24<>"Yes",Q24<>"City"),0,IF(S24="Cash capital",IF(T24<=20,IF(O24<>"",O24,MAX(0,N(I24)+N(K24))*IF(N24<>"",N24,M24)),0),IF(S24="Debt service",IF(T24>20,0,AL24*MAX(0,MIN(20-T24+1,U24))),IF(OR(S24="Annual O&M",S24="Maintenance-only"),IF(T24>20,0,IF(O24<>"",O24,MAX(0,N(I24)+N(K24))*IF(N24<>"",N24,M24))*MAX(0,20-T24+1)),0)))),0) -> 0 | AB24: =IFERROR(IF(OR(R24<>"Yes",Q24<>"City"),0,IF(S24="Cash capital",IF(T24<=30,IF(O24<>"",O24,MAX(0,N(J24)+N(K24))*IF(N24<>"",N24,M24)),0),IF(S24="Debt service",IF(T24>30,0,AM24*MAX(0,MIN(30-T24+1,U24))),IF(OR(S24="Annual O&M",S24="Maintenance-only"),IF(T24>30,0,IF(O24<>"",O24,MAX(0,N(J24)+N(K24))*IF(N24<>"",N24,M24))*MAX(0,30-T24+1)),0)))),0) -> 0 | AC24: =IFERROR(IF(OR(R24<>"Yes",Q24<>"ESD"),0,IF(S24="Cash capital",IF(T24<=5,IF(O24<>"",O24,MAX(0,N(F24)+N(K24))*IF(N24<>"",N24,M24)),0),IF(S24="Debt service",IF(T24>5,0,AI24*MAX(0,MIN(5-T24+1,U24))),IF(OR(S24="Annual O&M",S24="Maintenance-only"),IF(T24>5,0,IF(O24<>"",O24,MAX(0,N(F24)+N(K24))*IF(N24<>"",N24,M24))*MAX(0,5-T24+1)),0)))),0) -> 0 | AD24: =IFERROR(IF(OR(R24<>"Yes",Q24<>"ESD"),0,IF(S24="Cash capital",IF(T24<=10,IF(O24<>"",O24,MAX(0,N(G24)+N(K24))*IF(N24<>"",N24,M24)),0),IF(S24="Debt service",IF(T24>10,0,AJ24*MAX(0,MIN(10-T24+1,U24))),IF(OR(S24="Annual O&M",S24="Maintenance-only"),IF(T24>10,0,IF(O24<>"",O24,MAX(0,N(G24)+N(K24))*IF(N24<>"",N24,M24))*MAX(0,10-T24+1)),0)))),0) -> 0 | AE24: =IFERROR(IF(OR(R24<>"Yes",Q24<>"ESD"),0,IF(S24="Cash capital",IF(T24<=15,IF(O24<>"",O24,MAX(0,N(H24)+N(K24))*IF(N24<>"",N24,M24)),0),IF(S24="Debt service",IF(T24>15,0,AK24*MAX(0,MIN(15-T24+1,U24))),IF(OR(S24="Annual O&M",S24="Maintenance-only"),IF(T24>15,0,IF(O24<>"",O24,MAX(0,N(H24)+N(K24))*IF(N24<>"",N24,M24))*MAX(0,15-T24+1)),0)))),0) -> 0 | AF24: =IFERROR(IF(OR(R24<>"Yes",Q24<>"ESD"),0,IF(S24="Cash capital",IF(T24<=20,IF(O24<>"",O24,MAX(0,N(I24)+N(K24))*IF(N24<>"",N24,M24)),0),IF(S24="Debt service",IF(T24>20,0,AL24*MAX(0,MIN(20-T24+1,U24))),IF(OR(S24="Annual O&M",S24="Maintenance-only"),IF(T24>20,0,IF(O24<>"",O24,MAX(0,N(I24)+N(K24))*IF(N24<>"",N24,M24))*MAX(0,20-T24+1)),0)))),0) -> 0 | AG24: =IFERROR(IF(OR(R24<>"Yes",Q24<>"ESD"),0,IF(S24="Cash capital",IF(T24<=30,IF(O24<>"",O24,MAX(0,N(J24)+N(K24))*IF(N24<>"",N24,M24)),0),IF(S24="Debt service",IF(T24>30,0,AM24*MAX(0,MIN(30-T24+1,U24))),IF(OR(S24="Annual O&M",S24="Maintenance-only"),IF(T24>30,0,IF(O24<>"",O24,MAX(0,N(J24)+N(K24))*IF(N24<>"",N24,M24))*MAX(0,30-T24+1)),0)))),0) -> 0 | AH24: Wildland/acreage exposure trigger; ESD validation required. | Takeoff factor: 1500 captured acres; confidence Low; validate w/ ESD #2. | AI24: =IFERROR(IF(U24>0,IF(O24<>"",O24,MAX(0,N(F24)+N(K24))*IF(N24<>"",N24,M24))*IF(V24=0,1/U24,V24/(1-(1+V24)^(-U24))),0),0) -> 0 | AJ24: =IFERROR(IF(U24>0,IF(O24<>"",O24,MAX(0,N(G24)+N(K24))*IF(N24<>"",N24,M24))*IF(V24=0,1/U24,V24/(1-(1+V24)^(-U24))),0),0) -> 0 | AK24: =IFERROR(IF(U24>0,IF(O24<>"",O24,MAX(0,N(H24)+N(K24))*IF(N24<>"",N24,M24))*IF(V24=0,1/U24,V24/(1-(1+V24)^(-U24))),0),0) -> 0 | AL24: =IFERROR(IF(U24>0,IF(O24<>"",O24,MAX(0,N(I24)+N(K24))*IF(N24<>"",N24,M24))*IF(V24=0,1/U24,V24/(1-(1+V24)^(-U24))),0),0) -> 0 | AM24: =IFERROR(IF(U24>0,IF(O24<>"",O24,MAX(0,N(J24)+N(K24))*IF(N24<>"",N24,M24))*IF(V24=0,1/U24,V24/(1-(1+V24)^(-U24))),0),0) -> 0
A25: Command vehicles | B25: ESD | C25: fire stations | D25: each | E25: 1 per station | F25: =IF('03_Multi_Horizon_Results'!$B$7>='12_Takeoff_Assumptions'!$B$18,INT('03_Multi_Horizon_Results'!$B$7/'12_Takeoff_Assumptions'!$B$18),0) -> 0 | G25: =IF('03_Multi_Horizon_Results'!$C$7>='12_Takeoff_Assumptions'!$B$18,INT('03_Multi_Horizon_Results'!$C$7/'12_Takeoff_Assumptions'!$B$18),0) -> 0 | H25: =IF('03_Multi_Horizon_Results'!$D$7>='12_Takeoff_Assumptions'!$B$18,INT('03_Multi_Horizon_Results'!$D$7/'12_Takeoff_Assumptions'!$B$18),0) -> 0 | I25: =IF('03_Multi_Horizon_Results'!$E$7>='12_Takeoff_Assumptions'!$B$18,INT('03_Multi_Horizon_Results'!$E$7/'12_Takeoff_Assumptions'!$B$18),0) -> 0 | J25: =IF('03_Multi_Horizon_Results'!$F$7>='12_Takeoff_Assumptions'!$B$18,INT('03_Multi_Horizon_Results'!$F$7/'12_Takeoff_Assumptions'!$B$18),0) -> 0 | L25: =MAX(0,N(G25)+N(K25)) -> 0 | M25: 85000 | P25: =IFERROR(IF(O25<>"",O25,L25*IF(N25<>"",N25,M25)),0) -> 0 | Q25: ESD | R25: Yes | S25: Cash capital | T25: 1 | U25: 20 | V25: 0.045 | W25: =IFERROR(IF(AND(R25="Yes",S25="Debt service",U25>0),IF(V25=0,P25/U25,P25*V25/(1-(1+V25)^(-U25))),0),0) -> 0 | X25: =IFERROR(IF(OR(R25<>"Yes",Q25<>"City"),0,IF(S25="Cash capital",IF(T25<=5,IF(O25<>"",O25,MAX(0,N(F25)+N(K25))*IF(N25<>"",N25,M25)),0),IF(S25="Debt service",IF(T25>5,0,AI25*MAX(0,MIN(5-T25+1,U25))),IF(OR(S25="Annual O&M",S25="Maintenance-only"),IF(T25>5,0,IF(O25<>"",O25,MAX(0,N(F25)+N(K25))*IF(N25<>"",N25,M25))*MAX(0,5-T25+1)),0)))),0) -> 0 | Y25: =IFERROR(IF(OR(R25<>"Yes",Q25<>"City"),0,IF(S25="Cash capital",IF(T25<=10,IF(O25<>"",O25,MAX(0,N(G25)+N(K25))*IF(N25<>"",N25,M25)),0),IF(S25="Debt service",IF(T25>10,0,AJ25*MAX(0,MIN(10-T25+1,U25))),IF(OR(S25="Annual O&M",S25="Maintenance-only"),IF(T25>10,0,IF(O25<>"",O25,MAX(0,N(G25)+N(K25))*IF(N25<>"",N25,M25))*MAX(0,10-T25+1)),0)))),0) -> 0 | Z25: =IFERROR(IF(OR(R25<>"Yes",Q25<>"City"),0,IF(S25="Cash capital",IF(T25<=15,IF(O25<>"",O25,MAX(0,N(H25)+N(K25))*IF(N25<>"",N25,M25)),0),IF(S25="Debt service",IF(T25>15,0,AK25*MAX(0,MIN(15-T25+1,U25))),IF(OR(S25="Annual O&M",S25="Maintenance-only"),IF(T25>15,0,IF(O25<>"",O25,MAX(0,N(H25)+N(K25))*IF(N25<>"",N25,M25))*MAX(0,15-T25+1)),0)))),0) -> 0 | AA25: =IFERROR(IF(OR(R25<>"Yes",Q25<>"City"),0,IF(S25="Cash capital",IF(T25<=20,IF(O25<>"",O25,MAX(0,N(I25)+N(K25))*IF(N25<>"",N25,M25)),0),IF(S25="Debt service",IF(T25>20,0,AL25*MAX(0,MIN(20-T25+1,U25))),IF(OR(S25="Annual O&M",S25="Maintenance-only"),IF(T25>20,0,IF(O25<>"",O25,MAX(0,N(I25)+N(K25))*IF(N25<>"",N25,M25))*MAX(0,20-T25+1)),0)))),0) -> 0 | AB25: =IFERROR(IF(OR(R25<>"Yes",Q25<>"City"),0,IF(S25="Cash capital",IF(T25<=30,IF(O25<>"",O25,MAX(0,N(J25)+N(K25))*IF(N25<>"",N25,M25)),0),IF(S25="Debt service",IF(T25>30,0,AM25*MAX(0,MIN(30-T25+1,U25))),IF(OR(S25="Annual O&M",S25="Maintenance-only"),IF(T25>30,0,IF(O25<>"",O25,MAX(0,N(J25)+N(K25))*IF(N25<>"",N25,M25))*MAX(0,30-T25+1)),0)))),0) -> 0 | AC25: =IFERROR(IF(OR(R25<>"Yes",Q25<>"ESD"),0,IF(S25="Cash capital",IF(T25<=5,IF(O25<>"",O25,MAX(0,N(F25)+N(K25))*IF(N25<>"",N25,M25)),0),IF(S25="Debt service",IF(T25>5,0,AI25*MAX(0,MIN(5-T25+1,U25))),IF(OR(S25="Annual O&M",S25="Maintenance-only"),IF(T25>5,0,IF(O25<>"",O25,MAX(0,N(F25)+N(K25))*IF(N25<>"",N25,M25))*MAX(0,5-T25+1)),0)))),0) -> 0 | AD25: =IFERROR(IF(OR(R25<>"Yes",Q25<>"ESD"),0,IF(S25="Cash capital",IF(T25<=10,IF(O25<>"",O25,MAX(0,N(G25)+N(K25))*IF(N25<>"",N25,M25)),0),IF(S25="Debt service",IF(T25>10,0,AJ25*MAX(0,MIN(10-T25+1,U25))),IF(OR(S25="Annual O&M",S25="Maintenance-only"),IF(T25>10,0,IF(O25<>"",O25,MAX(0,N(G25)+N(K25))*IF(N25<>"",N25,M25))*MAX(0,10-T25+1)),0)))),0) -> 0 | AE25: =IFERROR(IF(OR(R25<>"Yes",Q25<>"ESD"),0,IF(S25="Cash capital",IF(T25<=15,IF(O25<>"",O25,MAX(0,N(H25)+N(K25))*IF(N25<>"",N25,M25)),0),IF(S25="Debt service",IF(T25>15,0,AK25*MAX(0,MIN(15-T25+1,U25))),IF(OR(S25="Annual O&M",S25="Maintenance-only"),IF(T25>15,0,IF(O25<>"",O25,MAX(0,N(H25)+N(K25))*IF(N25<>"",N25,M25))*MAX(0,15-T25+1)),0)))),0) -> 0 | AF25: =IFERROR(IF(OR(R25<>"Yes",Q25<>"ESD"),0,IF(S25="Cash capital",IF(T25<=20,IF(O25<>"",O25,MAX(0,N(I25)+N(K25))*IF(N25<>"",N25,M25)),0),IF(S25="Debt service",IF(T25>20,0,AL25*MAX(0,MIN(20-T25+1,U25))),IF(OR(S25="Annual O&M",S25="Maintenance-only"),IF(T25>20,0,IF(O25<>"",O25,MAX(0,N(I25)+N(K25))*IF(N25<>"",N25,M25))*MAX(0,20-T25+1)),0)))),0) -> 0 | AG25: =IFERROR(IF(OR(R25<>"Yes",Q25<>"ESD"),0,IF(S25="Cash capital",IF(T25<=30,IF(O25<>"",O25,MAX(0,N(J25)+N(K25))*IF(N25<>"",N25,M25)),0),IF(S25="Debt service",IF(T25>30,0,AM25*MAX(0,MIN(30-T25+1,U25))),IF(OR(S25="Annual O&M",S25="Maintenance-only"),IF(T25>30,0,IF(O25<>"",O25,MAX(0,N(J25)+N(K25))*IF(N25<>"",N25,M25))*MAX(0,30-T25+1)),0)))),0) -> 0 | AH25: Command vehicle allowance tied to fire station trigger. | AI25: =IFERROR(IF(U25>0,IF(O25<>"",O25,MAX(0,N(F25)+N(K25))*IF(N25<>"",N25,M25))*IF(V25=0,1/U25,V25/(1-(1+V25)^(-U25))),0),0) -> 0 | AJ25: =IFERROR(IF(U25>0,IF(O25<>"",O25,MAX(0,N(G25)+N(K25))*IF(N25<>"",N25,M25))*IF(V25=0,1/U25,V25/(1-(1+V25)^(-U25))),0),0) -> 0 | AK25: =IFERROR(IF(U25>0,IF(O25<>"",O25,MAX(0,N(H25)+N(K25))*IF(N25<>"",N25,M25))*IF(V25=0,1/U25,V25/(1-(1+V25)^(-U25))),0),0) -> 0 | AL25: =IFERROR(IF(U25>0,IF(O25<>"",O25,MAX(0,N(I25)+N(K25))*IF(N25<>"",N25,M25))*IF(V25=0,1/U25,V25/(1-(1+V25)^(-U25))),0),0) -> 0 | AM25: =IFERROR(IF(U25>0,IF(O25<>"",O25,MAX(0,N(J25)+N(K25))*IF(N25<>"",N25,M25))*IF(V25=0,1/U25,V25/(1-(1+V25)^(-U25))),0),0) -> 0
A26: SCBA / PPE sets | B26: ESD | C26: firefighter FTE | D26: sets | E26: 1 set/FTE | F26: =('03_Multi_Horizon_Results'!$B$7/1000*'12_Takeoff_Assumptions'!$B$22)*'12_Takeoff_Assumptions'!$B$27 -> 0.27 | G26: =('03_Multi_Horizon_Results'!$C$7/1000*'12_Takeoff_Assumptions'!$B$22)*'12_Takeoff_Assumptions'!$B$27 -> 0.27 | H26: =('03_Multi_Horizon_Results'!$D$7/1000*'12_Takeoff_Assumptions'!$B$22)*'12_Takeoff_Assumptions'!$B$27 -> 0.27 | I26: =('03_Multi_Horizon_Results'!$E$7/1000*'12_Takeoff_Assumptions'!$B$22)*'12_Takeoff_Assumptions'!$B$27 -> 0.27 | J26: =('03_Multi_Horizon_Results'!$F$7/1000*'12_Takeoff_Assumptions'!$B$22)*'12_Takeoff_Assumptions'!$B$27 -> 0.27 | L26: =MAX(0,N(G26)+N(K26)) -> 0.27 | M26: 12500 | P26: =IFERROR(IF(O26<>"",O26,L26*IF(N26<>"",N26,M26)),0) -> 3375 | Q26: ESD | R26: Yes | S26: Cash capital | T26: 1 | U26: 20 | V26: 0.045 | W26: =IFERROR(IF(AND(R26="Yes",S26="Debt service",U26>0),IF(V26=0,P26/U26,P26*V26/(1-(1+V26)^(-U26))),0),0) -> 0 | X26: =IFERROR(IF(OR(R26<>"Yes",Q26<>"City"),0,IF(S26="Cash capital",IF(T26<=5,IF(O26<>"",O26,MAX(0,N(F26)+N(K26))*IF(N26<>"",N26,M26)),0),IF(S26="Debt service",IF(T26>5,0,AI26*MAX(0,MIN(5-T26+1,U26))),IF(OR(S26="Annual O&M",S26="Maintenance-only"),IF(T26>5,0,IF(O26<>"",O26,MAX(0,N(F26)+N(K26))*IF(N26<>"",N26,M26))*MAX(0,5-T26+1)),0)))),0) -> 0 | Y26: =IFERROR(IF(OR(R26<>"Yes",Q26<>"City"),0,IF(S26="Cash capital",IF(T26<=10,IF(O26<>"",O26,MAX(0,N(G26)+N(K26))*IF(N26<>"",N26,M26)),0),IF(S26="Debt service",IF(T26>10,0,AJ26*MAX(0,MIN(10-T26+1,U26))),IF(OR(S26="Annual O&M",S26="Maintenance-only"),IF(T26>10,0,IF(O26<>"",O26,MAX(0,N(G26)+N(K26))*IF(N26<>"",N26,M26))*MAX(0,10-T26+1)),0)))),0) -> 0 | Z26: =IFERROR(IF(OR(R26<>"Yes",Q26<>"City"),0,IF(S26="Cash capital",IF(T26<=15,IF(O26<>"",O26,MAX(0,N(H26)+N(K26))*IF(N26<>"",N26,M26)),0),IF(S26="Debt service",IF(T26>15,0,AK26*MAX(0,MIN(15-T26+1,U26))),IF(OR(S26="Annual O&M",S26="Maintenance-only"),IF(T26>15,0,IF(O26<>"",O26,MAX(0,N(H26)+N(K26))*IF(N26<>"",N26,M26))*MAX(0,15-T26+1)),0)))),0) -> 0 | AA26: =IFERROR(IF(OR(R26<>"Yes",Q26<>"City"),0,IF(S26="Cash capital",IF(T26<=20,IF(O26<>"",O26,MAX(0,N(I26)+N(K26))*IF(N26<>"",N26,M26)),0),IF(S26="Debt service",IF(T26>20,0,AL26*MAX(0,MIN(20-T26+1,U26))),IF(OR(S26="Annual O&M",S26="Maintenance-only"),IF(T26>20,0,IF(O26<>"",O26,MAX(0,N(I26)+N(K26))*IF(N26<>"",N26,M26))*MAX(0,20-T26+1)),0)))),0) -> 0 | AB26: =IFERROR(IF(OR(R26<>"Yes",Q26<>"City"),0,IF(S26="Cash capital",IF(T26<=30,IF(O26<>"",O26,MAX(0,N(J26)+N(K26))*IF(N26<>"",N26,M26)),0),IF(S26="Debt service",IF(T26>30,0,AM26*MAX(0,MIN(30-T26+1,U26))),IF(OR(S26="Annual O&M",S26="Maintenance-only"),IF(T26>30,0,IF(O26<>"",O26,MAX(0,N(J26)+N(K26))*IF(N26<>"",N26,M26))*MAX(0,30-T26+1)),0)))),0) -> 0 | AC26: =IFERROR(IF(OR(R26<>"Yes",Q26<>"ESD"),0,IF(S26="Cash capital",IF(T26<=5,IF(O26<>"",O26,MAX(0,N(F26)+N(K26))*IF(N26<>"",N26,M26)),0),IF(S26="Debt service",IF(T26>5,0,AI26*MAX(0,MIN(5-T26+1,U26))),IF(OR(S26="Annual O&M",S26="Maintenance-only"),IF(T26>5,0,IF(O26<>"",O26,MAX(0,N(F26)+N(K26))*IF(N26<>"",N26,M26))*MAX(0,5-T26+1)),0)))),0) -> 3375 | AD26: =IFERROR(IF(OR(R26<>"Yes",Q26<>"ESD"),0,IF(S26="Cash capital",IF(T26<=10,IF(O26<>"",O26,MAX(0,N(G26)+N(K26))*IF(N26<>"",N26,M26)),0),IF(S26="Debt service",IF(T26>10,0,AJ26*MAX(0,MIN(10-T26+1,U26))),IF(OR(S26="Annual O&M",S26="Maintenance-only"),IF(T26>10,0,IF(O26<>"",O26,MAX(0,N(G26)+N(K26))*IF(N26<>"",N26,M26))*MAX(0,10-T26+1)),0)))),0) -> 3375 | AE26: =IFERROR(IF(OR(R26<>"Yes",Q26<>"ESD"),0,IF(S26="Cash capital",IF(T26<=15,IF(O26<>"",O26,MAX(0,N(H26)+N(K26))*IF(N26<>"",N26,M26)),0),IF(S26="Debt service",IF(T26>15,0,AK26*MAX(0,MIN(15-T26+1,U26))),IF(OR(S26="Annual O&M",S26="Maintenance-only"),IF(T26>15,0,IF(O26<>"",O26,MAX(0,N(H26)+N(K26))*IF(N26<>"",N26,M26))*MAX(0,15-T26+1)),0)))),0) -> 3375 | AF26: =IFERROR(IF(OR(R26<>"Yes",Q26<>"ESD"),0,IF(S26="Cash capital",IF(T26<=20,IF(O26<>"",O26,MAX(0,N(I26)+N(K26))*IF(N26<>"",N26,M26)),0),IF(S26="Debt service",IF(T26>20,0,AL26*MAX(0,MIN(20-T26+1,U26))),IF(OR(S26="Annual O&M",S26="Maintenance-only"),IF(T26>20,0,IF(O26<>"",O26,MAX(0,N(I26)+N(K26))*IF(N26<>"",N26,M26))*MAX(0,20-T26+1)),0)))),0) -> 3375 | AG26: =IFERROR(IF(OR(R26<>"Yes",Q26<>"ESD"),0,IF(S26="Cash capital",IF(T26<=30,IF(O26<>"",O26,MAX(0,N(J26)+N(K26))*IF(N26<>"",N26,M26)),0),IF(S26="Debt service",IF(T26>30,0,AM26*MAX(0,MIN(30-T26+1,U26))),IF(OR(S26="Annual O&M",S26="Maintenance-only"),IF(T26>30,0,IF(O26<>"",O26,MAX(0,N(J26)+N(K26))*IF(N26<>"",N26,M26))*MAX(0,30-T26+1)),0)))),0) -> 3375 | AH26: Planning equipment allowance; validate with ESD equipment standards. | Takeoff factor: 1 set per FTE; confidence Low; validate w/ ESD #2. | AI26: =IFERROR(IF(U26>0,IF(O26<>"",O26,MAX(0,N(F26)+N(K26))*IF(N26<>"",N26,M26))*IF(V26=0,1/U26,V26/(1-(1+V26)^(-U26))),0),0) -> 259.45699 | AJ26: =IFERROR(IF(U26>0,IF(O26<>"",O26,MAX(0,N(G26)+N(K26))*IF(N26<>"",N26,M26))*IF(V26=0,1/U26,V26/(1-(1+V26)^(-U26))),0),0) -> 259.45699 | AK26: =IFERROR(IF(U26>0,IF(O26<>"",O26,MAX(0,N(H26)+N(K26))*IF(N26<>"",N26,M26))*IF(V26=0,1/U26,V26/(1-(1+V26)^(-U26))),0),0) -> 259.45699 | AL26: =IFERROR(IF(U26>0,IF(O26<>"",O26,MAX(0,N(I26)+N(K26))*IF(N26<>"",N26,M26))*IF(V26=0,1/U26,V26/(1-(1+V26)^(-U26))),0),0) -> 259.45699 | AM26: =IFERROR(IF(U26>0,IF(O26<>"",O26,MAX(0,N(J26)+N(K26))*IF(N26<>"",N26,M26))*IF(V26=0,1/U26,V26/(1-(1+V26)^(-U26))),0),0) -> 259.45699
A27: Firefighter / EMT FTEs | B27: ESD | C27: captured residents | D27: FTE | E27: 1.0 FTE/1,000 residents | F27: =('03_Multi_Horizon_Results'!$B$7/1000*'12_Takeoff_Assumptions'!$B$22) -> 0.27 | G27: =('03_Multi_Horizon_Results'!$C$7/1000*'12_Takeoff_Assumptions'!$B$22) -> 0.27 | H27: =('03_Multi_Horizon_Results'!$D$7/1000*'12_Takeoff_Assumptions'!$B$22) -> 0.27 | I27: =('03_Multi_Horizon_Results'!$E$7/1000*'12_Takeoff_Assumptions'!$B$22) -> 0.27 | J27: =('03_Multi_Horizon_Results'!$F$7/1000*'12_Takeoff_Assumptions'!$B$22) -> 0.27 | L27: =MAX(0,N(G27)+N(K27)) -> 0.27 | M27: 110000 | P27: =IFERROR(IF(O27<>"",O27,L27*IF(N27<>"",N27,M27)),0) -> 29700 | Q27: ESD | R27: Yes | S27: Annual O&M | T27: 1 | U27: 20 | V27: 0.045 | W27: =IFERROR(IF(AND(R27="Yes",S27="Debt service",U27>0),IF(V27=0,P27/U27,P27*V27/(1-(1+V27)^(-U27))),0),0) -> 0 | X27: =IFERROR(IF(OR(R27<>"Yes",Q27<>"City"),0,IF(S27="Cash capital",IF(T27<=5,IF(O27<>"",O27,MAX(0,N(F27)+N(K27))*IF(N27<>"",N27,M27)),0),IF(S27="Debt service",IF(T27>5,0,AI27*MAX(0,MIN(5-T27+1,U27))),IF(OR(S27="Annual O&M",S27="Maintenance-only"),IF(T27>5,0,IF(O27<>"",O27,MAX(0,N(F27)+N(K27))*IF(N27<>"",N27,M27))*MAX(0,5-T27+1)),0)))),0) -> 0 | Y27: =IFERROR(IF(OR(R27<>"Yes",Q27<>"City"),0,IF(S27="Cash capital",IF(T27<=10,IF(O27<>"",O27,MAX(0,N(G27)+N(K27))*IF(N27<>"",N27,M27)),0),IF(S27="Debt service",IF(T27>10,0,AJ27*MAX(0,MIN(10-T27+1,U27))),IF(OR(S27="Annual O&M",S27="Maintenance-only"),IF(T27>10,0,IF(O27<>"",O27,MAX(0,N(G27)+N(K27))*IF(N27<>"",N27,M27))*MAX(0,10-T27+1)),0)))),0) -> 0 | Z27: =IFERROR(IF(OR(R27<>"Yes",Q27<>"City"),0,IF(S27="Cash capital",IF(T27<=15,IF(O27<>"",O27,MAX(0,N(H27)+N(K27))*IF(N27<>"",N27,M27)),0),IF(S27="Debt service",IF(T27>15,0,AK27*MAX(0,MIN(15-T27+1,U27))),IF(OR(S27="Annual O&M",S27="Maintenance-only"),IF(T27>15,0,IF(O27<>"",O27,MAX(0,N(H27)+N(K27))*IF(N27<>"",N27,M27))*MAX(0,15-T27+1)),0)))),0) -> 0 | AA27: =IFERROR(IF(OR(R27<>"Yes",Q27<>"City"),0,IF(S27="Cash capital",IF(T27<=20,IF(O27<>"",O27,MAX(0,N(I27)+N(K27))*IF(N27<>"",N27,M27)),0),IF(S27="Debt service",IF(T27>20,0,AL27*MAX(0,MIN(20-T27+1,U27))),IF(OR(S27="Annual O&M",S27="Maintenance-only"),IF(T27>20,0,IF(O27<>"",O27,MAX(0,N(I27)+N(K27))*IF(N27<>"",N27,M27))*MAX(0,20-T27+1)),0)))),0) -> 0 | AB27: =IFERROR(IF(OR(R27<>"Yes",Q27<>"City"),0,IF(S27="Cash capital",IF(T27<=30,IF(O27<>"",O27,MAX(0,N(J27)+N(K27))*IF(N27<>"",N27,M27)),0),IF(S27="Debt service",IF(T27>30,0,AM27*MAX(0,MIN(30-T27+1,U27))),IF(OR(S27="Annual O&M",S27="Maintenance-only"),IF(T27>30,0,IF(O27<>"",O27,MAX(0,N(J27)+N(K27))*IF(N27<>"",N27,M27))*MAX(0,30-T27+1)),0)))),0) -> 0 | AC27: =IFERROR(IF(OR(R27<>"Yes",Q27<>"ESD"),0,IF(S27="Cash capital",IF(T27<=5,IF(O27<>"",O27,MAX(0,N(F27)+N(K27))*IF(N27<>"",N27,M27)),0),IF(S27="Debt service",IF(T27>5,0,AI27*MAX(0,MIN(5-T27+1,U27))),IF(OR(S27="Annual O&M",S27="Maintenance-only"),IF(T27>5,0,IF(O27<>"",O27,MAX(0,N(F27)+N(K27))*IF(N27<>"",N27,M27))*MAX(0,5-T27+1)),0)))),0) -> 148500 | AD27: =IFERROR(IF(OR(R27<>"Yes",Q27<>"ESD"),0,IF(S27="Cash capital",IF(T27<=10,IF(O27<>"",O27,MAX(0,N(G27)+N(K27))*IF(N27<>"",N27,M27)),0),IF(S27="Debt service",IF(T27>10,0,AJ27*MAX(0,MIN(10-T27+1,U27))),IF(OR(S27="Annual O&M",S27="Maintenance-only"),IF(T27>10,0,IF(O27<>"",O27,MAX(0,N(G27)+N(K27))*IF(N27<>"",N27,M27))*MAX(0,10-T27+1)),0)))),0) -> 297000 | AE27: =IFERROR(IF(OR(R27<>"Yes",Q27<>"ESD"),0,IF(S27="Cash capital",IF(T27<=15,IF(O27<>"",O27,MAX(0,N(H27)+N(K27))*IF(N27<>"",N27,M27)),0),IF(S27="Debt service",IF(T27>15,0,AK27*MAX(0,MIN(15-T27+1,U27))),IF(OR(S27="Annual O&M",S27="Maintenance-only"),IF(T27>15,0,IF(O27<>"",O27,MAX(0,N(H27)+N(K27))*IF(N27<>"",N27,M27))*MAX(0,15-T27+1)),0)))),0) -> 445500 | AF27: =IFERROR(IF(OR(R27<>"Yes",Q27<>"ESD"),0,IF(S27="Cash capital",IF(T27<=20,IF(O27<>"",O27,MAX(0,N(I27)+N(K27))*IF(N27<>"",N27,M27)),0),IF(S27="Debt service",IF(T27>20,0,AL27*MAX(0,MIN(20-T27+1,U27))),IF(OR(S27="Annual O&M",S27="Maintenance-only"),IF(T27>20,0,IF(O27<>"",O27,MAX(0,N(I27)+N(K27))*IF(N27<>"",N27,M27))*MAX(0,20-T27+1)),0)))),0) -> 594000 | AG27: =IFERROR(IF(OR(R27<>"Yes",Q27<>"ESD"),0,IF(S27="Cash capital",IF(T27<=30,IF(O27<>"",O27,MAX(0,N(J27)+N(K27))*IF(N27<>"",N27,M27)),0),IF(S27="Debt service",IF(T27>30,0,AM27*MAX(0,MIN(30-T27+1,U27))),IF(OR(S27="Annual O&M",S27="Maintenance-only"),IF(T27>30,0,IF(O27<>"",O27,MAX(0,N(J27)+N(K27))*IF(N27<>"",N27,M27))*MAX(0,30-T27+1)),0)))),0) -> 891000 | AH27: Fire/rescue and EMS-assist staffing benchmark; not ambulance transport staffing. | Takeoff factor: 1 FTE per 1,000 residents; confidence Low; validate w/ ESD #2. | AI27: =IFERROR(IF(U27>0,IF(O27<>"",O27,MAX(0,N(F27)+N(K27))*IF(N27<>"",N27,M27))*IF(V27=0,1/U27,V27/(1-(1+V27)^(-U27))),0),0) -> 2283.2215 | AJ27: =IFERROR(IF(U27>0,IF(O27<>"",O27,MAX(0,N(G27)+N(K27))*IF(N27<>"",N27,M27))*IF(V27=0,1/U27,V27/(1-(1+V27)^(-U27))),0),0) -> 2283.2215 | AK27: =IFERROR(IF(U27>0,IF(O27<>"",O27,MAX(0,N(H27)+N(K27))*IF(N27<>"",N27,M27))*IF(V27=0,1/U27,V27/(1-(1+V27)^(-U27))),0),0) -> 2283.2215 | AL27: =IFERROR(IF(U27>0,IF(O27<>"",O27,MAX(0,N(I27)+N(K27))*IF(N27<>"",N27,M27))*IF(V27=0,1/U27,V27/(1-(1+V27)^(-U27))),0),0) -> 2283.2215 | AM27: =IFERROR(IF(U27>0,IF(O27<>"",O27,MAX(0,N(J27)+N(K27))*IF(N27<>"",N27,M27))*IF(V27=0,1/U27,V27/(1-(1+V27)^(-U27))),0),0) -> 2283.2215
A28: Fire officer FTEs | B28: ESD | C28: firefighter FTE | D28: FTE | E28: 1 officer / 5 firefighter FTE | F28: =('03_Multi_Horizon_Results'!$B$7/1000*'12_Takeoff_Assumptions'!$B$22)/'12_Takeoff_Assumptions'!$B$23 -> 0.054 | G28: =('03_Multi_Horizon_Results'!$C$7/1000*'12_Takeoff_Assumptions'!$B$22)/'12_Takeoff_Assumptions'!$B$23 -> 0.054 | H28: =('03_Multi_Horizon_Results'!$D$7/1000*'12_Takeoff_Assumptions'!$B$22)/'12_Takeoff_Assumptions'!$B$23 -> 0.054 | I28: =('03_Multi_Horizon_Results'!$E$7/1000*'12_Takeoff_Assumptions'!$B$22)/'12_Takeoff_Assumptions'!$B$23 -> 0.054 | J28: =('03_Multi_Horizon_Results'!$F$7/1000*'12_Takeoff_Assumptions'!$B$22)/'12_Takeoff_Assumptions'!$B$23 -> 0.054 | L28: =MAX(0,N(G28)+N(K28)) -> 0.054 | M28: 135000 | P28: =IFERROR(IF(O28<>"",O28,L28*IF(N28<>"",N28,M28)),0) -> 7290 | Q28: ESD | R28: Yes | S28: Annual O&M | T28: 1 | U28: 20 | V28: 0.045 | W28: =IFERROR(IF(AND(R28="Yes",S28="Debt service",U28>0),IF(V28=0,P28/U28,P28*V28/(1-(1+V28)^(-U28))),0),0) -> 0 | X28: =IFERROR(IF(OR(R28<>"Yes",Q28<>"City"),0,IF(S28="Cash capital",IF(T28<=5,IF(O28<>"",O28,MAX(0,N(F28)+N(K28))*IF(N28<>"",N28,M28)),0),IF(S28="Debt service",IF(T28>5,0,AI28*MAX(0,MIN(5-T28+1,U28))),IF(OR(S28="Annual O&M",S28="Maintenance-only"),IF(T28>5,0,IF(O28<>"",O28,MAX(0,N(F28)+N(K28))*IF(N28<>"",N28,M28))*MAX(0,5-T28+1)),0)))),0) -> 0 | Y28: =IFERROR(IF(OR(R28<>"Yes",Q28<>"City"),0,IF(S28="Cash capital",IF(T28<=10,IF(O28<>"",O28,MAX(0,N(G28)+N(K28))*IF(N28<>"",N28,M28)),0),IF(S28="Debt service",IF(T28>10,0,AJ28*MAX(0,MIN(10-T28+1,U28))),IF(OR(S28="Annual O&M",S28="Maintenance-only"),IF(T28>10,0,IF(O28<>"",O28,MAX(0,N(G28)+N(K28))*IF(N28<>"",N28,M28))*MAX(0,10-T28+1)),0)))),0) -> 0 | Z28: =IFERROR(IF(OR(R28<>"Yes",Q28<>"City"),0,IF(S28="Cash capital",IF(T28<=15,IF(O28<>"",O28,MAX(0,N(H28)+N(K28))*IF(N28<>"",N28,M28)),0),IF(S28="Debt service",IF(T28>15,0,AK28*MAX(0,MIN(15-T28+1,U28))),IF(OR(S28="Annual O&M",S28="Maintenance-only"),IF(T28>15,0,IF(O28<>"",O28,MAX(0,N(H28)+N(K28))*IF(N28<>"",N28,M28))*MAX(0,15-T28+1)),0)))),0) -> 0 | AA28: =IFERROR(IF(OR(R28<>"Yes",Q28<>"City"),0,IF(S28="Cash capital",IF(T28<=20,IF(O28<>"",O28,MAX(0,N(I28)+N(K28))*IF(N28<>"",N28,M28)),0),IF(S28="Debt service",IF(T28>20,0,AL28*MAX(0,MIN(20-T28+1,U28))),IF(OR(S28="Annual O&M",S28="Maintenance-only"),IF(T28>20,0,IF(O28<>"",O28,MAX(0,N(I28)+N(K28))*IF(N28<>"",N28,M28))*MAX(0,20-T28+1)),0)))),0) -> 0 | AB28: =IFERROR(IF(OR(R28<>"Yes",Q28<>"City"),0,IF(S28="Cash capital",IF(T28<=30,IF(O28<>"",O28,MAX(0,N(J28)+N(K28))*IF(N28<>"",N28,M28)),0),IF(S28="Debt service",IF(T28>30,0,AM28*MAX(0,MIN(30-T28+1,U28))),IF(OR(S28="Annual O&M",S28="Maintenance-only"),IF(T28>30,0,IF(O28<>"",O28,MAX(0,N(J28)+N(K28))*IF(N28<>"",N28,M28))*MAX(0,30-T28+1)),0)))),0) -> 0 | AC28: =IFERROR(IF(OR(R28<>"Yes",Q28<>"ESD"),0,IF(S28="Cash capital",IF(T28<=5,IF(O28<>"",O28,MAX(0,N(F28)+N(K28))*IF(N28<>"",N28,M28)),0),IF(S28="Debt service",IF(T28>5,0,AI28*MAX(0,MIN(5-T28+1,U28))),IF(OR(S28="Annual O&M",S28="Maintenance-only"),IF(T28>5,0,IF(O28<>"",O28,MAX(0,N(F28)+N(K28))*IF(N28<>"",N28,M28))*MAX(0,5-T28+1)),0)))),0) -> 36450 | AD28: =IFERROR(IF(OR(R28<>"Yes",Q28<>"ESD"),0,IF(S28="Cash capital",IF(T28<=10,IF(O28<>"",O28,MAX(0,N(G28)+N(K28))*IF(N28<>"",N28,M28)),0),IF(S28="Debt service",IF(T28>10,0,AJ28*MAX(0,MIN(10-T28+1,U28))),IF(OR(S28="Annual O&M",S28="Maintenance-only"),IF(T28>10,0,IF(O28<>"",O28,MAX(0,N(G28)+N(K28))*IF(N28<>"",N28,M28))*MAX(0,10-T28+1)),0)))),0) -> 72900 | AE28: =IFERROR(IF(OR(R28<>"Yes",Q28<>"ESD"),0,IF(S28="Cash capital",IF(T28<=15,IF(O28<>"",O28,MAX(0,N(H28)+N(K28))*IF(N28<>"",N28,M28)),0),IF(S28="Debt service",IF(T28>15,0,AK28*MAX(0,MIN(15-T28+1,U28))),IF(OR(S28="Annual O&M",S28="Maintenance-only"),IF(T28>15,0,IF(O28<>"",O28,MAX(0,N(H28)+N(K28))*IF(N28<>"",N28,M28))*MAX(0,15-T28+1)),0)))),0) -> 109350 | AF28: =IFERROR(IF(OR(R28<>"Yes",Q28<>"ESD"),0,IF(S28="Cash capital",IF(T28<=20,IF(O28<>"",O28,MAX(0,N(I28)+N(K28))*IF(N28<>"",N28,M28)),0),IF(S28="Debt service",IF(T28>20,0,AL28*MAX(0,MIN(20-T28+1,U28))),IF(OR(S28="Annual O&M",S28="Maintenance-only"),IF(T28>20,0,IF(O28<>"",O28,MAX(0,N(I28)+N(K28))*IF(N28<>"",N28,M28))*MAX(0,20-T28+1)),0)))),0) -> 145800 | AG28: =IFERROR(IF(OR(R28<>"Yes",Q28<>"ESD"),0,IF(S28="Cash capital",IF(T28<=30,IF(O28<>"",O28,MAX(0,N(J28)+N(K28))*IF(N28<>"",N28,M28)),0),IF(S28="Debt service",IF(T28>30,0,AM28*MAX(0,MIN(30-T28+1,U28))),IF(OR(S28="Annual O&M",S28="Maintenance-only"),IF(T28>30,0,IF(O28<>"",O28,MAX(0,N(J28)+N(K28))*IF(N28<>"",N28,M28))*MAX(0,30-T28+1)),0)))),0) -> 218700 | AH28: Planning benchmark; validate with ESD staffing model. | Takeoff factor: 5 firefighter FTE per officer; confidence Low; validate w/ ESD #2. | AI28: =IFERROR(IF(U28>0,IF(O28<>"",O28,MAX(0,N(F28)+N(K28))*IF(N28<>"",N28,M28))*IF(V28=0,1/U28,V28/(1-(1+V28)^(-U28))),0),0) -> 560.42709 | AJ28: =IFERROR(IF(U28>0,IF(O28<>"",O28,MAX(0,N(G28)+N(K28))*IF(N28<>"",N28,M28))*IF(V28=0,1/U28,V28/(1-(1+V28)^(-U28))),0),0) -> 560.42709 | AK28: =IFERROR(IF(U28>0,IF(O28<>"",O28,MAX(0,N(H28)+N(K28))*IF(N28<>"",N28,M28))*IF(V28=0,1/U28,V28/(1-(1+V28)^(-U28))),0),0) -> 560.42709 | AL28: =IFERROR(IF(U28>0,IF(O28<>"",O28,MAX(0,N(I28)+N(K28))*IF(N28<>"",N28,M28))*IF(V28=0,1/U28,V28/(1-(1+V28)^(-U28))),0),0) -> 560.42709 | AM28: =IFERROR(IF(U28>0,IF(O28<>"",O28,MAX(0,N(J28)+N(K28))*IF(N28<>"",N28,M28))*IF(V28=0,1/U28,V28/(1-(1+V28)^(-U28))),0),0) -> 560.42709
A29: Custom infrastructure item 1 (e.g., electrical substation) | B29: City | C29: manual/custom | D29: each | E29: manual | F29: =0 -> 0 | G29: =0 -> 0 | H29: =0 -> 0 | I29: =0 -> 0 | J29: =0 -> 0 | L29: =MAX(0,N(G29)+N(K29)) -> 0 | M29: 0 | P29: =IFERROR(IF(O29<>"",O29,L29*IF(N29<>"",N29,M29)),0) -> 0 | Q29: Unknown | R29: No | S29: TBD | T29: 1 | U29: 20 | V29: 0.045 | W29: =IFERROR(IF(AND(R29="Yes",S29="Debt service",U29>0),IF(V29=0,P29/U29,P29*V29/(1-(1+V29)^(-U29))),0),0) -> 0 | X29: =IFERROR(IF(OR(R29<>"Yes",Q29<>"City"),0,IF(S29="Cash capital",IF(T29<=5,IF(O29<>"",O29,MAX(0,N(F29)+N(K29))*IF(N29<>"",N29,M29)),0),IF(S29="Debt service",IF(T29>5,0,AI29*MAX(0,MIN(5-T29+1,U29))),IF(OR(S29="Annual O&M",S29="Maintenance-only"),IF(T29>5,0,IF(O29<>"",O29,MAX(0,N(F29)+N(K29))*IF(N29<>"",N29,M29))*MAX(0,5-T29+1)),0)))),0) -> 0 | Y29: =IFERROR(IF(OR(R29<>"Yes",Q29<>"City"),0,IF(S29="Cash capital",IF(T29<=10,IF(O29<>"",O29,MAX(0,N(G29)+N(K29))*IF(N29<>"",N29,M29)),0),IF(S29="Debt service",IF(T29>10,0,AJ29*MAX(0,MIN(10-T29+1,U29))),IF(OR(S29="Annual O&M",S29="Maintenance-only"),IF(T29>10,0,IF(O29<>"",O29,MAX(0,N(G29)+N(K29))*IF(N29<>"",N29,M29))*MAX(0,10-T29+1)),0)))),0) -> 0 | Z29: =IFERROR(IF(OR(R29<>"Yes",Q29<>"City"),0,IF(S29="Cash capital",IF(T29<=15,IF(O29<>"",O29,MAX(0,N(H29)+N(K29))*IF(N29<>"",N29,M29)),0),IF(S29="Debt service",IF(T29>15,0,AK29*MAX(0,MIN(15-T29+1,U29))),IF(OR(S29="Annual O&M",S29="Maintenance-only"),IF(T29>15,0,IF(O29<>"",O29,MAX(0,N(H29)+N(K29))*IF(N29<>"",N29,M29))*MAX(0,15-T29+1)),0)))),0) -> 0 | AA29: =IFERROR(IF(OR(R29<>"Yes",Q29<>"City"),0,IF(S29="Cash capital",IF(T29<=20,IF(O29<>"",O29,MAX(0,N(I29)+N(K29))*IF(N29<>"",N29,M29)),0),IF(S29="Debt service",IF(T29>20,0,AL29*MAX(0,MIN(20-T29+1,U29))),IF(OR(S29="Annual O&M",S29="Maintenance-only"),IF(T29>20,0,IF(O29<>"",O29,MAX(0,N(I29)+N(K29))*IF(N29<>"",N29,M29))*MAX(0,20-T29+1)),0)))),0) -> 0 | AB29: =IFERROR(IF(OR(R29<>"Yes",Q29<>"City"),0,IF(S29="Cash capital",IF(T29<=30,IF(O29<>"",O29,MAX(0,N(J29)+N(K29))*IF(N29<>"",N29,M29)),0),IF(S29="Debt service",IF(T29>30,0,AM29*MAX(0,MIN(30-T29+1,U29))),IF(OR(S29="Annual O&M",S29="Maintenance-only"),IF(T29>30,0,IF(O29<>"",O29,MAX(0,N(J29)+N(K29))*IF(N29<>"",N29,M29))*MAX(0,30-T29+1)),0)))),0) -> 0 | AC29: =IFERROR(IF(OR(R29<>"Yes",Q29<>"ESD"),0,IF(S29="Cash capital",IF(T29<=5,IF(O29<>"",O29,MAX(0,N(F29)+N(K29))*IF(N29<>"",N29,M29)),0),IF(S29="Debt service",IF(T29>5,0,AI29*MAX(0,MIN(5-T29+1,U29))),IF(OR(S29="Annual O&M",S29="Maintenance-only"),IF(T29>5,0,IF(O29<>"",O29,MAX(0,N(F29)+N(K29))*IF(N29<>"",N29,M29))*MAX(0,5-T29+1)),0)))),0) -> 0 | AD29: =IFERROR(IF(OR(R29<>"Yes",Q29<>"ESD"),0,IF(S29="Cash capital",IF(T29<=10,IF(O29<>"",O29,MAX(0,N(G29)+N(K29))*IF(N29<>"",N29,M29)),0),IF(S29="Debt service",IF(T29>10,0,AJ29*MAX(0,MIN(10-T29+1,U29))),IF(OR(S29="Annual O&M",S29="Maintenance-only"),IF(T29>10,0,IF(O29<>"",O29,MAX(0,N(G29)+N(K29))*IF(N29<>"",N29,M29))*MAX(0,10-T29+1)),0)))),0) -> 0 | AE29: =IFERROR(IF(OR(R29<>"Yes",Q29<>"ESD"),0,IF(S29="Cash capital",IF(T29<=15,IF(O29<>"",O29,MAX(0,N(H29)+N(K29))*IF(N29<>"",N29,M29)),0),IF(S29="Debt service",IF(T29>15,0,AK29*MAX(0,MIN(15-T29+1,U29))),IF(OR(S29="Annual O&M",S29="Maintenance-only"),IF(T29>15,0,IF(O29<>"",O29,MAX(0,N(H29)+N(K29))*IF(N29<>"",N29,M29))*MAX(0,15-T29+1)),0)))),0) -> 0 | AF29: =IFERROR(IF(OR(R29<>"Yes",Q29<>"ESD"),0,IF(S29="Cash capital",IF(T29<=20,IF(O29<>"",O29,MAX(0,N(I29)+N(K29))*IF(N29<>"",N29,M29)),0),IF(S29="Debt service",IF(T29>20,0,AL29*MAX(0,MIN(20-T29+1,U29))),IF(OR(S29="Annual O&M",S29="Maintenance-only"),IF(T29>20,0,IF(O29<>"",O29,MAX(0,N(I29)+N(K29))*IF(N29<>"",N29,M29))*MAX(0,20-T29+1)),0)))),0) -> 0 | AG29: =IFERROR(IF(OR(R29<>"Yes",Q29<>"ESD"),0,IF(S29="Cash capital",IF(T29<=30,IF(O29<>"",O29,MAX(0,N(J29)+N(K29))*IF(N29<>"",N29,M29)),0),IF(S29="Debt service",IF(T29>30,0,AM29*MAX(0,MIN(30-T29+1,U29))),IF(OR(S29="Annual O&M",S29="Maintenance-only"),IF(T29>30,0,IF(O29<>"",O29,MAX(0,N(J29)+N(K29))*IF(N29<>"",N29,M29))*MAX(0,30-T29+1)),0)))),0) -> 0 | AH29: Custom row. Enter manual quantity/cost, funding responsibility, timing, and include-in-net choice. | AI29: =IFERROR(IF(U29>0,IF(O29<>"",O29,MAX(0,N(F29)+N(K29))*IF(N29<>"",N29,M29))*IF(V29=0,1/U29,V29/(1-(1+V29)^(-U29))),0),0) -> 0 | AJ29: =IFERROR(IF(U29>0,IF(O29<>"",O29,MAX(0,N(G29)+N(K29))*IF(N29<>"",N29,M29))*IF(V29=0,1/U29,V29/(1-(1+V29)^(-U29))),0),0) -> 0 | AK29: =IFERROR(IF(U29>0,IF(O29<>"",O29,MAX(0,N(H29)+N(K29))*IF(N29<>"",N29,M29))*IF(V29=0,1/U29,V29/(1-(1+V29)^(-U29))),0),0) -> 0 | AL29: =IFERROR(IF(U29>0,IF(O29<>"",O29,MAX(0,N(I29)+N(K29))*IF(N29<>"",N29,M29))*IF(V29=0,1/U29,V29/(1-(1+V29)^(-U29))),0),0) -> 0 | AM29: =IFERROR(IF(U29>0,IF(O29<>"",O29,MAX(0,N(J29)+N(K29))*IF(N29<>"",N29,M29))*IF(V29=0,1/U29,V29/(1-(1+V29)^(-U29))),0),0) -> 0
A30: Custom infrastructure item 2 (e.g., regional detention / off-site main) | B30: City | C30: manual/custom | D30: each | E30: manual | F30: =0 -> 0 | G30: =0 -> 0 | H30: =0 -> 0 | I30: =0 -> 0 | J30: =0 -> 0 | L30: =MAX(0,N(G30)+N(K30)) -> 0 | M30: 0 | P30: =IFERROR(IF(O30<>"",O30,L30*IF(N30<>"",N30,M30)),0) -> 0 | Q30: Unknown | R30: No | S30: TBD | T30: 1 | U30: 20 | V30: 0.045 | W30: =IFERROR(IF(AND(R30="Yes",S30="Debt service",U30>0),IF(V30=0,P30/U30,P30*V30/(1-(1+V30)^(-U30))),0),0) -> 0 | X30: =IFERROR(IF(OR(R30<>"Yes",Q30<>"City"),0,IF(S30="Cash capital",IF(T30<=5,IF(O30<>"",O30,MAX(0,N(F30)+N(K30))*IF(N30<>"",N30,M30)),0),IF(S30="Debt service",IF(T30>5,0,AI30*MAX(0,MIN(5-T30+1,U30))),IF(OR(S30="Annual O&M",S30="Maintenance-only"),IF(T30>5,0,IF(O30<>"",O30,MAX(0,N(F30)+N(K30))*IF(N30<>"",N30,M30))*MAX(0,5-T30+1)),0)))),0) -> 0 | Y30: =IFERROR(IF(OR(R30<>"Yes",Q30<>"City"),0,IF(S30="Cash capital",IF(T30<=10,IF(O30<>"",O30,MAX(0,N(G30)+N(K30))*IF(N30<>"",N30,M30)),0),IF(S30="Debt service",IF(T30>10,0,AJ30*MAX(0,MIN(10-T30+1,U30))),IF(OR(S30="Annual O&M",S30="Maintenance-only"),IF(T30>10,0,IF(O30<>"",O30,MAX(0,N(G30)+N(K30))*IF(N30<>"",N30,M30))*MAX(0,10-T30+1)),0)))),0) -> 0 | Z30: =IFERROR(IF(OR(R30<>"Yes",Q30<>"City"),0,IF(S30="Cash capital",IF(T30<=15,IF(O30<>"",O30,MAX(0,N(H30)+N(K30))*IF(N30<>"",N30,M30)),0),IF(S30="Debt service",IF(T30>15,0,AK30*MAX(0,MIN(15-T30+1,U30))),IF(OR(S30="Annual O&M",S30="Maintenance-only"),IF(T30>15,0,IF(O30<>"",O30,MAX(0,N(H30)+N(K30))*IF(N30<>"",N30,M30))*MAX(0,15-T30+1)),0)))),0) -> 0 | AA30: =IFERROR(IF(OR(R30<>"Yes",Q30<>"City"),0,IF(S30="Cash capital",IF(T30<=20,IF(O30<>"",O30,MAX(0,N(I30)+N(K30))*IF(N30<>"",N30,M30)),0),IF(S30="Debt service",IF(T30>20,0,AL30*MAX(0,MIN(20-T30+1,U30))),IF(OR(S30="Annual O&M",S30="Maintenance-only"),IF(T30>20,0,IF(O30<>"",O30,MAX(0,N(I30)+N(K30))*IF(N30<>"",N30,M30))*MAX(0,20-T30+1)),0)))),0) -> 0 | AB30: =IFERROR(IF(OR(R30<>"Yes",Q30<>"City"),0,IF(S30="Cash capital",IF(T30<=30,IF(O30<>"",O30,MAX(0,N(J30)+N(K30))*IF(N30<>"",N30,M30)),0),IF(S30="Debt service",IF(T30>30,0,AM30*MAX(0,MIN(30-T30+1,U30))),IF(OR(S30="Annual O&M",S30="Maintenance-only"),IF(T30>30,0,IF(O30<>"",O30,MAX(0,N(J30)+N(K30))*IF(N30<>"",N30,M30))*MAX(0,30-T30+1)),0)))),0) -> 0 | AC30: =IFERROR(IF(OR(R30<>"Yes",Q30<>"ESD"),0,IF(S30="Cash capital",IF(T30<=5,IF(O30<>"",O30,MAX(0,N(F30)+N(K30))*IF(N30<>"",N30,M30)),0),IF(S30="Debt service",IF(T30>5,0,AI30*MAX(0,MIN(5-T30+1,U30))),IF(OR(S30="Annual O&M",S30="Maintenance-only"),IF(T30>5,0,IF(O30<>"",O30,MAX(0,N(F30)+N(K30))*IF(N30<>"",N30,M30))*MAX(0,5-T30+1)),0)))),0) -> 0 | AD30: =IFERROR(IF(OR(R30<>"Yes",Q30<>"ESD"),0,IF(S30="Cash capital",IF(T30<=10,IF(O30<>"",O30,MAX(0,N(G30)+N(K30))*IF(N30<>"",N30,M30)),0),IF(S30="Debt service",IF(T30>10,0,AJ30*MAX(0,MIN(10-T30+1,U30))),IF(OR(S30="Annual O&M",S30="Maintenance-only"),IF(T30>10,0,IF(O30<>"",O30,MAX(0,N(G30)+N(K30))*IF(N30<>"",N30,M30))*MAX(0,10-T30+1)),0)))),0) -> 0 | AE30: =IFERROR(IF(OR(R30<>"Yes",Q30<>"ESD"),0,IF(S30="Cash capital",IF(T30<=15,IF(O30<>"",O30,MAX(0,N(H30)+N(K30))*IF(N30<>"",N30,M30)),0),IF(S30="Debt service",IF(T30>15,0,AK30*MAX(0,MIN(15-T30+1,U30))),IF(OR(S30="Annual O&M",S30="Maintenance-only"),IF(T30>15,0,IF(O30<>"",O30,MAX(0,N(H30)+N(K30))*IF(N30<>"",N30,M30))*MAX(0,15-T30+1)),0)))),0) -> 0 | AF30: =IFERROR(IF(OR(R30<>"Yes",Q30<>"ESD"),0,IF(S30="Cash capital",IF(T30<=20,IF(O30<>"",O30,MAX(0,N(I30)+N(K30))*IF(N30<>"",N30,M30)),0),IF(S30="Debt service",IF(T30>20,0,AL30*MAX(0,MIN(20-T30+1,U30))),IF(OR(S30="Annual O&M",S30="Maintenance-only"),IF(T30>20,0,IF(O30<>"",O30,MAX(0,N(I30)+N(K30))*IF(N30<>"",N30,M30))*MAX(0,20-T30+1)),0)))),0) -> 0 | AG30: =IFERROR(IF(OR(R30<>"Yes",Q30<>"ESD"),0,IF(S30="Cash capital",IF(T30<=30,IF(O30<>"",O30,MAX(0,N(J30)+N(K30))*IF(N30<>"",N30,M30)),0),IF(S30="Debt service",IF(T30>30,0,AM30*MAX(0,MIN(30-T30+1,U30))),IF(OR(S30="Annual O&M",S30="Maintenance-only"),IF(T30>30,0,IF(O30<>"",O30,MAX(0,N(J30)+N(K30))*IF(N30<>"",N30,M30))*MAX(0,30-T30+1)),0)))),0) -> 0 | AH30: Custom row. Use for items not in standard library; initially excluded from fiscal net. | AI30: =IFERROR(IF(U30>0,IF(O30<>"",O30,MAX(0,N(F30)+N(K30))*IF(N30<>"",N30,M30))*IF(V30=0,1/U30,V30/(1-(1+V30)^(-U30))),0),0) -> 0 | AJ30: =IFERROR(IF(U30>0,IF(O30<>"",O30,MAX(0,N(G30)+N(K30))*IF(N30<>"",N30,M30))*IF(V30=0,1/U30,V30/(1-(1+V30)^(-U30))),0),0) -> 0 | AK30: =IFERROR(IF(U30>0,IF(O30<>"",O30,MAX(0,N(H30)+N(K30))*IF(N30<>"",N30,M30))*IF(V30=0,1/U30,V30/(1-(1+V30)^(-U30))),0),0) -> 0 | AL30: =IFERROR(IF(U30>0,IF(O30<>"",O30,MAX(0,N(I30)+N(K30))*IF(N30<>"",N30,M30))*IF(V30=0,1/U30,V30/(1-(1+V30)^(-U30))),0),0) -> 0 | AM30: =IFERROR(IF(U30>0,IF(O30<>"",O30,MAX(0,N(J30)+N(K30))*IF(N30<>"",N30,M30))*IF(V30=0,1/U30,V30/(1-(1+V30)^(-U30))),0),0) -> 0
A31: Custom ESD / other item (e.g., radio system, special apparatus) | B31: ESD | C31: manual/custom | D31: each | E31: manual | F31: =0 -> 0 | G31: =0 -> 0 | H31: =0 -> 0 | I31: =0 -> 0 | J31: =0 -> 0 | L31: =MAX(0,N(G31)+N(K31)) -> 0 | M31: 0 | P31: =IFERROR(IF(O31<>"",O31,L31*IF(N31<>"",N31,M31)),0) -> 0 | Q31: Unknown | R31: No | S31: TBD | T31: 1 | U31: 20 | V31: 0.045 | W31: =IFERROR(IF(AND(R31="Yes",S31="Debt service",U31>0),IF(V31=0,P31/U31,P31*V31/(1-(1+V31)^(-U31))),0),0) -> 0 | X31: =IFERROR(IF(OR(R31<>"Yes",Q31<>"City"),0,IF(S31="Cash capital",IF(T31<=5,IF(O31<>"",O31,MAX(0,N(F31)+N(K31))*IF(N31<>"",N31,M31)),0),IF(S31="Debt service",IF(T31>5,0,AI31*MAX(0,MIN(5-T31+1,U31))),IF(OR(S31="Annual O&M",S31="Maintenance-only"),IF(T31>5,0,IF(O31<>"",O31,MAX(0,N(F31)+N(K31))*IF(N31<>"",N31,M31))*MAX(0,5-T31+1)),0)))),0) -> 0 | Y31: =IFERROR(IF(OR(R31<>"Yes",Q31<>"City"),0,IF(S31="Cash capital",IF(T31<=10,IF(O31<>"",O31,MAX(0,N(G31)+N(K31))*IF(N31<>"",N31,M31)),0),IF(S31="Debt service",IF(T31>10,0,AJ31*MAX(0,MIN(10-T31+1,U31))),IF(OR(S31="Annual O&M",S31="Maintenance-only"),IF(T31>10,0,IF(O31<>"",O31,MAX(0,N(G31)+N(K31))*IF(N31<>"",N31,M31))*MAX(0,10-T31+1)),0)))),0) -> 0 | Z31: =IFERROR(IF(OR(R31<>"Yes",Q31<>"City"),0,IF(S31="Cash capital",IF(T31<=15,IF(O31<>"",O31,MAX(0,N(H31)+N(K31))*IF(N31<>"",N31,M31)),0),IF(S31="Debt service",IF(T31>15,0,AK31*MAX(0,MIN(15-T31+1,U31))),IF(OR(S31="Annual O&M",S31="Maintenance-only"),IF(T31>15,0,IF(O31<>"",O31,MAX(0,N(H31)+N(K31))*IF(N31<>"",N31,M31))*MAX(0,15-T31+1)),0)))),0) -> 0 | AA31: =IFERROR(IF(OR(R31<>"Yes",Q31<>"City"),0,IF(S31="Cash capital",IF(T31<=20,IF(O31<>"",O31,MAX(0,N(I31)+N(K31))*IF(N31<>"",N31,M31)),0),IF(S31="Debt service",IF(T31>20,0,AL31*MAX(0,MIN(20-T31+1,U31))),IF(OR(S31="Annual O&M",S31="Maintenance-only"),IF(T31>20,0,IF(O31<>"",O31,MAX(0,N(I31)+N(K31))*IF(N31<>"",N31,M31))*MAX(0,20-T31+1)),0)))),0) -> 0 | AB31: =IFERROR(IF(OR(R31<>"Yes",Q31<>"City"),0,IF(S31="Cash capital",IF(T31<=30,IF(O31<>"",O31,MAX(0,N(J31)+N(K31))*IF(N31<>"",N31,M31)),0),IF(S31="Debt service",IF(T31>30,0,AM31*MAX(0,MIN(30-T31+1,U31))),IF(OR(S31="Annual O&M",S31="Maintenance-only"),IF(T31>30,0,IF(O31<>"",O31,MAX(0,N(J31)+N(K31))*IF(N31<>"",N31,M31))*MAX(0,30-T31+1)),0)))),0) -> 0 | AC31: =IFERROR(IF(OR(R31<>"Yes",Q31<>"ESD"),0,IF(S31="Cash capital",IF(T31<=5,IF(O31<>"",O31,MAX(0,N(F31)+N(K31))*IF(N31<>"",N31,M31)),0),IF(S31="Debt service",IF(T31>5,0,AI31*MAX(0,MIN(5-T31+1,U31))),IF(OR(S31="Annual O&M",S31="Maintenance-only"),IF(T31>5,0,IF(O31<>"",O31,MAX(0,N(F31)+N(K31))*IF(N31<>"",N31,M31))*MAX(0,5-T31+1)),0)))),0) -> 0 | AD31: =IFERROR(IF(OR(R31<>"Yes",Q31<>"ESD"),0,IF(S31="Cash capital",IF(T31<=10,IF(O31<>"",O31,MAX(0,N(G31)+N(K31))*IF(N31<>"",N31,M31)),0),IF(S31="Debt service",IF(T31>10,0,AJ31*MAX(0,MIN(10-T31+1,U31))),IF(OR(S31="Annual O&M",S31="Maintenance-only"),IF(T31>10,0,IF(O31<>"",O31,MAX(0,N(G31)+N(K31))*IF(N31<>"",N31,M31))*MAX(0,10-T31+1)),0)))),0) -> 0 | AE31: =IFERROR(IF(OR(R31<>"Yes",Q31<>"ESD"),0,IF(S31="Cash capital",IF(T31<=15,IF(O31<>"",O31,MAX(0,N(H31)+N(K31))*IF(N31<>"",N31,M31)),0),IF(S31="Debt service",IF(T31>15,0,AK31*MAX(0,MIN(15-T31+1,U31))),IF(OR(S31="Annual O&M",S31="Maintenance-only"),IF(T31>15,0,IF(O31<>"",O31,MAX(0,N(H31)+N(K31))*IF(N31<>"",N31,M31))*MAX(0,15-T31+1)),0)))),0) -> 0 | AF31: =IFERROR(IF(OR(R31<>"Yes",Q31<>"ESD"),0,IF(S31="Cash capital",IF(T31<=20,IF(O31<>"",O31,MAX(0,N(I31)+N(K31))*IF(N31<>"",N31,M31)),0),IF(S31="Debt service",IF(T31>20,0,AL31*MAX(0,MIN(20-T31+1,U31))),IF(OR(S31="Annual O&M",S31="Maintenance-only"),IF(T31>20,0,IF(O31<>"",O31,MAX(0,N(I31)+N(K31))*IF(N31<>"",N31,M31))*MAX(0,20-T31+1)),0)))),0) -> 0 | AG31: =IFERROR(IF(OR(R31<>"Yes",Q31<>"ESD"),0,IF(S31="Cash capital",IF(T31<=30,IF(O31<>"",O31,MAX(0,N(J31)+N(K31))*IF(N31<>"",N31,M31)),0),IF(S31="Debt service",IF(T31>30,0,AM31*MAX(0,MIN(30-T31+1,U31))),IF(OR(S31="Annual O&M",S31="Maintenance-only"),IF(T31>30,0,IF(O31<>"",O31,MAX(0,N(J31)+N(K31))*IF(N31<>"",N31,M31))*MAX(0,30-T31+1)),0)))),0) -> 0 | AH31: Custom ESD/other row; validate with ESD capital plan or responsible entity. | AI31: =IFERROR(IF(U31>0,IF(O31<>"",O31,MAX(0,N(F31)+N(K31))*IF(N31<>"",N31,M31))*IF(V31=0,1/U31,V31/(1-(1+V31)^(-U31))),0),0) -> 0 | AJ31: =IFERROR(IF(U31>0,IF(O31<>"",O31,MAX(0,N(G31)+N(K31))*IF(N31<>"",N31,M31))*IF(V31=0,1/U31,V31/(1-(1+V31)^(-U31))),0),0) -> 0 | AK31: =IFERROR(IF(U31>0,IF(O31<>"",O31,MAX(0,N(H31)+N(K31))*IF(N31<>"",N31,M31))*IF(V31=0,1/U31,V31/(1-(1+V31)^(-U31))),0),0) -> 0 | AL31: =IFERROR(IF(U31>0,IF(O31<>"",O31,MAX(0,N(I31)+N(K31))*IF(N31<>"",N31,M31))*IF(V31=0,1/U31,V31/(1-(1+V31)^(-U31))),0),0) -> 0 | AM31: =IFERROR(IF(U31>0,IF(O31<>"",O31,MAX(0,N(J31)+N(K31))*IF(N31<>"",N31,M31))*IF(V31=0,1/U31,V31/(1-(1+V31)^(-U31))),0),0) -> 0
A33: Totals / Fiscal-Net Inclusion Summary
A34: Included City fiscal-net impact by horizon | X34: =SUM(X4:X31) -> 4399527.6 | Y34: =SUM(Y4:Y31) -> 8799055.3 | Z34: =SUM(Z4:Z31) -> 13198583 | AA34: =SUM(AA4:AA31) -> 17598111 | AB34: =SUM(AB4:AB31) -> 18246111
A35: Included ESD fiscal-net impact by horizon | AC35: =SUM(AC4:AC31) -> 188325 | AD35: =SUM(AD4:AD31) -> 373275 | AE35: =SUM(AE4:AE31) -> 558225 | AF35: =SUM(AF4:AF31) -> 743175 | AG35: =SUM(AG4:AG31) -> 1113075
A37: Note: Standard infrastructure rows are informational unless selected for fiscal inclusion. To incorporate an item into the overall fiscal model, set Include in Fiscal Net? to Yes, select City or ESD as Funding Responsibility, choose Cost Treatment, and verify Timing Year / debt inputs.

Sheet Results
A1: RESULTS
A2: Sales tax (the ILA question) + fiscal context · cumulative totals over each horizon for the Active scenarios
A4: Sales-tax split applied (from INPUTS): | C4: City GF | D4: =IF('Advanced Inputs'!D6="","(enter)",'Advanced Inputs'!D6) -> (enter) | E4: Sealy EDC | F4: ='Advanced Inputs'!D7 -> 0 | G4: ESD #2 | H4: =IF('Advanced Inputs'!D8="","(enter)",'Advanced Inputs'!D8) -> (enter)
A5: (Split cells are blank until entered on INPUTS — City + ESD should total 100%.)
A7: SALES TAX — THE ILA QUESTION
A8: Metric | B8: 5-Year | C8: 10-Year | D8: 15-Year | E8: 20-Year | F8: 30-Year
A9: Total taxable sales generated | B9: ='03_Multi_Horizon_Results'!B14 -> 1.0391522e+08 | C9: ='03_Multi_Horizon_Results'!C14 -> 7.2994974e+08 | D9: ='03_Multi_Horizon_Results'!D14 -> 1.5873687e+09 | E9: ='03_Multi_Horizon_Results'!E14 -> 2.7617389e+09 | F9: ='03_Multi_Horizon_Results'!F14 -> 6.5735756e+09
A10: 1.5% ILA sales-tax pool (the pie to split) | B10: ='03_Multi_Horizon_Results'!B15 -> 1558728.3 | C10: ='03_Multi_Horizon_Results'!C15 -> 10949246 | D10: ='03_Multi_Horizon_Results'!D15 -> 23810531 | E10: ='03_Multi_Horizon_Results'!E15 -> 41426083 | F10: ='03_Multi_Horizon_Results'!F15 -> 98603635
A11: → City General Fund (net of EDC) | B11: ='03_Multi_Horizon_Results'!B18 -> 0 | C11: ='03_Multi_Horizon_Results'!C18 -> 0 | D11: ='03_Multi_Horizon_Results'!D18 -> 0 | E11: ='03_Multi_Horizon_Results'!E18 -> 0 | F11: ='03_Multi_Horizon_Results'!F18 -> 0
A12: → Sealy EDC (carve-out) | B12: ='03_Multi_Horizon_Results'!B17 -> 0 | C12: ='03_Multi_Horizon_Results'!C17 -> 0 | D12: ='03_Multi_Horizon_Results'!D17 -> 0 | E12: ='03_Multi_Horizon_Results'!E17 -> 0 | F12: ='03_Multi_Horizon_Results'!F17 -> 0
A13: → ESD #2 share | B13: ='03_Multi_Horizon_Results'!B19 -> 0 | C13: ='03_Multi_Horizon_Results'!C19 -> 0 | D13: ='03_Multi_Horizon_Results'!D19 -> 0 | E13: ='03_Multi_Horizon_Results'!E19 -> 0 | F13: ='03_Multi_Horizon_Results'!F19 -> 0
A15: FISCAL CONTEXT — broader development-feasibility (beyond the ILA sales-tax question)
A16: Capital/operating below assume full city-funded buildout of supporting infrastructure; the ILA concerns only the sales-tax pool above.
A17: Metric | B17: 5-Year | C17: 10-Year | D17: 15-Year | E17: 20-Year | F17: 30-Year
A18: City property tax (net of exemptions) | B18: ='03_Multi_Horizon_Results'!B20 -> 480191.29 | C18: ='03_Multi_Horizon_Results'!C20 -> 1472843.4 | D18: ='03_Multi_Horizon_Results'!D20 -> 2801235.8 | E18: ='03_Multi_Horizon_Results'!E20 -> 4578924.4 | F18: ='03_Multi_Horizon_Results'!F20 -> 10141443
A19: ESD #2 property tax (net of exemptions) | B19: ='03_Multi_Horizon_Results'!B21 -> 117160.85 | C19: ='03_Multi_Horizon_Results'!C21 -> 359250.09 | D19: ='03_Multi_Horizon_Results'!D21 -> 683220.11 | E19: ='03_Multi_Horizon_Results'!E21 -> 1116765.1 | F19: ='03_Multi_Horizon_Results'!F21 -> 2473359
A20: Impact fees (one-time) | B20: ='03_Multi_Horizon_Results'!B22 -> 1576300 | C20: ='03_Multi_Horizon_Results'!C22 -> 1576300 | D20: ='03_Multi_Horizon_Results'!D22 -> 1576300 | E20: ='03_Multi_Horizon_Results'!E22 -> 1576300 | F20: ='03_Multi_Horizon_Results'!F22 -> 1576300
A21: City operating cost | B21: ='03_Multi_Horizon_Results'!B23 -> 819887.66 | C21: ='03_Multi_Horizon_Results'!C23 -> 2308732.4 | D21: ='03_Multi_Horizon_Results'!D23 -> 3993223.7 | E21: ='03_Multi_Horizon_Results'!E23 -> 5899070.9 | F21: ='03_Multi_Horizon_Results'!F23 -> 10495008
A22: City capital / debt service (infrastructure) | B22: ='03_Multi_Horizon_Results'!B24 -> 4399527.6 | C22: ='03_Multi_Horizon_Results'!C24 -> 8799055.3 | D22: ='03_Multi_Horizon_Results'!D24 -> 13198583 | E22: ='03_Multi_Horizon_Results'!E24 -> 17598111 | F22: ='03_Multi_Horizon_Results'!F24 -> 18246111
A23: ESD operating cost | B23: ='03_Multi_Horizon_Results'!B26 -> 215519.49 | C23: ='03_Multi_Horizon_Results'!C26 -> 612708.31 | D23: ='03_Multi_Horizon_Results'!D26 -> 1062091 | E23: ='03_Multi_Horizon_Results'!E26 -> 1570526.3 | F23: ='03_Multi_Horizon_Results'!F26 -> 2796614.2
A24: ESD capital / debt service | B24: ='03_Multi_Horizon_Results'!B27 -> 188325 | C24: ='03_Multi_Horizon_Results'!C27 -> 373275 | D24: ='03_Multi_Horizon_Results'!D27 -> 558225 | E24: ='03_Multi_Horizon_Results'!E27 -> 743175 | F24: ='03_Multi_Horizon_Results'!F27 -> 1113075
A25: City NET fiscal position | B25: ='03_Multi_Horizon_Results'!B29 -> -3183421.2 | C25: ='03_Multi_Horizon_Results'!C29 -> -8116362.7 | D25: ='03_Multi_Horizon_Results'!D29 -> -12914101 | E25: ='03_Multi_Horizon_Results'!E29 -> -17489434 | F25: ='03_Multi_Horizon_Results'!F29 -> -17285751
A26: ESD #2 NET fiscal position | B26: ='03_Multi_Horizon_Results'!B30 -> -292071.62 | C26: ='03_Multi_Horizon_Results'!C30 -> -642050.92 | D26: ='03_Multi_Horizon_Results'!D30 -> -963648.17 | E26: ='03_Multi_Horizon_Results'!E30 -> -1236199.4 | F26: ='03_Multi_Horizon_Results'!F30 -> -1506245.6
A27: Combined NET fiscal position | B27: ='03_Multi_Horizon_Results'!B31 -> -3475492.8 | C27: ='03_Multi_Horizon_Results'!C31 -> -8758413.6 | D27: ='03_Multi_Horizon_Results'!D31 -> -13877750 | E27: ='03_Multi_Horizon_Results'!E31 -> -18725633 | F27: ='03_Multi_Horizon_Results'!F31 -> -18791996

Sheet SOURCES
A1: Source Log
A3: Input | B3: Value | C3: Source / Basis | D3: Confidence | E3: Last Verified | F3: Staff? | G3: City Attorney? | H3: Comptroller? | I3: Notes
A4: Pool rate (combined-area) | B4: ='00_Inputs_Dashboard'!$B$20 -> 0.015 | C4: Comptroller combined-area code 6008609 1.5%; 2.0% local cap | D4: High | E4: 2026-05-14 | F4: No | G4: No | H4: Yes | I4: Tex Tax Code Ch. 321
A5: Sealy current population | B5: ='00_Inputs_Dashboard'!$B$11 -> 7937 | C5: Sealy HB1378 §140.008 FY25 actual | D5: High | E5: 2026-05-14 (FY25 ACFR) | F5: No | G5: No | H5: No | I5: Sealy HB1378 §140.008 FY25 (city-published). CROSS-VALIDATED via FY25 ACFR statistical section: 7,553 (2025), 7,243 (2024), 7,059 (2023), 6,839 (2022). Source: US Census ACS 5-yr.
A6: Population CAGR | B6: ='00_Inputs_Dashboard'!$B$12 -> 0.032 | C6: Sealy HB1378 5-yr actual 6,450 → 7,553 | D6: High | E6: 2026-05-14 (FY25 ACFR) | F6: Yes | G6: No | H6: No | I6: Sealy HB1378 5-yr actual. CROSS-VALIDATED: FY25 ACFR 3-yr CAGR = (7,553/6,839)^(1/3)-1 = 3.36%. Model uses 3.2% — conservative.
A7: Current annual sales-tax pool | B7: ='00_Inputs_Dashboard'!$B$13 -> 3700000 | C7: FY26 Adopted Budget; cross-validated FY25 actual $4.0M (Comptroller 53-mo); FY26 YTD pacing | D7: High | E7: 2026-05-14 (FY25 ACFR) | F7: Yes | G7: No | H7: Yes | I7: FY26 Adopted Budget $3.7M. CROSS-VALIDATED: FY25 ACFR GF sales tax $2,756,699 (1.0% slice); implied 1.5% combined pool = $4.14M. Calendar 2025 Comptroller cash = $4.02M. Model conservative.
A8: Sales-tax pool CAGR | B8: ='00_Inputs_Dashboard'!$B$14 -> 0.065 | C8: Sealy 12-yr Comptroller actual (6.5% long-run); trailing 3-yr is 9.4%; March 2026 YoY +39% | D8: High | E8: 2026-05-14 | F8: Yes | G8: No | H8: No | I8: 6.5% = long-run mean. STRESS: trailing 3-yr CAGR is 9.4%; March 2026 YoY +39% (manufacturing-driven). Use 9% high-case sensitivity if needed.
A9: City property tax rate | B9: ='00_Inputs_Dashboard'!$B$21 -> 0.0037731 | C9: Sealy FY26 Ord. 2025-24 $0.37731/$100 | D9: High | E9: 2026-05-14 | F9: No | G9: No | H9: No | I9: Adopted
A10: ESD #2 ad valorem rate | B10: ='00_Inputs_Dashboard'!$B$22 -> 0.000931 | C10: Current adopted ESD #2 rate: $0.09310/$100 (2026 tax year). FY25 ACFR statistical section confirms historical: 2025=$0.09578, 2024=$0.09480, 2023=$0.099558. | D10: High | E10: 2026-05-15 | F10: No | G10: No | H10: No | I10: $0.09310 = 2026 current adopted rate (SB625 2026 filing entered 2026-02-26; Retreat at Sealy 2026 tax statement Acct 13818001). FY25 ACFR statistical section p.144 confirms 2025=$0.09578, 2024=$0.09480, 2023=$0.099558. Verify locally before public reliance.
A11: Sealy impact fee per LUE | B11: $7,165 | C11: Sealy 2018 Strand Impact Fee Study (water+sewer adopted) | D11: High | E11: 2026-05-14 | F11: No | G11: No | H11: No | I11: Adopted by Council 2018
A12: MFR AV per unit | B12: $80K/unit | C12: Retreat at Sealy actual ($19.89M/250u/11.3ac) | D12: High | E12: 2026-05-14 | F12: No | G12: No | H12: No | I12: Tax statement source
A13: Sealy FY26 fiscal-strength context | B13: 403 operating days @ Mar 31, 2026 | C13: 5/19/2026 council packet Financial Report (Matura) | D13: High | E13: 2026-05-14 | F13: No | G13: No | H13: No | I13: City at 403 days operating reserve, up from 239 in Oct 2025. Revenue at 85.52% of FY26 budget at 50% of fiscal year. Property tax 104.57% collected, sales tax 99.68%. NEGOTIATION CONTEXT for ESD #2 ILA.
A14: Sealy FY25 GF revenue actual | B14: $10,300,940 | C14: Sealy FY25 ACFR (acfr_fy2025.pdf, 185pp) | D14: High | E14: 2026-05-14 | F14: No | G14: No | H14: No | I14: Cross-validation input. FY26 budgeted GF revenue is conservative at approximately $8.9M (implied from 85.52% YTD).
A15: City PT rate FY25 vs FY26 trajectory | B15: FY26=$0.37731, FY25=$0.31091 | C15: FY25 ACFR statistical section (FY25 op rate $0.196930 + debt service $0.11398) | D15: High | E15: 2026-05-14 | F15: No | G15: No | H15: No | I15: City PT rate rose 21% YoY (FY25→FY26) tied to new $20M CO issuance. Higher PT revenue strengthens city fiscal position; relevant negotiation context.
A16: Walmart taxpayer concentration risk | B16: $130.6M = 14.8% of city AV | C16: FY25 ACFR principal taxpayer list (Wal-Mart Stores East US07036 #2 $74.3M + Wal-Mart Transportation #5 $28.6M + Wal-Mart Stores East US07036 #6 $27.7M) | D16: High | E16: 2026-05-14 | F16: No | G16: No | H16: No | I16: Top 10 taxpayers = 43.89% of $783.9M total AV. Walmart entities alone = 14.8%. Sealy's tax base is concentrated; ILA terms should account for downside risk if Walmart DC contracts.
A17: Sealy FY25 total city AV | B17: $783,888,923 | C17: FY25 ACFR statistical section | D17: High | E17: 2026-05-14 | F17: No | G17: No | H17: No | I17: Total city AV (governmental purposes). Stable around $780-800M last 4 years despite taxpayer churn (BAE left 2016-2025, Hailiang+Walmart+Gamechange added). AV per capita actually declined 2022-2025 due to population growth outpacing AV growth.
A18: Sealy FY25 debt issuance | B18: $20.7M (CO + premium) | C18: FY25 ACFR statistical section + debt service detail | D18: High | E18: 2026-05-14 | F18: No | G18: No | H18: No | I18: Sealy issued $19.91M in new COs + $807K premium = $20.72M proceeds in FY25. Drives the FY26 PT rate increase to $0.37731. Capital projects expanding — context for fiscal-strength position.
A19: Industrial AV per acre validation | B19: $750K/ac (model) | C19: Sika Corp FY25 ACFR: $18.72M / ~25ac developed = $749K/ac. Hailiang Copper $87.75M (#1 taxpayer). | D19: High (SOLID) | E19: 2026-05-14 (FY25 ACFR) | F19: No | G19: No | H19: No | I19: Triple-validated: Sika exact match. Hailiang at $878K/ac (~100ac) is higher-end. Model assumption sits within observed range.
A20: MFR AV per unit validation | B20: $80K/unit (model) | C20: Retreat at Sealy FY25 ACFR: $19.3M / ~250 units = $77K/unit | D20: High (SOLID) | E20: 2026-05-14 (FY25 ACFR) | F20: No | G20: No | H20: No | I20: Within 4% of model assumption. Validated.
A21: EDC retention (carve-out) | B21: ='00_Inputs_Dashboard'!$B$6 -> 0 | C21: Tex LGC Ch. 505 Type B / Sealy EDC. 0% is a MODELED ASSUMPTION ONLY. | D21: Low | E21: 2026-05-14 | F21: Yes | G21: Yes | H21: No | I21: Modeled assumption only; subject to City Attorney confirmation. Do NOT treat as legally resolved.
A22: Project capture rate | B22: ='00_Inputs_Dashboard'!$B$16 -> 0.8 | C22: Planning benchmark; per-project adjustable | D22: Low | E22: 2026-05-14 | F22: Yes | G22: No | H22: No | I22: Per-project override
A23: City reserve % | B23: ='00_Inputs_Dashboard'!$B$25 -> 0.025 | C23: Planning benchmark; applied to City basis | D23: Low | E23: 2026-05-14 | F23: Yes | G23: No | H23: No | I23: Adjust per policy
A24: ESD reserve % | B24: ='00_Inputs_Dashboard'!$B$26 -> 0.025 | C24: Planning benchmark; applied to ESD basis | D24: Low | E24: 2026-05-14 | F24: No | G24: No | H24: No | I24: ESD-side
A25: Online spend per occupied household | B25: ='00_Inputs_Dashboard'!$B$34 -> 6000 | C25: BASE $6,000/HH; Conservative $4K; High $8K | D25: Low | E25: 2026-05-14 | F25: Yes | G25: No | H25: No | I25: Low-confidence planning assumption; sensitivity $4K-$8K
A26: Online taxable share | B26: ='00_Inputs_Dashboard'!$B$35 -> 0.7 | C26: Base-case assumption shown on Inputs Dashboard; depends on marketplace facilitator scope | D26: Low | E26: 2026-05-14 | F26: Yes | G26: Yes | H26: Yes | I26: Low-confidence; depends on marketplace facilitator scope
A27: Online local capture factor | B27: ='00_Inputs_Dashboard'!$B$36 -> 0.75 | C27: BASE 75%; ship-to address mapping to combined area | D27: Low | E27: 2026-05-14 | F27: Yes | G27: No | H27: Yes | I27: Low-confidence; depends on ship-to address accuracy
A28: Online spend growth rate | B28: ='00_Inputs_Dashboard'!$B$37 -> 0.04 | C28: Annual real growth 4%/yr | D28: Low | E28: 2026-05-14 | F28: Yes | G28: No | H28: No | I28: Low-confidence forward projection
A29: Infrastructure takeoff factors | B29: See 12_Takeoff_Assumptions | C29: Planning benchmarks; not engineer-certified; informational unless linked | D29: Low | E29: 2026-05-15 | F29: Yes | G29: No | H29: No | I29: Water/sewer/street/hydrant/park/police/ESD factors require Public Works, engineer, ESD, and staff validation before public reliance.
A30: Infrastructure takeoff costs | B30: See 12_Takeoff_Assumptions | C30: Unit-cost planning allowances; not included in City/ESD NET unless explicitly linked | D30: Low | E30: 2026-05-15 | F30: Yes | G30: No | H30: No | I30: Takeoff costs are displayed as informational physical exposure only to avoid double-counting with existing opex/capital logic.
A31: AV growth CAGR | B31: ='00_Inputs_Dashboard'!$B$15 -> 0.06 | C31: Sealy HB1378-derived; 5-yr was 7.3% | D31: Medium | E31: 2026-05-14 | F31: Yes | G31: No | H31: No | I31: Forward assumption
A32: General opex inflation | B32: ='00_Inputs_Dashboard'!$B$23 -> 0.025 | C32: TML benchmark 2.5% | D32: Medium | E32: 2026-05-14 | F32: Yes | G32: No | H32: No | I32: Recurring
A33: Capital construction inflation | B33: ='00_Inputs_Dashboard'!$B$24 -> 0.045 | C33: Maxxbuilders TX 2024-2026 (3-6% range) | D33: Medium | E33: 2026-05-14 | F33: Yes | G33: No | H33: No | I33: NEW v3.4 lever
A34: SFR occupancy rate | B34: ='00_Inputs_Dashboard'!$B$30 -> 0.95 | C34: Planning benchmark 95% | D34: Medium | E34: 2026-05-14 | F34: Yes | G34: No | H34: No | I34: Sealy SF benchmark
A35: MFR occupancy rate | B35: ='00_Inputs_Dashboard'!$B$31 -> 0.92 | C35: MFR lease-up steady state 92% | D35: Medium | E35: 2026-05-14 | F35: Yes | G35: No | H35: No | I35: Retreat at Sealy
A36: SFR household size | B36: ='00_Inputs_Dashboard'!$B$32 -> 2.7 | C36: Sealy SF benchmark 2.7 | D36: Medium | E36: 2026-05-14 | F36: No | G36: No | H36: No | I36: Census-derived
A37: MFR household size | B37: ='00_Inputs_Dashboard'!$B$33 -> 2.1 | C37: Retreat at Sealy 2.1 | D37: Medium | E37: 2026-05-14 | F37: No | G37: No | H37: No | I37: MFR benchmark
A38: Industrial AV per acre | B38: $750K/ac | C38: Sika BPP / Hailiang Copper observed range | D38: Medium | E38: 2026-05-14 | F38: Yes | G38: No | H38: No | I38: Per spec cfe57b56 calibration
A39: City marginal opex per resident validation | B39: $680/resident SFR (model) | C39: FY25 ACFR departmental detail: scaling departments (Police $445/cap + Streets $83 + Parks $71 + Planning $69 + Building $43 + Court $45 + 50% of Capital $90) = $846/cap fully-loaded × 80% marginal = $677/cap | D39: Medium-High (SOLID-FY25) | E39: 2026-05-14 (FY25 ACFR) | F39: Yes | G39: No | H39: No | I39: Validated within $3 of FY25 actual at 80% marginal share. Was 'peer-derived (Schertz/Pflugerville via Verdunity)' — now anchored to Sealy FY25 ACFR. Per-acre commercial/industrial opex still planning-level. PEER METHOD: ICMA/TischlerBise per-capita LOS approach; Enumclaw WA FTE-per-capita annexation modeling corroborate the per-resident cost driver.
A40: City General Fund share | C40: User-entered allocation percentage; no preferred split implied | D40: n/a | E40: 2026-05-14 | F40: No | G40: No | H40: No | I40: Modeling assumption
A41: ESD share | C41: User-entered allocation percentage; City + ESD must equal 100% | D41: n/a | E41: 2026-05-14 | F41: No | G41: No | H41: No | I41: Modeling assumption
A42: Reserve basis includes capital? | B42: ='00_Inputs_Dashboard'!$B$27 -> 0 | C42: Spec #13 Option B — (opex + capital) × pct | D42: n/a | E42: 2026-05-14 | F42: Yes | G42: No | H42: No | I42: Toggle
A43: Online use-tax toggle | B43: ='00_Inputs_Dashboard'!$B$38 -> 1 | C43: 1=include / 0=exclude (Test 11/12) | D43: n/a | E43: 2026-05-14 | F43: No | G43: No | H43: No | I43: Toggle
A44: Sealy FY25 audit — material weakness | B44: Internal control over financial statement disclosure | C44: BrooksWatson & Co. FY25 audit, March 28 2026 letter | D44: n/a | E44: 2026-05-14 | F44: Yes | G44: No | H44: No | I44: Common finding for cities of this size (Brooks Watson prepared draft + material adjustments). Not a fraud/loss finding. Doesn't change model inputs.
A45: ESD #2 ILA — active in negotiation | B45: Exec session item J.a on 5/19/2026 agenda | C45: 5/19/2026 council packet, agenda item J.a (public) | D45: n/a | E45: 2026-05-14 | F45: No | G45: Yes | H45: No | I45: Active negotiation. Public agenda confirms ILA + Utility Billing + Lease are being discussed. Closed-session substance NOT in model.
A47: — External FIA peer validation (added v6.1, 2026-05-28; sources in 04_Research/FIA_External_Studies_2026-05-28) —
A48: Method validation — marginal/case-study | B48: v6 uses case-study/marginal-cost drivers (per-acre/resident/unit) | C48: TischlerBise specializes in case-study/marginal-cost over 1,000+ FIAs; ICMA MIS Report (Tischler) recommends it; Lincoln (Kotval-Mullin 2006) = 'classic marginal cost approach' | D48: Peer-sourced | E48: 2026-05-28 | F48: No | G48: No | H48: No | I48: Rebuts 'black-box / non-standard method' criticism.
A49: Method validation — open spreadsheet | B49: v6 is open, unprotected Excel with visible formulas | C49: TischlerBise FISCALS: 'designed in a spreadsheet environment, without protected cells and formulas' | D49: Peer-sourced | E49: 2026-05-28 | F49: No | G49: No | H49: No | I49: Leading FIA firm builds models exactly this way.
A50: Structure — scenarios/cumulative/break-even/zones | B50: v6 scenario builder + 5/10/15/20/30-yr horizons + break-even + per-project rows | C50: TischlerBise Growth Alternatives (cumulative 10-20 yr); Bryan RELLIS (3 scenarios, 4 FAZs, break-even); Verdunity DFIA/LUFA (10-40 yr) | D50: Peer-sourced | E50: 2026-05-28 | F50: No | G50: No | H50: No | I50: v6 30-yr horizon within standard practice range.
A51: Per-acre / value-per-acre dimension | B51: v6 uses per-acre cost AND revenue, not per-capita only | C51: Lincoln: Heikkila-Davis (1997) & Dekel (1995) - per-capita FIA misses spatial/density; Urban3 value/acre; Verdunity LUFA parcel rev/acre | D51: Peer-sourced | E51: 2026-05-28 | F51: No | G51: No | H51: No | I51: Academic basis for the per-acre approach.
A52: Result — residential net-negative | B52: v6: SFR net-negative for City & ESD | C52: COCS 150+ studies/26 states/~40 yrs: residential ratio >1.0; Chatham County NC 2025 residential $1.18/$1; Verdunity TX (sprawl SFR weakest per acre) | D52: Peer-sourced | E52: 2026-05-28 | F52: No | G52: No | H52: No | I52: COCS = existing pattern, not a forward projection (cite honestly).
A53: Result — commercial/industrial net-positive | B53: v6: retail/logistics/manufacturing net-positive | C53: COCS commercial/industrial ratio <1.0; Chatham 2025 commercial $0.29/$1; Castle Pines 2026 commercial-positive; SGA ~10x rev/acre (advocacy, paired w/ Urban3) | D53: Peer-sourced | E53: 2026-05-28 | F53: No | G53: No | H53: No | I53: Matches v6 directional result.
A54: Compact-vs-sprawl infra savings | B54: Informational context (not a base-case input) | C54: SGA Building Better Budgets ~38% lower upfront infra (advocacy meta-finding) - PAIRED with Verdunity TX unfunded-street liabilities (neutral) | D54: Peer-sourced (advocacy, paired) | E54: 2026-05-28 | F54: No | G54: No | H54: No | I54: Cite moderately; always pair w/ a neutral source.
A55: Peer unfunded street liabilities (TX) | B55: Pilot Point $52M; Crowley $127M; Bastrop $144M; Pflugerville $632M; New Braunfels $801M; Brownsville $1.3B | C55: Verdunity TX fiscal-analysis portfolio | D55: Peer-sourced | E55: 2026-05-28 | F55: No | G55: No | H55: No | I55: Neutral evidence that growth carries long-term infra liabilities.
A56: Triangulation defense | B56: 3 independent methods converge | C56: Castle Pines CO Crowsnest 2026: city-staff + TischlerBise dept-level + THK cost-per-acre all net-positive (~$112M/20yr) | D56: Peer-sourced | E56: 2026-05-28 | F56: No | G56: No | H56: No | I56: Gold-standard defensibility: different methods, same direction.
A57: Macro fiscal context | B57: Public safety ~60% of GF; optimism 45% (was 64%) | C57: NLC City Fiscal Conditions 2025 (40th annual; 263 cities) | D57: Peer-sourced | E57: 2026-05-28 | F57: No | G57: No | H57: No | I57: Supports 'fire stays with ESD' frame + capture-favorable-terms-now.
A58: Legal mechanism — city/ESD sales-tax allocation | B58: ILA allocates the combined-area local sales tax | C58: TML Municipal Annexation in TX 2025: Tex. H&S Code 775.0754 authorizes allocation agreement; first-in-time favors existing ESD; neither party compelled | D58: Peer-sourced | E58: 2026-05-28 | F58: No | G58: Yes | H58: No | I58: Confirms the SPA+ILA vehicle (Sec. 43.0751 SPA) the analysis assumes.
A59: Closest peer FIA — Bryan RELLIS | B59: Bryan TX annexation FIA adjacent to TX A&M RELLIS | C59: TischlerBise (KendigKeast Team): 3 scenarios, 4 fiscal-analysis zones, cumulative net, break-even - structurally identical to v6 | D59: Peer-sourced | E59: 2026-05-28 | F59: No | G59: No | H59: No | I59: Full report not public; TPIA deferred per Bobby (2026-05-28).
A61: SALES-TAX SOURCING (Texas Comptroller Pub. 94-105) — how each revenue line is sourced
A62: Retail / commercial at the site | C62: ORIGIN — local sales tax is consummated at the seller's place of business. An annexed retail center's tax flows to the Sealy/ESD combined-area pool (code 6008609) regardless of where shoppers live.
A63: Residential | C63: A home generates NO sales tax itself. Resident in-store spending is origin-sourced to wherever the store is (leaks out unless they shop in Sealy). Only residents' online/delivery purchases shipped to the Sealy address generate local USE tax for Sealy — captured via the online use-tax line.
A64: Online / Amazon / marketplace | C64: DESTINATION (ship-to address). Marketplace providers (Amazon, eBay, Walmart Mktp, Etsy) and remote sellers source local tax to delivery address — not shipment origin, not manufacturer. Remote sellers may elect a single 1.75% local rate; marketplaces cannot.
A65: Manufacturing / distribution warehouse | C65: Generally LITTLE-TO-NO local sales tax. Manufacturers sell wholesale/for-resale (resale exemption) or ship interstate; a warehouse is explicitly NOT a 'place of business' (94-105), so shipping from it does not originate local tax. These are PROPERTY-TAX plays. Modeled at $0 sales by default; manual override only if a facility truly qualifies as an order-receipt place of business.
A66: Legal-uncertainty flag | C66: The in-state 'where an order is received' sourcing rule (Comptroller Rule 3.334) is under a court injunction (Dec 2024) and not being enforced — another reason to keep the online local-capture factor conservative.
A67: Combined area | C67: Sealy + ESD #2 sit in combined-area code 6008609; the Comptroller holds the rate at 2% and splits it between the two — this is the pool the model allocates.
A69: Peer-study benchmarks & methodology validation: see companion v6.1 Peer-Calibration documentation (unhide via right-click).

Sheet Scenarios
A1: Scenario Builder — one row per project. Active rows feed model.
A2: # | B2: Project Name | C2: Active? | D2: Development Type | E2: Quantity Type | F2: Quantity | G2: Acres/Unit (lookup) | H2: Manual Acres Override | I2: Final Acres | J2: Start Year | K2: Buildout Years | L2: Capture Rate | M2: Captured Acres | N2: AV basis (lookup) | O2: Manual AV Override | P2: Final AV ($) | Q2: Sales basis (lookup) | R2: Manual Sales Override | S2: Final Annual Taxable Sales ($) | T2: Captured Building SqFt | U2: Captured Residential Units | V2: Captured Residents | W2: LUE Count | X2: Impact Fee/LUE ($) | Y2: Manual Impact Fee Override | Z2: Final Impact Fee ($) | AA2: Manual City Opex Override (annual $) | AB2: Manual ESD Opex Override (annual $) | AC2: Notes / Source | AD2: City Taxable AV ($) | AE2: ESD Taxable AV ($) | AF2: City Industrial Taxable AV ($) | AG2: ESD Industrial Taxable AV ($) | AH2: Annexed Acres | AI2: Surplus Acres | AJ2: Surplus AV ($) | AK2: Surplus City Tax AV | AL2: Surplus ESD Tax AV
A3: 1 | B3: ='Advanced Inputs'!$A$55 -> Big-Box / Anchor Retail | C3: =('Advanced Inputs'!$B$55="Yes") -> TRUE | D3: ='Advanced Inputs'!$A$55 -> Big-Box / Anchor Retail | E3: ='Advanced Inputs'!$D$55 -> acres | F3: ='Advanced Inputs'!$E$55 -> 10 | G3: =IF('Advanced Inputs'!$N$55<>"",'Advanced Inputs'!$N$55,IFERROR(VLOOKUP(D3,'02_Type_Assumptions'!$A$4:$Z$25,3,FALSE()),0)) -> 1 | H3: =IF('Advanced Inputs'!$F$55="","",'Advanced Inputs'!$F$55) | I3: =(IF(ISNUMBER(H3),H3,IF(LOWER(E3)="sqft",IFERROR(F3/43560/'00_Inputs_Dashboard'!$B$51,0),IF(LOWER(E3)="acres",IFERROR(F3,0),IFERROR(F3*G3,0)))))*(1+IF('Typical Inputs'!E13="",0,'Typical Inputs'!E13)) -> 10 | J3: ='Advanced Inputs'!$G$55 -> 1 | K3: ='Advanced Inputs'!$H$55 -> 4 | L3: ='Advanced Inputs'!$I$55 -> 1 | M3: =I3*L3 -> 10 | N3: =IFERROR(IF(LOWER(E3)="rooms",VLOOKUP(D3,'02_Type_Assumptions'!$A$4:$Z$25,6,FALSE()),IF(LOWER(E3)="acres",VLOOKUP(D3,'02_Type_Assumptions'!$A$4:$Z$25,5,FALSE()),VLOOKUP(D3,'02_Type_Assumptions'!$A$4:$Z$25,4,FALSE()))),0) -> 850000 | P3: =IF(ISNUMBER(O3),O3,IF(LOWER(E3)="rooms",F3*N3*L3,IF(LOWER(E3)="acres",M3*N3,IF(LOWER(E3)="sqft",M3*VLOOKUP(D3,'02_Type_Assumptions'!$A$4:$Z$25,5,FALSE()),F3*N3*L3)))) -> 8500000 | Q3: =IFERROR(IF(VLOOKUP(D3,'02_Type_Assumptions'!$A$4:$Z$25,23,FALSE())="per_acre",VLOOKUP(D3,'02_Type_Assumptions'!$A$4:$Z$25,8,FALSE()),0),0) -> 8000000 | S3: =IF(ISNUMBER(R3),R3*L3,M3*Q3) -> 80000000 | T3: =IF(LOWER(E3)="sqft",F3*L3,M3*IFERROR(VLOOKUP(D3,'02_Type_Assumptions'!$A$4:$Z$25,9,FALSE()),0)) -> 180000 | U3: =IF(OR(LOWER(E3)="lots",LOWER(E3)="units"),F3*L3,0) -> 0 | V3: =U3*IFERROR(VLOOKUP(D3,'02_Type_Assumptions'!$A$4:$Z$25,21,FALSE()),0) -> 0 | W3: =IFERROR(IF(OR(LOWER(E3)="lots",LOWER(E3)="units",LOWER(E3)="rooms"),F3*L3*VLOOKUP(D3,'02_Type_Assumptions'!$A$4:$Z$25,10,FALSE()),IF(LOWER(E3)="acres",M3*VLOOKUP(D3,'02_Type_Assumptions'!$A$4:$Z$25,11,FALSE()),IF(LOWER(E3)="sqft",T3/1000*VLOOKUP(D3,'02_Type_Assumptions'!$A$4:$Z$25,12,FALSE()),0))),0) -> 120 | X3: ='Advanced Inputs'!$D$50 -> 7165 | Z3: =IF(ISNUMBER(Y3),Y3,W3*X3) -> 859800 | AC3: Single-family subdivision — detached homes on standard lots. | AD3: =IFERROR($P3*VLOOKUP($D3,'02_Type_Assumptions'!$A$4:$AC$25,28,FALSE()),$P3)+IFERROR(AK3,0) -> 8415000 | AE3: =IFERROR($P3*VLOOKUP($D3,'02_Type_Assumptions'!$A$4:$AC$25,29,FALSE()),$P3)+IFERROR(AL3,0) -> 8415000 | AF3: =IF(IFERROR(VLOOKUP($D3,'02_Type_Assumptions'!$A$4:$AC$25,27,FALSE()),"")="Industrial",$AD3,0) -> 0 | AG3: =IF(IFERROR(VLOOKUP($D3,'02_Type_Assumptions'!$A$4:$AC$25,27,FALSE()),"")="Industrial",$AE3,0) -> 0 | AH3: =IF('Advanced Inputs'!$L$55="",I3,'Advanced Inputs'!$L$55) -> 10 | AI3: =MAX(0,AH3-I3) -> 0 | AJ3: =AI3*IF(LOWER('Advanced Inputs'!$M$55)="ag",'Advanced Inputs'!$D$51,'02_Type_Assumptions'!$E$18) -> 0 | AK3: =AJ3*'02_Type_Assumptions'!$AB$18 -> 0 | AL3: =AJ3*'02_Type_Assumptions'!$AC$18 -> 0
A4: 2 | B4: ='Advanced Inputs'!$A$56 -> Retail Center / Strip | C4: =('Advanced Inputs'!$B$56="Yes") -> FALSE | D4: ='Advanced Inputs'!$A$56 -> Retail Center / Strip | E4: ='Advanced Inputs'!$D$56 -> acres | F4: ='Advanced Inputs'!$E$56 -> 10 | G4: =IF('Advanced Inputs'!$N$56<>"",'Advanced Inputs'!$N$56,IFERROR(VLOOKUP(D4,'02_Type_Assumptions'!$A$4:$Z$25,3,FALSE()),0)) -> 1 | H4: =IF('Advanced Inputs'!$F$56="","",'Advanced Inputs'!$F$56) | I4: =(IF(ISNUMBER(H4),H4,IF(LOWER(E4)="sqft",IFERROR(F4/43560/'00_Inputs_Dashboard'!$B$51,0),IF(LOWER(E4)="acres",IFERROR(F4,0),IFERROR(F4*G4,0)))))*(1+IF('Typical Inputs'!E14="",0,'Typical Inputs'!E14)) -> 10 | J4: ='Advanced Inputs'!$G$56 -> 1 | K4: ='Advanced Inputs'!$H$56 -> 2 | L4: ='Advanced Inputs'!$I$56 -> 1 | M4: =I4*L4 -> 10 | N4: =IFERROR(IF(LOWER(E4)="rooms",VLOOKUP(D4,'02_Type_Assumptions'!$A$4:$Z$25,6,FALSE()),IF(LOWER(E4)="acres",VLOOKUP(D4,'02_Type_Assumptions'!$A$4:$Z$25,5,FALSE()),VLOOKUP(D4,'02_Type_Assumptions'!$A$4:$Z$25,4,FALSE()))),0) -> 550000 | P4: =IF(ISNUMBER(O4),O4,IF(LOWER(E4)="rooms",F4*N4*L4,IF(LOWER(E4)="acres",M4*N4,IF(LOWER(E4)="sqft",M4*VLOOKUP(D4,'02_Type_Assumptions'!$A$4:$Z$25,5,FALSE()),F4*N4*L4)))) -> 5500000 | Q4: =IFERROR(IF(VLOOKUP(D4,'02_Type_Assumptions'!$A$4:$Z$25,23,FALSE())="per_acre",VLOOKUP(D4,'02_Type_Assumptions'!$A$4:$Z$25,8,FALSE()),0),0) -> 3500000 | S4: =IF(ISNUMBER(R4),R4*L4,M4*Q4) -> 35000000 | T4: =IF(LOWER(E4)="sqft",F4*L4,M4*IFERROR(VLOOKUP(D4,'02_Type_Assumptions'!$A$4:$Z$25,9,FALSE()),0)) -> 120000 | U4: =IF(OR(LOWER(E4)="lots",LOWER(E4)="units"),F4*L4,0) -> 0 | V4: =U4*IFERROR(VLOOKUP(D4,'02_Type_Assumptions'!$A$4:$Z$25,21,FALSE()),0) -> 0 | W4: =IFERROR(IF(OR(LOWER(E4)="lots",LOWER(E4)="units",LOWER(E4)="rooms"),F4*L4*VLOOKUP(D4,'02_Type_Assumptions'!$A$4:$Z$25,10,FALSE()),IF(LOWER(E4)="acres",M4*VLOOKUP(D4,'02_Type_Assumptions'!$A$4:$Z$25,11,FALSE()),IF(LOWER(E4)="sqft",T4/1000*VLOOKUP(D4,'02_Type_Assumptions'!$A$4:$Z$25,12,FALSE()),0))),0) -> 80 | X4: ='Advanced Inputs'!$D$50 -> 7165 | Z4: =IF(ISNUMBER(Y4),Y4,W4*X4) -> 573200 | AC4: Single-family urban / patio — small-lot detached homes. | AD4: =IFERROR($P4*VLOOKUP($D4,'02_Type_Assumptions'!$A$4:$AC$25,28,FALSE()),$P4)+IFERROR(AK4,0) -> 5445000 | AE4: =IFERROR($P4*VLOOKUP($D4,'02_Type_Assumptions'!$A$4:$AC$25,29,FALSE()),$P4)+IFERROR(AL4,0) -> 5445000 | AF4: =IF(IFERROR(VLOOKUP($D4,'02_Type_Assumptions'!$A$4:$AC$25,27,FALSE()),"")="Industrial",$AD4,0) -> 0 | AG4: =IF(IFERROR(VLOOKUP($D4,'02_Type_Assumptions'!$A$4:$AC$25,27,FALSE()),"")="Industrial",$AE4,0) -> 0 | AH4: =IF('Advanced Inputs'!$L$56="",I4,'Advanced Inputs'!$L$56) -> 10 | AI4: =MAX(0,AH4-I4) -> 0 | AJ4: =AI4*IF(LOWER('Advanced Inputs'!$M$56)="ag",'Advanced Inputs'!$D$51,'02_Type_Assumptions'!$E$18) -> 0 | AK4: =AJ4*'02_Type_Assumptions'!$AB$18 -> 0 | AL4: =AJ4*'02_Type_Assumptions'!$AC$18 -> 0
