Workbook

Sheet INPUTS
A1: INPUTS — all user-editable assumptions (edit the yellow 'Your input' column)
A2: Recommended values + their basis are shown for reference. Scenario projects are on the 'Scenarios' tab; large capital items on 'Capital_Items'. Results on 'RESULTS'.
A4: Assumption | B4: Recommended | C4: Basis / source | D4: Your input
A5: A. ALLOCATION & TAX RATES
A6: City General Fund share of sales-tax pool | B6: 50% | C6: User input; no preferred split implied | D6: 0.5
A7: EDC retention (% of City share) | B7: 0% | C7: MODELING ASSUMPTION — subject to City Attorney (Tex LGC Ch.505) | D7: 0
A8: ESD #2 share of sales-tax pool | B8: 50% | C8: User input; City + ESD must = 100% | D8: 0.5
A9: Sales-tax pool rate | B9: 1.5% | C9: Combined-area code 6008609; 2.0% local cap (Tex Tax Ch.321) | D9: 0.015
A10: City property tax rate (per $1 AV) | B10: 0.0037731 | C10: Sealy FY26 Ord. 2025-24 ($0.37731/$100) | D10: 0.0037731
A11: ESD #2 property tax rate (per $1 AV) | B11: 0.000931 | C11: ESD #2 2026 ($0.09310/$100); FY25 ACFR confirms | D11: 0.000931
A12: B. GROWTH & FINANCIAL
A13: Sealy current population | B13: 7,553 | C13: HB1378 §140.008 FY25; FY25 ACFR cross-val | D13: 7553
A14: Population CAGR | B14: 3.2% | C14: HB1378 5-yr actual 6,450→7,553 | D14: 0.032
A15: Current annual sales-tax pool ($) | B15: 3,700,000 | C15: FY26 Adopted Budget (conservative floor) | D15: 3700000
A16: Sales-tax pool CAGR | B16: 6.5% | C16: Sealy 12-yr Comptroller; 9% high-case sensitivity | D16: 0.065
A17: Property AV growth CAGR | B17: 6.0% | C17: HB1378-derived; 5-yr was 7.3% (conservative) | D17: 0.06
A18: Annexation capture rate | B18: 80% | C18: Planning benchmark; per-project adjustable | D18: 0.8
A19: General opex inflation CAGR | B19: 2.5% | C19: TML benchmark | D19: 0.025
A20: Capital construction inflation CAGR | B20: 4.5% | C20: Maxxbuilders TX 2024-2026 (3-6%) | D20: 0.045
A21: City reserve % (opex+capital basis) | B21: 2.5% | C21: Planning benchmark | D21: 0.025
A22: ESD reserve % (opex+capital basis) | B22: 2.5% | C22: Planning benchmark | D22: 0.025
A23: Reserve basis includes capital? (1=Yes,0=No) | B23: 1 | C23: Spec #13 Option B | D23: 1
A24: Property tax collection rate | B24: 100% | C24: FY25 ACFR collected ~104.6%; default 100% | D24: 1
A25: C. RESIDENT ONLINE / DELIVERY USE-TAX
A26: SFR occupancy rate | B26: 95% | C26: Planning benchmark | D26: 0.95
A27: MFR occupancy rate | B27: 92% | C27: Retreat at Sealy lease-up | D27: 0.92
A28: SFR household size | B28: 2.7 | C28: Census-derived | D28: 2.7
A29: MFR household size | B29: 2.1 | C29: Retreat at Sealy | D29: 2.1
A30: Online spend per occupied household ($) | B30: 6,000 | C30: Base case; $4K cons / $8K high | D30: 6000
A31: Taxable share of online spending | B31: 70% | C31: Marketplace + remote-seller scope | D31: 0.7
A32: Local address capture factor | B32: 75% | C32: Destination ship-to to Sealy/ESD combined area | D32: 0.75
A33: Online spend growth (CAGR) | B33: 4% | C33: Real growth/HH | D33: 0.04
A34: Include online use-tax? (1=Yes,0=No) | B34: 1 | C34: Toggle (Test 11/12) | D34: 1
A36: D. EXEMPTION ADJUSTMENT — effective taxable-value factor (edit % cells; factor = 1 − sum)
A37: Category | B37: Homestead% | C37: Over65% | D37: DisVet% | E37: Freeport% | F37: Pollution% | G37: Other% | H37: Haircut | I37: Factor | J37: ESD Hmstd% | K37: ESD Ov65% | L37: ESD DVet% | M37: ESD Free% | N37: ESD Poll% | O37: ESD Other% | P37: ESD Haircut | Q37: ESD Factor
A38: Residential | B38: 0 | C38: 0.005 | D38: 0.015 | E38: 0 | F38: 0 | G38: 0 | H38: =SUM(B38:G38) | I38: =MAX(0,1-H38) | J38: 0.015 | K38: 0.005 | L38: 0.015 | M38: 0 | N38: 0 | O38: 0 | P38: =SUM(J38:O38) | Q38: =MAX(0,1-P38)
A39: Commercial | B39: 0 | C39: 0 | D39: 0 | E39: 0 | F39: 0 | G39: 0.01 | H39: =SUM(B39:G39) | I39: =MAX(0,1-H39) | J39: 0 | K39: 0 | L39: 0 | M39: 0 | N39: 0 | O39: 0.01 | P39: =SUM(J39:O39) | Q39: =MAX(0,1-P39)
A40: Industrial | B40: 0 | C40: 0 | D40: 0 | E40: 0.05 | F40: 0.02 | G40: 0.01 | H40: =SUM(B40:G40) | I40: =MAX(0,1-H40) | J40: 0 | K40: 0 | L40: 0 | M40: 0.05 | N40: 0.02 | O40: 0.01 | P40: =SUM(J40:O40) | Q40: =MAX(0,1-P40)
A41: Civic | B41: 0 | C41: 0 | D41: 0 | E41: 0 | F41: 0 | G41: 1 | H41: =SUM(B41:G41) | I41: =MAX(0,1-H41) | J41: 0 | K41: 0 | L41: 0 | M41: 0 | N41: 0 | O41: 1 | P41: =SUM(J41:O41) | Q41: =MAX(0,1-P41)
A42: Vacant | B42: 0 | C42: 0 | D42: 0 | E42: 0 | F42: 0 | G42: 0 | H42: =SUM(B42:G42) | I42: =MAX(0,1-H42) | J42: 0 | K42: 0 | L42: 0 | M42: 0 | N42: 0 | O42: 0 | P42: =SUM(J42:O42) | Q42: =MAX(0,1-P42)
A44: Factors flow to Type coefficients → property tax. City of Sealy: no general homestead. ESD #2: 1% homestead. Confirm vs Austin CAD certified roll.
A46: E. DEVELOPMENT GEOMETRY & INCENTIVES
A47: Floor-Area-Ratio (FAR) for sqft-entered projects | B47: 30% | C47: Building footprint vs lot area. Applies only when a project is entered by sqft (e.g., 200K sqft ÷ 43,560 ÷ FAR = land acres). Industrial 25–30% typical. | D47: 0.30
A48: New industrial tax abatement % | B48: 0% | C48: Generic Ch.312-style abatement on NEW industrial taxable value (city & ESD). 0% = full taxation (default). Stress lever only; not tied to any named project. | D48: 0
A49: Industrial abatement term (years) | B49: 10 (max) | C49: Ch.312 abatements last up to 10 yrs, then full tax resumes (Tex Tax Code §312.204). Applies to city + ESD property tax; not sales tax. | D49: 10
A50: Water + sewer impact fee per LUE ($) | B50: $7,165 | C50: Sealy 2018 Strand study: $3,381 water + $3,784 sewer (adopted). Drives Scenario impact fees + Capital LUE triggers. | D50: 7165
A52: F. SCENARIO PROJECTS — set Active=Yes to include a project. Type & Quantity Type are dropdowns. Manual Acres only to override the lookup.
A53: Project Name | B53: Active? | C53: Development Type | D53: Quantity Type | E53: Quantity | F53: Manual Acres (opt.) | G53: Start Year | H53: Buildout Yrs | I53: Capture % | T53: (type list)
A54: 100-home SFR subdivision | B54: No | C54: Single-Family Subdivision | D54: lots | E54: 100 | G54: 1 | H54: 5 | I54: 1 | T54: Single-Family Subdivision
A55: 600-lot SFR subdivision | B55: No | C55: Single-Family Subdivision | D55: lots | E55: 600 | G55: 1 | H55: 8 | I55: 1 | T55: Single-Family Urban / Patio
A56: 20-acre retail center | B56: Yes | C56: Retail Center / Strip | D56: acres | E56: 20 | G56: 2 | H56: 3 | I56: 1 | T56: Townhome / Condo
A57: 200,000 sqft manufacturing | B57: No | C57: Manufacturing | D57: sqft | E57: 200000 | G57: 3 | H57: 2 | I57: 1 | T57: Multifamily Apartments
A58: 40-acre industrial / logistics | B58: No | C58: Industrial / Logistics | D58: acres | E58: 40 | G58: 2 | H58: 4 | I58: 1 | T58: Big-Box / Anchor Retail
A59: 100-room hotel | B59: No | C59: Hotel | D59: rooms | E59: 100 | G59: 2 | H59: 2 | I59: 1 | T59: Retail Center / Strip
A60: 250-unit multifamily apartments | B60: No | C60: Multifamily Apartments | D60: units | E60: 250 | G60: 2 | H60: 3 | I60: 1 | T60: Office / Business Park
B61: No | T61: Hotel
B62: No | T62: Manufacturing
B63: No | T63: Industrial / Logistics
B64: No | T64: Light Industrial / Flex
B65: No | T65: Mixed-Use Pad / Vertical
T66: Civic / Institutional
T67: Parks / Open Space
T68: Vacant / Holding Land

Sheet Capital_Items
A1: Capital Items — large infrastructure & equipment (set the white cells; results flow to RESULTS)
A2: HOW TO READ: Quantities are CUMULATIVE totals at buildout, NOT per-year — a value that's the same across years just means that item is fully built and not still growing. A cost affects City/ESD NET only when 'Include in net?' = Yes AND 'Who pays' = City or ESD (choosing Developer or another payer removes it from the fiscal net). 'How it's paid' = Cash capital (one-time) or Debt service (financed over the term).
A3: Item | B3: Entity | C3: Driver (what triggers qty) | D3: Unit | E3: Typical factor | F3: 5-year auto qty | G3: 10-year auto qty | H3: 15-year auto qty | I3: 20-year auto qty | J3: 30-year auto qty | K3: Manual qty +/- | L3: Cumulative quantity (at buildout) | M3: Unit cost ($) | N3: Unit cost override | O3: Manual Total Cost Override | P3: Total cost (today's $) | Q3: Who pays | R3: Include in net? | S3: How it's paid | T3: Start year | U3: Debt term (yrs) | V3: Debt rate | W3: Annual Debt Service | X3: City 5-year impact | Y3: City 10-year impact | Z3: City 15-year impact | AA3: City 20-year impact | AB3: City 30-year impact | AC3: ESD 5-year impact | AD3: ESD 10-year impact | AE3: ESD 15-year impact | AF3: ESD 20-year impact | AG3: ESD 30-year impact | AH3: Source / Note
A4: 12-inch water main, transmission | B4: City | C4: captured acres | D4: linear ft | E4: 60 LF/ac | F4: ='03_Multi_Horizon_Results'!$B$5*'12_Takeoff_Assumptions'!$B$3 | G4: ='03_Multi_Horizon_Results'!$C$5*'12_Takeoff_Assumptions'!$B$3 | H4: ='03_Multi_Horizon_Results'!$D$5*'12_Takeoff_Assumptions'!$B$3 | I4: ='03_Multi_Horizon_Results'!$E$5*'12_Takeoff_Assumptions'!$B$3 | J4: ='03_Multi_Horizon_Results'!$F$5*'12_Takeoff_Assumptions'!$B$3 | L4: =MAX(0,N(G4)+N(K4)) | M4: 600 | P4: =IFERROR(IF(O4<>"",O4,L4*IF(N4<>"",N4,M4)),0) | Q4: City | R4: No | S4: Debt service | T4: 1 | U4: 20 | V4: 0.045 | W4: =IFERROR(IF(AND(R4="Yes",S4="Debt service",U4>0),IF(V4=0,P4/U4,P4*V4/(1-(1+V4)^(-U4))),0),0) | X4: =IFERROR(IF(OR(R4<>"Yes",Q4<>"City"),0,IF(S4="Cash capital",IF(T4<=5,IF(O4<>"",O4,MAX(0,N(F4)+N(K4))*IF(N4<>"",N4,M4)),0),IF(S4="Debt service",IF(T4>5,0,W4*MAX(0,MIN(5-T4+1,U4))),IF(OR(S4="Annual O&M",S4="Maintenance-only"),IF(T4>5,0,IF(O4<>"",O4,MAX(0,N(F4)+N(K4))*IF(N4<>"",N4,M4))*MAX(0,5-T4+1)),0)))),0) | Y4: =IFERROR(IF(OR(R4<>"Yes",Q4<>"City"),0,IF(S4="Cash capital",IF(T4<=10,IF(O4<>"",O4,MAX(0,N(G4)+N(K4))*IF(N4<>"",N4,M4)),0),IF(S4="Debt service",IF(T4>10,0,W4*MAX(0,MIN(10-T4+1,U4))),IF(OR(S4="Annual O&M",S4="Maintenance-only"),IF(T4>10,0,IF(O4<>"",O4,MAX(0,N(G4)+N(K4))*IF(N4<>"",N4,M4))*MAX(0,10-T4+1)),0)))),0) | Z4: =IFERROR(IF(OR(R4<>"Yes",Q4<>"City"),0,IF(S4="Cash capital",IF(T4<=15,IF(O4<>"",O4,MAX(0,N(H4)+N(K4))*IF(N4<>"",N4,M4)),0),IF(S4="Debt service",IF(T4>15,0,W4*MAX(0,MIN(15-T4+1,U4))),IF(OR(S4="Annual O&M",S4="Maintenance-only"),IF(T4>15,0,IF(O4<>"",O4,MAX(0,N(H4)+N(K4))*IF(N4<>"",N4,M4))*MAX(0,15-T4+1)),0)))),0) | AA4: =IFERROR(IF(OR(R4<>"Yes",Q4<>"City"),0,IF(S4="Cash capital",IF(T4<=20,IF(O4<>"",O4,MAX(0,N(I4)+N(K4))*IF(N4<>"",N4,M4)),0),IF(S4="Debt service",IF(T4>20,0,W4*MAX(0,MIN(20-T4+1,U4))),IF(OR(S4="Annual O&M",S4="Maintenance-only"),IF(T4>20,0,IF(O4<>"",O4,MAX(0,N(I4)+N(K4))*IF(N4<>"",N4,M4))*MAX(0,20-T4+1)),0)))),0) | AB4: =IFERROR(IF(OR(R4<>"Yes",Q4<>"City"),0,IF(S4="Cash capital",IF(T4<=30,IF(O4<>"",O4,MAX(0,N(J4)+N(K4))*IF(N4<>"",N4,M4)),0),IF(S4="Debt service",IF(T4>30,0,W4*MAX(0,MIN(30-T4+1,U4))),IF(OR(S4="Annual O&M",S4="Maintenance-only"),IF(T4>30,0,IF(O4<>"",O4,MAX(0,N(J4)+N(K4))*IF(N4<>"",N4,M4))*MAX(0,30-T4+1)),0)))),0) | AC4: =IFERROR(IF(OR(R4<>"Yes",Q4<>"ESD"),0,IF(S4="Cash capital",IF(T4<=5,IF(O4<>"",O4,MAX(0,N(F4)+N(K4))*IF(N4<>"",N4,M4)),0),IF(S4="Debt service",IF(T4>5,0,W4*MAX(0,MIN(5-T4+1,U4))),IF(OR(S4="Annual O&M",S4="Maintenance-only"),IF(T4>5,0,IF(O4<>"",O4,MAX(0,N(F4)+N(K4))*IF(N4<>"",N4,M4))*MAX(0,5-T4+1)),0)))),0) | AD4: =IFERROR(IF(OR(R4<>"Yes",Q4<>"ESD"),0,IF(S4="Cash capital",IF(T4<=10,IF(O4<>"",O4,MAX(0,N(G4)+N(K4))*IF(N4<>"",N4,M4)),0),IF(S4="Debt service",IF(T4>10,0,W4*MAX(0,MIN(10-T4+1,U4))),IF(OR(S4="Annual O&M",S4="Maintenance-only"),IF(T4>10,0,IF(O4<>"",O4,MAX(0,N(G4)+N(K4))*IF(N4<>"",N4,M4))*MAX(0,10-T4+1)),0)))),0) | AE4: =IFERROR(IF(OR(R4<>"Yes",Q4<>"ESD"),0,IF(S4="Cash capital",IF(T4<=15,IF(O4<>"",O4,MAX(0,N(H4)+N(K4))*IF(N4<>"",N4,M4)),0),IF(S4="Debt service",IF(T4>15,0,W4*MAX(0,MIN(15-T4+1,U4))),IF(OR(S4="Annual O&M",S4="Maintenance-only"),IF(T4>15,0,IF(O4<>"",O4,MAX(0,N(H4)+N(K4))*IF(N4<>"",N4,M4))*MAX(0,15-T4+1)),0)))),0) | AF4: =IFERROR(IF(OR(R4<>"Yes",Q4<>"ESD"),0,IF(S4="Cash capital",IF(T4<=20,IF(O4<>"",O4,MAX(0,N(I4)+N(K4))*IF(N4<>"",N4,M4)),0),IF(S4="Debt service",IF(T4>20,0,W4*MAX(0,MIN(20-T4+1,U4))),IF(OR(S4="Annual O&M",S4="Maintenance-only"),IF(T4>20,0,IF(O4<>"",O4,MAX(0,N(I4)+N(K4))*IF(N4<>"",N4,M4))*MAX(0,20-T4+1)),0)))),0) | AG4: =IFERROR(IF(OR(R4<>"Yes",Q4<>"ESD"),0,IF(S4="Cash capital",IF(T4<=30,IF(O4<>"",O4,MAX(0,N(J4)+N(K4))*IF(N4<>"",N4,M4)),0),IF(S4="Debt service",IF(T4>30,0,W4*MAX(0,MIN(30-T4+1,U4))),IF(OR(S4="Annual O&M",S4="Maintenance-only"),IF(T4>30,0,IF(O4<>"",O4,MAX(0,N(J4)+N(K4))*IF(N4<>"",N4,M4))*MAX(0,30-T4+1)),0)))),0) | AH4: Planning allowance for trunk/looping needs; engineer/Public Works validation required.
A5: 8-inch water main, distribution | B5: City | C5: captured acres | D5: linear ft | E5: 400 LF/ac | F5: ='03_Multi_Horizon_Results'!$B$5*'12_Takeoff_Assumptions'!$B$2 | G5: ='03_Multi_Horizon_Results'!$C$5*'12_Takeoff_Assumptions'!$B$2 | H5: ='03_Multi_Horizon_Results'!$D$5*'12_Takeoff_Assumptions'!$B$2 | I5: ='03_Multi_Horizon_Results'!$E$5*'12_Takeoff_Assumptions'!$B$2 | J5: ='03_Multi_Horizon_Results'!$F$5*'12_Takeoff_Assumptions'!$B$2 | L5: =MAX(0,N(G5)+N(K5)) | M5: 250 | P5: =IFERROR(IF(O5<>"",O5,L5*IF(N5<>"",N5,M5)),0) | Q5: City | R5: No | S5: Debt service | T5: 1 | U5: 20 | V5: 0.045 | W5: =IFERROR(IF(AND(R5="Yes",S5="Debt service",U5>0),IF(V5=0,P5/U5,P5*V5/(1-(1+V5)^(-U5))),0),0) | X5: =IFERROR(IF(OR(R5<>"Yes",Q5<>"City"),0,IF(S5="Cash capital",IF(T5<=5,IF(O5<>"",O5,MAX(0,N(F5)+N(K5))*IF(N5<>"",N5,M5)),0),IF(S5="Debt service",IF(T5>5,0,W5*MAX(0,MIN(5-T5+1,U5))),IF(OR(S5="Annual O&M",S5="Maintenance-only"),IF(T5>5,0,IF(O5<>"",O5,MAX(0,N(F5)+N(K5))*IF(N5<>"",N5,M5))*MAX(0,5-T5+1)),0)))),0) | Y5: =IFERROR(IF(OR(R5<>"Yes",Q5<>"City"),0,IF(S5="Cash capital",IF(T5<=10,IF(O5<>"",O5,MAX(0,N(G5)+N(K5))*IF(N5<>"",N5,M5)),0),IF(S5="Debt service",IF(T5>10,0,W5*MAX(0,MIN(10-T5+1,U5))),IF(OR(S5="Annual O&M",S5="Maintenance-only"),IF(T5>10,0,IF(O5<>"",O5,MAX(0,N(G5)+N(K5))*IF(N5<>"",N5,M5))*MAX(0,10-T5+1)),0)))),0) | Z5: =IFERROR(IF(OR(R5<>"Yes",Q5<>"City"),0,IF(S5="Cash capital",IF(T5<=15,IF(O5<>"",O5,MAX(0,N(H5)+N(K5))*IF(N5<>"",N5,M5)),0),IF(S5="Debt service",IF(T5>15,0,W5*MAX(0,MIN(15-T5+1,U5))),IF(OR(S5="Annual O&M",S5="Maintenance-only"),IF(T5>15,0,IF(O5<>"",O5,MAX(0,N(H5)+N(K5))*IF(N5<>"",N5,M5))*MAX(0,15-T5+1)),0)))),0) | AA5: =IFERROR(IF(OR(R5<>"Yes",Q5<>"City"),0,IF(S5="Cash capital",IF(T5<=20,IF(O5<>"",O5,MAX(0,N(I5)+N(K5))*IF(N5<>"",N5,M5)),0),IF(S5="Debt service",IF(T5>20,0,W5*MAX(0,MIN(20-T5+1,U5))),IF(OR(S5="Annual O&M",S5="Maintenance-only"),IF(T5>20,0,IF(O5<>"",O5,MAX(0,N(I5)+N(K5))*IF(N5<>"",N5,M5))*MAX(0,20-T5+1)),0)))),0) | AB5: =IFERROR(IF(OR(R5<>"Yes",Q5<>"City"),0,IF(S5="Cash capital",IF(T5<=30,IF(O5<>"",O5,MAX(0,N(J5)+N(K5))*IF(N5<>"",N5,M5)),0),IF(S5="Debt service",IF(T5>30,0,W5*MAX(0,MIN(30-T5+1,U5))),IF(OR(S5="Annual O&M",S5="Maintenance-only"),IF(T5>30,0,IF(O5<>"",O5,MAX(0,N(J5)+N(K5))*IF(N5<>"",N5,M5))*MAX(0,30-T5+1)),0)))),0) | AC5: =IFERROR(IF(OR(R5<>"Yes",Q5<>"ESD"),0,IF(S5="Cash capital",IF(T5<=5,IF(O5<>"",O5,MAX(0,N(F5)+N(K5))*IF(N5<>"",N5,M5)),0),IF(S5="Debt service",IF(T5>5,0,W5*MAX(0,MIN(5-T5+1,U5))),IF(OR(S5="Annual O&M",S5="Maintenance-only"),IF(T5>5,0,IF(O5<>"",O5,MAX(0,N(F5)+N(K5))*IF(N5<>"",N5,M5))*MAX(0,5-T5+1)),0)))),0) | AD5: =IFERROR(IF(OR(R5<>"Yes",Q5<>"ESD"),0,IF(S5="Cash capital",IF(T5<=10,IF(O5<>"",O5,MAX(0,N(G5)+N(K5))*IF(N5<>"",N5,M5)),0),IF(S5="Debt service",IF(T5>10,0,W5*MAX(0,MIN(10-T5+1,U5))),IF(OR(S5="Annual O&M",S5="Maintenance-only"),IF(T5>10,0,IF(O5<>"",O5,MAX(0,N(G5)+N(K5))*IF(N5<>"",N5,M5))*MAX(0,10-T5+1)),0)))),0) | AE5: =IFERROR(IF(OR(R5<>"Yes",Q5<>"ESD"),0,IF(S5="Cash capital",IF(T5<=15,IF(O5<>"",O5,MAX(0,N(H5)+N(K5))*IF(N5<>"",N5,M5)),0),IF(S5="Debt service",IF(T5>15,0,W5*MAX(0,MIN(15-T5+1,U5))),IF(OR(S5="Annual O&M",S5="Maintenance-only"),IF(T5>15,0,IF(O5<>"",O5,MAX(0,N(H5)+N(K5))*IF(N5<>"",N5,M5))*MAX(0,15-T5+1)),0)))),0) | AF5: =IFERROR(IF(OR(R5<>"Yes",Q5<>"ESD"),0,IF(S5="Cash capital",IF(T5<=20,IF(O5<>"",O5,MAX(0,N(I5)+N(K5))*IF(N5<>"",N5,M5)),0),IF(S5="Debt service",IF(T5>20,0,W5*MAX(0,MIN(20-T5+1,U5))),IF(OR(S5="Annual O&M",S5="Maintenance-only"),IF(T5>20,0,IF(O5<>"",O5,MAX(0,N(I5)+N(K5))*IF(N5<>"",N5,M5))*MAX(0,20-T5+1)),0)))),0) | AG5: =IFERROR(IF(OR(R5<>"Yes",Q5<>"ESD"),0,IF(S5="Cash capital",IF(T5<=30,IF(O5<>"",O5,MAX(0,N(J5)+N(K5))*IF(N5<>"",N5,M5)),0),IF(S5="Debt service",IF(T5>30,0,W5*MAX(0,MIN(30-T5+1,U5))),IF(OR(S5="Annual O&M",S5="Maintenance-only"),IF(T5>30,0,IF(O5<>"",O5,MAX(0,N(J5)+N(K5))*IF(N5<>"",N5,M5))*MAX(0,30-T5+1)),0)))),0) | AH5: Subdivision/internal water distribution planning allowance; actual plat should override.
A6: Fire hydrants | B6: City | C6: water distribution LF | D6: each | E6: hydrant spacing 500 LF | F6: =IFERROR(ROUNDUP(('03_Multi_Horizon_Results'!$B$5*'12_Takeoff_Assumptions'!$B$2)/'12_Takeoff_Assumptions'!$B$9,0),0) | G6: =IFERROR(ROUNDUP(('03_Multi_Horizon_Results'!$C$5*'12_Takeoff_Assumptions'!$B$2)/'12_Takeoff_Assumptions'!$B$9,0),0) | H6: =IFERROR(ROUNDUP(('03_Multi_Horizon_Results'!$D$5*'12_Takeoff_Assumptions'!$B$2)/'12_Takeoff_Assumptions'!$B$9,0),0) | I6: =IFERROR(ROUNDUP(('03_Multi_Horizon_Results'!$E$5*'12_Takeoff_Assumptions'!$B$2)/'12_Takeoff_Assumptions'!$B$9,0),0) | J6: =IFERROR(ROUNDUP(('03_Multi_Horizon_Results'!$F$5*'12_Takeoff_Assumptions'!$B$2)/'12_Takeoff_Assumptions'!$B$9,0),0) | L6: =MAX(0,N(G6)+N(K6)) | M6: 7500 | P6: =IFERROR(IF(O6<>"",O6,L6*IF(N6<>"",N6,M6)),0) | Q6: City | R6: No | S6: Debt service | T6: 1 | U6: 20 | V6: 0.045 | W6: =IFERROR(IF(AND(R6="Yes",S6="Debt service",U6>0),IF(V6=0,P6/U6,P6*V6/(1-(1+V6)^(-U6))),0),0) | X6: =IFERROR(IF(OR(R6<>"Yes",Q6<>"City"),0,IF(S6="Cash capital",IF(T6<=5,IF(O6<>"",O6,MAX(0,N(F6)+N(K6))*IF(N6<>"",N6,M6)),0),IF(S6="Debt service",IF(T6>5,0,W6*MAX(0,MIN(5-T6+1,U6))),IF(OR(S6="Annual O&M",S6="Maintenance-only"),IF(T6>5,0,IF(O6<>"",O6,MAX(0,N(F6)+N(K6))*IF(N6<>"",N6,M6))*MAX(0,5-T6+1)),0)))),0) | Y6: =IFERROR(IF(OR(R6<>"Yes",Q6<>"City"),0,IF(S6="Cash capital",IF(T6<=10,IF(O6<>"",O6,MAX(0,N(G6)+N(K6))*IF(N6<>"",N6,M6)),0),IF(S6="Debt service",IF(T6>10,0,W6*MAX(0,MIN(10-T6+1,U6))),IF(OR(S6="Annual O&M",S6="Maintenance-only"),IF(T6>10,0,IF(O6<>"",O6,MAX(0,N(G6)+N(K6))*IF(N6<>"",N6,M6))*MAX(0,10-T6+1)),0)))),0) | Z6: =IFERROR(IF(OR(R6<>"Yes",Q6<>"City"),0,IF(S6="Cash capital",IF(T6<=15,IF(O6<>"",O6,MAX(0,N(H6)+N(K6))*IF(N6<>"",N6,M6)),0),IF(S6="Debt service",IF(T6>15,0,W6*MAX(0,MIN(15-T6+1,U6))),IF(OR(S6="Annual O&M",S6="Maintenance-only"),IF(T6>15,0,IF(O6<>"",O6,MAX(0,N(H6)+N(K6))*IF(N6<>"",N6,M6))*MAX(0,15-T6+1)),0)))),0) | AA6: =IFERROR(IF(OR(R6<>"Yes",Q6<>"City"),0,IF(S6="Cash capital",IF(T6<=20,IF(O6<>"",O6,MAX(0,N(I6)+N(K6))*IF(N6<>"",N6,M6)),0),IF(S6="Debt service",IF(T6>20,0,W6*MAX(0,MIN(20-T6+1,U6))),IF(OR(S6="Annual O&M",S6="Maintenance-only"),IF(T6>20,0,IF(O6<>"",O6,MAX(0,N(I6)+N(K6))*IF(N6<>"",N6,M6))*MAX(0,20-T6+1)),0)))),0) | AB6: =IFERROR(IF(OR(R6<>"Yes",Q6<>"City"),0,IF(S6="Cash capital",IF(T6<=30,IF(O6<>"",O6,MAX(0,N(J6)+N(K6))*IF(N6<>"",N6,M6)),0),IF(S6="Debt service",IF(T6>30,0,W6*MAX(0,MIN(30-T6+1,U6))),IF(OR(S6="Annual O&M",S6="Maintenance-only"),IF(T6>30,0,IF(O6<>"",O6,MAX(0,N(J6)+N(K6))*IF(N6<>"",N6,M6))*MAX(0,30-T6+1)),0)))),0) | AC6: =IFERROR(IF(OR(R6<>"Yes",Q6<>"ESD"),0,IF(S6="Cash capital",IF(T6<=5,IF(O6<>"",O6,MAX(0,N(F6)+N(K6))*IF(N6<>"",N6,M6)),0),IF(S6="Debt service",IF(T6>5,0,W6*MAX(0,MIN(5-T6+1,U6))),IF(OR(S6="Annual O&M",S6="Maintenance-only"),IF(T6>5,0,IF(O6<>"",O6,MAX(0,N(F6)+N(K6))*IF(N6<>"",N6,M6))*MAX(0,5-T6+1)),0)))),0) | AD6: =IFERROR(IF(OR(R6<>"Yes",Q6<>"ESD"),0,IF(S6="Cash capital",IF(T6<=10,IF(O6<>"",O6,MAX(0,N(G6)+N(K6))*IF(N6<>"",N6,M6)),0),IF(S6="Debt service",IF(T6>10,0,W6*MAX(0,MIN(10-T6+1,U6))),IF(OR(S6="Annual O&M",S6="Maintenance-only"),IF(T6>10,0,IF(O6<>"",O6,MAX(0,N(G6)+N(K6))*IF(N6<>"",N6,M6))*MAX(0,10-T6+1)),0)))),0) | AE6: =IFERROR(IF(OR(R6<>"Yes",Q6<>"ESD"),0,IF(S6="Cash capital",IF(T6<=15,IF(O6<>"",O6,MAX(0,N(H6)+N(K6))*IF(N6<>"",N6,M6)),0),IF(S6="Debt service",IF(T6>15,0,W6*MAX(0,MIN(15-T6+1,U6))),IF(OR(S6="Annual O&M",S6="Maintenance-only"),IF(T6>15,0,IF(O6<>"",O6,MAX(0,N(H6)+N(K6))*IF(N6<>"",N6,M6))*MAX(0,15-T6+1)),0)))),0) | AF6: =IFERROR(IF(OR(R6<>"Yes",Q6<>"ESD"),0,IF(S6="Cash capital",IF(T6<=20,IF(O6<>"",O6,MAX(0,N(I6)+N(K6))*IF(N6<>"",N6,M6)),0),IF(S6="Debt service",IF(T6>20,0,W6*MAX(0,MIN(20-T6+1,U6))),IF(OR(S6="Annual O&M",S6="Maintenance-only"),IF(T6>20,0,IF(O6<>"",O6,MAX(0,N(I6)+N(K6))*IF(N6<>"",N6,M6))*MAX(0,20-T6+1)),0)))),0) | AG6: =IFERROR(IF(OR(R6<>"Yes",Q6<>"ESD"),0,IF(S6="Cash capital",IF(T6<=30,IF(O6<>"",O6,MAX(0,N(J6)+N(K6))*IF(N6<>"",N6,M6)),0),IF(S6="Debt service",IF(T6>30,0,W6*MAX(0,MIN(30-T6+1,U6))),IF(OR(S6="Annual O&M",S6="Maintenance-only"),IF(T6>30,0,IF(O6<>"",O6,MAX(0,N(J6)+N(K6))*IF(N6<>"",N6,M6))*MAX(0,30-T6+1)),0)))),0) | AH6: Hydrant count from distribution LF / spacing; verify fire code and utility standards.
A7: Water wells, 1,500 gpm | B7: City | C7: water demand MGD | D7: each | E7: threshold 0.50 MGD | F7: =IF((('03_Multi_Horizon_Results'!$B$22/INPUTS!$D$50)*'12_Takeoff_Assumptions'!$B$13/1000000)>'12_Takeoff_Assumptions'!$B$16,ROUNDUP((('03_Multi_Horizon_Results'!$B$22/INPUTS!$D$50)*'12_Takeoff_Assumptions'!$B$13/1000000)/'12_Takeoff_Assumptions'!$B$16,0),0) | G7: =IF((('03_Multi_Horizon_Results'!$C$22/INPUTS!$D$50)*'12_Takeoff_Assumptions'!$B$13/1000000)>'12_Takeoff_Assumptions'!$B$16,ROUNDUP((('03_Multi_Horizon_Results'!$C$22/INPUTS!$D$50)*'12_Takeoff_Assumptions'!$B$13/1000000)/'12_Takeoff_Assumptions'!$B$16,0),0) | H7: =IF((('03_Multi_Horizon_Results'!$D$22/INPUTS!$D$50)*'12_Takeoff_Assumptions'!$B$13/1000000)>'12_Takeoff_Assumptions'!$B$16,ROUNDUP((('03_Multi_Horizon_Results'!$D$22/INPUTS!$D$50)*'12_Takeoff_Assumptions'!$B$13/1000000)/'12_Takeoff_Assumptions'!$B$16,0),0) | I7: =IF((('03_Multi_Horizon_Results'!$E$22/INPUTS!$D$50)*'12_Takeoff_Assumptions'!$B$13/1000000)>'12_Takeoff_Assumptions'!$B$16,ROUNDUP((('03_Multi_Horizon_Results'!$E$22/INPUTS!$D$50)*'12_Takeoff_Assumptions'!$B$13/1000000)/'12_Takeoff_Assumptions'!$B$16,0),0) | J7: =IF((('03_Multi_Horizon_Results'!$F$22/INPUTS!$D$50)*'12_Takeoff_Assumptions'!$B$13/1000000)>'12_Takeoff_Assumptions'!$B$16,ROUNDUP((('03_Multi_Horizon_Results'!$F$22/INPUTS!$D$50)*'12_Takeoff_Assumptions'!$B$13/1000000)/'12_Takeoff_Assumptions'!$B$16,0),0) | L7: =MAX(0,N(G7)+N(K7)) | M7: 1500000 | P7: =IFERROR(IF(O7<>"",O7,L7*IF(N7<>"",N7,M7)),0) | Q7: City | R7: No | S7: Debt service | T7: 1 | U7: 20 | V7: 0.045 | W7: =IFERROR(IF(AND(R7="Yes",S7="Debt service",U7>0),IF(V7=0,P7/U7,P7*V7/(1-(1+V7)^(-U7))),0),0) | X7: =IFERROR(IF(OR(R7<>"Yes",Q7<>"City"),0,IF(S7="Cash capital",IF(T7<=5,IF(O7<>"",O7,MAX(0,N(F7)+N(K7))*IF(N7<>"",N7,M7)),0),IF(S7="Debt service",IF(T7>5,0,W7*MAX(0,MIN(5-T7+1,U7))),IF(OR(S7="Annual O&M",S7="Maintenance-only"),IF(T7>5,0,IF(O7<>"",O7,MAX(0,N(F7)+N(K7))*IF(N7<>"",N7,M7))*MAX(0,5-T7+1)),0)))),0) | Y7: =IFERROR(IF(OR(R7<>"Yes",Q7<>"City"),0,IF(S7="Cash capital",IF(T7<=10,IF(O7<>"",O7,MAX(0,N(G7)+N(K7))*IF(N7<>"",N7,M7)),0),IF(S7="Debt service",IF(T7>10,0,W7*MAX(0,MIN(10-T7+1,U7))),IF(OR(S7="Annual O&M",S7="Maintenance-only"),IF(T7>10,0,IF(O7<>"",O7,MAX(0,N(G7)+N(K7))*IF(N7<>"",N7,M7))*MAX(0,10-T7+1)),0)))),0) | Z7: =IFERROR(IF(OR(R7<>"Yes",Q7<>"City"),0,IF(S7="Cash capital",IF(T7<=15,IF(O7<>"",O7,MAX(0,N(H7)+N(K7))*IF(N7<>"",N7,M7)),0),IF(S7="Debt service",IF(T7>15,0,W7*MAX(0,MIN(15-T7+1,U7))),IF(OR(S7="Annual O&M",S7="Maintenance-only"),IF(T7>15,0,IF(O7<>"",O7,MAX(0,N(H7)+N(K7))*IF(N7<>"",N7,M7))*MAX(0,15-T7+1)),0)))),0) | AA7: =IFERROR(IF(OR(R7<>"Yes",Q7<>"City"),0,IF(S7="Cash capital",IF(T7<=20,IF(O7<>"",O7,MAX(0,N(I7)+N(K7))*IF(N7<>"",N7,M7)),0),IF(S7="Debt service",IF(T7>20,0,W7*MAX(0,MIN(20-T7+1,U7))),IF(OR(S7="Annual O&M",S7="Maintenance-only"),IF(T7>20,0,IF(O7<>"",O7,MAX(0,N(I7)+N(K7))*IF(N7<>"",N7,M7))*MAX(0,20-T7+1)),0)))),0) | AB7: =IFERROR(IF(OR(R7<>"Yes",Q7<>"City"),0,IF(S7="Cash capital",IF(T7<=30,IF(O7<>"",O7,MAX(0,N(J7)+N(K7))*IF(N7<>"",N7,M7)),0),IF(S7="Debt service",IF(T7>30,0,W7*MAX(0,MIN(30-T7+1,U7))),IF(OR(S7="Annual O&M",S7="Maintenance-only"),IF(T7>30,0,IF(O7<>"",O7,MAX(0,N(J7)+N(K7))*IF(N7<>"",N7,M7))*MAX(0,30-T7+1)),0)))),0) | AC7: =IFERROR(IF(OR(R7<>"Yes",Q7<>"ESD"),0,IF(S7="Cash capital",IF(T7<=5,IF(O7<>"",O7,MAX(0,N(F7)+N(K7))*IF(N7<>"",N7,M7)),0),IF(S7="Debt service",IF(T7>5,0,W7*MAX(0,MIN(5-T7+1,U7))),IF(OR(S7="Annual O&M",S7="Maintenance-only"),IF(T7>5,0,IF(O7<>"",O7,MAX(0,N(F7)+N(K7))*IF(N7<>"",N7,M7))*MAX(0,5-T7+1)),0)))),0) | AD7: =IFERROR(IF(OR(R7<>"Yes",Q7<>"ESD"),0,IF(S7="Cash capital",IF(T7<=10,IF(O7<>"",O7,MAX(0,N(G7)+N(K7))*IF(N7<>"",N7,M7)),0),IF(S7="Debt service",IF(T7>10,0,W7*MAX(0,MIN(10-T7+1,U7))),IF(OR(S7="Annual O&M",S7="Maintenance-only"),IF(T7>10,0,IF(O7<>"",O7,MAX(0,N(G7)+N(K7))*IF(N7<>"",N7,M7))*MAX(0,10-T7+1)),0)))),0) | AE7: =IFERROR(IF(OR(R7<>"Yes",Q7<>"ESD"),0,IF(S7="Cash capital",IF(T7<=15,IF(O7<>"",O7,MAX(0,N(H7)+N(K7))*IF(N7<>"",N7,M7)),0),IF(S7="Debt service",IF(T7>15,0,W7*MAX(0,MIN(15-T7+1,U7))),IF(OR(S7="Annual O&M",S7="Maintenance-only"),IF(T7>15,0,IF(O7<>"",O7,MAX(0,N(H7)+N(K7))*IF(N7<>"",N7,M7))*MAX(0,15-T7+1)),0)))),0) | AF7: =IFERROR(IF(OR(R7<>"Yes",Q7<>"ESD"),0,IF(S7="Cash capital",IF(T7<=20,IF(O7<>"",O7,MAX(0,N(I7)+N(K7))*IF(N7<>"",N7,M7)),0),IF(S7="Debt service",IF(T7>20,0,W7*MAX(0,MIN(20-T7+1,U7))),IF(OR(S7="Annual O&M",S7="Maintenance-only"),IF(T7>20,0,IF(O7<>"",O7,MAX(0,N(I7)+N(K7))*IF(N7<>"",N7,M7))*MAX(0,20-T7+1)),0)))),0) | AG7: =IFERROR(IF(OR(R7<>"Yes",Q7<>"ESD"),0,IF(S7="Cash capital",IF(T7<=30,IF(O7<>"",O7,MAX(0,N(J7)+N(K7))*IF(N7<>"",N7,M7)),0),IF(S7="Debt service",IF(T7>30,0,W7*MAX(0,MIN(30-T7+1,U7))),IF(OR(S7="Annual O&M",S7="Maintenance-only"),IF(T7>30,0,IF(O7<>"",O7,MAX(0,N(J7)+N(K7))*IF(N7<>"",N7,M7))*MAX(0,30-T7+1)),0)))),0) | AH7: Demand-based planning trigger; validate with water master plan and TCEQ capacity review.
A8: Gravity sewer main, 10-inch | B8: City | C8: captured acres | D8: linear ft | E8: 300 LF/ac | F8: ='03_Multi_Horizon_Results'!$B$5*'12_Takeoff_Assumptions'!$B$4 | G8: ='03_Multi_Horizon_Results'!$C$5*'12_Takeoff_Assumptions'!$B$4 | H8: ='03_Multi_Horizon_Results'!$D$5*'12_Takeoff_Assumptions'!$B$4 | I8: ='03_Multi_Horizon_Results'!$E$5*'12_Takeoff_Assumptions'!$B$4 | J8: ='03_Multi_Horizon_Results'!$F$5*'12_Takeoff_Assumptions'!$B$4 | L8: =MAX(0,N(G8)+N(K8)) | M8: 325 | P8: =IFERROR(IF(O8<>"",O8,L8*IF(N8<>"",N8,M8)),0) | Q8: City | R8: No | S8: Debt service | T8: 1 | U8: 20 | V8: 0.045 | W8: =IFERROR(IF(AND(R8="Yes",S8="Debt service",U8>0),IF(V8=0,P8/U8,P8*V8/(1-(1+V8)^(-U8))),0),0) | X8: =IFERROR(IF(OR(R8<>"Yes",Q8<>"City"),0,IF(S8="Cash capital",IF(T8<=5,IF(O8<>"",O8,MAX(0,N(F8)+N(K8))*IF(N8<>"",N8,M8)),0),IF(S8="Debt service",IF(T8>5,0,W8*MAX(0,MIN(5-T8+1,U8))),IF(OR(S8="Annual O&M",S8="Maintenance-only"),IF(T8>5,0,IF(O8<>"",O8,MAX(0,N(F8)+N(K8))*IF(N8<>"",N8,M8))*MAX(0,5-T8+1)),0)))),0) | Y8: =IFERROR(IF(OR(R8<>"Yes",Q8<>"City"),0,IF(S8="Cash capital",IF(T8<=10,IF(O8<>"",O8,MAX(0,N(G8)+N(K8))*IF(N8<>"",N8,M8)),0),IF(S8="Debt service",IF(T8>10,0,W8*MAX(0,MIN(10-T8+1,U8))),IF(OR(S8="Annual O&M",S8="Maintenance-only"),IF(T8>10,0,IF(O8<>"",O8,MAX(0,N(G8)+N(K8))*IF(N8<>"",N8,M8))*MAX(0,10-T8+1)),0)))),0) | Z8: =IFERROR(IF(OR(R8<>"Yes",Q8<>"City"),0,IF(S8="Cash capital",IF(T8<=15,IF(O8<>"",O8,MAX(0,N(H8)+N(K8))*IF(N8<>"",N8,M8)),0),IF(S8="Debt service",IF(T8>15,0,W8*MAX(0,MIN(15-T8+1,U8))),IF(OR(S8="Annual O&M",S8="Maintenance-only"),IF(T8>15,0,IF(O8<>"",O8,MAX(0,N(H8)+N(K8))*IF(N8<>"",N8,M8))*MAX(0,15-T8+1)),0)))),0) | AA8: =IFERROR(IF(OR(R8<>"Yes",Q8<>"City"),0,IF(S8="Cash capital",IF(T8<=20,IF(O8<>"",O8,MAX(0,N(I8)+N(K8))*IF(N8<>"",N8,M8)),0),IF(S8="Debt service",IF(T8>20,0,W8*MAX(0,MIN(20-T8+1,U8))),IF(OR(S8="Annual O&M",S8="Maintenance-only"),IF(T8>20,0,IF(O8<>"",O8,MAX(0,N(I8)+N(K8))*IF(N8<>"",N8,M8))*MAX(0,20-T8+1)),0)))),0) | AB8: =IFERROR(IF(OR(R8<>"Yes",Q8<>"City"),0,IF(S8="Cash capital",IF(T8<=30,IF(O8<>"",O8,MAX(0,N(J8)+N(K8))*IF(N8<>"",N8,M8)),0),IF(S8="Debt service",IF(T8>30,0,W8*MAX(0,MIN(30-T8+1,U8))),IF(OR(S8="Annual O&M",S8="Maintenance-only"),IF(T8>30,0,IF(O8<>"",O8,MAX(0,N(J8)+N(K8))*IF(N8<>"",N8,M8))*MAX(0,30-T8+1)),0)))),0) | AC8: =IFERROR(IF(OR(R8<>"Yes",Q8<>"ESD"),0,IF(S8="Cash capital",IF(T8<=5,IF(O8<>"",O8,MAX(0,N(F8)+N(K8))*IF(N8<>"",N8,M8)),0),IF(S8="Debt service",IF(T8>5,0,W8*MAX(0,MIN(5-T8+1,U8))),IF(OR(S8="Annual O&M",S8="Maintenance-only"),IF(T8>5,0,IF(O8<>"",O8,MAX(0,N(F8)+N(K8))*IF(N8<>"",N8,M8))*MAX(0,5-T8+1)),0)))),0) | AD8: =IFERROR(IF(OR(R8<>"Yes",Q8<>"ESD"),0,IF(S8="Cash capital",IF(T8<=10,IF(O8<>"",O8,MAX(0,N(G8)+N(K8))*IF(N8<>"",N8,M8)),0),IF(S8="Debt service",IF(T8>10,0,W8*MAX(0,MIN(10-T8+1,U8))),IF(OR(S8="Annual O&M",S8="Maintenance-only"),IF(T8>10,0,IF(O8<>"",O8,MAX(0,N(G8)+N(K8))*IF(N8<>"",N8,M8))*MAX(0,10-T8+1)),0)))),0) | AE8: =IFERROR(IF(OR(R8<>"Yes",Q8<>"ESD"),0,IF(S8="Cash capital",IF(T8<=15,IF(O8<>"",O8,MAX(0,N(H8)+N(K8))*IF(N8<>"",N8,M8)),0),IF(S8="Debt service",IF(T8>15,0,W8*MAX(0,MIN(15-T8+1,U8))),IF(OR(S8="Annual O&M",S8="Maintenance-only"),IF(T8>15,0,IF(O8<>"",O8,MAX(0,N(H8)+N(K8))*IF(N8<>"",N8,M8))*MAX(0,15-T8+1)),0)))),0) | AF8: =IFERROR(IF(OR(R8<>"Yes",Q8<>"ESD"),0,IF(S8="Cash capital",IF(T8<=20,IF(O8<>"",O8,MAX(0,N(I8)+N(K8))*IF(N8<>"",N8,M8)),0),IF(S8="Debt service",IF(T8>20,0,W8*MAX(0,MIN(20-T8+1,U8))),IF(OR(S8="Annual O&M",S8="Maintenance-only"),IF(T8>20,0,IF(O8<>"",O8,MAX(0,N(I8)+N(K8))*IF(N8<>"",N8,M8))*MAX(0,20-T8+1)),0)))),0) | AG8: =IFERROR(IF(OR(R8<>"Yes",Q8<>"ESD"),0,IF(S8="Cash capital",IF(T8<=30,IF(O8<>"",O8,MAX(0,N(J8)+N(K8))*IF(N8<>"",N8,M8)),0),IF(S8="Debt service",IF(T8>30,0,W8*MAX(0,MIN(30-T8+1,U8))),IF(OR(S8="Annual O&M",S8="Maintenance-only"),IF(T8>30,0,IF(O8<>"",O8,MAX(0,N(J8)+N(K8))*IF(N8<>"",N8,M8))*MAX(0,30-T8+1)),0)))),0) | AH8: Gravity sewer planning allowance; actual basin/topography should override.
A9: Force main | B9: City | C9: captured acres | D9: linear ft | E9: 40 LF/ac | F9: ='03_Multi_Horizon_Results'!$B$5*'12_Takeoff_Assumptions'!$B$5 | G9: ='03_Multi_Horizon_Results'!$C$5*'12_Takeoff_Assumptions'!$B$5 | H9: ='03_Multi_Horizon_Results'!$D$5*'12_Takeoff_Assumptions'!$B$5 | I9: ='03_Multi_Horizon_Results'!$E$5*'12_Takeoff_Assumptions'!$B$5 | J9: ='03_Multi_Horizon_Results'!$F$5*'12_Takeoff_Assumptions'!$B$5 | L9: =MAX(0,N(G9)+N(K9)) | M9: 225 | P9: =IFERROR(IF(O9<>"",O9,L9*IF(N9<>"",N9,M9)),0) | Q9: City | R9: No | S9: Debt service | T9: 1 | U9: 20 | V9: 0.045 | W9: =IFERROR(IF(AND(R9="Yes",S9="Debt service",U9>0),IF(V9=0,P9/U9,P9*V9/(1-(1+V9)^(-U9))),0),0) | X9: =IFERROR(IF(OR(R9<>"Yes",Q9<>"City"),0,IF(S9="Cash capital",IF(T9<=5,IF(O9<>"",O9,MAX(0,N(F9)+N(K9))*IF(N9<>"",N9,M9)),0),IF(S9="Debt service",IF(T9>5,0,W9*MAX(0,MIN(5-T9+1,U9))),IF(OR(S9="Annual O&M",S9="Maintenance-only"),IF(T9>5,0,IF(O9<>"",O9,MAX(0,N(F9)+N(K9))*IF(N9<>"",N9,M9))*MAX(0,5-T9+1)),0)))),0) | Y9: =IFERROR(IF(OR(R9<>"Yes",Q9<>"City"),0,IF(S9="Cash capital",IF(T9<=10,IF(O9<>"",O9,MAX(0,N(G9)+N(K9))*IF(N9<>"",N9,M9)),0),IF(S9="Debt service",IF(T9>10,0,W9*MAX(0,MIN(10-T9+1,U9))),IF(OR(S9="Annual O&M",S9="Maintenance-only"),IF(T9>10,0,IF(O9<>"",O9,MAX(0,N(G9)+N(K9))*IF(N9<>"",N9,M9))*MAX(0,10-T9+1)),0)))),0) | Z9: =IFERROR(IF(OR(R9<>"Yes",Q9<>"City"),0,IF(S9="Cash capital",IF(T9<=15,IF(O9<>"",O9,MAX(0,N(H9)+N(K9))*IF(N9<>"",N9,M9)),0),IF(S9="Debt service",IF(T9>15,0,W9*MAX(0,MIN(15-T9+1,U9))),IF(OR(S9="Annual O&M",S9="Maintenance-only"),IF(T9>15,0,IF(O9<>"",O9,MAX(0,N(H9)+N(K9))*IF(N9<>"",N9,M9))*MAX(0,15-T9+1)),0)))),0) | AA9: =IFERROR(IF(OR(R9<>"Yes",Q9<>"City"),0,IF(S9="Cash capital",IF(T9<=20,IF(O9<>"",O9,MAX(0,N(I9)+N(K9))*IF(N9<>"",N9,M9)),0),IF(S9="Debt service",IF(T9>20,0,W9*MAX(0,MIN(20-T9+1,U9))),IF(OR(S9="Annual O&M",S9="Maintenance-only"),IF(T9>20,0,IF(O9<>"",O9,MAX(0,N(I9)+N(K9))*IF(N9<>"",N9,M9))*MAX(0,20-T9+1)),0)))),0) | AB9: =IFERROR(IF(OR(R9<>"Yes",Q9<>"City"),0,IF(S9="Cash capital",IF(T9<=30,IF(O9<>"",O9,MAX(0,N(J9)+N(K9))*IF(N9<>"",N9,M9)),0),IF(S9="Debt service",IF(T9>30,0,W9*MAX(0,MIN(30-T9+1,U9))),IF(OR(S9="Annual O&M",S9="Maintenance-only"),IF(T9>30,0,IF(O9<>"",O9,MAX(0,N(J9)+N(K9))*IF(N9<>"",N9,M9))*MAX(0,30-T9+1)),0)))),0) | AC9: =IFERROR(IF(OR(R9<>"Yes",Q9<>"ESD"),0,IF(S9="Cash capital",IF(T9<=5,IF(O9<>"",O9,MAX(0,N(F9)+N(K9))*IF(N9<>"",N9,M9)),0),IF(S9="Debt service",IF(T9>5,0,W9*MAX(0,MIN(5-T9+1,U9))),IF(OR(S9="Annual O&M",S9="Maintenance-only"),IF(T9>5,0,IF(O9<>"",O9,MAX(0,N(F9)+N(K9))*IF(N9<>"",N9,M9))*MAX(0,5-T9+1)),0)))),0) | AD9: =IFERROR(IF(OR(R9<>"Yes",Q9<>"ESD"),0,IF(S9="Cash capital",IF(T9<=10,IF(O9<>"",O9,MAX(0,N(G9)+N(K9))*IF(N9<>"",N9,M9)),0),IF(S9="Debt service",IF(T9>10,0,W9*MAX(0,MIN(10-T9+1,U9))),IF(OR(S9="Annual O&M",S9="Maintenance-only"),IF(T9>10,0,IF(O9<>"",O9,MAX(0,N(G9)+N(K9))*IF(N9<>"",N9,M9))*MAX(0,10-T9+1)),0)))),0) | AE9: =IFERROR(IF(OR(R9<>"Yes",Q9<>"ESD"),0,IF(S9="Cash capital",IF(T9<=15,IF(O9<>"",O9,MAX(0,N(H9)+N(K9))*IF(N9<>"",N9,M9)),0),IF(S9="Debt service",IF(T9>15,0,W9*MAX(0,MIN(15-T9+1,U9))),IF(OR(S9="Annual O&M",S9="Maintenance-only"),IF(T9>15,0,IF(O9<>"",O9,MAX(0,N(H9)+N(K9))*IF(N9<>"",N9,M9))*MAX(0,15-T9+1)),0)))),0) | AF9: =IFERROR(IF(OR(R9<>"Yes",Q9<>"ESD"),0,IF(S9="Cash capital",IF(T9<=20,IF(O9<>"",O9,MAX(0,N(I9)+N(K9))*IF(N9<>"",N9,M9)),0),IF(S9="Debt service",IF(T9>20,0,W9*MAX(0,MIN(20-T9+1,U9))),IF(OR(S9="Annual O&M",S9="Maintenance-only"),IF(T9>20,0,IF(O9<>"",O9,MAX(0,N(I9)+N(K9))*IF(N9<>"",N9,M9))*MAX(0,20-T9+1)),0)))),0) | AG9: =IFERROR(IF(OR(R9<>"Yes",Q9<>"ESD"),0,IF(S9="Cash capital",IF(T9<=30,IF(O9<>"",O9,MAX(0,N(J9)+N(K9))*IF(N9<>"",N9,M9)),0),IF(S9="Debt service",IF(T9>30,0,W9*MAX(0,MIN(30-T9+1,U9))),IF(OR(S9="Annual O&M",S9="Maintenance-only"),IF(T9>30,0,IF(O9<>"",O9,MAX(0,N(J9)+N(K9))*IF(N9<>"",N9,M9))*MAX(0,30-T9+1)),0)))),0) | AH9: Force-main planning allowance; actual need depends on lift-station/basin design.
A10: Lift stations | B10: City | C10: sewer demand MGD | D10: each | E10: threshold 0.25 MGD | F10: =IF((('03_Multi_Horizon_Results'!$B$22/INPUTS!$D$50)*'12_Takeoff_Assumptions'!$B$14/1000000)>'12_Takeoff_Assumptions'!$B$15,ROUNDUP((('03_Multi_Horizon_Results'!$B$22/INPUTS!$D$50)*'12_Takeoff_Assumptions'!$B$14/1000000)/'12_Takeoff_Assumptions'!$B$15,0),0) | G10: =IF((('03_Multi_Horizon_Results'!$C$22/INPUTS!$D$50)*'12_Takeoff_Assumptions'!$B$14/1000000)>'12_Takeoff_Assumptions'!$B$15,ROUNDUP((('03_Multi_Horizon_Results'!$C$22/INPUTS!$D$50)*'12_Takeoff_Assumptions'!$B$14/1000000)/'12_Takeoff_Assumptions'!$B$15,0),0) | H10: =IF((('03_Multi_Horizon_Results'!$D$22/INPUTS!$D$50)*'12_Takeoff_Assumptions'!$B$14/1000000)>'12_Takeoff_Assumptions'!$B$15,ROUNDUP((('03_Multi_Horizon_Results'!$D$22/INPUTS!$D$50)*'12_Takeoff_Assumptions'!$B$14/1000000)/'12_Takeoff_Assumptions'!$B$15,0),0) | I10: =IF((('03_Multi_Horizon_Results'!$E$22/INPUTS!$D$50)*'12_Takeoff_Assumptions'!$B$14/1000000)>'12_Takeoff_Assumptions'!$B$15,ROUNDUP((('03_Multi_Horizon_Results'!$E$22/INPUTS!$D$50)*'12_Takeoff_Assumptions'!$B$14/1000000)/'12_Takeoff_Assumptions'!$B$15,0),0) | J10: =IF((('03_Multi_Horizon_Results'!$F$22/INPUTS!$D$50)*'12_Takeoff_Assumptions'!$B$14/1000000)>'12_Takeoff_Assumptions'!$B$15,ROUNDUP((('03_Multi_Horizon_Results'!$F$22/INPUTS!$D$50)*'12_Takeoff_Assumptions'!$B$14/1000000)/'12_Takeoff_Assumptions'!$B$15,0),0) | L10: =MAX(0,N(G10)+N(K10)) | M10: 1250000 | P10: =IFERROR(IF(O10<>"",O10,L10*IF(N10<>"",N10,M10)),0) | Q10: City | R10: No | S10: Debt service | T10: 1 | U10: 20 | V10: 0.045 | W10: =IFERROR(IF(AND(R10="Yes",S10="Debt service",U10>0),IF(V10=0,P10/U10,P10*V10/(1-(1+V10)^(-U10))),0),0) | X10: =IFERROR(IF(OR(R10<>"Yes",Q10<>"City"),0,IF(S10="Cash capital",IF(T10<=5,IF(O10<>"",O10,MAX(0,N(F10)+N(K10))*IF(N10<>"",N10,M10)),0),IF(S10="Debt service",IF(T10>5,0,W10*MAX(0,MIN(5-T10+1,U10))),IF(OR(S10="Annual O&M",S10="Maintenance-only"),IF(T10>5,0,IF(O10<>"",O10,MAX(0,N(F10)+N(K10))*IF(N10<>"",N10,M10))*MAX(0,5-T10+1)),0)))),0) | Y10: =IFERROR(IF(OR(R10<>"Yes",Q10<>"City"),0,IF(S10="Cash capital",IF(T10<=10,IF(O10<>"",O10,MAX(0,N(G10)+N(K10))*IF(N10<>"",N10,M10)),0),IF(S10="Debt service",IF(T10>10,0,W10*MAX(0,MIN(10-T10+1,U10))),IF(OR(S10="Annual O&M",S10="Maintenance-only"),IF(T10>10,0,IF(O10<>"",O10,MAX(0,N(G10)+N(K10))*IF(N10<>"",N10,M10))*MAX(0,10-T10+1)),0)))),0) | Z10: =IFERROR(IF(OR(R10<>"Yes",Q10<>"City"),0,IF(S10="Cash capital",IF(T10<=15,IF(O10<>"",O10,MAX(0,N(H10)+N(K10))*IF(N10<>"",N10,M10)),0),IF(S10="Debt service",IF(T10>15,0,W10*MAX(0,MIN(15-T10+1,U10))),IF(OR(S10="Annual O&M",S10="Maintenance-only"),IF(T10>15,0,IF(O10<>"",O10,MAX(0,N(H10)+N(K10))*IF(N10<>"",N10,M10))*MAX(0,15-T10+1)),0)))),0) | AA10: =IFERROR(IF(OR(R10<>"Yes",Q10<>"City"),0,IF(S10="Cash capital",IF(T10<=20,IF(O10<>"",O10,MAX(0,N(I10)+N(K10))*IF(N10<>"",N10,M10)),0),IF(S10="Debt service",IF(T10>20,0,W10*MAX(0,MIN(20-T10+1,U10))),IF(OR(S10="Annual O&M",S10="Maintenance-only"),IF(T10>20,0,IF(O10<>"",O10,MAX(0,N(I10)+N(K10))*IF(N10<>"",N10,M10))*MAX(0,20-T10+1)),0)))),0) | AB10: =IFERROR(IF(OR(R10<>"Yes",Q10<>"City"),0,IF(S10="Cash capital",IF(T10<=30,IF(O10<>"",O10,MAX(0,N(J10)+N(K10))*IF(N10<>"",N10,M10)),0),IF(S10="Debt service",IF(T10>30,0,W10*MAX(0,MIN(30-T10+1,U10))),IF(OR(S10="Annual O&M",S10="Maintenance-only"),IF(T10>30,0,IF(O10<>"",O10,MAX(0,N(J10)+N(K10))*IF(N10<>"",N10,M10))*MAX(0,30-T10+1)),0)))),0) | AC10: =IFERROR(IF(OR(R10<>"Yes",Q10<>"ESD"),0,IF(S10="Cash capital",IF(T10<=5,IF(O10<>"",O10,MAX(0,N(F10)+N(K10))*IF(N10<>"",N10,M10)),0),IF(S10="Debt service",IF(T10>5,0,W10*MAX(0,MIN(5-T10+1,U10))),IF(OR(S10="Annual O&M",S10="Maintenance-only"),IF(T10>5,0,IF(O10<>"",O10,MAX(0,N(F10)+N(K10))*IF(N10<>"",N10,M10))*MAX(0,5-T10+1)),0)))),0) | AD10: =IFERROR(IF(OR(R10<>"Yes",Q10<>"ESD"),0,IF(S10="Cash capital",IF(T10<=10,IF(O10<>"",O10,MAX(0,N(G10)+N(K10))*IF(N10<>"",N10,M10)),0),IF(S10="Debt service",IF(T10>10,0,W10*MAX(0,MIN(10-T10+1,U10))),IF(OR(S10="Annual O&M",S10="Maintenance-only"),IF(T10>10,0,IF(O10<>"",O10,MAX(0,N(G10)+N(K10))*IF(N10<>"",N10,M10))*MAX(0,10-T10+1)),0)))),0) | AE10: =IFERROR(IF(OR(R10<>"Yes",Q10<>"ESD"),0,IF(S10="Cash capital",IF(T10<=15,IF(O10<>"",O10,MAX(0,N(H10)+N(K10))*IF(N10<>"",N10,M10)),0),IF(S10="Debt service",IF(T10>15,0,W10*MAX(0,MIN(15-T10+1,U10))),IF(OR(S10="Annual O&M",S10="Maintenance-only"),IF(T10>15,0,IF(O10<>"",O10,MAX(0,N(H10)+N(K10))*IF(N10<>"",N10,M10))*MAX(0,15-T10+1)),0)))),0) | AF10: =IFERROR(IF(OR(R10<>"Yes",Q10<>"ESD"),0,IF(S10="Cash capital",IF(T10<=20,IF(O10<>"",O10,MAX(0,N(I10)+N(K10))*IF(N10<>"",N10,M10)),0),IF(S10="Debt service",IF(T10>20,0,W10*MAX(0,MIN(20-T10+1,U10))),IF(OR(S10="Annual O&M",S10="Maintenance-only"),IF(T10>20,0,IF(O10<>"",O10,MAX(0,N(I10)+N(K10))*IF(N10<>"",N10,M10))*MAX(0,20-T10+1)),0)))),0) | AG10: =IFERROR(IF(OR(R10<>"Yes",Q10<>"ESD"),0,IF(S10="Cash capital",IF(T10<=30,IF(O10<>"",O10,MAX(0,N(J10)+N(K10))*IF(N10<>"",N10,M10)),0),IF(S10="Debt service",IF(T10>30,0,W10*MAX(0,MIN(30-T10+1,U10))),IF(OR(S10="Annual O&M",S10="Maintenance-only"),IF(T10>30,0,IF(O10<>"",O10,MAX(0,N(J10)+N(K10))*IF(N10<>"",N10,M10))*MAX(0,30-T10+1)),0)))),0) | AH10: Planning trigger only; topography and basin engineer review required.
A11: WWTP expansion capacity | B11: City | C11: sewer demand MGD | D11: MGD | E11: 250 gpd/LUE | F11: =(('03_Multi_Horizon_Results'!$B$22/INPUTS!$D$50)*'12_Takeoff_Assumptions'!$B$14/1000000) | G11: =(('03_Multi_Horizon_Results'!$C$22/INPUTS!$D$50)*'12_Takeoff_Assumptions'!$B$14/1000000) | H11: =(('03_Multi_Horizon_Results'!$D$22/INPUTS!$D$50)*'12_Takeoff_Assumptions'!$B$14/1000000) | I11: =(('03_Multi_Horizon_Results'!$E$22/INPUTS!$D$50)*'12_Takeoff_Assumptions'!$B$14/1000000) | J11: =(('03_Multi_Horizon_Results'!$F$22/INPUTS!$D$50)*'12_Takeoff_Assumptions'!$B$14/1000000) | L11: =MAX(0,N(G11)+N(K11)) | M11: 6000000 | P11: =IFERROR(IF(O11<>"",O11,L11*IF(N11<>"",N11,M11)),0) | Q11: City | R11: No | S11: Debt service | T11: 1 | U11: 20 | V11: 0.045 | W11: =IFERROR(IF(AND(R11="Yes",S11="Debt service",U11>0),IF(V11=0,P11/U11,P11*V11/(1-(1+V11)^(-U11))),0),0) | X11: =IFERROR(IF(OR(R11<>"Yes",Q11<>"City"),0,IF(S11="Cash capital",IF(T11<=5,IF(O11<>"",O11,MAX(0,N(F11)+N(K11))*IF(N11<>"",N11,M11)),0),IF(S11="Debt service",IF(T11>5,0,W11*MAX(0,MIN(5-T11+1,U11))),IF(OR(S11="Annual O&M",S11="Maintenance-only"),IF(T11>5,0,IF(O11<>"",O11,MAX(0,N(F11)+N(K11))*IF(N11<>"",N11,M11))*MAX(0,5-T11+1)),0)))),0) | Y11: =IFERROR(IF(OR(R11<>"Yes",Q11<>"City"),0,IF(S11="Cash capital",IF(T11<=10,IF(O11<>"",O11,MAX(0,N(G11)+N(K11))*IF(N11<>"",N11,M11)),0),IF(S11="Debt service",IF(T11>10,0,W11*MAX(0,MIN(10-T11+1,U11))),IF(OR(S11="Annual O&M",S11="Maintenance-only"),IF(T11>10,0,IF(O11<>"",O11,MAX(0,N(G11)+N(K11))*IF(N11<>"",N11,M11))*MAX(0,10-T11+1)),0)))),0) | Z11: =IFERROR(IF(OR(R11<>"Yes",Q11<>"City"),0,IF(S11="Cash capital",IF(T11<=15,IF(O11<>"",O11,MAX(0,N(H11)+N(K11))*IF(N11<>"",N11,M11)),0),IF(S11="Debt service",IF(T11>15,0,W11*MAX(0,MIN(15-T11+1,U11))),IF(OR(S11="Annual O&M",S11="Maintenance-only"),IF(T11>15,0,IF(O11<>"",O11,MAX(0,N(H11)+N(K11))*IF(N11<>"",N11,M11))*MAX(0,15-T11+1)),0)))),0) | AA11: =IFERROR(IF(OR(R11<>"Yes",Q11<>"City"),0,IF(S11="Cash capital",IF(T11<=20,IF(O11<>"",O11,MAX(0,N(I11)+N(K11))*IF(N11<>"",N11,M11)),0),IF(S11="Debt service",IF(T11>20,0,W11*MAX(0,MIN(20-T11+1,U11))),IF(OR(S11="Annual O&M",S11="Maintenance-only"),IF(T11>20,0,IF(O11<>"",O11,MAX(0,N(I11)+N(K11))*IF(N11<>"",N11,M11))*MAX(0,20-T11+1)),0)))),0) | AB11: =IFERROR(IF(OR(R11<>"Yes",Q11<>"City"),0,IF(S11="Cash capital",IF(T11<=30,IF(O11<>"",O11,MAX(0,N(J11)+N(K11))*IF(N11<>"",N11,M11)),0),IF(S11="Debt service",IF(T11>30,0,W11*MAX(0,MIN(30-T11+1,U11))),IF(OR(S11="Annual O&M",S11="Maintenance-only"),IF(T11>30,0,IF(O11<>"",O11,MAX(0,N(J11)+N(K11))*IF(N11<>"",N11,M11))*MAX(0,30-T11+1)),0)))),0) | AC11: =IFERROR(IF(OR(R11<>"Yes",Q11<>"ESD"),0,IF(S11="Cash capital",IF(T11<=5,IF(O11<>"",O11,MAX(0,N(F11)+N(K11))*IF(N11<>"",N11,M11)),0),IF(S11="Debt service",IF(T11>5,0,W11*MAX(0,MIN(5-T11+1,U11))),IF(OR(S11="Annual O&M",S11="Maintenance-only"),IF(T11>5,0,IF(O11<>"",O11,MAX(0,N(F11)+N(K11))*IF(N11<>"",N11,M11))*MAX(0,5-T11+1)),0)))),0) | AD11: =IFERROR(IF(OR(R11<>"Yes",Q11<>"ESD"),0,IF(S11="Cash capital",IF(T11<=10,IF(O11<>"",O11,MAX(0,N(G11)+N(K11))*IF(N11<>"",N11,M11)),0),IF(S11="Debt service",IF(T11>10,0,W11*MAX(0,MIN(10-T11+1,U11))),IF(OR(S11="Annual O&M",S11="Maintenance-only"),IF(T11>10,0,IF(O11<>"",O11,MAX(0,N(G11)+N(K11))*IF(N11<>"",N11,M11))*MAX(0,10-T11+1)),0)))),0) | AE11: =IFERROR(IF(OR(R11<>"Yes",Q11<>"ESD"),0,IF(S11="Cash capital",IF(T11<=15,IF(O11<>"",O11,MAX(0,N(H11)+N(K11))*IF(N11<>"",N11,M11)),0),IF(S11="Debt service",IF(T11>15,0,W11*MAX(0,MIN(15-T11+1,U11))),IF(OR(S11="Annual O&M",S11="Maintenance-only"),IF(T11>15,0,IF(O11<>"",O11,MAX(0,N(H11)+N(K11))*IF(N11<>"",N11,M11))*MAX(0,15-T11+1)),0)))),0) | AF11: =IFERROR(IF(OR(R11<>"Yes",Q11<>"ESD"),0,IF(S11="Cash capital",IF(T11<=20,IF(O11<>"",O11,MAX(0,N(I11)+N(K11))*IF(N11<>"",N11,M11)),0),IF(S11="Debt service",IF(T11>20,0,W11*MAX(0,MIN(20-T11+1,U11))),IF(OR(S11="Annual O&M",S11="Maintenance-only"),IF(T11>20,0,IF(O11<>"",O11,MAX(0,N(I11)+N(K11))*IF(N11<>"",N11,M11))*MAX(0,20-T11+1)),0)))),0) | AG11: =IFERROR(IF(OR(R11<>"Yes",Q11<>"ESD"),0,IF(S11="Cash capital",IF(T11<=30,IF(O11<>"",O11,MAX(0,N(J11)+N(K11))*IF(N11<>"",N11,M11)),0),IF(S11="Debt service",IF(T11>30,0,W11*MAX(0,MIN(30-T11+1,U11))),IF(OR(S11="Annual O&M",S11="Maintenance-only"),IF(T11>30,0,IF(O11<>"",O11,MAX(0,N(J11)+N(K11))*IF(N11<>"",N11,M11))*MAX(0,30-T11+1)),0)))),0) | AH11: Shows estimated sewer demand capacity exposure, not an engineering design directive.
A12: Collector street | B12: City | C12: captured acres | D12: lane-miles | E12: 0.02 lane-mi/ac | F12: ='03_Multi_Horizon_Results'!$B$5*'12_Takeoff_Assumptions'!$B$7 | G12: ='03_Multi_Horizon_Results'!$C$5*'12_Takeoff_Assumptions'!$B$7 | H12: ='03_Multi_Horizon_Results'!$D$5*'12_Takeoff_Assumptions'!$B$7 | I12: ='03_Multi_Horizon_Results'!$E$5*'12_Takeoff_Assumptions'!$B$7 | J12: ='03_Multi_Horizon_Results'!$F$5*'12_Takeoff_Assumptions'!$B$7 | L12: =MAX(0,N(G12)+N(K12)) | M12: 750000 | P12: =IFERROR(IF(O12<>"",O12,L12*IF(N12<>"",N12,M12)),0) | Q12: City | R12: No | S12: Debt service | T12: 1 | U12: 20 | V12: 0.045 | W12: =IFERROR(IF(AND(R12="Yes",S12="Debt service",U12>0),IF(V12=0,P12/U12,P12*V12/(1-(1+V12)^(-U12))),0),0) | X12: =IFERROR(IF(OR(R12<>"Yes",Q12<>"City"),0,IF(S12="Cash capital",IF(T12<=5,IF(O12<>"",O12,MAX(0,N(F12)+N(K12))*IF(N12<>"",N12,M12)),0),IF(S12="Debt service",IF(T12>5,0,W12*MAX(0,MIN(5-T12+1,U12))),IF(OR(S12="Annual O&M",S12="Maintenance-only"),IF(T12>5,0,IF(O12<>"",O12,MAX(0,N(F12)+N(K12))*IF(N12<>"",N12,M12))*MAX(0,5-T12+1)),0)))),0) | Y12: =IFERROR(IF(OR(R12<>"Yes",Q12<>"City"),0,IF(S12="Cash capital",IF(T12<=10,IF(O12<>"",O12,MAX(0,N(G12)+N(K12))*IF(N12<>"",N12,M12)),0),IF(S12="Debt service",IF(T12>10,0,W12*MAX(0,MIN(10-T12+1,U12))),IF(OR(S12="Annual O&M",S12="Maintenance-only"),IF(T12>10,0,IF(O12<>"",O12,MAX(0,N(G12)+N(K12))*IF(N12<>"",N12,M12))*MAX(0,10-T12+1)),0)))),0) | Z12: =IFERROR(IF(OR(R12<>"Yes",Q12<>"City"),0,IF(S12="Cash capital",IF(T12<=15,IF(O12<>"",O12,MAX(0,N(H12)+N(K12))*IF(N12<>"",N12,M12)),0),IF(S12="Debt service",IF(T12>15,0,W12*MAX(0,MIN(15-T12+1,U12))),IF(OR(S12="Annual O&M",S12="Maintenance-only"),IF(T12>15,0,IF(O12<>"",O12,MAX(0,N(H12)+N(K12))*IF(N12<>"",N12,M12))*MAX(0,15-T12+1)),0)))),0) | AA12: =IFERROR(IF(OR(R12<>"Yes",Q12<>"City"),0,IF(S12="Cash capital",IF(T12<=20,IF(O12<>"",O12,MAX(0,N(I12)+N(K12))*IF(N12<>"",N12,M12)),0),IF(S12="Debt service",IF(T12>20,0,W12*MAX(0,MIN(20-T12+1,U12))),IF(OR(S12="Annual O&M",S12="Maintenance-only"),IF(T12>20,0,IF(O12<>"",O12,MAX(0,N(I12)+N(K12))*IF(N12<>"",N12,M12))*MAX(0,20-T12+1)),0)))),0) | AB12: =IFERROR(IF(OR(R12<>"Yes",Q12<>"City"),0,IF(S12="Cash capital",IF(T12<=30,IF(O12<>"",O12,MAX(0,N(J12)+N(K12))*IF(N12<>"",N12,M12)),0),IF(S12="Debt service",IF(T12>30,0,W12*MAX(0,MIN(30-T12+1,U12))),IF(OR(S12="Annual O&M",S12="Maintenance-only"),IF(T12>30,0,IF(O12<>"",O12,MAX(0,N(J12)+N(K12))*IF(N12<>"",N12,M12))*MAX(0,30-T12+1)),0)))),0) | AC12: =IFERROR(IF(OR(R12<>"Yes",Q12<>"ESD"),0,IF(S12="Cash capital",IF(T12<=5,IF(O12<>"",O12,MAX(0,N(F12)+N(K12))*IF(N12<>"",N12,M12)),0),IF(S12="Debt service",IF(T12>5,0,W12*MAX(0,MIN(5-T12+1,U12))),IF(OR(S12="Annual O&M",S12="Maintenance-only"),IF(T12>5,0,IF(O12<>"",O12,MAX(0,N(F12)+N(K12))*IF(N12<>"",N12,M12))*MAX(0,5-T12+1)),0)))),0) | AD12: =IFERROR(IF(OR(R12<>"Yes",Q12<>"ESD"),0,IF(S12="Cash capital",IF(T12<=10,IF(O12<>"",O12,MAX(0,N(G12)+N(K12))*IF(N12<>"",N12,M12)),0),IF(S12="Debt service",IF(T12>10,0,W12*MAX(0,MIN(10-T12+1,U12))),IF(OR(S12="Annual O&M",S12="Maintenance-only"),IF(T12>10,0,IF(O12<>"",O12,MAX(0,N(G12)+N(K12))*IF(N12<>"",N12,M12))*MAX(0,10-T12+1)),0)))),0) | AE12: =IFERROR(IF(OR(R12<>"Yes",Q12<>"ESD"),0,IF(S12="Cash capital",IF(T12<=15,IF(O12<>"",O12,MAX(0,N(H12)+N(K12))*IF(N12<>"",N12,M12)),0),IF(S12="Debt service",IF(T12>15,0,W12*MAX(0,MIN(15-T12+1,U12))),IF(OR(S12="Annual O&M",S12="Maintenance-only"),IF(T12>15,0,IF(O12<>"",O12,MAX(0,N(H12)+N(K12))*IF(N12<>"",N12,M12))*MAX(0,15-T12+1)),0)))),0) | AF12: =IFERROR(IF(OR(R12<>"Yes",Q12<>"ESD"),0,IF(S12="Cash capital",IF(T12<=20,IF(O12<>"",O12,MAX(0,N(I12)+N(K12))*IF(N12<>"",N12,M12)),0),IF(S12="Debt service",IF(T12>20,0,W12*MAX(0,MIN(20-T12+1,U12))),IF(OR(S12="Annual O&M",S12="Maintenance-only"),IF(T12>20,0,IF(O12<>"",O12,MAX(0,N(I12)+N(K12))*IF(N12<>"",N12,M12))*MAX(0,20-T12+1)),0)))),0) | AG12: =IFERROR(IF(OR(R12<>"Yes",Q12<>"ESD"),0,IF(S12="Cash capital",IF(T12<=30,IF(O12<>"",O12,MAX(0,N(J12)+N(K12))*IF(N12<>"",N12,M12)),0),IF(S12="Debt service",IF(T12>30,0,W12*MAX(0,MIN(30-T12+1,U12))),IF(OR(S12="Annual O&M",S12="Maintenance-only"),IF(T12>30,0,IF(O12<>"",O12,MAX(0,N(J12)+N(K12))*IF(N12<>"",N12,M12))*MAX(0,30-T12+1)),0)))),0) | AH12: Thoroughfare planning allowance; actual route/section should override.
A13: Local street | B13: City | C13: captured acres | D13: lane-miles | E13: 120 centerline LF/ac × 2 lanes | F13: =('03_Multi_Horizon_Results'!$B$5*'12_Takeoff_Assumptions'!$B$6/5280)*'12_Takeoff_Assumptions'!$B$8 | G13: =('03_Multi_Horizon_Results'!$C$5*'12_Takeoff_Assumptions'!$B$6/5280)*'12_Takeoff_Assumptions'!$B$8 | H13: =('03_Multi_Horizon_Results'!$D$5*'12_Takeoff_Assumptions'!$B$6/5280)*'12_Takeoff_Assumptions'!$B$8 | I13: =('03_Multi_Horizon_Results'!$E$5*'12_Takeoff_Assumptions'!$B$6/5280)*'12_Takeoff_Assumptions'!$B$8 | J13: =('03_Multi_Horizon_Results'!$F$5*'12_Takeoff_Assumptions'!$B$6/5280)*'12_Takeoff_Assumptions'!$B$8 | L13: =MAX(0,N(G13)+N(K13)) | M13: 600000 | P13: =IFERROR(IF(O13<>"",O13,L13*IF(N13<>"",N13,M13)),0) | Q13: City | R13: No | S13: Debt service | T13: 1 | U13: 20 | V13: 0.045 | W13: =IFERROR(IF(AND(R13="Yes",S13="Debt service",U13>0),IF(V13=0,P13/U13,P13*V13/(1-(1+V13)^(-U13))),0),0) | X13: =IFERROR(IF(OR(R13<>"Yes",Q13<>"City"),0,IF(S13="Cash capital",IF(T13<=5,IF(O13<>"",O13,MAX(0,N(F13)+N(K13))*IF(N13<>"",N13,M13)),0),IF(S13="Debt service",IF(T13>5,0,W13*MAX(0,MIN(5-T13+1,U13))),IF(OR(S13="Annual O&M",S13="Maintenance-only"),IF(T13>5,0,IF(O13<>"",O13,MAX(0,N(F13)+N(K13))*IF(N13<>"",N13,M13))*MAX(0,5-T13+1)),0)))),0) | Y13: =IFERROR(IF(OR(R13<>"Yes",Q13<>"City"),0,IF(S13="Cash capital",IF(T13<=10,IF(O13<>"",O13,MAX(0,N(G13)+N(K13))*IF(N13<>"",N13,M13)),0),IF(S13="Debt service",IF(T13>10,0,W13*MAX(0,MIN(10-T13+1,U13))),IF(OR(S13="Annual O&M",S13="Maintenance-only"),IF(T13>10,0,IF(O13<>"",O13,MAX(0,N(G13)+N(K13))*IF(N13<>"",N13,M13))*MAX(0,10-T13+1)),0)))),0) | Z13: =IFERROR(IF(OR(R13<>"Yes",Q13<>"City"),0,IF(S13="Cash capital",IF(T13<=15,IF(O13<>"",O13,MAX(0,N(H13)+N(K13))*IF(N13<>"",N13,M13)),0),IF(S13="Debt service",IF(T13>15,0,W13*MAX(0,MIN(15-T13+1,U13))),IF(OR(S13="Annual O&M",S13="Maintenance-only"),IF(T13>15,0,IF(O13<>"",O13,MAX(0,N(H13)+N(K13))*IF(N13<>"",N13,M13))*MAX(0,15-T13+1)),0)))),0) | AA13: =IFERROR(IF(OR(R13<>"Yes",Q13<>"City"),0,IF(S13="Cash capital",IF(T13<=20,IF(O13<>"",O13,MAX(0,N(I13)+N(K13))*IF(N13<>"",N13,M13)),0),IF(S13="Debt service",IF(T13>20,0,W13*MAX(0,MIN(20-T13+1,U13))),IF(OR(S13="Annual O&M",S13="Maintenance-only"),IF(T13>20,0,IF(O13<>"",O13,MAX(0,N(I13)+N(K13))*IF(N13<>"",N13,M13))*MAX(0,20-T13+1)),0)))),0) | AB13: =IFERROR(IF(OR(R13<>"Yes",Q13<>"City"),0,IF(S13="Cash capital",IF(T13<=30,IF(O13<>"",O13,MAX(0,N(J13)+N(K13))*IF(N13<>"",N13,M13)),0),IF(S13="Debt service",IF(T13>30,0,W13*MAX(0,MIN(30-T13+1,U13))),IF(OR(S13="Annual O&M",S13="Maintenance-only"),IF(T13>30,0,IF(O13<>"",O13,MAX(0,N(J13)+N(K13))*IF(N13<>"",N13,M13))*MAX(0,30-T13+1)),0)))),0) | AC13: =IFERROR(IF(OR(R13<>"Yes",Q13<>"ESD"),0,IF(S13="Cash capital",IF(T13<=5,IF(O13<>"",O13,MAX(0,N(F13)+N(K13))*IF(N13<>"",N13,M13)),0),IF(S13="Debt service",IF(T13>5,0,W13*MAX(0,MIN(5-T13+1,U13))),IF(OR(S13="Annual O&M",S13="Maintenance-only"),IF(T13>5,0,IF(O13<>"",O13,MAX(0,N(F13)+N(K13))*IF(N13<>"",N13,M13))*MAX(0,5-T13+1)),0)))),0) | AD13: =IFERROR(IF(OR(R13<>"Yes",Q13<>"ESD"),0,IF(S13="Cash capital",IF(T13<=10,IF(O13<>"",O13,MAX(0,N(G13)+N(K13))*IF(N13<>"",N13,M13)),0),IF(S13="Debt service",IF(T13>10,0,W13*MAX(0,MIN(10-T13+1,U13))),IF(OR(S13="Annual O&M",S13="Maintenance-only"),IF(T13>10,0,IF(O13<>"",O13,MAX(0,N(G13)+N(K13))*IF(N13<>"",N13,M13))*MAX(0,10-T13+1)),0)))),0) | AE13: =IFERROR(IF(OR(R13<>"Yes",Q13<>"ESD"),0,IF(S13="Cash capital",IF(T13<=15,IF(O13<>"",O13,MAX(0,N(H13)+N(K13))*IF(N13<>"",N13,M13)),0),IF(S13="Debt service",IF(T13>15,0,W13*MAX(0,MIN(15-T13+1,U13))),IF(OR(S13="Annual O&M",S13="Maintenance-only"),IF(T13>15,0,IF(O13<>"",O13,MAX(0,N(H13)+N(K13))*IF(N13<>"",N13,M13))*MAX(0,15-T13+1)),0)))),0) | AF13: =IFERROR(IF(OR(R13<>"Yes",Q13<>"ESD"),0,IF(S13="Cash capital",IF(T13<=20,IF(O13<>"",O13,MAX(0,N(I13)+N(K13))*IF(N13<>"",N13,M13)),0),IF(S13="Debt service",IF(T13>20,0,W13*MAX(0,MIN(20-T13+1,U13))),IF(OR(S13="Annual O&M",S13="Maintenance-only"),IF(T13>20,0,IF(O13<>"",O13,MAX(0,N(I13)+N(K13))*IF(N13<>"",N13,M13))*MAX(0,20-T13+1)),0)))),0) | AG13: =IFERROR(IF(OR(R13<>"Yes",Q13<>"ESD"),0,IF(S13="Cash capital",IF(T13<=30,IF(O13<>"",O13,MAX(0,N(J13)+N(K13))*IF(N13<>"",N13,M13)),0),IF(S13="Debt service",IF(T13>30,0,W13*MAX(0,MIN(30-T13+1,U13))),IF(OR(S13="Annual O&M",S13="Maintenance-only"),IF(T13>30,0,IF(O13<>"",O13,MAX(0,N(J13)+N(K13))*IF(N13<>"",N13,M13))*MAX(0,30-T13+1)),0)))),0) | AH13: Local street lane-mile takeoff; actual plat should override.
A14: Sidewalk / trail | B14: City | C14: captured acres | D14: linear ft | E14: 300 LF/ac | F14: ='03_Multi_Horizon_Results'!$B$5*'12_Takeoff_Assumptions'!$B$24 | G14: ='03_Multi_Horizon_Results'!$C$5*'12_Takeoff_Assumptions'!$B$24 | H14: ='03_Multi_Horizon_Results'!$D$5*'12_Takeoff_Assumptions'!$B$24 | I14: ='03_Multi_Horizon_Results'!$E$5*'12_Takeoff_Assumptions'!$B$24 | J14: ='03_Multi_Horizon_Results'!$F$5*'12_Takeoff_Assumptions'!$B$24 | L14: =MAX(0,N(G14)+N(K14)) | M14: 75 | P14: =IFERROR(IF(O14<>"",O14,L14*IF(N14<>"",N14,M14)),0) | Q14: City | R14: No | S14: Debt service | T14: 1 | U14: 20 | V14: 0.045 | W14: =IFERROR(IF(AND(R14="Yes",S14="Debt service",U14>0),IF(V14=0,P14/U14,P14*V14/(1-(1+V14)^(-U14))),0),0) | X14: =IFERROR(IF(OR(R14<>"Yes",Q14<>"City"),0,IF(S14="Cash capital",IF(T14<=5,IF(O14<>"",O14,MAX(0,N(F14)+N(K14))*IF(N14<>"",N14,M14)),0),IF(S14="Debt service",IF(T14>5,0,W14*MAX(0,MIN(5-T14+1,U14))),IF(OR(S14="Annual O&M",S14="Maintenance-only"),IF(T14>5,0,IF(O14<>"",O14,MAX(0,N(F14)+N(K14))*IF(N14<>"",N14,M14))*MAX(0,5-T14+1)),0)))),0) | Y14: =IFERROR(IF(OR(R14<>"Yes",Q14<>"City"),0,IF(S14="Cash capital",IF(T14<=10,IF(O14<>"",O14,MAX(0,N(G14)+N(K14))*IF(N14<>"",N14,M14)),0),IF(S14="Debt service",IF(T14>10,0,W14*MAX(0,MIN(10-T14+1,U14))),IF(OR(S14="Annual O&M",S14="Maintenance-only"),IF(T14>10,0,IF(O14<>"",O14,MAX(0,N(G14)+N(K14))*IF(N14<>"",N14,M14))*MAX(0,10-T14+1)),0)))),0) | Z14: =IFERROR(IF(OR(R14<>"Yes",Q14<>"City"),0,IF(S14="Cash capital",IF(T14<=15,IF(O14<>"",O14,MAX(0,N(H14)+N(K14))*IF(N14<>"",N14,M14)),0),IF(S14="Debt service",IF(T14>15,0,W14*MAX(0,MIN(15-T14+1,U14))),IF(OR(S14="Annual O&M",S14="Maintenance-only"),IF(T14>15,0,IF(O14<>"",O14,MAX(0,N(H14)+N(K14))*IF(N14<>"",N14,M14))*MAX(0,15-T14+1)),0)))),0) | AA14: =IFERROR(IF(OR(R14<>"Yes",Q14<>"City"),0,IF(S14="Cash capital",IF(T14<=20,IF(O14<>"",O14,MAX(0,N(I14)+N(K14))*IF(N14<>"",N14,M14)),0),IF(S14="Debt service",IF(T14>20,0,W14*MAX(0,MIN(20-T14+1,U14))),IF(OR(S14="Annual O&M",S14="Maintenance-only"),IF(T14>20,0,IF(O14<>"",O14,MAX(0,N(I14)+N(K14))*IF(N14<>"",N14,M14))*MAX(0,20-T14+1)),0)))),0) | AB14: =IFERROR(IF(OR(R14<>"Yes",Q14<>"City"),0,IF(S14="Cash capital",IF(T14<=30,IF(O14<>"",O14,MAX(0,N(J14)+N(K14))*IF(N14<>"",N14,M14)),0),IF(S14="Debt service",IF(T14>30,0,W14*MAX(0,MIN(30-T14+1,U14))),IF(OR(S14="Annual O&M",S14="Maintenance-only"),IF(T14>30,0,IF(O14<>"",O14,MAX(0,N(J14)+N(K14))*IF(N14<>"",N14,M14))*MAX(0,30-T14+1)),0)))),0) | AC14: =IFERROR(IF(OR(R14<>"Yes",Q14<>"ESD"),0,IF(S14="Cash capital",IF(T14<=5,IF(O14<>"",O14,MAX(0,N(F14)+N(K14))*IF(N14<>"",N14,M14)),0),IF(S14="Debt service",IF(T14>5,0,W14*MAX(0,MIN(5-T14+1,U14))),IF(OR(S14="Annual O&M",S14="Maintenance-only"),IF(T14>5,0,IF(O14<>"",O14,MAX(0,N(F14)+N(K14))*IF(N14<>"",N14,M14))*MAX(0,5-T14+1)),0)))),0) | AD14: =IFERROR(IF(OR(R14<>"Yes",Q14<>"ESD"),0,IF(S14="Cash capital",IF(T14<=10,IF(O14<>"",O14,MAX(0,N(G14)+N(K14))*IF(N14<>"",N14,M14)),0),IF(S14="Debt service",IF(T14>10,0,W14*MAX(0,MIN(10-T14+1,U14))),IF(OR(S14="Annual O&M",S14="Maintenance-only"),IF(T14>10,0,IF(O14<>"",O14,MAX(0,N(G14)+N(K14))*IF(N14<>"",N14,M14))*MAX(0,10-T14+1)),0)))),0) | AE14: =IFERROR(IF(OR(R14<>"Yes",Q14<>"ESD"),0,IF(S14="Cash capital",IF(T14<=15,IF(O14<>"",O14,MAX(0,N(H14)+N(K14))*IF(N14<>"",N14,M14)),0),IF(S14="Debt service",IF(T14>15,0,W14*MAX(0,MIN(15-T14+1,U14))),IF(OR(S14="Annual O&M",S14="Maintenance-only"),IF(T14>15,0,IF(O14<>"",O14,MAX(0,N(H14)+N(K14))*IF(N14<>"",N14,M14))*MAX(0,15-T14+1)),0)))),0) | AF14: =IFERROR(IF(OR(R14<>"Yes",Q14<>"ESD"),0,IF(S14="Cash capital",IF(T14<=20,IF(O14<>"",O14,MAX(0,N(I14)+N(K14))*IF(N14<>"",N14,M14)),0),IF(S14="Debt service",IF(T14>20,0,W14*MAX(0,MIN(20-T14+1,U14))),IF(OR(S14="Annual O&M",S14="Maintenance-only"),IF(T14>20,0,IF(O14<>"",O14,MAX(0,N(I14)+N(K14))*IF(N14<>"",N14,M14))*MAX(0,20-T14+1)),0)))),0) | AG14: =IFERROR(IF(OR(R14<>"Yes",Q14<>"ESD"),0,IF(S14="Cash capital",IF(T14<=30,IF(O14<>"",O14,MAX(0,N(J14)+N(K14))*IF(N14<>"",N14,M14)),0),IF(S14="Debt service",IF(T14>30,0,W14*MAX(0,MIN(30-T14+1,U14))),IF(OR(S14="Annual O&M",S14="Maintenance-only"),IF(T14>30,0,IF(O14<>"",O14,MAX(0,N(J14)+N(K14))*IF(N14<>"",N14,M14))*MAX(0,30-T14+1)),0)))),0) | AH14: Planning benchmark; frontage/trail plans should override.
A15: Drainage / detention acreage | B15: City | C15: captured acres | D15: acres | E15: 0.10 ac/ac | F15: ='03_Multi_Horizon_Results'!$B$5*'12_Takeoff_Assumptions'!$B$25 | G15: ='03_Multi_Horizon_Results'!$C$5*'12_Takeoff_Assumptions'!$B$25 | H15: ='03_Multi_Horizon_Results'!$D$5*'12_Takeoff_Assumptions'!$B$25 | I15: ='03_Multi_Horizon_Results'!$E$5*'12_Takeoff_Assumptions'!$B$25 | J15: ='03_Multi_Horizon_Results'!$F$5*'12_Takeoff_Assumptions'!$B$25 | L15: =MAX(0,N(G15)+N(K15)) | M15: 150000 | P15: =IFERROR(IF(O15<>"",O15,L15*IF(N15<>"",N15,M15)),0) | Q15: City | R15: No | S15: Debt service | T15: 1 | U15: 20 | V15: 0.045 | W15: =IFERROR(IF(AND(R15="Yes",S15="Debt service",U15>0),IF(V15=0,P15/U15,P15*V15/(1-(1+V15)^(-U15))),0),0) | X15: =IFERROR(IF(OR(R15<>"Yes",Q15<>"City"),0,IF(S15="Cash capital",IF(T15<=5,IF(O15<>"",O15,MAX(0,N(F15)+N(K15))*IF(N15<>"",N15,M15)),0),IF(S15="Debt service",IF(T15>5,0,W15*MAX(0,MIN(5-T15+1,U15))),IF(OR(S15="Annual O&M",S15="Maintenance-only"),IF(T15>5,0,IF(O15<>"",O15,MAX(0,N(F15)+N(K15))*IF(N15<>"",N15,M15))*MAX(0,5-T15+1)),0)))),0) | Y15: =IFERROR(IF(OR(R15<>"Yes",Q15<>"City"),0,IF(S15="Cash capital",IF(T15<=10,IF(O15<>"",O15,MAX(0,N(G15)+N(K15))*IF(N15<>"",N15,M15)),0),IF(S15="Debt service",IF(T15>10,0,W15*MAX(0,MIN(10-T15+1,U15))),IF(OR(S15="Annual O&M",S15="Maintenance-only"),IF(T15>10,0,IF(O15<>"",O15,MAX(0,N(G15)+N(K15))*IF(N15<>"",N15,M15))*MAX(0,10-T15+1)),0)))),0) | Z15: =IFERROR(IF(OR(R15<>"Yes",Q15<>"City"),0,IF(S15="Cash capital",IF(T15<=15,IF(O15<>"",O15,MAX(0,N(H15)+N(K15))*IF(N15<>"",N15,M15)),0),IF(S15="Debt service",IF(T15>15,0,W15*MAX(0,MIN(15-T15+1,U15))),IF(OR(S15="Annual O&M",S15="Maintenance-only"),IF(T15>15,0,IF(O15<>"",O15,MAX(0,N(H15)+N(K15))*IF(N15<>"",N15,M15))*MAX(0,15-T15+1)),0)))),0) | AA15: =IFERROR(IF(OR(R15<>"Yes",Q15<>"City"),0,IF(S15="Cash capital",IF(T15<=20,IF(O15<>"",O15,MAX(0,N(I15)+N(K15))*IF(N15<>"",N15,M15)),0),IF(S15="Debt service",IF(T15>20,0,W15*MAX(0,MIN(20-T15+1,U15))),IF(OR(S15="Annual O&M",S15="Maintenance-only"),IF(T15>20,0,IF(O15<>"",O15,MAX(0,N(I15)+N(K15))*IF(N15<>"",N15,M15))*MAX(0,20-T15+1)),0)))),0) | AB15: =IFERROR(IF(OR(R15<>"Yes",Q15<>"City"),0,IF(S15="Cash capital",IF(T15<=30,IF(O15<>"",O15,MAX(0,N(J15)+N(K15))*IF(N15<>"",N15,M15)),0),IF(S15="Debt service",IF(T15>30,0,W15*MAX(0,MIN(30-T15+1,U15))),IF(OR(S15="Annual O&M",S15="Maintenance-only"),IF(T15>30,0,IF(O15<>"",O15,MAX(0,N(J15)+N(K15))*IF(N15<>"",N15,M15))*MAX(0,30-T15+1)),0)))),0) | AC15: =IFERROR(IF(OR(R15<>"Yes",Q15<>"ESD"),0,IF(S15="Cash capital",IF(T15<=5,IF(O15<>"",O15,MAX(0,N(F15)+N(K15))*IF(N15<>"",N15,M15)),0),IF(S15="Debt service",IF(T15>5,0,W15*MAX(0,MIN(5-T15+1,U15))),IF(OR(S15="Annual O&M",S15="Maintenance-only"),IF(T15>5,0,IF(O15<>"",O15,MAX(0,N(F15)+N(K15))*IF(N15<>"",N15,M15))*MAX(0,5-T15+1)),0)))),0) | AD15: =IFERROR(IF(OR(R15<>"Yes",Q15<>"ESD"),0,IF(S15="Cash capital",IF(T15<=10,IF(O15<>"",O15,MAX(0,N(G15)+N(K15))*IF(N15<>"",N15,M15)),0),IF(S15="Debt service",IF(T15>10,0,W15*MAX(0,MIN(10-T15+1,U15))),IF(OR(S15="Annual O&M",S15="Maintenance-only"),IF(T15>10,0,IF(O15<>"",O15,MAX(0,N(G15)+N(K15))*IF(N15<>"",N15,M15))*MAX(0,10-T15+1)),0)))),0) | AE15: =IFERROR(IF(OR(R15<>"Yes",Q15<>"ESD"),0,IF(S15="Cash capital",IF(T15<=15,IF(O15<>"",O15,MAX(0,N(H15)+N(K15))*IF(N15<>"",N15,M15)),0),IF(S15="Debt service",IF(T15>15,0,W15*MAX(0,MIN(15-T15+1,U15))),IF(OR(S15="Annual O&M",S15="Maintenance-only"),IF(T15>15,0,IF(O15<>"",O15,MAX(0,N(H15)+N(K15))*IF(N15<>"",N15,M15))*MAX(0,15-T15+1)),0)))),0) | AF15: =IFERROR(IF(OR(R15<>"Yes",Q15<>"ESD"),0,IF(S15="Cash capital",IF(T15<=20,IF(O15<>"",O15,MAX(0,N(I15)+N(K15))*IF(N15<>"",N15,M15)),0),IF(S15="Debt service",IF(T15>20,0,W15*MAX(0,MIN(20-T15+1,U15))),IF(OR(S15="Annual O&M",S15="Maintenance-only"),IF(T15>20,0,IF(O15<>"",O15,MAX(0,N(I15)+N(K15))*IF(N15<>"",N15,M15))*MAX(0,20-T15+1)),0)))),0) | AG15: =IFERROR(IF(OR(R15<>"Yes",Q15<>"ESD"),0,IF(S15="Cash capital",IF(T15<=30,IF(O15<>"",O15,MAX(0,N(J15)+N(K15))*IF(N15<>"",N15,M15)),0),IF(S15="Debt service",IF(T15>30,0,W15*MAX(0,MIN(30-T15+1,U15))),IF(OR(S15="Annual O&M",S15="Maintenance-only"),IF(T15>30,0,IF(O15<>"",O15,MAX(0,N(J15)+N(K15))*IF(N15<>"",N15,M15))*MAX(0,30-T15+1)),0)))),0) | AH15: Drainage/detention planning share; drainage study should override.
A16: Traffic signals | B16: City | C16: commercial/industrial sqft | D16: each | E16: threshold 150,000 sqft | F16: =IF('03_Multi_Horizon_Results'!$B$10>'12_Takeoff_Assumptions'!$B$26,ROUNDUP('03_Multi_Horizon_Results'!$B$10/'12_Takeoff_Assumptions'!$B$26,0),0) | G16: =IF('03_Multi_Horizon_Results'!$C$10>'12_Takeoff_Assumptions'!$B$26,ROUNDUP('03_Multi_Horizon_Results'!$C$10/'12_Takeoff_Assumptions'!$B$26,0),0) | H16: =IF('03_Multi_Horizon_Results'!$D$10>'12_Takeoff_Assumptions'!$B$26,ROUNDUP('03_Multi_Horizon_Results'!$D$10/'12_Takeoff_Assumptions'!$B$26,0),0) | I16: =IF('03_Multi_Horizon_Results'!$E$10>'12_Takeoff_Assumptions'!$B$26,ROUNDUP('03_Multi_Horizon_Results'!$E$10/'12_Takeoff_Assumptions'!$B$26,0),0) | J16: =IF('03_Multi_Horizon_Results'!$F$10>'12_Takeoff_Assumptions'!$B$26,ROUNDUP('03_Multi_Horizon_Results'!$F$10/'12_Takeoff_Assumptions'!$B$26,0),0) | L16: =MAX(0,N(G16)+N(K16)) | M16: 350000 | P16: =IFERROR(IF(O16<>"",O16,L16*IF(N16<>"",N16,M16)),0) | Q16: City | R16: No | S16: Debt service | T16: 1 | U16: 20 | V16: 0.045 | W16: =IFERROR(IF(AND(R16="Yes",S16="Debt service",U16>0),IF(V16=0,P16/U16,P16*V16/(1-(1+V16)^(-U16))),0),0) | X16: =IFERROR(IF(OR(R16<>"Yes",Q16<>"City"),0,IF(S16="Cash capital",IF(T16<=5,IF(O16<>"",O16,MAX(0,N(F16)+N(K16))*IF(N16<>"",N16,M16)),0),IF(S16="Debt service",IF(T16>5,0,W16*MAX(0,MIN(5-T16+1,U16))),IF(OR(S16="Annual O&M",S16="Maintenance-only"),IF(T16>5,0,IF(O16<>"",O16,MAX(0,N(F16)+N(K16))*IF(N16<>"",N16,M16))*MAX(0,5-T16+1)),0)))),0) | Y16: =IFERROR(IF(OR(R16<>"Yes",Q16<>"City"),0,IF(S16="Cash capital",IF(T16<=10,IF(O16<>"",O16,MAX(0,N(G16)+N(K16))*IF(N16<>"",N16,M16)),0),IF(S16="Debt service",IF(T16>10,0,W16*MAX(0,MIN(10-T16+1,U16))),IF(OR(S16="Annual O&M",S16="Maintenance-only"),IF(T16>10,0,IF(O16<>"",O16,MAX(0,N(G16)+N(K16))*IF(N16<>"",N16,M16))*MAX(0,10-T16+1)),0)))),0) | Z16: =IFERROR(IF(OR(R16<>"Yes",Q16<>"City"),0,IF(S16="Cash capital",IF(T16<=15,IF(O16<>"",O16,MAX(0,N(H16)+N(K16))*IF(N16<>"",N16,M16)),0),IF(S16="Debt service",IF(T16>15,0,W16*MAX(0,MIN(15-T16+1,U16))),IF(OR(S16="Annual O&M",S16="Maintenance-only"),IF(T16>15,0,IF(O16<>"",O16,MAX(0,N(H16)+N(K16))*IF(N16<>"",N16,M16))*MAX(0,15-T16+1)),0)))),0) | AA16: =IFERROR(IF(OR(R16<>"Yes",Q16<>"City"),0,IF(S16="Cash capital",IF(T16<=20,IF(O16<>"",O16,MAX(0,N(I16)+N(K16))*IF(N16<>"",N16,M16)),0),IF(S16="Debt service",IF(T16>20,0,W16*MAX(0,MIN(20-T16+1,U16))),IF(OR(S16="Annual O&M",S16="Maintenance-only"),IF(T16>20,0,IF(O16<>"",O16,MAX(0,N(I16)+N(K16))*IF(N16<>"",N16,M16))*MAX(0,20-T16+1)),0)))),0) | AB16: =IFERROR(IF(OR(R16<>"Yes",Q16<>"City"),0,IF(S16="Cash capital",IF(T16<=30,IF(O16<>"",O16,MAX(0,N(J16)+N(K16))*IF(N16<>"",N16,M16)),0),IF(S16="Debt service",IF(T16>30,0,W16*MAX(0,MIN(30-T16+1,U16))),IF(OR(S16="Annual O&M",S16="Maintenance-only"),IF(T16>30,0,IF(O16<>"",O16,MAX(0,N(J16)+N(K16))*IF(N16<>"",N16,M16))*MAX(0,30-T16+1)),0)))),0) | AC16: =IFERROR(IF(OR(R16<>"Yes",Q16<>"ESD"),0,IF(S16="Cash capital",IF(T16<=5,IF(O16<>"",O16,MAX(0,N(F16)+N(K16))*IF(N16<>"",N16,M16)),0),IF(S16="Debt service",IF(T16>5,0,W16*MAX(0,MIN(5-T16+1,U16))),IF(OR(S16="Annual O&M",S16="Maintenance-only"),IF(T16>5,0,IF(O16<>"",O16,MAX(0,N(F16)+N(K16))*IF(N16<>"",N16,M16))*MAX(0,5-T16+1)),0)))),0) | AD16: =IFERROR(IF(OR(R16<>"Yes",Q16<>"ESD"),0,IF(S16="Cash capital",IF(T16<=10,IF(O16<>"",O16,MAX(0,N(G16)+N(K16))*IF(N16<>"",N16,M16)),0),IF(S16="Debt service",IF(T16>10,0,W16*MAX(0,MIN(10-T16+1,U16))),IF(OR(S16="Annual O&M",S16="Maintenance-only"),IF(T16>10,0,IF(O16<>"",O16,MAX(0,N(G16)+N(K16))*IF(N16<>"",N16,M16))*MAX(0,10-T16+1)),0)))),0) | AE16: =IFERROR(IF(OR(R16<>"Yes",Q16<>"ESD"),0,IF(S16="Cash capital",IF(T16<=15,IF(O16<>"",O16,MAX(0,N(H16)+N(K16))*IF(N16<>"",N16,M16)),0),IF(S16="Debt service",IF(T16>15,0,W16*MAX(0,MIN(15-T16+1,U16))),IF(OR(S16="Annual O&M",S16="Maintenance-only"),IF(T16>15,0,IF(O16<>"",O16,MAX(0,N(H16)+N(K16))*IF(N16<>"",N16,M16))*MAX(0,15-T16+1)),0)))),0) | AF16: =IFERROR(IF(OR(R16<>"Yes",Q16<>"ESD"),0,IF(S16="Cash capital",IF(T16<=20,IF(O16<>"",O16,MAX(0,N(I16)+N(K16))*IF(N16<>"",N16,M16)),0),IF(S16="Debt service",IF(T16>20,0,W16*MAX(0,MIN(20-T16+1,U16))),IF(OR(S16="Annual O&M",S16="Maintenance-only"),IF(T16>20,0,IF(O16<>"",O16,MAX(0,N(I16)+N(K16))*IF(N16<>"",N16,M16))*MAX(0,20-T16+1)),0)))),0) | AG16: =IFERROR(IF(OR(R16<>"Yes",Q16<>"ESD"),0,IF(S16="Cash capital",IF(T16<=30,IF(O16<>"",O16,MAX(0,N(J16)+N(K16))*IF(N16<>"",N16,M16)),0),IF(S16="Debt service",IF(T16>30,0,W16*MAX(0,MIN(30-T16+1,U16))),IF(OR(S16="Annual O&M",S16="Maintenance-only"),IF(T16>30,0,IF(O16<>"",O16,MAX(0,N(J16)+N(K16))*IF(N16<>"",N16,M16))*MAX(0,30-T16+1)),0)))),0) | AH16: Planning trigger; traffic impact analysis should override.
A17: Police FTEs (sworn) | B17: City | C17: captured residents | D17: FTE | E17: 2.0 FTE/1,000 residents | F17: =('03_Multi_Horizon_Results'!$B$7/1000*'12_Takeoff_Assumptions'!$B$11) | G17: =('03_Multi_Horizon_Results'!$C$7/1000*'12_Takeoff_Assumptions'!$B$11) | H17: =('03_Multi_Horizon_Results'!$D$7/1000*'12_Takeoff_Assumptions'!$B$11) | I17: =('03_Multi_Horizon_Results'!$E$7/1000*'12_Takeoff_Assumptions'!$B$11) | J17: =('03_Multi_Horizon_Results'!$F$7/1000*'12_Takeoff_Assumptions'!$B$11) | L17: =MAX(0,N(G17)+N(K17)) | M17: 120000 | P17: =IFERROR(IF(O17<>"",O17,L17*IF(N17<>"",N17,M17)),0) | Q17: City | R17: No | S17: Debt service | T17: 1 | U17: 20 | V17: 0.045 | W17: =IFERROR(IF(AND(R17="Yes",S17="Debt service",U17>0),IF(V17=0,P17/U17,P17*V17/(1-(1+V17)^(-U17))),0),0) | X17: =IFERROR(IF(OR(R17<>"Yes",Q17<>"City"),0,IF(S17="Cash capital",IF(T17<=5,IF(O17<>"",O17,MAX(0,N(F17)+N(K17))*IF(N17<>"",N17,M17)),0),IF(S17="Debt service",IF(T17>5,0,W17*MAX(0,MIN(5-T17+1,U17))),IF(OR(S17="Annual O&M",S17="Maintenance-only"),IF(T17>5,0,IF(O17<>"",O17,MAX(0,N(F17)+N(K17))*IF(N17<>"",N17,M17))*MAX(0,5-T17+1)),0)))),0) | Y17: =IFERROR(IF(OR(R17<>"Yes",Q17<>"City"),0,IF(S17="Cash capital",IF(T17<=10,IF(O17<>"",O17,MAX(0,N(G17)+N(K17))*IF(N17<>"",N17,M17)),0),IF(S17="Debt service",IF(T17>10,0,W17*MAX(0,MIN(10-T17+1,U17))),IF(OR(S17="Annual O&M",S17="Maintenance-only"),IF(T17>10,0,IF(O17<>"",O17,MAX(0,N(G17)+N(K17))*IF(N17<>"",N17,M17))*MAX(0,10-T17+1)),0)))),0) | Z17: =IFERROR(IF(OR(R17<>"Yes",Q17<>"City"),0,IF(S17="Cash capital",IF(T17<=15,IF(O17<>"",O17,MAX(0,N(H17)+N(K17))*IF(N17<>"",N17,M17)),0),IF(S17="Debt service",IF(T17>15,0,W17*MAX(0,MIN(15-T17+1,U17))),IF(OR(S17="Annual O&M",S17="Maintenance-only"),IF(T17>15,0,IF(O17<>"",O17,MAX(0,N(H17)+N(K17))*IF(N17<>"",N17,M17))*MAX(0,15-T17+1)),0)))),0) | AA17: =IFERROR(IF(OR(R17<>"Yes",Q17<>"City"),0,IF(S17="Cash capital",IF(T17<=20,IF(O17<>"",O17,MAX(0,N(I17)+N(K17))*IF(N17<>"",N17,M17)),0),IF(S17="Debt service",IF(T17>20,0,W17*MAX(0,MIN(20-T17+1,U17))),IF(OR(S17="Annual O&M",S17="Maintenance-only"),IF(T17>20,0,IF(O17<>"",O17,MAX(0,N(I17)+N(K17))*IF(N17<>"",N17,M17))*MAX(0,20-T17+1)),0)))),0) | AB17: =IFERROR(IF(OR(R17<>"Yes",Q17<>"City"),0,IF(S17="Cash capital",IF(T17<=30,IF(O17<>"",O17,MAX(0,N(J17)+N(K17))*IF(N17<>"",N17,M17)),0),IF(S17="Debt service",IF(T17>30,0,W17*MAX(0,MIN(30-T17+1,U17))),IF(OR(S17="Annual O&M",S17="Maintenance-only"),IF(T17>30,0,IF(O17<>"",O17,MAX(0,N(J17)+N(K17))*IF(N17<>"",N17,M17))*MAX(0,30-T17+1)),0)))),0) | AC17: =IFERROR(IF(OR(R17<>"Yes",Q17<>"ESD"),0,IF(S17="Cash capital",IF(T17<=5,IF(O17<>"",O17,MAX(0,N(F17)+N(K17))*IF(N17<>"",N17,M17)),0),IF(S17="Debt service",IF(T17>5,0,W17*MAX(0,MIN(5-T17+1,U17))),IF(OR(S17="Annual O&M",S17="Maintenance-only"),IF(T17>5,0,IF(O17<>"",O17,MAX(0,N(F17)+N(K17))*IF(N17<>"",N17,M17))*MAX(0,5-T17+1)),0)))),0) | AD17: =IFERROR(IF(OR(R17<>"Yes",Q17<>"ESD"),0,IF(S17="Cash capital",IF(T17<=10,IF(O17<>"",O17,MAX(0,N(G17)+N(K17))*IF(N17<>"",N17,M17)),0),IF(S17="Debt service",IF(T17>10,0,W17*MAX(0,MIN(10-T17+1,U17))),IF(OR(S17="Annual O&M",S17="Maintenance-only"),IF(T17>10,0,IF(O17<>"",O17,MAX(0,N(G17)+N(K17))*IF(N17<>"",N17,M17))*MAX(0,10-T17+1)),0)))),0) | AE17: =IFERROR(IF(OR(R17<>"Yes",Q17<>"ESD"),0,IF(S17="Cash capital",IF(T17<=15,IF(O17<>"",O17,MAX(0,N(H17)+N(K17))*IF(N17<>"",N17,M17)),0),IF(S17="Debt service",IF(T17>15,0,W17*MAX(0,MIN(15-T17+1,U17))),IF(OR(S17="Annual O&M",S17="Maintenance-only"),IF(T17>15,0,IF(O17<>"",O17,MAX(0,N(H17)+N(K17))*IF(N17<>"",N17,M17))*MAX(0,15-T17+1)),0)))),0) | AF17: =IFERROR(IF(OR(R17<>"Yes",Q17<>"ESD"),0,IF(S17="Cash capital",IF(T17<=20,IF(O17<>"",O17,MAX(0,N(I17)+N(K17))*IF(N17<>"",N17,M17)),0),IF(S17="Debt service",IF(T17>20,0,W17*MAX(0,MIN(20-T17+1,U17))),IF(OR(S17="Annual O&M",S17="Maintenance-only"),IF(T17>20,0,IF(O17<>"",O17,MAX(0,N(I17)+N(K17))*IF(N17<>"",N17,M17))*MAX(0,20-T17+1)),0)))),0) | AG17: =IFERROR(IF(OR(R17<>"Yes",Q17<>"ESD"),0,IF(S17="Cash capital",IF(T17<=30,IF(O17<>"",O17,MAX(0,N(J17)+N(K17))*IF(N17<>"",N17,M17)),0),IF(S17="Debt service",IF(T17>30,0,W17*MAX(0,MIN(30-T17+1,U17))),IF(OR(S17="Annual O&M",S17="Maintenance-only"),IF(T17>30,0,IF(O17<>"",O17,MAX(0,N(J17)+N(K17))*IF(N17<>"",N17,M17))*MAX(0,30-T17+1)),0)))),0) | AH17: Planning benchmark only; workload-based police staffing should validate.
A18: Police vehicles | B18: City | C18: police FTE | D18: each | E18: 1 vehicle / 2 FTE | F18: =IF(('03_Multi_Horizon_Results'!$B$7/1000*'12_Takeoff_Assumptions'!$B$11)>=1,ROUNDUP(('03_Multi_Horizon_Results'!$B$7/1000*'12_Takeoff_Assumptions'!$B$11)/2,0),0) | G18: =IF(('03_Multi_Horizon_Results'!$C$7/1000*'12_Takeoff_Assumptions'!$B$11)>=1,ROUNDUP(('03_Multi_Horizon_Results'!$C$7/1000*'12_Takeoff_Assumptions'!$B$11)/2,0),0) | H18: =IF(('03_Multi_Horizon_Results'!$D$7/1000*'12_Takeoff_Assumptions'!$B$11)>=1,ROUNDUP(('03_Multi_Horizon_Results'!$D$7/1000*'12_Takeoff_Assumptions'!$B$11)/2,0),0) | I18: =IF(('03_Multi_Horizon_Results'!$E$7/1000*'12_Takeoff_Assumptions'!$B$11)>=1,ROUNDUP(('03_Multi_Horizon_Results'!$E$7/1000*'12_Takeoff_Assumptions'!$B$11)/2,0),0) | J18: =IF(('03_Multi_Horizon_Results'!$F$7/1000*'12_Takeoff_Assumptions'!$B$11)>=1,ROUNDUP(('03_Multi_Horizon_Results'!$F$7/1000*'12_Takeoff_Assumptions'!$B$11)/2,0),0) | L18: =MAX(0,N(G18)+N(K18)) | M18: 65000 | P18: =IFERROR(IF(O18<>"",O18,L18*IF(N18<>"",N18,M18)),0) | Q18: City | R18: No | S18: Debt service | T18: 1 | U18: 20 | V18: 0.045 | W18: =IFERROR(IF(AND(R18="Yes",S18="Debt service",U18>0),IF(V18=0,P18/U18,P18*V18/(1-(1+V18)^(-U18))),0),0) | X18: =IFERROR(IF(OR(R18<>"Yes",Q18<>"City"),0,IF(S18="Cash capital",IF(T18<=5,IF(O18<>"",O18,MAX(0,N(F18)+N(K18))*IF(N18<>"",N18,M18)),0),IF(S18="Debt service",IF(T18>5,0,W18*MAX(0,MIN(5-T18+1,U18))),IF(OR(S18="Annual O&M",S18="Maintenance-only"),IF(T18>5,0,IF(O18<>"",O18,MAX(0,N(F18)+N(K18))*IF(N18<>"",N18,M18))*MAX(0,5-T18+1)),0)))),0) | Y18: =IFERROR(IF(OR(R18<>"Yes",Q18<>"City"),0,IF(S18="Cash capital",IF(T18<=10,IF(O18<>"",O18,MAX(0,N(G18)+N(K18))*IF(N18<>"",N18,M18)),0),IF(S18="Debt service",IF(T18>10,0,W18*MAX(0,MIN(10-T18+1,U18))),IF(OR(S18="Annual O&M",S18="Maintenance-only"),IF(T18>10,0,IF(O18<>"",O18,MAX(0,N(G18)+N(K18))*IF(N18<>"",N18,M18))*MAX(0,10-T18+1)),0)))),0) | Z18: =IFERROR(IF(OR(R18<>"Yes",Q18<>"City"),0,IF(S18="Cash capital",IF(T18<=15,IF(O18<>"",O18,MAX(0,N(H18)+N(K18))*IF(N18<>"",N18,M18)),0),IF(S18="Debt service",IF(T18>15,0,W18*MAX(0,MIN(15-T18+1,U18))),IF(OR(S18="Annual O&M",S18="Maintenance-only"),IF(T18>15,0,IF(O18<>"",O18,MAX(0,N(H18)+N(K18))*IF(N18<>"",N18,M18))*MAX(0,15-T18+1)),0)))),0) | AA18: =IFERROR(IF(OR(R18<>"Yes",Q18<>"City"),0,IF(S18="Cash capital",IF(T18<=20,IF(O18<>"",O18,MAX(0,N(I18)+N(K18))*IF(N18<>"",N18,M18)),0),IF(S18="Debt service",IF(T18>20,0,W18*MAX(0,MIN(20-T18+1,U18))),IF(OR(S18="Annual O&M",S18="Maintenance-only"),IF(T18>20,0,IF(O18<>"",O18,MAX(0,N(I18)+N(K18))*IF(N18<>"",N18,M18))*MAX(0,20-T18+1)),0)))),0) | AB18: =IFERROR(IF(OR(R18<>"Yes",Q18<>"City"),0,IF(S18="Cash capital",IF(T18<=30,IF(O18<>"",O18,MAX(0,N(J18)+N(K18))*IF(N18<>"",N18,M18)),0),IF(S18="Debt service",IF(T18>30,0,W18*MAX(0,MIN(30-T18+1,U18))),IF(OR(S18="Annual O&M",S18="Maintenance-only"),IF(T18>30,0,IF(O18<>"",O18,MAX(0,N(J18)+N(K18))*IF(N18<>"",N18,M18))*MAX(0,30-T18+1)),0)))),0) | AC18: =IFERROR(IF(OR(R18<>"Yes",Q18<>"ESD"),0,IF(S18="Cash capital",IF(T18<=5,IF(O18<>"",O18,MAX(0,N(F18)+N(K18))*IF(N18<>"",N18,M18)),0),IF(S18="Debt service",IF(T18>5,0,W18*MAX(0,MIN(5-T18+1,U18))),IF(OR(S18="Annual O&M",S18="Maintenance-only"),IF(T18>5,0,IF(O18<>"",O18,MAX(0,N(F18)+N(K18))*IF(N18<>"",N18,M18))*MAX(0,5-T18+1)),0)))),0) | AD18: =IFERROR(IF(OR(R18<>"Yes",Q18<>"ESD"),0,IF(S18="Cash capital",IF(T18<=10,IF(O18<>"",O18,MAX(0,N(G18)+N(K18))*IF(N18<>"",N18,M18)),0),IF(S18="Debt service",IF(T18>10,0,W18*MAX(0,MIN(10-T18+1,U18))),IF(OR(S18="Annual O&M",S18="Maintenance-only"),IF(T18>10,0,IF(O18<>"",O18,MAX(0,N(G18)+N(K18))*IF(N18<>"",N18,M18))*MAX(0,10-T18+1)),0)))),0) | AE18: =IFERROR(IF(OR(R18<>"Yes",Q18<>"ESD"),0,IF(S18="Cash capital",IF(T18<=15,IF(O18<>"",O18,MAX(0,N(H18)+N(K18))*IF(N18<>"",N18,M18)),0),IF(S18="Debt service",IF(T18>15,0,W18*MAX(0,MIN(15-T18+1,U18))),IF(OR(S18="Annual O&M",S18="Maintenance-only"),IF(T18>15,0,IF(O18<>"",O18,MAX(0,N(H18)+N(K18))*IF(N18<>"",N18,M18))*MAX(0,15-T18+1)),0)))),0) | AF18: =IFERROR(IF(OR(R18<>"Yes",Q18<>"ESD"),0,IF(S18="Cash capital",IF(T18<=20,IF(O18<>"",O18,MAX(0,N(I18)+N(K18))*IF(N18<>"",N18,M18)),0),IF(S18="Debt service",IF(T18>20,0,W18*MAX(0,MIN(20-T18+1,U18))),IF(OR(S18="Annual O&M",S18="Maintenance-only"),IF(T18>20,0,IF(O18<>"",O18,MAX(0,N(I18)+N(K18))*IF(N18<>"",N18,M18))*MAX(0,20-T18+1)),0)))),0) | AG18: =IFERROR(IF(OR(R18<>"Yes",Q18<>"ESD"),0,IF(S18="Cash capital",IF(T18<=30,IF(O18<>"",O18,MAX(0,N(J18)+N(K18))*IF(N18<>"",N18,M18)),0),IF(S18="Debt service",IF(T18>30,0,W18*MAX(0,MIN(30-T18+1,U18))),IF(OR(S18="Annual O&M",S18="Maintenance-only"),IF(T18>30,0,IF(O18<>"",O18,MAX(0,N(J18)+N(K18))*IF(N18<>"",N18,M18))*MAX(0,30-T18+1)),0)))),0) | AH18: Planning fleet benchmark; police/fleet plan should validate.
A19: Park acreage | B19: City | C19: captured residents | D19: acres | E19: 5 ac/1,000 residents | F19: ='03_Multi_Horizon_Results'!$B$7/1000*'12_Takeoff_Assumptions'!$B$10 | G19: ='03_Multi_Horizon_Results'!$C$7/1000*'12_Takeoff_Assumptions'!$B$10 | H19: ='03_Multi_Horizon_Results'!$D$7/1000*'12_Takeoff_Assumptions'!$B$10 | I19: ='03_Multi_Horizon_Results'!$E$7/1000*'12_Takeoff_Assumptions'!$B$10 | J19: ='03_Multi_Horizon_Results'!$F$7/1000*'12_Takeoff_Assumptions'!$B$10 | L19: =MAX(0,N(G19)+N(K19)) | M19: 100000 | P19: =IFERROR(IF(O19<>"",O19,L19*IF(N19<>"",N19,M19)),0) | Q19: City | R19: No | S19: Debt service | T19: 1 | U19: 20 | V19: 0.045 | W19: =IFERROR(IF(AND(R19="Yes",S19="Debt service",U19>0),IF(V19=0,P19/U19,P19*V19/(1-(1+V19)^(-U19))),0),0) | X19: =IFERROR(IF(OR(R19<>"Yes",Q19<>"City"),0,IF(S19="Cash capital",IF(T19<=5,IF(O19<>"",O19,MAX(0,N(F19)+N(K19))*IF(N19<>"",N19,M19)),0),IF(S19="Debt service",IF(T19>5,0,W19*MAX(0,MIN(5-T19+1,U19))),IF(OR(S19="Annual O&M",S19="Maintenance-only"),IF(T19>5,0,IF(O19<>"",O19,MAX(0,N(F19)+N(K19))*IF(N19<>"",N19,M19))*MAX(0,5-T19+1)),0)))),0) | Y19: =IFERROR(IF(OR(R19<>"Yes",Q19<>"City"),0,IF(S19="Cash capital",IF(T19<=10,IF(O19<>"",O19,MAX(0,N(G19)+N(K19))*IF(N19<>"",N19,M19)),0),IF(S19="Debt service",IF(T19>10,0,W19*MAX(0,MIN(10-T19+1,U19))),IF(OR(S19="Annual O&M",S19="Maintenance-only"),IF(T19>10,0,IF(O19<>"",O19,MAX(0,N(G19)+N(K19))*IF(N19<>"",N19,M19))*MAX(0,10-T19+1)),0)))),0) | Z19: =IFERROR(IF(OR(R19<>"Yes",Q19<>"City"),0,IF(S19="Cash capital",IF(T19<=15,IF(O19<>"",O19,MAX(0,N(H19)+N(K19))*IF(N19<>"",N19,M19)),0),IF(S19="Debt service",IF(T19>15,0,W19*MAX(0,MIN(15-T19+1,U19))),IF(OR(S19="Annual O&M",S19="Maintenance-only"),IF(T19>15,0,IF(O19<>"",O19,MAX(0,N(H19)+N(K19))*IF(N19<>"",N19,M19))*MAX(0,15-T19+1)),0)))),0) | AA19: =IFERROR(IF(OR(R19<>"Yes",Q19<>"City"),0,IF(S19="Cash capital",IF(T19<=20,IF(O19<>"",O19,MAX(0,N(I19)+N(K19))*IF(N19<>"",N19,M19)),0),IF(S19="Debt service",IF(T19>20,0,W19*MAX(0,MIN(20-T19+1,U19))),IF(OR(S19="Annual O&M",S19="Maintenance-only"),IF(T19>20,0,IF(O19<>"",O19,MAX(0,N(I19)+N(K19))*IF(N19<>"",N19,M19))*MAX(0,20-T19+1)),0)))),0) | AB19: =IFERROR(IF(OR(R19<>"Yes",Q19<>"City"),0,IF(S19="Cash capital",IF(T19<=30,IF(O19<>"",O19,MAX(0,N(J19)+N(K19))*IF(N19<>"",N19,M19)),0),IF(S19="Debt service",IF(T19>30,0,W19*MAX(0,MIN(30-T19+1,U19))),IF(OR(S19="Annual O&M",S19="Maintenance-only"),IF(T19>30,0,IF(O19<>"",O19,MAX(0,N(J19)+N(K19))*IF(N19<>"",N19,M19))*MAX(0,30-T19+1)),0)))),0) | AC19: =IFERROR(IF(OR(R19<>"Yes",Q19<>"ESD"),0,IF(S19="Cash capital",IF(T19<=5,IF(O19<>"",O19,MAX(0,N(F19)+N(K19))*IF(N19<>"",N19,M19)),0),IF(S19="Debt service",IF(T19>5,0,W19*MAX(0,MIN(5-T19+1,U19))),IF(OR(S19="Annual O&M",S19="Maintenance-only"),IF(T19>5,0,IF(O19<>"",O19,MAX(0,N(F19)+N(K19))*IF(N19<>"",N19,M19))*MAX(0,5-T19+1)),0)))),0) | AD19: =IFERROR(IF(OR(R19<>"Yes",Q19<>"ESD"),0,IF(S19="Cash capital",IF(T19<=10,IF(O19<>"",O19,MAX(0,N(G19)+N(K19))*IF(N19<>"",N19,M19)),0),IF(S19="Debt service",IF(T19>10,0,W19*MAX(0,MIN(10-T19+1,U19))),IF(OR(S19="Annual O&M",S19="Maintenance-only"),IF(T19>10,0,IF(O19<>"",O19,MAX(0,N(G19)+N(K19))*IF(N19<>"",N19,M19))*MAX(0,10-T19+1)),0)))),0) | AE19: =IFERROR(IF(OR(R19<>"Yes",Q19<>"ESD"),0,IF(S19="Cash capital",IF(T19<=15,IF(O19<>"",O19,MAX(0,N(H19)+N(K19))*IF(N19<>"",N19,M19)),0),IF(S19="Debt service",IF(T19>15,0,W19*MAX(0,MIN(15-T19+1,U19))),IF(OR(S19="Annual O&M",S19="Maintenance-only"),IF(T19>15,0,IF(O19<>"",O19,MAX(0,N(H19)+N(K19))*IF(N19<>"",N19,M19))*MAX(0,15-T19+1)),0)))),0) | AF19: =IFERROR(IF(OR(R19<>"Yes",Q19<>"ESD"),0,IF(S19="Cash capital",IF(T19<=20,IF(O19<>"",O19,MAX(0,N(I19)+N(K19))*IF(N19<>"",N19,M19)),0),IF(S19="Debt service",IF(T19>20,0,W19*MAX(0,MIN(20-T19+1,U19))),IF(OR(S19="Annual O&M",S19="Maintenance-only"),IF(T19>20,0,IF(O19<>"",O19,MAX(0,N(I19)+N(K19))*IF(N19<>"",N19,M19))*MAX(0,20-T19+1)),0)))),0) | AG19: =IFERROR(IF(OR(R19<>"Yes",Q19<>"ESD"),0,IF(S19="Cash capital",IF(T19<=30,IF(O19<>"",O19,MAX(0,N(J19)+N(K19))*IF(N19<>"",N19,M19)),0),IF(S19="Debt service",IF(T19>30,0,W19*MAX(0,MIN(30-T19+1,U19))),IF(OR(S19="Annual O&M",S19="Maintenance-only"),IF(T19>30,0,IF(O19<>"",O19,MAX(0,N(J19)+N(K19))*IF(N19<>"",N19,M19))*MAX(0,30-T19+1)),0)))),0) | AH19: Local planning target, not an NRPA universal standard.
A20: Public works vehicles | B20: City | C20: captured acres | D20: each | E20: threshold 500 ac | F20: =IF('03_Multi_Horizon_Results'!$B$5>='12_Takeoff_Assumptions'!$B$17,ROUNDUP('03_Multi_Horizon_Results'!$B$5/'12_Takeoff_Assumptions'!$B$17,0),0) | G20: =IF('03_Multi_Horizon_Results'!$C$5>='12_Takeoff_Assumptions'!$B$17,ROUNDUP('03_Multi_Horizon_Results'!$C$5/'12_Takeoff_Assumptions'!$B$17,0),0) | H20: =IF('03_Multi_Horizon_Results'!$D$5>='12_Takeoff_Assumptions'!$B$17,ROUNDUP('03_Multi_Horizon_Results'!$D$5/'12_Takeoff_Assumptions'!$B$17,0),0) | I20: =IF('03_Multi_Horizon_Results'!$E$5>='12_Takeoff_Assumptions'!$B$17,ROUNDUP('03_Multi_Horizon_Results'!$E$5/'12_Takeoff_Assumptions'!$B$17,0),0) | J20: =IF('03_Multi_Horizon_Results'!$F$5>='12_Takeoff_Assumptions'!$B$17,ROUNDUP('03_Multi_Horizon_Results'!$F$5/'12_Takeoff_Assumptions'!$B$17,0),0) | L20: =MAX(0,N(G20)+N(K20)) | M20: 150000 | P20: =IFERROR(IF(O20<>"",O20,L20*IF(N20<>"",N20,M20)),0) | Q20: City | R20: No | S20: Debt service | T20: 1 | U20: 20 | V20: 0.045 | W20: =IFERROR(IF(AND(R20="Yes",S20="Debt service",U20>0),IF(V20=0,P20/U20,P20*V20/(1-(1+V20)^(-U20))),0),0) | X20: =IFERROR(IF(OR(R20<>"Yes",Q20<>"City"),0,IF(S20="Cash capital",IF(T20<=5,IF(O20<>"",O20,MAX(0,N(F20)+N(K20))*IF(N20<>"",N20,M20)),0),IF(S20="Debt service",IF(T20>5,0,W20*MAX(0,MIN(5-T20+1,U20))),IF(OR(S20="Annual O&M",S20="Maintenance-only"),IF(T20>5,0,IF(O20<>"",O20,MAX(0,N(F20)+N(K20))*IF(N20<>"",N20,M20))*MAX(0,5-T20+1)),0)))),0) | Y20: =IFERROR(IF(OR(R20<>"Yes",Q20<>"City"),0,IF(S20="Cash capital",IF(T20<=10,IF(O20<>"",O20,MAX(0,N(G20)+N(K20))*IF(N20<>"",N20,M20)),0),IF(S20="Debt service",IF(T20>10,0,W20*MAX(0,MIN(10-T20+1,U20))),IF(OR(S20="Annual O&M",S20="Maintenance-only"),IF(T20>10,0,IF(O20<>"",O20,MAX(0,N(G20)+N(K20))*IF(N20<>"",N20,M20))*MAX(0,10-T20+1)),0)))),0) | Z20: =IFERROR(IF(OR(R20<>"Yes",Q20<>"City"),0,IF(S20="Cash capital",IF(T20<=15,IF(O20<>"",O20,MAX(0,N(H20)+N(K20))*IF(N20<>"",N20,M20)),0),IF(S20="Debt service",IF(T20>15,0,W20*MAX(0,MIN(15-T20+1,U20))),IF(OR(S20="Annual O&M",S20="Maintenance-only"),IF(T20>15,0,IF(O20<>"",O20,MAX(0,N(H20)+N(K20))*IF(N20<>"",N20,M20))*MAX(0,15-T20+1)),0)))),0) | AA20: =IFERROR(IF(OR(R20<>"Yes",Q20<>"City"),0,IF(S20="Cash capital",IF(T20<=20,IF(O20<>"",O20,MAX(0,N(I20)+N(K20))*IF(N20<>"",N20,M20)),0),IF(S20="Debt service",IF(T20>20,0,W20*MAX(0,MIN(20-T20+1,U20))),IF(OR(S20="Annual O&M",S20="Maintenance-only"),IF(T20>20,0,IF(O20<>"",O20,MAX(0,N(I20)+N(K20))*IF(N20<>"",N20,M20))*MAX(0,20-T20+1)),0)))),0) | AB20: =IFERROR(IF(OR(R20<>"Yes",Q20<>"City"),0,IF(S20="Cash capital",IF(T20<=30,IF(O20<>"",O20,MAX(0,N(J20)+N(K20))*IF(N20<>"",N20,M20)),0),IF(S20="Debt service",IF(T20>30,0,W20*MAX(0,MIN(30-T20+1,U20))),IF(OR(S20="Annual O&M",S20="Maintenance-only"),IF(T20>30,0,IF(O20<>"",O20,MAX(0,N(J20)+N(K20))*IF(N20<>"",N20,M20))*MAX(0,30-T20+1)),0)))),0) | AC20: =IFERROR(IF(OR(R20<>"Yes",Q20<>"ESD"),0,IF(S20="Cash capital",IF(T20<=5,IF(O20<>"",O20,MAX(0,N(F20)+N(K20))*IF(N20<>"",N20,M20)),0),IF(S20="Debt service",IF(T20>5,0,W20*MAX(0,MIN(5-T20+1,U20))),IF(OR(S20="Annual O&M",S20="Maintenance-only"),IF(T20>5,0,IF(O20<>"",O20,MAX(0,N(F20)+N(K20))*IF(N20<>"",N20,M20))*MAX(0,5-T20+1)),0)))),0) | AD20: =IFERROR(IF(OR(R20<>"Yes",Q20<>"ESD"),0,IF(S20="Cash capital",IF(T20<=10,IF(O20<>"",O20,MAX(0,N(G20)+N(K20))*IF(N20<>"",N20,M20)),0),IF(S20="Debt service",IF(T20>10,0,W20*MAX(0,MIN(10-T20+1,U20))),IF(OR(S20="Annual O&M",S20="Maintenance-only"),IF(T20>10,0,IF(O20<>"",O20,MAX(0,N(G20)+N(K20))*IF(N20<>"",N20,M20))*MAX(0,10-T20+1)),0)))),0) | AE20: =IFERROR(IF(OR(R20<>"Yes",Q20<>"ESD"),0,IF(S20="Cash capital",IF(T20<=15,IF(O20<>"",O20,MAX(0,N(H20)+N(K20))*IF(N20<>"",N20,M20)),0),IF(S20="Debt service",IF(T20>15,0,W20*MAX(0,MIN(15-T20+1,U20))),IF(OR(S20="Annual O&M",S20="Maintenance-only"),IF(T20>15,0,IF(O20<>"",O20,MAX(0,N(H20)+N(K20))*IF(N20<>"",N20,M20))*MAX(0,15-T20+1)),0)))),0) | AF20: =IFERROR(IF(OR(R20<>"Yes",Q20<>"ESD"),0,IF(S20="Cash capital",IF(T20<=20,IF(O20<>"",O20,MAX(0,N(I20)+N(K20))*IF(N20<>"",N20,M20)),0),IF(S20="Debt service",IF(T20>20,0,W20*MAX(0,MIN(20-T20+1,U20))),IF(OR(S20="Annual O&M",S20="Maintenance-only"),IF(T20>20,0,IF(O20<>"",O20,MAX(0,N(I20)+N(K20))*IF(N20<>"",N20,M20))*MAX(0,20-T20+1)),0)))),0) | AG20: =IFERROR(IF(OR(R20<>"Yes",Q20<>"ESD"),0,IF(S20="Cash capital",IF(T20<=30,IF(O20<>"",O20,MAX(0,N(J20)+N(K20))*IF(N20<>"",N20,M20)),0),IF(S20="Debt service",IF(T20>30,0,W20*MAX(0,MIN(30-T20+1,U20))),IF(OR(S20="Annual O&M",S20="Maintenance-only"),IF(T20>30,0,IF(O20<>"",O20,MAX(0,N(J20)+N(K20))*IF(N20<>"",N20,M20))*MAX(0,30-T20+1)),0)))),0) | AH20: Fleet planning trigger; Public Works validation required.
A21: Fire stations | B21: ESD | C21: captured residents | D21: each | E21: threshold 3,500 residents | F21: =IF('03_Multi_Horizon_Results'!$B$7>='12_Takeoff_Assumptions'!$B$18,INT('03_Multi_Horizon_Results'!$B$7/'12_Takeoff_Assumptions'!$B$18),0) | G21: =IF('03_Multi_Horizon_Results'!$C$7>='12_Takeoff_Assumptions'!$B$18,INT('03_Multi_Horizon_Results'!$C$7/'12_Takeoff_Assumptions'!$B$18),0) | H21: =IF('03_Multi_Horizon_Results'!$D$7>='12_Takeoff_Assumptions'!$B$18,INT('03_Multi_Horizon_Results'!$D$7/'12_Takeoff_Assumptions'!$B$18),0) | I21: =IF('03_Multi_Horizon_Results'!$E$7>='12_Takeoff_Assumptions'!$B$18,INT('03_Multi_Horizon_Results'!$E$7/'12_Takeoff_Assumptions'!$B$18),0) | J21: =IF('03_Multi_Horizon_Results'!$F$7>='12_Takeoff_Assumptions'!$B$18,INT('03_Multi_Horizon_Results'!$F$7/'12_Takeoff_Assumptions'!$B$18),0) | L21: =MAX(0,N(G21)+N(K21)) | M21: 5000000 | P21: =IFERROR(IF(O21<>"",O21,L21*IF(N21<>"",N21,M21)),0) | Q21: ESD | R21: No | S21: Debt service | T21: 1 | U21: 20 | V21: 0.045 | W21: =IFERROR(IF(AND(R21="Yes",S21="Debt service",U21>0),IF(V21=0,P21/U21,P21*V21/(1-(1+V21)^(-U21))),0),0) | X21: =IFERROR(IF(OR(R21<>"Yes",Q21<>"City"),0,IF(S21="Cash capital",IF(T21<=5,IF(O21<>"",O21,MAX(0,N(F21)+N(K21))*IF(N21<>"",N21,M21)),0),IF(S21="Debt service",IF(T21>5,0,W21*MAX(0,MIN(5-T21+1,U21))),IF(OR(S21="Annual O&M",S21="Maintenance-only"),IF(T21>5,0,IF(O21<>"",O21,MAX(0,N(F21)+N(K21))*IF(N21<>"",N21,M21))*MAX(0,5-T21+1)),0)))),0) | Y21: =IFERROR(IF(OR(R21<>"Yes",Q21<>"City"),0,IF(S21="Cash capital",IF(T21<=10,IF(O21<>"",O21,MAX(0,N(G21)+N(K21))*IF(N21<>"",N21,M21)),0),IF(S21="Debt service",IF(T21>10,0,W21*MAX(0,MIN(10-T21+1,U21))),IF(OR(S21="Annual O&M",S21="Maintenance-only"),IF(T21>10,0,IF(O21<>"",O21,MAX(0,N(G21)+N(K21))*IF(N21<>"",N21,M21))*MAX(0,10-T21+1)),0)))),0) | Z21: =IFERROR(IF(OR(R21<>"Yes",Q21<>"City"),0,IF(S21="Cash capital",IF(T21<=15,IF(O21<>"",O21,MAX(0,N(H21)+N(K21))*IF(N21<>"",N21,M21)),0),IF(S21="Debt service",IF(T21>15,0,W21*MAX(0,MIN(15-T21+1,U21))),IF(OR(S21="Annual O&M",S21="Maintenance-only"),IF(T21>15,0,IF(O21<>"",O21,MAX(0,N(H21)+N(K21))*IF(N21<>"",N21,M21))*MAX(0,15-T21+1)),0)))),0) | AA21: =IFERROR(IF(OR(R21<>"Yes",Q21<>"City"),0,IF(S21="Cash capital",IF(T21<=20,IF(O21<>"",O21,MAX(0,N(I21)+N(K21))*IF(N21<>"",N21,M21)),0),IF(S21="Debt service",IF(T21>20,0,W21*MAX(0,MIN(20-T21+1,U21))),IF(OR(S21="Annual O&M",S21="Maintenance-only"),IF(T21>20,0,IF(O21<>"",O21,MAX(0,N(I21)+N(K21))*IF(N21<>"",N21,M21))*MAX(0,20-T21+1)),0)))),0) | AB21: =IFERROR(IF(OR(R21<>"Yes",Q21<>"City"),0,IF(S21="Cash capital",IF(T21<=30,IF(O21<>"",O21,MAX(0,N(J21)+N(K21))*IF(N21<>"",N21,M21)),0),IF(S21="Debt service",IF(T21>30,0,W21*MAX(0,MIN(30-T21+1,U21))),IF(OR(S21="Annual O&M",S21="Maintenance-only"),IF(T21>30,0,IF(O21<>"",O21,MAX(0,N(J21)+N(K21))*IF(N21<>"",N21,M21))*MAX(0,30-T21+1)),0)))),0) | AC21: =IFERROR(IF(OR(R21<>"Yes",Q21<>"ESD"),0,IF(S21="Cash capital",IF(T21<=5,IF(O21<>"",O21,MAX(0,N(F21)+N(K21))*IF(N21<>"",N21,M21)),0),IF(S21="Debt service",IF(T21>5,0,W21*MAX(0,MIN(5-T21+1,U21))),IF(OR(S21="Annual O&M",S21="Maintenance-only"),IF(T21>5,0,IF(O21<>"",O21,MAX(0,N(F21)+N(K21))*IF(N21<>"",N21,M21))*MAX(0,5-T21+1)),0)))),0) | AD21: =IFERROR(IF(OR(R21<>"Yes",Q21<>"ESD"),0,IF(S21="Cash capital",IF(T21<=10,IF(O21<>"",O21,MAX(0,N(G21)+N(K21))*IF(N21<>"",N21,M21)),0),IF(S21="Debt service",IF(T21>10,0,W21*MAX(0,MIN(10-T21+1,U21))),IF(OR(S21="Annual O&M",S21="Maintenance-only"),IF(T21>10,0,IF(O21<>"",O21,MAX(0,N(G21)+N(K21))*IF(N21<>"",N21,M21))*MAX(0,10-T21+1)),0)))),0) | AE21: =IFERROR(IF(OR(R21<>"Yes",Q21<>"ESD"),0,IF(S21="Cash capital",IF(T21<=15,IF(O21<>"",O21,MAX(0,N(H21)+N(K21))*IF(N21<>"",N21,M21)),0),IF(S21="Debt service",IF(T21>15,0,W21*MAX(0,MIN(15-T21+1,U21))),IF(OR(S21="Annual O&M",S21="Maintenance-only"),IF(T21>15,0,IF(O21<>"",O21,MAX(0,N(H21)+N(K21))*IF(N21<>"",N21,M21))*MAX(0,15-T21+1)),0)))),0) | AF21: =IFERROR(IF(OR(R21<>"Yes",Q21<>"ESD"),0,IF(S21="Cash capital",IF(T21<=20,IF(O21<>"",O21,MAX(0,N(I21)+N(K21))*IF(N21<>"",N21,M21)),0),IF(S21="Debt service",IF(T21>20,0,W21*MAX(0,MIN(20-T21+1,U21))),IF(OR(S21="Annual O&M",S21="Maintenance-only"),IF(T21>20,0,IF(O21<>"",O21,MAX(0,N(I21)+N(K21))*IF(N21<>"",N21,M21))*MAX(0,20-T21+1)),0)))),0) | AG21: =IFERROR(IF(OR(R21<>"Yes",Q21<>"ESD"),0,IF(S21="Cash capital",IF(T21<=30,IF(O21<>"",O21,MAX(0,N(J21)+N(K21))*IF(N21<>"",N21,M21)),0),IF(S21="Debt service",IF(T21>30,0,W21*MAX(0,MIN(30-T21+1,U21))),IF(OR(S21="Annual O&M",S21="Maintenance-only"),IF(T21>30,0,IF(O21<>"",O21,MAX(0,N(J21)+N(K21))*IF(N21<>"",N21,M21))*MAX(0,30-T21+1)),0)))),0) | AH21: ESD fire/rescue and EMS-assist station trigger; call-volume validation required.
A22: Engine companies (Type I pumper) | B22: ESD | C22: captured residents | D22: each | E22: threshold 7,000 residents | F22: =IF('03_Multi_Horizon_Results'!$B$7>='12_Takeoff_Assumptions'!$B$19,INT('03_Multi_Horizon_Results'!$B$7/'12_Takeoff_Assumptions'!$B$19),0) | G22: =IF('03_Multi_Horizon_Results'!$C$7>='12_Takeoff_Assumptions'!$B$19,INT('03_Multi_Horizon_Results'!$C$7/'12_Takeoff_Assumptions'!$B$19),0) | H22: =IF('03_Multi_Horizon_Results'!$D$7>='12_Takeoff_Assumptions'!$B$19,INT('03_Multi_Horizon_Results'!$D$7/'12_Takeoff_Assumptions'!$B$19),0) | I22: =IF('03_Multi_Horizon_Results'!$E$7>='12_Takeoff_Assumptions'!$B$19,INT('03_Multi_Horizon_Results'!$E$7/'12_Takeoff_Assumptions'!$B$19),0) | J22: =IF('03_Multi_Horizon_Results'!$F$7>='12_Takeoff_Assumptions'!$B$19,INT('03_Multi_Horizon_Results'!$F$7/'12_Takeoff_Assumptions'!$B$19),0) | L22: =MAX(0,N(G22)+N(K22)) | M22: 1200000 | P22: =IFERROR(IF(O22<>"",O22,L22*IF(N22<>"",N22,M22)),0) | Q22: ESD | R22: No | S22: Debt service | T22: 1 | U22: 20 | V22: 0.045 | W22: =IFERROR(IF(AND(R22="Yes",S22="Debt service",U22>0),IF(V22=0,P22/U22,P22*V22/(1-(1+V22)^(-U22))),0),0) | X22: =IFERROR(IF(OR(R22<>"Yes",Q22<>"City"),0,IF(S22="Cash capital",IF(T22<=5,IF(O22<>"",O22,MAX(0,N(F22)+N(K22))*IF(N22<>"",N22,M22)),0),IF(S22="Debt service",IF(T22>5,0,W22*MAX(0,MIN(5-T22+1,U22))),IF(OR(S22="Annual O&M",S22="Maintenance-only"),IF(T22>5,0,IF(O22<>"",O22,MAX(0,N(F22)+N(K22))*IF(N22<>"",N22,M22))*MAX(0,5-T22+1)),0)))),0) | Y22: =IFERROR(IF(OR(R22<>"Yes",Q22<>"City"),0,IF(S22="Cash capital",IF(T22<=10,IF(O22<>"",O22,MAX(0,N(G22)+N(K22))*IF(N22<>"",N22,M22)),0),IF(S22="Debt service",IF(T22>10,0,W22*MAX(0,MIN(10-T22+1,U22))),IF(OR(S22="Annual O&M",S22="Maintenance-only"),IF(T22>10,0,IF(O22<>"",O22,MAX(0,N(G22)+N(K22))*IF(N22<>"",N22,M22))*MAX(0,10-T22+1)),0)))),0) | Z22: =IFERROR(IF(OR(R22<>"Yes",Q22<>"City"),0,IF(S22="Cash capital",IF(T22<=15,IF(O22<>"",O22,MAX(0,N(H22)+N(K22))*IF(N22<>"",N22,M22)),0),IF(S22="Debt service",IF(T22>15,0,W22*MAX(0,MIN(15-T22+1,U22))),IF(OR(S22="Annual O&M",S22="Maintenance-only"),IF(T22>15,0,IF(O22<>"",O22,MAX(0,N(H22)+N(K22))*IF(N22<>"",N22,M22))*MAX(0,15-T22+1)),0)))),0) | AA22: =IFERROR(IF(OR(R22<>"Yes",Q22<>"City"),0,IF(S22="Cash capital",IF(T22<=20,IF(O22<>"",O22,MAX(0,N(I22)+N(K22))*IF(N22<>"",N22,M22)),0),IF(S22="Debt service",IF(T22>20,0,W22*MAX(0,MIN(20-T22+1,U22))),IF(OR(S22="Annual O&M",S22="Maintenance-only"),IF(T22>20,0,IF(O22<>"",O22,MAX(0,N(I22)+N(K22))*IF(N22<>"",N22,M22))*MAX(0,20-T22+1)),0)))),0) | AB22: =IFERROR(IF(OR(R22<>"Yes",Q22<>"City"),0,IF(S22="Cash capital",IF(T22<=30,IF(O22<>"",O22,MAX(0,N(J22)+N(K22))*IF(N22<>"",N22,M22)),0),IF(S22="Debt service",IF(T22>30,0,W22*MAX(0,MIN(30-T22+1,U22))),IF(OR(S22="Annual O&M",S22="Maintenance-only"),IF(T22>30,0,IF(O22<>"",O22,MAX(0,N(J22)+N(K22))*IF(N22<>"",N22,M22))*MAX(0,30-T22+1)),0)))),0) | AC22: =IFERROR(IF(OR(R22<>"Yes",Q22<>"ESD"),0,IF(S22="Cash capital",IF(T22<=5,IF(O22<>"",O22,MAX(0,N(F22)+N(K22))*IF(N22<>"",N22,M22)),0),IF(S22="Debt service",IF(T22>5,0,W22*MAX(0,MIN(5-T22+1,U22))),IF(OR(S22="Annual O&M",S22="Maintenance-only"),IF(T22>5,0,IF(O22<>"",O22,MAX(0,N(F22)+N(K22))*IF(N22<>"",N22,M22))*MAX(0,5-T22+1)),0)))),0) | AD22: =IFERROR(IF(OR(R22<>"Yes",Q22<>"ESD"),0,IF(S22="Cash capital",IF(T22<=10,IF(O22<>"",O22,MAX(0,N(G22)+N(K22))*IF(N22<>"",N22,M22)),0),IF(S22="Debt service",IF(T22>10,0,W22*MAX(0,MIN(10-T22+1,U22))),IF(OR(S22="Annual O&M",S22="Maintenance-only"),IF(T22>10,0,IF(O22<>"",O22,MAX(0,N(G22)+N(K22))*IF(N22<>"",N22,M22))*MAX(0,10-T22+1)),0)))),0) | AE22: =IFERROR(IF(OR(R22<>"Yes",Q22<>"ESD"),0,IF(S22="Cash capital",IF(T22<=15,IF(O22<>"",O22,MAX(0,N(H22)+N(K22))*IF(N22<>"",N22,M22)),0),IF(S22="Debt service",IF(T22>15,0,W22*MAX(0,MIN(15-T22+1,U22))),IF(OR(S22="Annual O&M",S22="Maintenance-only"),IF(T22>15,0,IF(O22<>"",O22,MAX(0,N(H22)+N(K22))*IF(N22<>"",N22,M22))*MAX(0,15-T22+1)),0)))),0) | AF22: =IFERROR(IF(OR(R22<>"Yes",Q22<>"ESD"),0,IF(S22="Cash capital",IF(T22<=20,IF(O22<>"",O22,MAX(0,N(I22)+N(K22))*IF(N22<>"",N22,M22)),0),IF(S22="Debt service",IF(T22>20,0,W22*MAX(0,MIN(20-T22+1,U22))),IF(OR(S22="Annual O&M",S22="Maintenance-only"),IF(T22>20,0,IF(O22<>"",O22,MAX(0,N(I22)+N(K22))*IF(N22<>"",N22,M22))*MAX(0,20-T22+1)),0)))),0) | AG22: =IFERROR(IF(OR(R22<>"Yes",Q22<>"ESD"),0,IF(S22="Cash capital",IF(T22<=30,IF(O22<>"",O22,MAX(0,N(J22)+N(K22))*IF(N22<>"",N22,M22)),0),IF(S22="Debt service",IF(T22>30,0,W22*MAX(0,MIN(30-T22+1,U22))),IF(OR(S22="Annual O&M",S22="Maintenance-only"),IF(T22>30,0,IF(O22<>"",O22,MAX(0,N(J22)+N(K22))*IF(N22<>"",N22,M22))*MAX(0,30-T22+1)),0)))),0) | AH22: Apparatus trigger; ESD capital plan should validate.
A23: Ladder trucks / quints | B23: ESD | C23: captured residents | D23: each | E23: threshold 14,000 residents | F23: =IF('03_Multi_Horizon_Results'!$B$7>='12_Takeoff_Assumptions'!$B$20,INT('03_Multi_Horizon_Results'!$B$7/'12_Takeoff_Assumptions'!$B$20),0) | G23: =IF('03_Multi_Horizon_Results'!$C$7>='12_Takeoff_Assumptions'!$B$20,INT('03_Multi_Horizon_Results'!$C$7/'12_Takeoff_Assumptions'!$B$20),0) | H23: =IF('03_Multi_Horizon_Results'!$D$7>='12_Takeoff_Assumptions'!$B$20,INT('03_Multi_Horizon_Results'!$D$7/'12_Takeoff_Assumptions'!$B$20),0) | I23: =IF('03_Multi_Horizon_Results'!$E$7>='12_Takeoff_Assumptions'!$B$20,INT('03_Multi_Horizon_Results'!$E$7/'12_Takeoff_Assumptions'!$B$20),0) | J23: =IF('03_Multi_Horizon_Results'!$F$7>='12_Takeoff_Assumptions'!$B$20,INT('03_Multi_Horizon_Results'!$F$7/'12_Takeoff_Assumptions'!$B$20),0) | L23: =MAX(0,N(G23)+N(K23)) | M23: 1500000 | P23: =IFERROR(IF(O23<>"",O23,L23*IF(N23<>"",N23,M23)),0) | Q23: ESD | R23: No | S23: Debt service | T23: 1 | U23: 20 | V23: 0.045 | W23: =IFERROR(IF(AND(R23="Yes",S23="Debt service",U23>0),IF(V23=0,P23/U23,P23*V23/(1-(1+V23)^(-U23))),0),0) | X23: =IFERROR(IF(OR(R23<>"Yes",Q23<>"City"),0,IF(S23="Cash capital",IF(T23<=5,IF(O23<>"",O23,MAX(0,N(F23)+N(K23))*IF(N23<>"",N23,M23)),0),IF(S23="Debt service",IF(T23>5,0,W23*MAX(0,MIN(5-T23+1,U23))),IF(OR(S23="Annual O&M",S23="Maintenance-only"),IF(T23>5,0,IF(O23<>"",O23,MAX(0,N(F23)+N(K23))*IF(N23<>"",N23,M23))*MAX(0,5-T23+1)),0)))),0) | Y23: =IFERROR(IF(OR(R23<>"Yes",Q23<>"City"),0,IF(S23="Cash capital",IF(T23<=10,IF(O23<>"",O23,MAX(0,N(G23)+N(K23))*IF(N23<>"",N23,M23)),0),IF(S23="Debt service",IF(T23>10,0,W23*MAX(0,MIN(10-T23+1,U23))),IF(OR(S23="Annual O&M",S23="Maintenance-only"),IF(T23>10,0,IF(O23<>"",O23,MAX(0,N(G23)+N(K23))*IF(N23<>"",N23,M23))*MAX(0,10-T23+1)),0)))),0) | Z23: =IFERROR(IF(OR(R23<>"Yes",Q23<>"City"),0,IF(S23="Cash capital",IF(T23<=15,IF(O23<>"",O23,MAX(0,N(H23)+N(K23))*IF(N23<>"",N23,M23)),0),IF(S23="Debt service",IF(T23>15,0,W23*MAX(0,MIN(15-T23+1,U23))),IF(OR(S23="Annual O&M",S23="Maintenance-only"),IF(T23>15,0,IF(O23<>"",O23,MAX(0,N(H23)+N(K23))*IF(N23<>"",N23,M23))*MAX(0,15-T23+1)),0)))),0) | AA23: =IFERROR(IF(OR(R23<>"Yes",Q23<>"City"),0,IF(S23="Cash capital",IF(T23<=20,IF(O23<>"",O23,MAX(0,N(I23)+N(K23))*IF(N23<>"",N23,M23)),0),IF(S23="Debt service",IF(T23>20,0,W23*MAX(0,MIN(20-T23+1,U23))),IF(OR(S23="Annual O&M",S23="Maintenance-only"),IF(T23>20,0,IF(O23<>"",O23,MAX(0,N(I23)+N(K23))*IF(N23<>"",N23,M23))*MAX(0,20-T23+1)),0)))),0) | AB23: =IFERROR(IF(OR(R23<>"Yes",Q23<>"City"),0,IF(S23="Cash capital",IF(T23<=30,IF(O23<>"",O23,MAX(0,N(J23)+N(K23))*IF(N23<>"",N23,M23)),0),IF(S23="Debt service",IF(T23>30,0,W23*MAX(0,MIN(30-T23+1,U23))),IF(OR(S23="Annual O&M",S23="Maintenance-only"),IF(T23>30,0,IF(O23<>"",O23,MAX(0,N(J23)+N(K23))*IF(N23<>"",N23,M23))*MAX(0,30-T23+1)),0)))),0) | AC23: =IFERROR(IF(OR(R23<>"Yes",Q23<>"ESD"),0,IF(S23="Cash capital",IF(T23<=5,IF(O23<>"",O23,MAX(0,N(F23)+N(K23))*IF(N23<>"",N23,M23)),0),IF(S23="Debt service",IF(T23>5,0,W23*MAX(0,MIN(5-T23+1,U23))),IF(OR(S23="Annual O&M",S23="Maintenance-only"),IF(T23>5,0,IF(O23<>"",O23,MAX(0,N(F23)+N(K23))*IF(N23<>"",N23,M23))*MAX(0,5-T23+1)),0)))),0) | AD23: =IFERROR(IF(OR(R23<>"Yes",Q23<>"ESD"),0,IF(S23="Cash capital",IF(T23<=10,IF(O23<>"",O23,MAX(0,N(G23)+N(K23))*IF(N23<>"",N23,M23)),0),IF(S23="Debt service",IF(T23>10,0,W23*MAX(0,MIN(10-T23+1,U23))),IF(OR(S23="Annual O&M",S23="Maintenance-only"),IF(T23>10,0,IF(O23<>"",O23,MAX(0,N(G23)+N(K23))*IF(N23<>"",N23,M23))*MAX(0,10-T23+1)),0)))),0) | AE23: =IFERROR(IF(OR(R23<>"Yes",Q23<>"ESD"),0,IF(S23="Cash capital",IF(T23<=15,IF(O23<>"",O23,MAX(0,N(H23)+N(K23))*IF(N23<>"",N23,M23)),0),IF(S23="Debt service",IF(T23>15,0,W23*MAX(0,MIN(15-T23+1,U23))),IF(OR(S23="Annual O&M",S23="Maintenance-only"),IF(T23>15,0,IF(O23<>"",O23,MAX(0,N(H23)+N(K23))*IF(N23<>"",N23,M23))*MAX(0,15-T23+1)),0)))),0) | AF23: =IFERROR(IF(OR(R23<>"Yes",Q23<>"ESD"),0,IF(S23="Cash capital",IF(T23<=20,IF(O23<>"",O23,MAX(0,N(I23)+N(K23))*IF(N23<>"",N23,M23)),0),IF(S23="Debt service",IF(T23>20,0,W23*MAX(0,MIN(20-T23+1,U23))),IF(OR(S23="Annual O&M",S23="Maintenance-only"),IF(T23>20,0,IF(O23<>"",O23,MAX(0,N(I23)+N(K23))*IF(N23<>"",N23,M23))*MAX(0,20-T23+1)),0)))),0) | AG23: =IFERROR(IF(OR(R23<>"Yes",Q23<>"ESD"),0,IF(S23="Cash capital",IF(T23<=30,IF(O23<>"",O23,MAX(0,N(J23)+N(K23))*IF(N23<>"",N23,M23)),0),IF(S23="Debt service",IF(T23>30,0,W23*MAX(0,MIN(30-T23+1,U23))),IF(OR(S23="Annual O&M",S23="Maintenance-only"),IF(T23>30,0,IF(O23<>"",O23,MAX(0,N(J23)+N(K23))*IF(N23<>"",N23,M23))*MAX(0,30-T23+1)),0)))),0) | AH23: Apparatus trigger; may require manual override for tall/industrial risk.
A24: Brush trucks | B24: ESD | C24: captured acres | D24: each | E24: threshold 1,500 ac | F24: =IF('03_Multi_Horizon_Results'!$B$5>='12_Takeoff_Assumptions'!$B$21,INT('03_Multi_Horizon_Results'!$B$5/'12_Takeoff_Assumptions'!$B$21),0) | G24: =IF('03_Multi_Horizon_Results'!$C$5>='12_Takeoff_Assumptions'!$B$21,INT('03_Multi_Horizon_Results'!$C$5/'12_Takeoff_Assumptions'!$B$21),0) | H24: =IF('03_Multi_Horizon_Results'!$D$5>='12_Takeoff_Assumptions'!$B$21,INT('03_Multi_Horizon_Results'!$D$5/'12_Takeoff_Assumptions'!$B$21),0) | I24: =IF('03_Multi_Horizon_Results'!$E$5>='12_Takeoff_Assumptions'!$B$21,INT('03_Multi_Horizon_Results'!$E$5/'12_Takeoff_Assumptions'!$B$21),0) | J24: =IF('03_Multi_Horizon_Results'!$F$5>='12_Takeoff_Assumptions'!$B$21,INT('03_Multi_Horizon_Results'!$F$5/'12_Takeoff_Assumptions'!$B$21),0) | L24: =MAX(0,N(G24)+N(K24)) | M24: 400000 | P24: =IFERROR(IF(O24<>"",O24,L24*IF(N24<>"",N24,M24)),0) | Q24: ESD | R24: No | S24: Debt service | T24: 1 | U24: 20 | V24: 0.045 | W24: =IFERROR(IF(AND(R24="Yes",S24="Debt service",U24>0),IF(V24=0,P24/U24,P24*V24/(1-(1+V24)^(-U24))),0),0) | X24: =IFERROR(IF(OR(R24<>"Yes",Q24<>"City"),0,IF(S24="Cash capital",IF(T24<=5,IF(O24<>"",O24,MAX(0,N(F24)+N(K24))*IF(N24<>"",N24,M24)),0),IF(S24="Debt service",IF(T24>5,0,W24*MAX(0,MIN(5-T24+1,U24))),IF(OR(S24="Annual O&M",S24="Maintenance-only"),IF(T24>5,0,IF(O24<>"",O24,MAX(0,N(F24)+N(K24))*IF(N24<>"",N24,M24))*MAX(0,5-T24+1)),0)))),0) | Y24: =IFERROR(IF(OR(R24<>"Yes",Q24<>"City"),0,IF(S24="Cash capital",IF(T24<=10,IF(O24<>"",O24,MAX(0,N(G24)+N(K24))*IF(N24<>"",N24,M24)),0),IF(S24="Debt service",IF(T24>10,0,W24*MAX(0,MIN(10-T24+1,U24))),IF(OR(S24="Annual O&M",S24="Maintenance-only"),IF(T24>10,0,IF(O24<>"",O24,MAX(0,N(G24)+N(K24))*IF(N24<>"",N24,M24))*MAX(0,10-T24+1)),0)))),0) | Z24: =IFERROR(IF(OR(R24<>"Yes",Q24<>"City"),0,IF(S24="Cash capital",IF(T24<=15,IF(O24<>"",O24,MAX(0,N(H24)+N(K24))*IF(N24<>"",N24,M24)),0),IF(S24="Debt service",IF(T24>15,0,W24*MAX(0,MIN(15-T24+1,U24))),IF(OR(S24="Annual O&M",S24="Maintenance-only"),IF(T24>15,0,IF(O24<>"",O24,MAX(0,N(H24)+N(K24))*IF(N24<>"",N24,M24))*MAX(0,15-T24+1)),0)))),0) | AA24: =IFERROR(IF(OR(R24<>"Yes",Q24<>"City"),0,IF(S24="Cash capital",IF(T24<=20,IF(O24<>"",O24,MAX(0,N(I24)+N(K24))*IF(N24<>"",N24,M24)),0),IF(S24="Debt service",IF(T24>20,0,W24*MAX(0,MIN(20-T24+1,U24))),IF(OR(S24="Annual O&M",S24="Maintenance-only"),IF(T24>20,0,IF(O24<>"",O24,MAX(0,N(I24)+N(K24))*IF(N24<>"",N24,M24))*MAX(0,20-T24+1)),0)))),0) | AB24: =IFERROR(IF(OR(R24<>"Yes",Q24<>"City"),0,IF(S24="Cash capital",IF(T24<=30,IF(O24<>"",O24,MAX(0,N(J24)+N(K24))*IF(N24<>"",N24,M24)),0),IF(S24="Debt service",IF(T24>30,0,W24*MAX(0,MIN(30-T24+1,U24))),IF(OR(S24="Annual O&M",S24="Maintenance-only"),IF(T24>30,0,IF(O24<>"",O24,MAX(0,N(J24)+N(K24))*IF(N24<>"",N24,M24))*MAX(0,30-T24+1)),0)))),0) | AC24: =IFERROR(IF(OR(R24<>"Yes",Q24<>"ESD"),0,IF(S24="Cash capital",IF(T24<=5,IF(O24<>"",O24,MAX(0,N(F24)+N(K24))*IF(N24<>"",N24,M24)),0),IF(S24="Debt service",IF(T24>5,0,W24*MAX(0,MIN(5-T24+1,U24))),IF(OR(S24="Annual O&M",S24="Maintenance-only"),IF(T24>5,0,IF(O24<>"",O24,MAX(0,N(F24)+N(K24))*IF(N24<>"",N24,M24))*MAX(0,5-T24+1)),0)))),0) | AD24: =IFERROR(IF(OR(R24<>"Yes",Q24<>"ESD"),0,IF(S24="Cash capital",IF(T24<=10,IF(O24<>"",O24,MAX(0,N(G24)+N(K24))*IF(N24<>"",N24,M24)),0),IF(S24="Debt service",IF(T24>10,0,W24*MAX(0,MIN(10-T24+1,U24))),IF(OR(S24="Annual O&M",S24="Maintenance-only"),IF(T24>10,0,IF(O24<>"",O24,MAX(0,N(G24)+N(K24))*IF(N24<>"",N24,M24))*MAX(0,10-T24+1)),0)))),0) | AE24: =IFERROR(IF(OR(R24<>"Yes",Q24<>"ESD"),0,IF(S24="Cash capital",IF(T24<=15,IF(O24<>"",O24,MAX(0,N(H24)+N(K24))*IF(N24<>"",N24,M24)),0),IF(S24="Debt service",IF(T24>15,0,W24*MAX(0,MIN(15-T24+1,U24))),IF(OR(S24="Annual O&M",S24="Maintenance-only"),IF(T24>15,0,IF(O24<>"",O24,MAX(0,N(H24)+N(K24))*IF(N24<>"",N24,M24))*MAX(0,15-T24+1)),0)))),0) | AF24: =IFERROR(IF(OR(R24<>"Yes",Q24<>"ESD"),0,IF(S24="Cash capital",IF(T24<=20,IF(O24<>"",O24,MAX(0,N(I24)+N(K24))*IF(N24<>"",N24,M24)),0),IF(S24="Debt service",IF(T24>20,0,W24*MAX(0,MIN(20-T24+1,U24))),IF(OR(S24="Annual O&M",S24="Maintenance-only"),IF(T24>20,0,IF(O24<>"",O24,MAX(0,N(I24)+N(K24))*IF(N24<>"",N24,M24))*MAX(0,20-T24+1)),0)))),0) | AG24: =IFERROR(IF(OR(R24<>"Yes",Q24<>"ESD"),0,IF(S24="Cash capital",IF(T24<=30,IF(O24<>"",O24,MAX(0,N(J24)+N(K24))*IF(N24<>"",N24,M24)),0),IF(S24="Debt service",IF(T24>30,0,W24*MAX(0,MIN(30-T24+1,U24))),IF(OR(S24="Annual O&M",S24="Maintenance-only"),IF(T24>30,0,IF(O24<>"",O24,MAX(0,N(J24)+N(K24))*IF(N24<>"",N24,M24))*MAX(0,30-T24+1)),0)))),0) | AH24: Wildland/acreage exposure trigger; ESD validation required.
A25: Command vehicles | B25: ESD | C25: fire stations | D25: each | E25: 1 per station | F25: =IF('03_Multi_Horizon_Results'!$B$7>='12_Takeoff_Assumptions'!$B$18,INT('03_Multi_Horizon_Results'!$B$7/'12_Takeoff_Assumptions'!$B$18),0) | G25: =IF('03_Multi_Horizon_Results'!$C$7>='12_Takeoff_Assumptions'!$B$18,INT('03_Multi_Horizon_Results'!$C$7/'12_Takeoff_Assumptions'!$B$18),0) | H25: =IF('03_Multi_Horizon_Results'!$D$7>='12_Takeoff_Assumptions'!$B$18,INT('03_Multi_Horizon_Results'!$D$7/'12_Takeoff_Assumptions'!$B$18),0) | I25: =IF('03_Multi_Horizon_Results'!$E$7>='12_Takeoff_Assumptions'!$B$18,INT('03_Multi_Horizon_Results'!$E$7/'12_Takeoff_Assumptions'!$B$18),0) | J25: =IF('03_Multi_Horizon_Results'!$F$7>='12_Takeoff_Assumptions'!$B$18,INT('03_Multi_Horizon_Results'!$F$7/'12_Takeoff_Assumptions'!$B$18),0) | L25: =MAX(0,N(G25)+N(K25)) | M25: 85000 | P25: =IFERROR(IF(O25<>"",O25,L25*IF(N25<>"",N25,M25)),0) | Q25: ESD | R25: No | S25: Debt service | T25: 1 | U25: 20 | V25: 0.045 | W25: =IFERROR(IF(AND(R25="Yes",S25="Debt service",U25>0),IF(V25=0,P25/U25,P25*V25/(1-(1+V25)^(-U25))),0),0) | X25: =IFERROR(IF(OR(R25<>"Yes",Q25<>"City"),0,IF(S25="Cash capital",IF(T25<=5,IF(O25<>"",O25,MAX(0,N(F25)+N(K25))*IF(N25<>"",N25,M25)),0),IF(S25="Debt service",IF(T25>5,0,W25*MAX(0,MIN(5-T25+1,U25))),IF(OR(S25="Annual O&M",S25="Maintenance-only"),IF(T25>5,0,IF(O25<>"",O25,MAX(0,N(F25)+N(K25))*IF(N25<>"",N25,M25))*MAX(0,5-T25+1)),0)))),0) | Y25: =IFERROR(IF(OR(R25<>"Yes",Q25<>"City"),0,IF(S25="Cash capital",IF(T25<=10,IF(O25<>"",O25,MAX(0,N(G25)+N(K25))*IF(N25<>"",N25,M25)),0),IF(S25="Debt service",IF(T25>10,0,W25*MAX(0,MIN(10-T25+1,U25))),IF(OR(S25="Annual O&M",S25="Maintenance-only"),IF(T25>10,0,IF(O25<>"",O25,MAX(0,N(G25)+N(K25))*IF(N25<>"",N25,M25))*MAX(0,10-T25+1)),0)))),0) | Z25: =IFERROR(IF(OR(R25<>"Yes",Q25<>"City"),0,IF(S25="Cash capital",IF(T25<=15,IF(O25<>"",O25,MAX(0,N(H25)+N(K25))*IF(N25<>"",N25,M25)),0),IF(S25="Debt service",IF(T25>15,0,W25*MAX(0,MIN(15-T25+1,U25))),IF(OR(S25="Annual O&M",S25="Maintenance-only"),IF(T25>15,0,IF(O25<>"",O25,MAX(0,N(H25)+N(K25))*IF(N25<>"",N25,M25))*MAX(0,15-T25+1)),0)))),0) | AA25: =IFERROR(IF(OR(R25<>"Yes",Q25<>"City"),0,IF(S25="Cash capital",IF(T25<=20,IF(O25<>"",O25,MAX(0,N(I25)+N(K25))*IF(N25<>"",N25,M25)),0),IF(S25="Debt service",IF(T25>20,0,W25*MAX(0,MIN(20-T25+1,U25))),IF(OR(S25="Annual O&M",S25="Maintenance-only"),IF(T25>20,0,IF(O25<>"",O25,MAX(0,N(I25)+N(K25))*IF(N25<>"",N25,M25))*MAX(0,20-T25+1)),0)))),0) | AB25: =IFERROR(IF(OR(R25<>"Yes",Q25<>"City"),0,IF(S25="Cash capital",IF(T25<=30,IF(O25<>"",O25,MAX(0,N(J25)+N(K25))*IF(N25<>"",N25,M25)),0),IF(S25="Debt service",IF(T25>30,0,W25*MAX(0,MIN(30-T25+1,U25))),IF(OR(S25="Annual O&M",S25="Maintenance-only"),IF(T25>30,0,IF(O25<>"",O25,MAX(0,N(J25)+N(K25))*IF(N25<>"",N25,M25))*MAX(0,30-T25+1)),0)))),0) | AC25: =IFERROR(IF(OR(R25<>"Yes",Q25<>"ESD"),0,IF(S25="Cash capital",IF(T25<=5,IF(O25<>"",O25,MAX(0,N(F25)+N(K25))*IF(N25<>"",N25,M25)),0),IF(S25="Debt service",IF(T25>5,0,W25*MAX(0,MIN(5-T25+1,U25))),IF(OR(S25="Annual O&M",S25="Maintenance-only"),IF(T25>5,0,IF(O25<>"",O25,MAX(0,N(F25)+N(K25))*IF(N25<>"",N25,M25))*MAX(0,5-T25+1)),0)))),0) | AD25: =IFERROR(IF(OR(R25<>"Yes",Q25<>"ESD"),0,IF(S25="Cash capital",IF(T25<=10,IF(O25<>"",O25,MAX(0,N(G25)+N(K25))*IF(N25<>"",N25,M25)),0),IF(S25="Debt service",IF(T25>10,0,W25*MAX(0,MIN(10-T25+1,U25))),IF(OR(S25="Annual O&M",S25="Maintenance-only"),IF(T25>10,0,IF(O25<>"",O25,MAX(0,N(G25)+N(K25))*IF(N25<>"",N25,M25))*MAX(0,10-T25+1)),0)))),0) | AE25: =IFERROR(IF(OR(R25<>"Yes",Q25<>"ESD"),0,IF(S25="Cash capital",IF(T25<=15,IF(O25<>"",O25,MAX(0,N(H25)+N(K25))*IF(N25<>"",N25,M25)),0),IF(S25="Debt service",IF(T25>15,0,W25*MAX(0,MIN(15-T25+1,U25))),IF(OR(S25="Annual O&M",S25="Maintenance-only"),IF(T25>15,0,IF(O25<>"",O25,MAX(0,N(H25)+N(K25))*IF(N25<>"",N25,M25))*MAX(0,15-T25+1)),0)))),0) | AF25: =IFERROR(IF(OR(R25<>"Yes",Q25<>"ESD"),0,IF(S25="Cash capital",IF(T25<=20,IF(O25<>"",O25,MAX(0,N(I25)+N(K25))*IF(N25<>"",N25,M25)),0),IF(S25="Debt service",IF(T25>20,0,W25*MAX(0,MIN(20-T25+1,U25))),IF(OR(S25="Annual O&M",S25="Maintenance-only"),IF(T25>20,0,IF(O25<>"",O25,MAX(0,N(I25)+N(K25))*IF(N25<>"",N25,M25))*MAX(0,20-T25+1)),0)))),0) | AG25: =IFERROR(IF(OR(R25<>"Yes",Q25<>"ESD"),0,IF(S25="Cash capital",IF(T25<=30,IF(O25<>"",O25,MAX(0,N(J25)+N(K25))*IF(N25<>"",N25,M25)),0),IF(S25="Debt service",IF(T25>30,0,W25*MAX(0,MIN(30-T25+1,U25))),IF(OR(S25="Annual O&M",S25="Maintenance-only"),IF(T25>30,0,IF(O25<>"",O25,MAX(0,N(J25)+N(K25))*IF(N25<>"",N25,M25))*MAX(0,30-T25+1)),0)))),0) | AH25: Command vehicle allowance tied to fire station trigger.
A26: SCBA / PPE sets | B26: ESD | C26: firefighter FTE | D26: sets | E26: 1 set/FTE | F26: =('03_Multi_Horizon_Results'!$B$7/1000*'12_Takeoff_Assumptions'!$B$22)*'12_Takeoff_Assumptions'!$B$27 | G26: =('03_Multi_Horizon_Results'!$C$7/1000*'12_Takeoff_Assumptions'!$B$22)*'12_Takeoff_Assumptions'!$B$27 | H26: =('03_Multi_Horizon_Results'!$D$7/1000*'12_Takeoff_Assumptions'!$B$22)*'12_Takeoff_Assumptions'!$B$27 | I26: =('03_Multi_Horizon_Results'!$E$7/1000*'12_Takeoff_Assumptions'!$B$22)*'12_Takeoff_Assumptions'!$B$27 | J26: =('03_Multi_Horizon_Results'!$F$7/1000*'12_Takeoff_Assumptions'!$B$22)*'12_Takeoff_Assumptions'!$B$27 | L26: =MAX(0,N(G26)+N(K26)) | M26: 12500 | P26: =IFERROR(IF(O26<>"",O26,L26*IF(N26<>"",N26,M26)),0) | Q26: ESD | R26: No | S26: Debt service | T26: 1 | U26: 20 | V26: 0.045 | W26: =IFERROR(IF(AND(R26="Yes",S26="Debt service",U26>0),IF(V26=0,P26/U26,P26*V26/(1-(1+V26)^(-U26))),0),0) | X26: =IFERROR(IF(OR(R26<>"Yes",Q26<>"City"),0,IF(S26="Cash capital",IF(T26<=5,IF(O26<>"",O26,MAX(0,N(F26)+N(K26))*IF(N26<>"",N26,M26)),0),IF(S26="Debt service",IF(T26>5,0,W26*MAX(0,MIN(5-T26+1,U26))),IF(OR(S26="Annual O&M",S26="Maintenance-only"),IF(T26>5,0,IF(O26<>"",O26,MAX(0,N(F26)+N(K26))*IF(N26<>"",N26,M26))*MAX(0,5-T26+1)),0)))),0) | Y26: =IFERROR(IF(OR(R26<>"Yes",Q26<>"City"),0,IF(S26="Cash capital",IF(T26<=10,IF(O26<>"",O26,MAX(0,N(G26)+N(K26))*IF(N26<>"",N26,M26)),0),IF(S26="Debt service",IF(T26>10,0,W26*MAX(0,MIN(10-T26+1,U26))),IF(OR(S26="Annual O&M",S26="Maintenance-only"),IF(T26>10,0,IF(O26<>"",O26,MAX(0,N(G26)+N(K26))*IF(N26<>"",N26,M26))*MAX(0,10-T26+1)),0)))),0) | Z26: =IFERROR(IF(OR(R26<>"Yes",Q26<>"City"),0,IF(S26="Cash capital",IF(T26<=15,IF(O26<>"",O26,MAX(0,N(H26)+N(K26))*IF(N26<>"",N26,M26)),0),IF(S26="Debt service",IF(T26>15,0,W26*MAX(0,MIN(15-T26+1,U26))),IF(OR(S26="Annual O&M",S26="Maintenance-only"),IF(T26>15,0,IF(O26<>"",O26,MAX(0,N(H26)+N(K26))*IF(N26<>"",N26,M26))*MAX(0,15-T26+1)),0)))),0) | AA26: =IFERROR(IF(OR(R26<>"Yes",Q26<>"City"),0,IF(S26="Cash capital",IF(T26<=20,IF(O26<>"",O26,MAX(0,N(I26)+N(K26))*IF(N26<>"",N26,M26)),0),IF(S26="Debt service",IF(T26>20,0,W26*MAX(0,MIN(20-T26+1,U26))),IF(OR(S26="Annual O&M",S26="Maintenance-only"),IF(T26>20,0,IF(O26<>"",O26,MAX(0,N(I26)+N(K26))*IF(N26<>"",N26,M26))*MAX(0,20-T26+1)),0)))),0) | AB26: =IFERROR(IF(OR(R26<>"Yes",Q26<>"City"),0,IF(S26="Cash capital",IF(T26<=30,IF(O26<>"",O26,MAX(0,N(J26)+N(K26))*IF(N26<>"",N26,M26)),0),IF(S26="Debt service",IF(T26>30,0,W26*MAX(0,MIN(30-T26+1,U26))),IF(OR(S26="Annual O&M",S26="Maintenance-only"),IF(T26>30,0,IF(O26<>"",O26,MAX(0,N(J26)+N(K26))*IF(N26<>"",N26,M26))*MAX(0,30-T26+1)),0)))),0) | AC26: =IFERROR(IF(OR(R26<>"Yes",Q26<>"ESD"),0,IF(S26="Cash capital",IF(T26<=5,IF(O26<>"",O26,MAX(0,N(F26)+N(K26))*IF(N26<>"",N26,M26)),0),IF(S26="Debt service",IF(T26>5,0,W26*MAX(0,MIN(5-T26+1,U26))),IF(OR(S26="Annual O&M",S26="Maintenance-only"),IF(T26>5,0,IF(O26<>"",O26,MAX(0,N(F26)+N(K26))*IF(N26<>"",N26,M26))*MAX(0,5-T26+1)),0)))),0) | AD26: =IFERROR(IF(OR(R26<>"Yes",Q26<>"ESD"),0,IF(S26="Cash capital",IF(T26<=10,IF(O26<>"",O26,MAX(0,N(G26)+N(K26))*IF(N26<>"",N26,M26)),0),IF(S26="Debt service",IF(T26>10,0,W26*MAX(0,MIN(10-T26+1,U26))),IF(OR(S26="Annual O&M",S26="Maintenance-only"),IF(T26>10,0,IF(O26<>"",O26,MAX(0,N(G26)+N(K26))*IF(N26<>"",N26,M26))*MAX(0,10-T26+1)),0)))),0) | AE26: =IFERROR(IF(OR(R26<>"Yes",Q26<>"ESD"),0,IF(S26="Cash capital",IF(T26<=15,IF(O26<>"",O26,MAX(0,N(H26)+N(K26))*IF(N26<>"",N26,M26)),0),IF(S26="Debt service",IF(T26>15,0,W26*MAX(0,MIN(15-T26+1,U26))),IF(OR(S26="Annual O&M",S26="Maintenance-only"),IF(T26>15,0,IF(O26<>"",O26,MAX(0,N(H26)+N(K26))*IF(N26<>"",N26,M26))*MAX(0,15-T26+1)),0)))),0) | AF26: =IFERROR(IF(OR(R26<>"Yes",Q26<>"ESD"),0,IF(S26="Cash capital",IF(T26<=20,IF(O26<>"",O26,MAX(0,N(I26)+N(K26))*IF(N26<>"",N26,M26)),0),IF(S26="Debt service",IF(T26>20,0,W26*MAX(0,MIN(20-T26+1,U26))),IF(OR(S26="Annual O&M",S26="Maintenance-only"),IF(T26>20,0,IF(O26<>"",O26,MAX(0,N(I26)+N(K26))*IF(N26<>"",N26,M26))*MAX(0,20-T26+1)),0)))),0) | AG26: =IFERROR(IF(OR(R26<>"Yes",Q26<>"ESD"),0,IF(S26="Cash capital",IF(T26<=30,IF(O26<>"",O26,MAX(0,N(J26)+N(K26))*IF(N26<>"",N26,M26)),0),IF(S26="Debt service",IF(T26>30,0,W26*MAX(0,MIN(30-T26+1,U26))),IF(OR(S26="Annual O&M",S26="Maintenance-only"),IF(T26>30,0,IF(O26<>"",O26,MAX(0,N(J26)+N(K26))*IF(N26<>"",N26,M26))*MAX(0,30-T26+1)),0)))),0) | AH26: Planning equipment allowance; validate with ESD equipment standards.
A27: Firefighter / EMT FTEs | B27: ESD | C27: captured residents | D27: FTE | E27: 1.0 FTE/1,000 residents | F27: =('03_Multi_Horizon_Results'!$B$7/1000*'12_Takeoff_Assumptions'!$B$22) | G27: =('03_Multi_Horizon_Results'!$C$7/1000*'12_Takeoff_Assumptions'!$B$22) | H27: =('03_Multi_Horizon_Results'!$D$7/1000*'12_Takeoff_Assumptions'!$B$22) | I27: =('03_Multi_Horizon_Results'!$E$7/1000*'12_Takeoff_Assumptions'!$B$22) | J27: =('03_Multi_Horizon_Results'!$F$7/1000*'12_Takeoff_Assumptions'!$B$22) | L27: =MAX(0,N(G27)+N(K27)) | M27: 110000 | P27: =IFERROR(IF(O27<>"",O27,L27*IF(N27<>"",N27,M27)),0) | Q27: ESD | R27: No | S27: Debt service | T27: 1 | U27: 20 | V27: 0.045 | W27: =IFERROR(IF(AND(R27="Yes",S27="Debt service",U27>0),IF(V27=0,P27/U27,P27*V27/(1-(1+V27)^(-U27))),0),0) | X27: =IFERROR(IF(OR(R27<>"Yes",Q27<>"City"),0,IF(S27="Cash capital",IF(T27<=5,IF(O27<>"",O27,MAX(0,N(F27)+N(K27))*IF(N27<>"",N27,M27)),0),IF(S27="Debt service",IF(T27>5,0,W27*MAX(0,MIN(5-T27+1,U27))),IF(OR(S27="Annual O&M",S27="Maintenance-only"),IF(T27>5,0,IF(O27<>"",O27,MAX(0,N(F27)+N(K27))*IF(N27<>"",N27,M27))*MAX(0,5-T27+1)),0)))),0) | Y27: =IFERROR(IF(OR(R27<>"Yes",Q27<>"City"),0,IF(S27="Cash capital",IF(T27<=10,IF(O27<>"",O27,MAX(0,N(G27)+N(K27))*IF(N27<>"",N27,M27)),0),IF(S27="Debt service",IF(T27>10,0,W27*MAX(0,MIN(10-T27+1,U27))),IF(OR(S27="Annual O&M",S27="Maintenance-only"),IF(T27>10,0,IF(O27<>"",O27,MAX(0,N(G27)+N(K27))*IF(N27<>"",N27,M27))*MAX(0,10-T27+1)),0)))),0) | Z27: =IFERROR(IF(OR(R27<>"Yes",Q27<>"City"),0,IF(S27="Cash capital",IF(T27<=15,IF(O27<>"",O27,MAX(0,N(H27)+N(K27))*IF(N27<>"",N27,M27)),0),IF(S27="Debt service",IF(T27>15,0,W27*MAX(0,MIN(15-T27+1,U27))),IF(OR(S27="Annual O&M",S27="Maintenance-only"),IF(T27>15,0,IF(O27<>"",O27,MAX(0,N(H27)+N(K27))*IF(N27<>"",N27,M27))*MAX(0,15-T27+1)),0)))),0) | AA27: =IFERROR(IF(OR(R27<>"Yes",Q27<>"City"),0,IF(S27="Cash capital",IF(T27<=20,IF(O27<>"",O27,MAX(0,N(I27)+N(K27))*IF(N27<>"",N27,M27)),0),IF(S27="Debt service",IF(T27>20,0,W27*MAX(0,MIN(20-T27+1,U27))),IF(OR(S27="Annual O&M",S27="Maintenance-only"),IF(T27>20,0,IF(O27<>"",O27,MAX(0,N(I27)+N(K27))*IF(N27<>"",N27,M27))*MAX(0,20-T27+1)),0)))),0) | AB27: =IFERROR(IF(OR(R27<>"Yes",Q27<>"City"),0,IF(S27="Cash capital",IF(T27<=30,IF(O27<>"",O27,MAX(0,N(J27)+N(K27))*IF(N27<>"",N27,M27)),0),IF(S27="Debt service",IF(T27>30,0,W27*MAX(0,MIN(30-T27+1,U27))),IF(OR(S27="Annual O&M",S27="Maintenance-only"),IF(T27>30,0,IF(O27<>"",O27,MAX(0,N(J27)+N(K27))*IF(N27<>"",N27,M27))*MAX(0,30-T27+1)),0)))),0) | AC27: =IFERROR(IF(OR(R27<>"Yes",Q27<>"ESD"),0,IF(S27="Cash capital",IF(T27<=5,IF(O27<>"",O27,MAX(0,N(F27)+N(K27))*IF(N27<>"",N27,M27)),0),IF(S27="Debt service",IF(T27>5,0,W27*MAX(0,MIN(5-T27+1,U27))),IF(OR(S27="Annual O&M",S27="Maintenance-only"),IF(T27>5,0,IF(O27<>"",O27,MAX(0,N(F27)+N(K27))*IF(N27<>"",N27,M27))*MAX(0,5-T27+1)),0)))),0) | AD27: =IFERROR(IF(OR(R27<>"Yes",Q27<>"ESD"),0,IF(S27="Cash capital",IF(T27<=10,IF(O27<>"",O27,MAX(0,N(G27)+N(K27))*IF(N27<>"",N27,M27)),0),IF(S27="Debt service",IF(T27>10,0,W27*MAX(0,MIN(10-T27+1,U27))),IF(OR(S27="Annual O&M",S27="Maintenance-only"),IF(T27>10,0,IF(O27<>"",O27,MAX(0,N(G27)+N(K27))*IF(N27<>"",N27,M27))*MAX(0,10-T27+1)),0)))),0) | AE27: =IFERROR(IF(OR(R27<>"Yes",Q27<>"ESD"),0,IF(S27="Cash capital",IF(T27<=15,IF(O27<>"",O27,MAX(0,N(H27)+N(K27))*IF(N27<>"",N27,M27)),0),IF(S27="Debt service",IF(T27>15,0,W27*MAX(0,MIN(15-T27+1,U27))),IF(OR(S27="Annual O&M",S27="Maintenance-only"),IF(T27>15,0,IF(O27<>"",O27,MAX(0,N(H27)+N(K27))*IF(N27<>"",N27,M27))*MAX(0,15-T27+1)),0)))),0) | AF27: =IFERROR(IF(OR(R27<>"Yes",Q27<>"ESD"),0,IF(S27="Cash capital",IF(T27<=20,IF(O27<>"",O27,MAX(0,N(I27)+N(K27))*IF(N27<>"",N27,M27)),0),IF(S27="Debt service",IF(T27>20,0,W27*MAX(0,MIN(20-T27+1,U27))),IF(OR(S27="Annual O&M",S27="Maintenance-only"),IF(T27>20,0,IF(O27<>"",O27,MAX(0,N(I27)+N(K27))*IF(N27<>"",N27,M27))*MAX(0,20-T27+1)),0)))),0) | AG27: =IFERROR(IF(OR(R27<>"Yes",Q27<>"ESD"),0,IF(S27="Cash capital",IF(T27<=30,IF(O27<>"",O27,MAX(0,N(J27)+N(K27))*IF(N27<>"",N27,M27)),0),IF(S27="Debt service",IF(T27>30,0,W27*MAX(0,MIN(30-T27+1,U27))),IF(OR(S27="Annual O&M",S27="Maintenance-only"),IF(T27>30,0,IF(O27<>"",O27,MAX(0,N(J27)+N(K27))*IF(N27<>"",N27,M27))*MAX(0,30-T27+1)),0)))),0) | AH27: Fire/rescue and EMS-assist staffing benchmark; not ambulance transport staffing.
A28: Fire officer FTEs | B28: ESD | C28: firefighter FTE | D28: FTE | E28: 1 officer / 5 firefighter FTE | F28: =('03_Multi_Horizon_Results'!$B$7/1000*'12_Takeoff_Assumptions'!$B$22)/'12_Takeoff_Assumptions'!$B$23 | G28: =('03_Multi_Horizon_Results'!$C$7/1000*'12_Takeoff_Assumptions'!$B$22)/'12_Takeoff_Assumptions'!$B$23 | H28: =('03_Multi_Horizon_Results'!$D$7/1000*'12_Takeoff_Assumptions'!$B$22)/'12_Takeoff_Assumptions'!$B$23 | I28: =('03_Multi_Horizon_Results'!$E$7/1000*'12_Takeoff_Assumptions'!$B$22)/'12_Takeoff_Assumptions'!$B$23 | J28: =('03_Multi_Horizon_Results'!$F$7/1000*'12_Takeoff_Assumptions'!$B$22)/'12_Takeoff_Assumptions'!$B$23 | L28: =MAX(0,N(G28)+N(K28)) | M28: 135000 | P28: =IFERROR(IF(O28<>"",O28,L28*IF(N28<>"",N28,M28)),0) | Q28: ESD | R28: No | S28: Debt service | T28: 1 | U28: 20 | V28: 0.045 | W28: =IFERROR(IF(AND(R28="Yes",S28="Debt service",U28>0),IF(V28=0,P28/U28,P28*V28/(1-(1+V28)^(-U28))),0),0) | X28: =IFERROR(IF(OR(R28<>"Yes",Q28<>"City"),0,IF(S28="Cash capital",IF(T28<=5,IF(O28<>"",O28,MAX(0,N(F28)+N(K28))*IF(N28<>"",N28,M28)),0),IF(S28="Debt service",IF(T28>5,0,W28*MAX(0,MIN(5-T28+1,U28))),IF(OR(S28="Annual O&M",S28="Maintenance-only"),IF(T28>5,0,IF(O28<>"",O28,MAX(0,N(F28)+N(K28))*IF(N28<>"",N28,M28))*MAX(0,5-T28+1)),0)))),0) | Y28: =IFERROR(IF(OR(R28<>"Yes",Q28<>"City"),0,IF(S28="Cash capital",IF(T28<=10,IF(O28<>"",O28,MAX(0,N(G28)+N(K28))*IF(N28<>"",N28,M28)),0),IF(S28="Debt service",IF(T28>10,0,W28*MAX(0,MIN(10-T28+1,U28))),IF(OR(S28="Annual O&M",S28="Maintenance-only"),IF(T28>10,0,IF(O28<>"",O28,MAX(0,N(G28)+N(K28))*IF(N28<>"",N28,M28))*MAX(0,10-T28+1)),0)))),0) | Z28: =IFERROR(IF(OR(R28<>"Yes",Q28<>"City"),0,IF(S28="Cash capital",IF(T28<=15,IF(O28<>"",O28,MAX(0,N(H28)+N(K28))*IF(N28<>"",N28,M28)),0),IF(S28="Debt service",IF(T28>15,0,W28*MAX(0,MIN(15-T28+1,U28))),IF(OR(S28="Annual O&M",S28="Maintenance-only"),IF(T28>15,0,IF(O28<>"",O28,MAX(0,N(H28)+N(K28))*IF(N28<>"",N28,M28))*MAX(0,15-T28+1)),0)))),0) | AA28: =IFERROR(IF(OR(R28<>"Yes",Q28<>"City"),0,IF(S28="Cash capital",IF(T28<=20,IF(O28<>"",O28,MAX(0,N(I28)+N(K28))*IF(N28<>"",N28,M28)),0),IF(S28="Debt service",IF(T28>20,0,W28*MAX(0,MIN(20-T28+1,U28))),IF(OR(S28="Annual O&M",S28="Maintenance-only"),IF(T28>20,0,IF(O28<>"",O28,MAX(0,N(I28)+N(K28))*IF(N28<>"",N28,M28))*MAX(0,20-T28+1)),0)))),0) | AB28: =IFERROR(IF(OR(R28<>"Yes",Q28<>"City"),0,IF(S28="Cash capital",IF(T28<=30,IF(O28<>"",O28,MAX(0,N(J28)+N(K28))*IF(N28<>"",N28,M28)),0),IF(S28="Debt service",IF(T28>30,0,W28*MAX(0,MIN(30-T28+1,U28))),IF(OR(S28="Annual O&M",S28="Maintenance-only"),IF(T28>30,0,IF(O28<>"",O28,MAX(0,N(J28)+N(K28))*IF(N28<>"",N28,M28))*MAX(0,30-T28+1)),0)))),0) | AC28: =IFERROR(IF(OR(R28<>"Yes",Q28<>"ESD"),0,IF(S28="Cash capital",IF(T28<=5,IF(O28<>"",O28,MAX(0,N(F28)+N(K28))*IF(N28<>"",N28,M28)),0),IF(S28="Debt service",IF(T28>5,0,W28*MAX(0,MIN(5-T28+1,U28))),IF(OR(S28="Annual O&M",S28="Maintenance-only"),IF(T28>5,0,IF(O28<>"",O28,MAX(0,N(F28)+N(K28))*IF(N28<>"",N28,M28))*MAX(0,5-T28+1)),0)))),0) | AD28: =IFERROR(IF(OR(R28<>"Yes",Q28<>"ESD"),0,IF(S28="Cash capital",IF(T28<=10,IF(O28<>"",O28,MAX(0,N(G28)+N(K28))*IF(N28<>"",N28,M28)),0),IF(S28="Debt service",IF(T28>10,0,W28*MAX(0,MIN(10-T28+1,U28))),IF(OR(S28="Annual O&M",S28="Maintenance-only"),IF(T28>10,0,IF(O28<>"",O28,MAX(0,N(G28)+N(K28))*IF(N28<>"",N28,M28))*MAX(0,10-T28+1)),0)))),0) | AE28: =IFERROR(IF(OR(R28<>"Yes",Q28<>"ESD"),0,IF(S28="Cash capital",IF(T28<=15,IF(O28<>"",O28,MAX(0,N(H28)+N(K28))*IF(N28<>"",N28,M28)),0),IF(S28="Debt service",IF(T28>15,0,W28*MAX(0,MIN(15-T28+1,U28))),IF(OR(S28="Annual O&M",S28="Maintenance-only"),IF(T28>15,0,IF(O28<>"",O28,MAX(0,N(H28)+N(K28))*IF(N28<>"",N28,M28))*MAX(0,15-T28+1)),0)))),0) | AF28: =IFERROR(IF(OR(R28<>"Yes",Q28<>"ESD"),0,IF(S28="Cash capital",IF(T28<=20,IF(O28<>"",O28,MAX(0,N(I28)+N(K28))*IF(N28<>"",N28,M28)),0),IF(S28="Debt service",IF(T28>20,0,W28*MAX(0,MIN(20-T28+1,U28))),IF(OR(S28="Annual O&M",S28="Maintenance-only"),IF(T28>20,0,IF(O28<>"",O28,MAX(0,N(I28)+N(K28))*IF(N28<>"",N28,M28))*MAX(0,20-T28+1)),0)))),0) | AG28: =IFERROR(IF(OR(R28<>"Yes",Q28<>"ESD"),0,IF(S28="Cash capital",IF(T28<=30,IF(O28<>"",O28,MAX(0,N(J28)+N(K28))*IF(N28<>"",N28,M28)),0),IF(S28="Debt service",IF(T28>30,0,W28*MAX(0,MIN(30-T28+1,U28))),IF(OR(S28="Annual O&M",S28="Maintenance-only"),IF(T28>30,0,IF(O28<>"",O28,MAX(0,N(J28)+N(K28))*IF(N28<>"",N28,M28))*MAX(0,30-T28+1)),0)))),0) | AH28: Planning benchmark; validate with ESD staffing model.
A29: Custom infrastructure item 1 (e.g., electrical substation) | B29: City | C29: manual/custom | D29: each | E29: manual | F29: =0 | G29: =0 | H29: =0 | I29: =0 | J29: =0 | L29: =MAX(0,N(G29)+N(K29)) | M29: 0 | P29: =IFERROR(IF(O29<>"",O29,L29*IF(N29<>"",N29,M29)),0) | Q29: Unknown | R29: No | S29: Debt service | T29: 1 | U29: 20 | V29: 0.045 | W29: =IFERROR(IF(AND(R29="Yes",S29="Debt service",U29>0),IF(V29=0,P29/U29,P29*V29/(1-(1+V29)^(-U29))),0),0) | X29: =IFERROR(IF(OR(R29<>"Yes",Q29<>"City"),0,IF(S29="Cash capital",IF(T29<=5,IF(O29<>"",O29,MAX(0,N(F29)+N(K29))*IF(N29<>"",N29,M29)),0),IF(S29="Debt service",IF(T29>5,0,W29*MAX(0,MIN(5-T29+1,U29))),IF(OR(S29="Annual O&M",S29="Maintenance-only"),IF(T29>5,0,IF(O29<>"",O29,MAX(0,N(F29)+N(K29))*IF(N29<>"",N29,M29))*MAX(0,5-T29+1)),0)))),0) | Y29: =IFERROR(IF(OR(R29<>"Yes",Q29<>"City"),0,IF(S29="Cash capital",IF(T29<=10,IF(O29<>"",O29,MAX(0,N(G29)+N(K29))*IF(N29<>"",N29,M29)),0),IF(S29="Debt service",IF(T29>10,0,W29*MAX(0,MIN(10-T29+1,U29))),IF(OR(S29="Annual O&M",S29="Maintenance-only"),IF(T29>10,0,IF(O29<>"",O29,MAX(0,N(G29)+N(K29))*IF(N29<>"",N29,M29))*MAX(0,10-T29+1)),0)))),0) | Z29: =IFERROR(IF(OR(R29<>"Yes",Q29<>"City"),0,IF(S29="Cash capital",IF(T29<=15,IF(O29<>"",O29,MAX(0,N(H29)+N(K29))*IF(N29<>"",N29,M29)),0),IF(S29="Debt service",IF(T29>15,0,W29*MAX(0,MIN(15-T29+1,U29))),IF(OR(S29="Annual O&M",S29="Maintenance-only"),IF(T29>15,0,IF(O29<>"",O29,MAX(0,N(H29)+N(K29))*IF(N29<>"",N29,M29))*MAX(0,15-T29+1)),0)))),0) | AA29: =IFERROR(IF(OR(R29<>"Yes",Q29<>"City"),0,IF(S29="Cash capital",IF(T29<=20,IF(O29<>"",O29,MAX(0,N(I29)+N(K29))*IF(N29<>"",N29,M29)),0),IF(S29="Debt service",IF(T29>20,0,W29*MAX(0,MIN(20-T29+1,U29))),IF(OR(S29="Annual O&M",S29="Maintenance-only"),IF(T29>20,0,IF(O29<>"",O29,MAX(0,N(I29)+N(K29))*IF(N29<>"",N29,M29))*MAX(0,20-T29+1)),0)))),0) | AB29: =IFERROR(IF(OR(R29<>"Yes",Q29<>"City"),0,IF(S29="Cash capital",IF(T29<=30,IF(O29<>"",O29,MAX(0,N(J29)+N(K29))*IF(N29<>"",N29,M29)),0),IF(S29="Debt service",IF(T29>30,0,W29*MAX(0,MIN(30-T29+1,U29))),IF(OR(S29="Annual O&M",S29="Maintenance-only"),IF(T29>30,0,IF(O29<>"",O29,MAX(0,N(J29)+N(K29))*IF(N29<>"",N29,M29))*MAX(0,30-T29+1)),0)))),0) | AC29: =IFERROR(IF(OR(R29<>"Yes",Q29<>"ESD"),0,IF(S29="Cash capital",IF(T29<=5,IF(O29<>"",O29,MAX(0,N(F29)+N(K29))*IF(N29<>"",N29,M29)),0),IF(S29="Debt service",IF(T29>5,0,W29*MAX(0,MIN(5-T29+1,U29))),IF(OR(S29="Annual O&M",S29="Maintenance-only"),IF(T29>5,0,IF(O29<>"",O29,MAX(0,N(F29)+N(K29))*IF(N29<>"",N29,M29))*MAX(0,5-T29+1)),0)))),0) | AD29: =IFERROR(IF(OR(R29<>"Yes",Q29<>"ESD"),0,IF(S29="Cash capital",IF(T29<=10,IF(O29<>"",O29,MAX(0,N(G29)+N(K29))*IF(N29<>"",N29,M29)),0),IF(S29="Debt service",IF(T29>10,0,W29*MAX(0,MIN(10-T29+1,U29))),IF(OR(S29="Annual O&M",S29="Maintenance-only"),IF(T29>10,0,IF(O29<>"",O29,MAX(0,N(G29)+N(K29))*IF(N29<>"",N29,M29))*MAX(0,10-T29+1)),0)))),0) | AE29: =IFERROR(IF(OR(R29<>"Yes",Q29<>"ESD"),0,IF(S29="Cash capital",IF(T29<=15,IF(O29<>"",O29,MAX(0,N(H29)+N(K29))*IF(N29<>"",N29,M29)),0),IF(S29="Debt service",IF(T29>15,0,W29*MAX(0,MIN(15-T29+1,U29))),IF(OR(S29="Annual O&M",S29="Maintenance-only"),IF(T29>15,0,IF(O29<>"",O29,MAX(0,N(H29)+N(K29))*IF(N29<>"",N29,M29))*MAX(0,15-T29+1)),0)))),0) | AF29: =IFERROR(IF(OR(R29<>"Yes",Q29<>"ESD"),0,IF(S29="Cash capital",IF(T29<=20,IF(O29<>"",O29,MAX(0,N(I29)+N(K29))*IF(N29<>"",N29,M29)),0),IF(S29="Debt service",IF(T29>20,0,W29*MAX(0,MIN(20-T29+1,U29))),IF(OR(S29="Annual O&M",S29="Maintenance-only"),IF(T29>20,0,IF(O29<>"",O29,MAX(0,N(I29)+N(K29))*IF(N29<>"",N29,M29))*MAX(0,20-T29+1)),0)))),0) | AG29: =IFERROR(IF(OR(R29<>"Yes",Q29<>"ESD"),0,IF(S29="Cash capital",IF(T29<=30,IF(O29<>"",O29,MAX(0,N(J29)+N(K29))*IF(N29<>"",N29,M29)),0),IF(S29="Debt service",IF(T29>30,0,W29*MAX(0,MIN(30-T29+1,U29))),IF(OR(S29="Annual O&M",S29="Maintenance-only"),IF(T29>30,0,IF(O29<>"",O29,MAX(0,N(J29)+N(K29))*IF(N29<>"",N29,M29))*MAX(0,30-T29+1)),0)))),0) | AH29: Custom row. Enter manual quantity/cost, funding responsibility, timing, and include-in-net choice.
A30: Custom infrastructure item 2 (e.g., regional detention / off-site main) | B30: City | C30: manual/custom | D30: each | E30: manual | F30: =0 | G30: =0 | H30: =0 | I30: =0 | J30: =0 | L30: =MAX(0,N(G30)+N(K30)) | M30: 0 | P30: =IFERROR(IF(O30<>"",O30,L30*IF(N30<>"",N30,M30)),0) | Q30: Unknown | R30: No | S30: Debt service | T30: 1 | U30: 20 | V30: 0.045 | W30: =IFERROR(IF(AND(R30="Yes",S30="Debt service",U30>0),IF(V30=0,P30/U30,P30*V30/(1-(1+V30)^(-U30))),0),0) | X30: =IFERROR(IF(OR(R30<>"Yes",Q30<>"City"),0,IF(S30="Cash capital",IF(T30<=5,IF(O30<>"",O30,MAX(0,N(F30)+N(K30))*IF(N30<>"",N30,M30)),0),IF(S30="Debt service",IF(T30>5,0,W30*MAX(0,MIN(5-T30+1,U30))),IF(OR(S30="Annual O&M",S30="Maintenance-only"),IF(T30>5,0,IF(O30<>"",O30,MAX(0,N(F30)+N(K30))*IF(N30<>"",N30,M30))*MAX(0,5-T30+1)),0)))),0) | Y30: =IFERROR(IF(OR(R30<>"Yes",Q30<>"City"),0,IF(S30="Cash capital",IF(T30<=10,IF(O30<>"",O30,MAX(0,N(G30)+N(K30))*IF(N30<>"",N30,M30)),0),IF(S30="Debt service",IF(T30>10,0,W30*MAX(0,MIN(10-T30+1,U30))),IF(OR(S30="Annual O&M",S30="Maintenance-only"),IF(T30>10,0,IF(O30<>"",O30,MAX(0,N(G30)+N(K30))*IF(N30<>"",N30,M30))*MAX(0,10-T30+1)),0)))),0) | Z30: =IFERROR(IF(OR(R30<>"Yes",Q30<>"City"),0,IF(S30="Cash capital",IF(T30<=15,IF(O30<>"",O30,MAX(0,N(H30)+N(K30))*IF(N30<>"",N30,M30)),0),IF(S30="Debt service",IF(T30>15,0,W30*MAX(0,MIN(15-T30+1,U30))),IF(OR(S30="Annual O&M",S30="Maintenance-only"),IF(T30>15,0,IF(O30<>"",O30,MAX(0,N(H30)+N(K30))*IF(N30<>"",N30,M30))*MAX(0,15-T30+1)),0)))),0) | AA30: =IFERROR(IF(OR(R30<>"Yes",Q30<>"City"),0,IF(S30="Cash capital",IF(T30<=20,IF(O30<>"",O30,MAX(0,N(I30)+N(K30))*IF(N30<>"",N30,M30)),0),IF(S30="Debt service",IF(T30>20,0,W30*MAX(0,MIN(20-T30+1,U30))),IF(OR(S30="Annual O&M",S30="Maintenance-only"),IF(T30>20,0,IF(O30<>"",O30,MAX(0,N(I30)+N(K30))*IF(N30<>"",N30,M30))*MAX(0,20-T30+1)),0)))),0) | AB30: =IFERROR(IF(OR(R30<>"Yes",Q30<>"City"),0,IF(S30="Cash capital",IF(T30<=30,IF(O30<>"",O30,MAX(0,N(J30)+N(K30))*IF(N30<>"",N30,M30)),0),IF(S30="Debt service",IF(T30>30,0,W30*MAX(0,MIN(30-T30+1,U30))),IF(OR(S30="Annual O&M",S30="Maintenance-only"),IF(T30>30,0,IF(O30<>"",O30,MAX(0,N(J30)+N(K30))*IF(N30<>"",N30,M30))*MAX(0,30-T30+1)),0)))),0) | AC30: =IFERROR(IF(OR(R30<>"Yes",Q30<>"ESD"),0,IF(S30="Cash capital",IF(T30<=5,IF(O30<>"",O30,MAX(0,N(F30)+N(K30))*IF(N30<>"",N30,M30)),0),IF(S30="Debt service",IF(T30>5,0,W30*MAX(0,MIN(5-T30+1,U30))),IF(OR(S30="Annual O&M",S30="Maintenance-only"),IF(T30>5,0,IF(O30<>"",O30,MAX(0,N(F30)+N(K30))*IF(N30<>"",N30,M30))*MAX(0,5-T30+1)),0)))),0) | AD30: =IFERROR(IF(OR(R30<>"Yes",Q30<>"ESD"),0,IF(S30="Cash capital",IF(T30<=10,IF(O30<>"",O30,MAX(0,N(G30)+N(K30))*IF(N30<>"",N30,M30)),0),IF(S30="Debt service",IF(T30>10,0,W30*MAX(0,MIN(10-T30+1,U30))),IF(OR(S30="Annual O&M",S30="Maintenance-only"),IF(T30>10,0,IF(O30<>"",O30,MAX(0,N(G30)+N(K30))*IF(N30<>"",N30,M30))*MAX(0,10-T30+1)),0)))),0) | AE30: =IFERROR(IF(OR(R30<>"Yes",Q30<>"ESD"),0,IF(S30="Cash capital",IF(T30<=15,IF(O30<>"",O30,MAX(0,N(H30)+N(K30))*IF(N30<>"",N30,M30)),0),IF(S30="Debt service",IF(T30>15,0,W30*MAX(0,MIN(15-T30+1,U30))),IF(OR(S30="Annual O&M",S30="Maintenance-only"),IF(T30>15,0,IF(O30<>"",O30,MAX(0,N(H30)+N(K30))*IF(N30<>"",N30,M30))*MAX(0,15-T30+1)),0)))),0) | AF30: =IFERROR(IF(OR(R30<>"Yes",Q30<>"ESD"),0,IF(S30="Cash capital",IF(T30<=20,IF(O30<>"",O30,MAX(0,N(I30)+N(K30))*IF(N30<>"",N30,M30)),0),IF(S30="Debt service",IF(T30>20,0,W30*MAX(0,MIN(20-T30+1,U30))),IF(OR(S30="Annual O&M",S30="Maintenance-only"),IF(T30>20,0,IF(O30<>"",O30,MAX(0,N(I30)+N(K30))*IF(N30<>"",N30,M30))*MAX(0,20-T30+1)),0)))),0) | AG30: =IFERROR(IF(OR(R30<>"Yes",Q30<>"ESD"),0,IF(S30="Cash capital",IF(T30<=30,IF(O30<>"",O30,MAX(0,N(J30)+N(K30))*IF(N30<>"",N30,M30)),0),IF(S30="Debt service",IF(T30>30,0,W30*MAX(0,MIN(30-T30+1,U30))),IF(OR(S30="Annual O&M",S30="Maintenance-only"),IF(T30>30,0,IF(O30<>"",O30,MAX(0,N(J30)+N(K30))*IF(N30<>"",N30,M30))*MAX(0,30-T30+1)),0)))),0) | AH30: Custom row. Use for items not in standard library; initially excluded from fiscal net.
A31: Custom ESD / other item (e.g., radio system, special apparatus) | B31: ESD | C31: manual/custom | D31: each | E31: manual | F31: =0 | G31: =0 | H31: =0 | I31: =0 | J31: =0 | L31: =MAX(0,N(G31)+N(K31)) | M31: 0 | P31: =IFERROR(IF(O31<>"",O31,L31*IF(N31<>"",N31,M31)),0) | Q31: Unknown | R31: No | S31: Debt service | T31: 1 | U31: 20 | V31: 0.045 | W31: =IFERROR(IF(AND(R31="Yes",S31="Debt service",U31>0),IF(V31=0,P31/U31,P31*V31/(1-(1+V31)^(-U31))),0),0) | X31: =IFERROR(IF(OR(R31<>"Yes",Q31<>"City"),0,IF(S31="Cash capital",IF(T31<=5,IF(O31<>"",O31,MAX(0,N(F31)+N(K31))*IF(N31<>"",N31,M31)),0),IF(S31="Debt service",IF(T31>5,0,W31*MAX(0,MIN(5-T31+1,U31))),IF(OR(S31="Annual O&M",S31="Maintenance-only"),IF(T31>5,0,IF(O31<>"",O31,MAX(0,N(F31)+N(K31))*IF(N31<>"",N31,M31))*MAX(0,5-T31+1)),0)))),0) | Y31: =IFERROR(IF(OR(R31<>"Yes",Q31<>"City"),0,IF(S31="Cash capital",IF(T31<=10,IF(O31<>"",O31,MAX(0,N(G31)+N(K31))*IF(N31<>"",N31,M31)),0),IF(S31="Debt service",IF(T31>10,0,W31*MAX(0,MIN(10-T31+1,U31))),IF(OR(S31="Annual O&M",S31="Maintenance-only"),IF(T31>10,0,IF(O31<>"",O31,MAX(0,N(G31)+N(K31))*IF(N31<>"",N31,M31))*MAX(0,10-T31+1)),0)))),0) | Z31: =IFERROR(IF(OR(R31<>"Yes",Q31<>"City"),0,IF(S31="Cash capital",IF(T31<=15,IF(O31<>"",O31,MAX(0,N(H31)+N(K31))*IF(N31<>"",N31,M31)),0),IF(S31="Debt service",IF(T31>15,0,W31*MAX(0,MIN(15-T31+1,U31))),IF(OR(S31="Annual O&M",S31="Maintenance-only"),IF(T31>15,0,IF(O31<>"",O31,MAX(0,N(H31)+N(K31))*IF(N31<>"",N31,M31))*MAX(0,15-T31+1)),0)))),0) | AA31: =IFERROR(IF(OR(R31<>"Yes",Q31<>"City"),0,IF(S31="Cash capital",IF(T31<=20,IF(O31<>"",O31,MAX(0,N(I31)+N(K31))*IF(N31<>"",N31,M31)),0),IF(S31="Debt service",IF(T31>20,0,W31*MAX(0,MIN(20-T31+1,U31))),IF(OR(S31="Annual O&M",S31="Maintenance-only"),IF(T31>20,0,IF(O31<>"",O31,MAX(0,N(I31)+N(K31))*IF(N31<>"",N31,M31))*MAX(0,20-T31+1)),0)))),0) | AB31: =IFERROR(IF(OR(R31<>"Yes",Q31<>"City"),0,IF(S31="Cash capital",IF(T31<=30,IF(O31<>"",O31,MAX(0,N(J31)+N(K31))*IF(N31<>"",N31,M31)),0),IF(S31="Debt service",IF(T31>30,0,W31*MAX(0,MIN(30-T31+1,U31))),IF(OR(S31="Annual O&M",S31="Maintenance-only"),IF(T31>30,0,IF(O31<>"",O31,MAX(0,N(J31)+N(K31))*IF(N31<>"",N31,M31))*MAX(0,30-T31+1)),0)))),0) | AC31: =IFERROR(IF(OR(R31<>"Yes",Q31<>"ESD"),0,IF(S31="Cash capital",IF(T31<=5,IF(O31<>"",O31,MAX(0,N(F31)+N(K31))*IF(N31<>"",N31,M31)),0),IF(S31="Debt service",IF(T31>5,0,W31*MAX(0,MIN(5-T31+1,U31))),IF(OR(S31="Annual O&M",S31="Maintenance-only"),IF(T31>5,0,IF(O31<>"",O31,MAX(0,N(F31)+N(K31))*IF(N31<>"",N31,M31))*MAX(0,5-T31+1)),0)))),0) | AD31: =IFERROR(IF(OR(R31<>"Yes",Q31<>"ESD"),0,IF(S31="Cash capital",IF(T31<=10,IF(O31<>"",O31,MAX(0,N(G31)+N(K31))*IF(N31<>"",N31,M31)),0),IF(S31="Debt service",IF(T31>10,0,W31*MAX(0,MIN(10-T31+1,U31))),IF(OR(S31="Annual O&M",S31="Maintenance-only"),IF(T31>10,0,IF(O31<>"",O31,MAX(0,N(G31)+N(K31))*IF(N31<>"",N31,M31))*MAX(0,10-T31+1)),0)))),0) | AE31: =IFERROR(IF(OR(R31<>"Yes",Q31<>"ESD"),0,IF(S31="Cash capital",IF(T31<=15,IF(O31<>"",O31,MAX(0,N(H31)+N(K31))*IF(N31<>"",N31,M31)),0),IF(S31="Debt service",IF(T31>15,0,W31*MAX(0,MIN(15-T31+1,U31))),IF(OR(S31="Annual O&M",S31="Maintenance-only"),IF(T31>15,0,IF(O31<>"",O31,MAX(0,N(H31)+N(K31))*IF(N31<>"",N31,M31))*MAX(0,15-T31+1)),0)))),0) | AF31: =IFERROR(IF(OR(R31<>"Yes",Q31<>"ESD"),0,IF(S31="Cash capital",IF(T31<=20,IF(O31<>"",O31,MAX(0,N(I31)+N(K31))*IF(N31<>"",N31,M31)),0),IF(S31="Debt service",IF(T31>20,0,W31*MAX(0,MIN(20-T31+1,U31))),IF(OR(S31="Annual O&M",S31="Maintenance-only"),IF(T31>20,0,IF(O31<>"",O31,MAX(0,N(I31)+N(K31))*IF(N31<>"",N31,M31))*MAX(0,20-T31+1)),0)))),0) | AG31: =IFERROR(IF(OR(R31<>"Yes",Q31<>"ESD"),0,IF(S31="Cash capital",IF(T31<=30,IF(O31<>"",O31,MAX(0,N(J31)+N(K31))*IF(N31<>"",N31,M31)),0),IF(S31="Debt service",IF(T31>30,0,W31*MAX(0,MIN(30-T31+1,U31))),IF(OR(S31="Annual O&M",S31="Maintenance-only"),IF(T31>30,0,IF(O31<>"",O31,MAX(0,N(J31)+N(K31))*IF(N31<>"",N31,M31))*MAX(0,30-T31+1)),0)))),0) | AH31: Custom ESD/other row; validate with ESD capital plan or responsible entity.
A33: Totals / Fiscal-Net Inclusion Summary
A34: Included City fiscal-net impact by horizon | X34: =SUM(X4:X31) | Y34: =SUM(Y4:Y31) | Z34: =SUM(Z4:Z31) | AA34: =SUM(AA4:AA31) | AB34: =SUM(AB4:AB31)
A35: Included ESD fiscal-net impact by horizon | AC35: =SUM(AC4:AC31) | AD35: =SUM(AD4:AD31) | AE35: =SUM(AE4:AE31) | AF35: =SUM(AF4:AF31) | AG35: =SUM(AG4:AG31)
A37: Note: Standard infrastructure rows are informational unless selected for fiscal inclusion. To incorporate an item into the overall fiscal model, set Include in Fiscal Net? to Yes, select City or ESD as Funding Responsibility, choose Cost Treatment, and verify Timing Year / debt inputs.

Sheet RESULTS
A1: RESULTS — Fiscal Impact by Horizon (active scenario)
A2: All figures are sums over the horizon unless noted. Split-neutral; property tax is net of exemptions. Planning-level.
A4: Active split (City / ESD): | B4: =TEXT('00_Inputs_Dashboard'!B5,"0%")&" / "&TEXT('00_Inputs_Dashboard'!B7,"0%") | D4: Pool rate: | E4: ='00_Inputs_Dashboard'!B20
A6: Metric | B6: 5-Year | C6: 10-Year | D6: 15-Year | E6: 20-Year | F6: 30-Year
A7: REVENUE
A8: 1.5% ILA sales-tax pool | B8: ='03_Multi_Horizon_Results'!B15 | C8: ='03_Multi_Horizon_Results'!C15 | D8: ='03_Multi_Horizon_Results'!D15 | E8: ='03_Multi_Horizon_Results'!E15 | F8: ='03_Multi_Horizon_Results'!F15
A9: City sales-tax share (net of EDC) | B9: ='03_Multi_Horizon_Results'!B18 | C9: ='03_Multi_Horizon_Results'!C18 | D9: ='03_Multi_Horizon_Results'!D18 | E9: ='03_Multi_Horizon_Results'!E18 | F9: ='03_Multi_Horizon_Results'!F18
A10: ESD sales-tax share | B10: ='03_Multi_Horizon_Results'!B19 | C10: ='03_Multi_Horizon_Results'!C19 | D10: ='03_Multi_Horizon_Results'!D19 | E10: ='03_Multi_Horizon_Results'!E19 | F10: ='03_Multi_Horizon_Results'!F19
A11: City property tax (net of exemptions) | B11: ='03_Multi_Horizon_Results'!B20 | C11: ='03_Multi_Horizon_Results'!C20 | D11: ='03_Multi_Horizon_Results'!D20 | E11: ='03_Multi_Horizon_Results'!E20 | F11: ='03_Multi_Horizon_Results'!F20
A12: ESD property tax (net of exemptions) | B12: ='03_Multi_Horizon_Results'!B21 | C12: ='03_Multi_Horizon_Results'!C21 | D12: ='03_Multi_Horizon_Results'!D21 | E12: ='03_Multi_Horizon_Results'!E21 | F12: ='03_Multi_Horizon_Results'!F21
A13: Impact fees (one-time) | B13: ='03_Multi_Horizon_Results'!B22 | C13: ='03_Multi_Horizon_Results'!C22 | D13: ='03_Multi_Horizon_Results'!D22 | E13: ='03_Multi_Horizon_Results'!E22 | F13: ='03_Multi_Horizon_Results'!F22
A14: COST
A15: City operating cost | B15: ='03_Multi_Horizon_Results'!B23 | C15: ='03_Multi_Horizon_Results'!C23 | D15: ='03_Multi_Horizon_Results'!D23 | E15: ='03_Multi_Horizon_Results'!E23 | F15: ='03_Multi_Horizon_Results'!F23
A16: City capital / debt service (incl. infrastructure) | B16: ='03_Multi_Horizon_Results'!B24 | C16: ='03_Multi_Horizon_Results'!C24 | D16: ='03_Multi_Horizon_Results'!D24 | E16: ='03_Multi_Horizon_Results'!E24 | F16: ='03_Multi_Horizon_Results'!F24
A17: City reserve | B17: ='03_Multi_Horizon_Results'!B25 | C17: ='03_Multi_Horizon_Results'!C25 | D17: ='03_Multi_Horizon_Results'!D25 | E17: ='03_Multi_Horizon_Results'!E25 | F17: ='03_Multi_Horizon_Results'!F25
A18: ESD operating cost | B18: ='03_Multi_Horizon_Results'!B26 | C18: ='03_Multi_Horizon_Results'!C26 | D18: ='03_Multi_Horizon_Results'!D26 | E18: ='03_Multi_Horizon_Results'!E26 | F18: ='03_Multi_Horizon_Results'!F26
A19: ESD capital / debt service (incl. infrastructure) | B19: ='03_Multi_Horizon_Results'!B27 | C19: ='03_Multi_Horizon_Results'!C27 | D19: ='03_Multi_Horizon_Results'!D27 | E19: ='03_Multi_Horizon_Results'!E27 | F19: ='03_Multi_Horizon_Results'!F27
A20: ESD reserve | B20: ='03_Multi_Horizon_Results'!B28 | C20: ='03_Multi_Horizon_Results'!C28 | D20: ='03_Multi_Horizon_Results'!D28 | E20: ='03_Multi_Horizon_Results'!E28 | F20: ='03_Multi_Horizon_Results'!F28
A21: NET FISCAL POSITION
A22: City NET | B22: ='03_Multi_Horizon_Results'!B29 | C22: ='03_Multi_Horizon_Results'!C29 | D22: ='03_Multi_Horizon_Results'!D29 | E22: ='03_Multi_Horizon_Results'!E29 | F22: ='03_Multi_Horizon_Results'!F29
A23: ESD NET | B23: ='03_Multi_Horizon_Results'!B30 | C23: ='03_Multi_Horizon_Results'!C30 | D23: ='03_Multi_Horizon_Results'!D30 | E23: ='03_Multi_Horizon_Results'!E30 | F23: ='03_Multi_Horizon_Results'!F30
A24: Combined NET | B24: ='03_Multi_Horizon_Results'!B31 | C24: ='03_Multi_Horizon_Results'!C31 | D24: ='03_Multi_Horizon_Results'!D31 | E24: ='03_Multi_Horizon_Results'!E31 | F24: ='03_Multi_Horizon_Results'!F31
A25: DOES THE SALES-TAX SPLIT MOVE THE NEEDLE? (isolation)
A26: City NET excluding sales-tax allocation | B26: ='03_Multi_Horizon_Results'!B29-'03_Multi_Horizon_Results'!B18 | C26: ='03_Multi_Horizon_Results'!C29-'03_Multi_Horizon_Results'!C18 | D26: ='03_Multi_Horizon_Results'!D29-'03_Multi_Horizon_Results'!D18 | E26: ='03_Multi_Horizon_Results'!E29-'03_Multi_Horizon_Results'!E18 | F26: ='03_Multi_Horizon_Results'!F29-'03_Multi_Horizon_Results'!F18
A27: + City sales-tax share | B27: ='03_Multi_Horizon_Results'!B18 | C27: ='03_Multi_Horizon_Results'!C18 | D27: ='03_Multi_Horizon_Results'!D18 | E27: ='03_Multi_Horizon_Results'!E18 | F27: ='03_Multi_Horizon_Results'!F18
A28: City NET incl. sales tax (check) | B28: ='03_Multi_Horizon_Results'!B29 | C28: ='03_Multi_Horizon_Results'!C29 | D28: ='03_Multi_Horizon_Results'!D29 | E28: ='03_Multi_Horizon_Results'!E29 | F28: ='03_Multi_Horizon_Results'!F29
A29: ESD NET excluding sales-tax allocation | B29: ='03_Multi_Horizon_Results'!B30-'03_Multi_Horizon_Results'!B19 | C29: ='03_Multi_Horizon_Results'!C30-'03_Multi_Horizon_Results'!C19 | D29: ='03_Multi_Horizon_Results'!D30-'03_Multi_Horizon_Results'!D19 | E29: ='03_Multi_Horizon_Results'!E30-'03_Multi_Horizon_Results'!E19 | F29: ='03_Multi_Horizon_Results'!F30-'03_Multi_Horizon_Results'!F19
A30: + ESD sales-tax share | B30: ='03_Multi_Horizon_Results'!B19 | C30: ='03_Multi_Horizon_Results'!C19 | D30: ='03_Multi_Horizon_Results'!D19 | E30: ='03_Multi_Horizon_Results'!E19 | F30: ='03_Multi_Horizon_Results'!F19
A31: ESD NET incl. sales tax (check) | B31: ='03_Multi_Horizon_Results'!B30 | C31: ='03_Multi_Horizon_Results'!C30 | D31: ='03_Multi_Horizon_Results'!D30 | E31: ='03_Multi_Horizon_Results'!E30 | F31: ='03_Multi_Horizon_Results'!F30
A32: PROPERTY TAX — EXEMPTION IMPACT
A33: City property tax — gross (pre-exemption) | B33: =SUM('04_Annual_Calculations'!B36:F36) | C33: =SUM('04_Annual_Calculations'!B36:K36) | D33: =SUM('04_Annual_Calculations'!B36:P36) | E33: =SUM('04_Annual_Calculations'!B36:U36) | F33: =SUM('04_Annual_Calculations'!B36:AE36)
A34: City property tax — net of exemptions | B34: ='03_Multi_Horizon_Results'!B20 | C34: ='03_Multi_Horizon_Results'!C20 | D34: ='03_Multi_Horizon_Results'!D20 | E34: ='03_Multi_Horizon_Results'!E20 | F34: ='03_Multi_Horizon_Results'!F20
A35: City revenue reduced by exemptions | B35: =SUM('04_Annual_Calculations'!B36:F36)-'03_Multi_Horizon_Results'!B20 | C35: =SUM('04_Annual_Calculations'!B36:K36)-'03_Multi_Horizon_Results'!C20 | D35: =SUM('04_Annual_Calculations'!B36:P36)-'03_Multi_Horizon_Results'!D20 | E35: =SUM('04_Annual_Calculations'!B36:U36)-'03_Multi_Horizon_Results'!E20 | F35: =SUM('04_Annual_Calculations'!B36:AE36)-'03_Multi_Horizon_Results'!F20
A36: ESD property tax — gross (pre-exemption) | B36: =SUM('04_Annual_Calculations'!B37:F37) | C36: =SUM('04_Annual_Calculations'!B37:K37) | D36: =SUM('04_Annual_Calculations'!B37:P37) | E36: =SUM('04_Annual_Calculations'!B37:U37) | F36: =SUM('04_Annual_Calculations'!B37:AE37)
A37: ESD property tax — net of exemptions | B37: ='03_Multi_Horizon_Results'!B21 | C37: ='03_Multi_Horizon_Results'!C21 | D37: ='03_Multi_Horizon_Results'!D21 | E37: ='03_Multi_Horizon_Results'!E21 | F37: ='03_Multi_Horizon_Results'!F21
A38: ESD revenue reduced by exemptions | B38: =SUM('04_Annual_Calculations'!B37:F37)-'03_Multi_Horizon_Results'!B21 | C38: =SUM('04_Annual_Calculations'!B37:K37)-'03_Multi_Horizon_Results'!C21 | D38: =SUM('04_Annual_Calculations'!B37:P37)-'03_Multi_Horizon_Results'!D21 | E38: =SUM('04_Annual_Calculations'!B37:U37)-'03_Multi_Horizon_Results'!E21 | F38: =SUM('04_Annual_Calculations'!B37:AE37)-'03_Multi_Horizon_Results'!F21
A40: LARGE CAPITAL ITEMS INCLUDED IN THIS SCENARIO (from Capital Items inputs)
A41: Item | B41: Quantity | C41: Unit | D41: Payer | E41: Included? | F41: Cost treatment | G41: 10-yr cost in NET
A42: =Capital_Items!A4 | B42: =Capital_Items!L4 | C42: =Capital_Items!D4 | D42: =Capital_Items!Q4 | E42: =Capital_Items!R4 | F42: =Capital_Items!S4 | G42: =Capital_Items!Y4+Capital_Items!AD4
A43: =Capital_Items!A5 | B43: =Capital_Items!L5 | C43: =Capital_Items!D5 | D43: =Capital_Items!Q5 | E43: =Capital_Items!R5 | F43: =Capital_Items!S5 | G43: =Capital_Items!Y5+Capital_Items!AD5
A44: =Capital_Items!A6 | B44: =Capital_Items!L6 | C44: =Capital_Items!D6 | D44: =Capital_Items!Q6 | E44: =Capital_Items!R6 | F44: =Capital_Items!S6 | G44: =Capital_Items!Y6+Capital_Items!AD6
A45: =Capital_Items!A7 | B45: =Capital_Items!L7 | C45: =Capital_Items!D7 | D45: =Capital_Items!Q7 | E45: =Capital_Items!R7 | F45: =Capital_Items!S7 | G45: =Capital_Items!Y7+Capital_Items!AD7
A46: =Capital_Items!A8 | B46: =Capital_Items!L8 | C46: =Capital_Items!D8 | D46: =Capital_Items!Q8 | E46: =Capital_Items!R8 | F46: =Capital_Items!S8 | G46: =Capital_Items!Y8+Capital_Items!AD8
A47: =Capital_Items!A9 | B47: =Capital_Items!L9 | C47: =Capital_Items!D9 | D47: =Capital_Items!Q9 | E47: =Capital_Items!R9 | F47: =Capital_Items!S9 | G47: =Capital_Items!Y9+Capital_Items!AD9
A48: =Capital_Items!A10 | B48: =Capital_Items!L10 | C48: =Capital_Items!D10 | D48: =Capital_Items!Q10 | E48: =Capital_Items!R10 | F48: =Capital_Items!S10 | G48: =Capital_Items!Y10+Capital_Items!AD10
A49: =Capital_Items!A11 | B49: =Capital_Items!L11 | C49: =Capital_Items!D11 | D49: =Capital_Items!Q11 | E49: =Capital_Items!R11 | F49: =Capital_Items!S11 | G49: =Capital_Items!Y11+Capital_Items!AD11
A50: =Capital_Items!A12 | B50: =Capital_Items!L12 | C50: =Capital_Items!D12 | D50: =Capital_Items!Q12 | E50: =Capital_Items!R12 | F50: =Capital_Items!S12 | G50: =Capital_Items!Y12+Capital_Items!AD12
A51: =Capital_Items!A13 | B51: =Capital_Items!L13 | C51: =Capital_Items!D13 | D51: =Capital_Items!Q13 | E51: =Capital_Items!R13 | F51: =Capital_Items!S13 | G51: =Capital_Items!Y13+Capital_Items!AD13
A52: =Capital_Items!A14 | B52: =Capital_Items!L14 | C52: =Capital_Items!D14 | D52: =Capital_Items!Q14 | E52: =Capital_Items!R14 | F52: =Capital_Items!S14 | G52: =Capital_Items!Y14+Capital_Items!AD14
A53: =Capital_Items!A15 | B53: =Capital_Items!L15 | C53: =Capital_Items!D15 | D53: =Capital_Items!Q15 | E53: =Capital_Items!R15 | F53: =Capital_Items!S15 | G53: =Capital_Items!Y15+Capital_Items!AD15
... A66: =Capital_Items!A28 | B66: =Capital_Items!L28 | C66: =Capital_Items!D28 | D66: =Capital_Items!Q28 | E66: =Capital_Items!R28 | F66: =Capital_Items!S28 | G66: =Capital_Items!Y28+Capital_Items!AD28
A67: Total included infrastructure (10-yr): City | G67: =Capital_Items!Y34
A68: Total included infrastructure (10-yr): ESD | G68: =Capital_Items!AD35

Sheet SOURCES
A1: Source Log
A3: Input | B3: Value | C3: Source / Basis | D3: Confidence | E3: Last Verified | F3: Staff? | G3: City Attorney? | H3: Comptroller? | I3: Notes
A4: Pool rate (combined-area) | B4: ='00_Inputs_Dashboard'!$B$20 | C4: Comptroller combined-area code 6008609 1.5%; 2.0% local cap | D4: High | E4: 2026-05-14 | F4: No | G4: No | H4: Yes | I4: Tex Tax Code Ch. 321
A5: Sealy current population | B5: ='00_Inputs_Dashboard'!$B$11 | C5: Sealy HB1378 §140.008 FY25 actual | D5: High | E5: 2026-05-14 (FY25 ACFR) | F5: No | G5: No | H5: No | I5: Sealy HB1378 §140.008 FY25 (city-published). CROSS-VALIDATED via FY25 ACFR statistical section: 7,553 (2025), 7,243 (2024), 7,059 (2023), 6,839 (2022). Source: US Census ACS 5-yr.
A6: Population CAGR | B6: ='00_Inputs_Dashboard'!$B$12 | C6: Sealy HB1378 5-yr actual 6,450 → 7,553 | D6: High | E6: 2026-05-14 (FY25 ACFR) | F6: Yes | G6: No | H6: No | I6: Sealy HB1378 5-yr actual. CROSS-VALIDATED: FY25 ACFR 3-yr CAGR = (7,553/6,839)^(1/3)-1 = 3.36%. Model uses 3.2% — conservative.
A7: Current annual sales-tax pool | B7: ='00_Inputs_Dashboard'!$B$13 | C7: FY26 Adopted Budget; cross-validated FY25 actual $4.0M (Comptroller 53-mo); FY26 YTD pacing | D7: High | E7: 2026-05-14 (FY25 ACFR) | F7: Yes | G7: No | H7: Yes | I7: FY26 Adopted Budget $3.7M. CROSS-VALIDATED: FY25 ACFR GF sales tax $2,756,699 (1.0% slice); implied 1.5% combined pool = $4.14M. Calendar 2025 Comptroller cash = $4.02M. Model conservative.
A8: Sales-tax pool CAGR | B8: ='00_Inputs_Dashboard'!$B$14 | C8: Sealy 12-yr Comptroller actual (6.5% long-run); trailing 3-yr is 9.4%; March 2026 YoY +39% | D8: High | E8: 2026-05-14 | F8: Yes | G8: No | H8: No | I8: 6.5% = long-run mean. STRESS: trailing 3-yr CAGR is 9.4%; March 2026 YoY +39% (manufacturing-driven). Use 9% high-case sensitivity if needed.
A9: City property tax rate | B9: ='00_Inputs_Dashboard'!$B$21 | C9: Sealy FY26 Ord. 2025-24 $0.37731/$100 | D9: High | E9: 2026-05-14 | F9: No | G9: No | H9: No | I9: Adopted
A10: ESD #2 ad valorem rate | B10: ='00_Inputs_Dashboard'!$B$22 | C10: Current adopted ESD #2 rate: $0.09310/$100 (2026 tax year). FY25 ACFR statistical section confirms historical: 2025=$0.09578, 2024=$0.09480, 2023=$0.099558. | D10: High | E10: 2026-05-15 | F10: No | G10: No | H10: No | I10: $0.09310 = 2026 current adopted rate (SB625 2026 filing entered 2026-02-26; Retreat at Sealy 2026 tax statement Acct 13818001). FY25 ACFR statistical section p.144 confirms 2025=$0.09578, 2024=$0.09480, 2023=$0.099558. Verify locally before public reliance.
A11: Sealy impact fee per LUE | B11: $7,165 | C11: Sealy 2018 Strand Impact Fee Study (water+sewer adopted) | D11: High | E11: 2026-05-14 | F11: No | G11: No | H11: No | I11: Adopted by Council 2018
A12: MFR AV per unit | B12: $80K/unit | C12: Retreat at Sealy actual ($19.89M/250u/11.3ac) | D12: High | E12: 2026-05-14 | F12: No | G12: No | H12: No | I12: Tax statement source
A13: Sealy FY26 fiscal-strength context | B13: 403 operating days @ Mar 31, 2026 | C13: 5/19/2026 council packet Financial Report (Matura) | D13: High | E13: 2026-05-14 | F13: No | G13: No | H13: No | I13: City at 403 days operating reserve, up from 239 in Oct 2025. Revenue at 85.52% of FY26 budget at 50% of fiscal year. Property tax 104.57% collected, sales tax 99.68%. NEGOTIATION CONTEXT for ESD #2 ILA.
A14: Sealy FY25 GF revenue actual | B14: $10,300,940 | C14: Sealy FY25 ACFR (acfr_fy2025.pdf, 185pp) | D14: High | E14: 2026-05-14 | F14: No | G14: No | H14: No | I14: Cross-validation input. FY26 budgeted GF revenue is conservative at approximately $8.9M (implied from 85.52% YTD).
A15: City PT rate FY25 vs FY26 trajectory | B15: FY26=$0.37731, FY25=$0.31091 | C15: FY25 ACFR statistical section (FY25 op rate $0.196930 + debt service $0.11398) | D15: High | E15: 2026-05-14 | F15: No | G15: No | H15: No | I15: City PT rate rose 21% YoY (FY25→FY26) tied to new $20M CO issuance. Higher PT revenue strengthens city fiscal position; relevant negotiation context.
A16: Walmart taxpayer concentration risk | B16: $130.6M = 14.8% of city AV | C16: FY25 ACFR principal taxpayer list (Wal-Mart Stores East US07036 #2 $74.3M + Wal-Mart Transportation #5 $28.6M + Wal-Mart Stores East US07036 #6 $27.7M) | D16: High | E16: 2026-05-14 | F16: No | G16: No | H16: No | I16: Top 10 taxpayers = 43.89% of $783.9M total AV. Walmart entities alone = 14.8%. Sealy's tax base is concentrated; ILA terms should account for downside risk if Walmart DC contracts.
A17: Sealy FY25 total city AV | B17: $783,888,923 | C17: FY25 ACFR statistical section | D17: High | E17: 2026-05-14 | F17: No | G17: No | H17: No | I17: Total city AV (governmental purposes). Stable around $780-800M last 4 years despite taxpayer churn (BAE left 2016-2025, Hailiang+Walmart+Gamechange added). AV per capita actually declined 2022-2025 due to population growth outpacing AV growth.
A18: Sealy FY25 debt issuance | B18: $20.7M (CO + premium) | C18: FY25 ACFR statistical section + debt service detail | D18: High | E18: 2026-05-14 | F18: No | G18: No | H18: No | I18: Sealy issued $19.91M in new COs + $807K premium = $20.72M proceeds in FY25. Drives the FY26 PT rate increase to $0.37731. Capital projects expanding — context for fiscal-strength position.
A19: Industrial AV per acre validation | B19: $750K/ac (model) | C19: Sika Corp FY25 ACFR: $18.72M / ~25ac developed = $749K/ac. Hailiang Copper $87.75M (#1 taxpayer). | D19: High (SOLID) | E19: 2026-05-14 (FY25 ACFR) | F19: No | G19: No | H19: No | I19: Triple-validated: Sika exact match. Hailiang at $878K/ac (~100ac) is higher-end. Model assumption sits within observed range.
A20: MFR AV per unit validation | B20: $80K/unit (model) | C20: Retreat at Sealy FY25 ACFR: $19.3M / ~250 units = $77K/unit | D20: High (SOLID) | E20: 2026-05-14 (FY25 ACFR) | F20: No | G20: No | H20: No | I20: Within 4% of model assumption. Validated.
A21: EDC retention (carve-out) | B21: ='00_Inputs_Dashboard'!$B$6 | C21: Tex LGC Ch. 505 Type B / Sealy EDC. 0% is a MODELED ASSUMPTION ONLY. | D21: Low | E21: 2026-05-14 | F21: Yes | G21: Yes | H21: No | I21: Modeled assumption only; subject to City Attorney confirmation. Do NOT treat as legally resolved.
A22: Project capture rate | B22: ='00_Inputs_Dashboard'!$B$16 | C22: Planning benchmark; per-project adjustable | D22: Low | E22: 2026-05-14 | F22: Yes | G22: No | H22: No | I22: Per-project override
A23: City reserve % | B23: ='00_Inputs_Dashboard'!$B$25 | C23: Planning benchmark; applied to City basis | D23: Low | E23: 2026-05-14 | F23: Yes | G23: No | H23: No | I23: Adjust per policy
A24: ESD reserve % | B24: ='00_Inputs_Dashboard'!$B$26 | C24: Planning benchmark; applied to ESD basis | D24: Low | E24: 2026-05-14 | F24: No | G24: No | H24: No | I24: ESD-side
A25: Online spend per occupied household | B25: ='00_Inputs_Dashboard'!$B$34 | C25: BASE $6,000/HH; Conservative $4K; High $8K | D25: Low | E25: 2026-05-14 | F25: Yes | G25: No | H25: No | I25: Low-confidence planning assumption; sensitivity $4K-$8K
A26: Online taxable share | B26: ='00_Inputs_Dashboard'!$B$35 | C26: Base-case assumption shown on Inputs Dashboard; depends on marketplace facilitator scope | D26: Low | E26: 2026-05-14 | F26: Yes | G26: Yes | H26: Yes | I26: Low-confidence; depends on marketplace facilitator scope
A27: Online local capture factor | B27: ='00_Inputs_Dashboard'!$B$36 | C27: BASE 75%; ship-to address mapping to combined area | D27: Low | E27: 2026-05-14 | F27: Yes | G27: No | H27: Yes | I27: Low-confidence; depends on ship-to address accuracy
A28: Online spend growth rate | B28: ='00_Inputs_Dashboard'!$B$37 | C28: Annual real growth 4%/yr | D28: Low | E28: 2026-05-14 | F28: Yes | G28: No | H28: No | I28: Low-confidence forward projection
A29: Infrastructure takeoff factors | B29: See 12_Takeoff_Assumptions | C29: Planning benchmarks; not engineer-certified; informational unless linked | D29: Low | E29: 2026-05-15 | F29: Yes | G29: No | H29: No | I29: Water/sewer/street/hydrant/park/police/ESD factors require Public Works, engineer, ESD, and staff validation before public reliance.
A30: Infrastructure takeoff costs | B30: See 11_Infrastructure_Takeoff | C30: Unit-cost planning allowances; not included in City/ESD NET unless explicitly linked | D30: Low | E30: 2026-05-15 | F30: Yes | G30: No | H30: No | I30: Takeoff costs are displayed as informational physical exposure only to avoid double-counting with existing opex/capital logic.
A31: AV growth CAGR | B31: ='00_Inputs_Dashboard'!$B$15 | C31: Sealy HB1378-derived; 5-yr was 7.3% | D31: Medium | E31: 2026-05-14 | F31: Yes | G31: No | H31: No | I31: Forward assumption
A32: General opex inflation | B32: ='00_Inputs_Dashboard'!$B$23 | C32: TML benchmark 2.5% | D32: Medium | E32: 2026-05-14 | F32: Yes | G32: No | H32: No | I32: Recurring
A33: Capital construction inflation | B33: ='00_Inputs_Dashboard'!$B$24 | C33: Maxxbuilders TX 2024-2026 (3-6% range) | D33: Medium | E33: 2026-05-14 | F33: Yes | G33: No | H33: No | I33: NEW v3.4 lever
A34: SFR occupancy rate | B34: ='00_Inputs_Dashboard'!$B$30 | C34: Planning benchmark 95% | D34: Medium | E34: 2026-05-14 | F34: Yes | G34: No | H34: No | I34: Sealy SF benchmark
A35: MFR occupancy rate | B35: ='00_Inputs_Dashboard'!$B$31 | C35: MFR lease-up steady state 92% | D35: Medium | E35: 2026-05-14 | F35: Yes | G35: No | H35: No | I35: Retreat at Sealy
A36: SFR household size | B36: ='00_Inputs_Dashboard'!$B$32 | C36: Sealy SF benchmark 2.7 | D36: Medium | E36: 2026-05-14 | F36: No | G36: No | H36: No | I36: Census-derived
A37: MFR household size | B37: ='00_Inputs_Dashboard'!$B$33 | C37: Retreat at Sealy 2.1 | D37: Medium | E37: 2026-05-14 | F37: No | G37: No | H37: No | I37: MFR benchmark
A38: Industrial AV per acre | B38: $750K/ac | C38: Sika BPP / Hailiang Copper observed range | D38: Medium | E38: 2026-05-14 | F38: Yes | G38: No | H38: No | I38: Per spec cfe57b56 calibration
A39: City marginal opex per resident validation | B39: $680/resident SFR (model) | C39: FY25 ACFR departmental detail: scaling departments (Police $445/cap + Streets $83 + Parks $71 + Planning $69 + Building $43 + Court $45 + 50% of Capital $90) = $846/cap fully-loaded × 80% marginal = $677/cap | D39: Medium-High (SOLID-FY25) | E39: 2026-05-14 (FY25 ACFR) | F39: Yes | G39: No | H39: No | I39: Validated within $3 of FY25 actual at 80% marginal share. Was 'peer-derived (Schertz/Pflugerville via Verdunity)' — now anchored to Sealy FY25 ACFR. Per-acre commercial/industrial opex still planning-level. PEER METHOD: ICMA/TischlerBise per-capita LOS approach; Enumclaw WA FTE-per-capita annexation modeling corroborate the per-resident cost driver.
A40: City General Fund share | B40: 0.5 | C40: User-entered allocation percentage; no preferred split implied | D40: n/a | E40: 2026-05-14 | F40: No | G40: No | H40: No | I40: Modeling assumption
A41: ESD share | B41: 0.5 | C41: User-entered allocation percentage; City + ESD must equal 100% | D41: n/a | E41: 2026-05-14 | F41: No | G41: No | H41: No | I41: Modeling assumption
A42: Reserve basis includes capital? | B42: ='00_Inputs_Dashboard'!$B$27 | C42: Spec #13 Option B — (opex + capital) × pct | D42: n/a | E42: 2026-05-14 | F42: Yes | G42: No | H42: No | I42: Toggle
A43: Online use-tax toggle | B43: ='00_Inputs_Dashboard'!$B$38 | C43: 1=include / 0=exclude (Test 11/12) | D43: n/a | E43: 2026-05-14 | F43: No | G43: No | H43: No | I43: Toggle
A44: Sealy FY25 audit — material weakness | B44: Internal control over financial statement disclosure | C44: BrooksWatson & Co. FY25 audit, March 28 2026 letter | D44: n/a | E44: 2026-05-14 | F44: Yes | G44: No | H44: No | I44: Common finding for cities of this size (Brooks Watson prepared draft + material adjustments). Not a fraud/loss finding. Doesn't change model inputs.
A45: ESD #2 ILA — active in negotiation | B45: Exec session item J.a on 5/19/2026 agenda | C45: 5/19/2026 council packet, agenda item J.a (public) | D45: n/a | E45: 2026-05-14 | F45: No | G45: Yes | H45: No | I45: Active negotiation. Public agenda confirms ILA + Utility Billing + Lease are being discussed. Closed-session substance NOT in model.
A47: — External FIA peer validation (added v6.1, 2026-05-28; sources in 04_Research/FIA_External_Studies_2026-05-28) —
A48: Method validation — marginal/case-study | B48: v6 uses case-study/marginal-cost drivers (per-acre/resident/unit) | C48: TischlerBise specializes in case-study/marginal-cost over 1,000+ FIAs; ICMA MIS Report (Tischler) recommends it; Lincoln (Kotval-Mullin 2006) = 'classic marginal cost approach' | D48: Peer-sourced | E48: 2026-05-28 | F48: No | G48: No | H48: No | I48: Rebuts 'black-box / non-standard method' criticism.
A49: Method validation — open spreadsheet | B49: v6 is open, unprotected Excel with visible formulas | C49: TischlerBise FISCALS: 'designed in a spreadsheet environment, without protected cells and formulas' | D49: Peer-sourced | E49: 2026-05-28 | F49: No | G49: No | H49: No | I49: Leading FIA firm builds models exactly this way.
A50: Structure — scenarios/cumulative/break-even/zones | B50: v6 scenario builder + 5/10/15/20/30-yr horizons + break-even + per-project rows | C50: TischlerBise Growth Alternatives (cumulative 10-20 yr); Bryan RELLIS (3 scenarios, 4 FAZs, break-even); Verdunity DFIA/LUFA (10-40 yr) | D50: Peer-sourced | E50: 2026-05-28 | F50: No | G50: No | H50: No | I50: v6 30-yr horizon within standard practice range.
A51: Per-acre / value-per-acre dimension | B51: v6 uses per-acre cost AND revenue, not per-capita only | C51: Lincoln: Heikkila-Davis (1997) & Dekel (1995) - per-capita FIA misses spatial/density; Urban3 value/acre; Verdunity LUFA parcel rev/acre | D51: Peer-sourced | E51: 2026-05-28 | F51: No | G51: No | H51: No | I51: Academic basis for the per-acre approach.
A52: Result — residential net-negative | B52: v6: SFR net-negative for City & ESD | C52: COCS 150+ studies/26 states/~40 yrs: residential ratio >1.0; Chatham County NC 2025 residential $1.18/$1; Verdunity TX (sprawl SFR weakest per acre) | D52: Peer-sourced | E52: 2026-05-28 | F52: No | G52: No | H52: No | I52: COCS = existing pattern, not a forward projection (cite honestly).
A53: Result — commercial/industrial net-positive | B53: v6: retail/logistics/manufacturing net-positive | C53: COCS commercial/industrial ratio <1.0; Chatham 2025 commercial $0.29/$1; Castle Pines 2026 commercial-positive; SGA ~10x rev/acre (advocacy, paired w/ Urban3) | D53: Peer-sourced | E53: 2026-05-28 | F53: No | G53: No | H53: No | I53: Matches v6 directional result.
A54: Compact-vs-sprawl infra savings | B54: Informational context (not a base-case input) | C54: SGA Building Better Budgets ~38% lower upfront infra (advocacy meta-finding) - PAIRED with Verdunity TX unfunded-street liabilities (neutral) | D54: Peer-sourced (advocacy, paired) | E54: 2026-05-28 | F54: No | G54: No | H54: No | I54: Cite moderately; always pair w/ a neutral source.
A55: Peer unfunded street liabilities (TX) | B55: Pilot Point $52M; Crowley $127M; Bastrop $144M; Pflugerville $632M; New Braunfels $801M; Brownsville $1.3B | C55: Verdunity TX fiscal-analysis portfolio | D55: Peer-sourced | E55: 2026-05-28 | F55: No | G55: No | H55: No | I55: Neutral evidence that growth carries long-term infra liabilities.
A56: Triangulation defense | B56: 3 independent methods converge | C56: Castle Pines CO Crowsnest 2026: city-staff + TischlerBise dept-level + THK cost-per-acre all net-positive (~$112M/20yr) | D56: Peer-sourced | E56: 2026-05-28 | F56: No | G56: No | H56: No | I56: Gold-standard defensibility: different methods, same direction.
A57: Macro fiscal context | B57: Public safety ~60% of GF; optimism 45% (was 64%) | C57: NLC City Fiscal Conditions 2025 (40th annual; 263 cities) | D57: Peer-sourced | E57: 2026-05-28 | F57: No | G57: No | H57: No | I57: Supports 'fire stays with ESD' frame + capture-favorable-terms-now.
A58: Legal mechanism — city/ESD sales-tax allocation | B58: ILA allocates the combined-area local sales tax | C58: TML Municipal Annexation in TX 2025: Tex. H&S Code 775.0754 authorizes allocation agreement; first-in-time favors existing ESD; neither party compelled | D58: Peer-sourced | E58: 2026-05-28 | F58: No | G58: Yes | H58: No | I58: Confirms the SPA+ILA vehicle (Sec. 43.0751 SPA) the analysis assumes.
A59: Closest peer FIA — Bryan RELLIS | B59: Bryan TX annexation FIA adjacent to TX A&M RELLIS | C59: TischlerBise (KendigKeast Team): 3 scenarios, 4 fiscal-analysis zones, cumulative net, break-even - structurally identical to v6 | D59: Peer-sourced | E59: 2026-05-28 | F59: No | G59: No | H59: No | I59: Full report not public; TPIA deferred per Bobby (2026-05-28).
A61: SALES-TAX SOURCING (Texas Comptroller Pub. 94-105) — how each revenue line is sourced
A62: Retail / commercial at the site | C62: ORIGIN — local sales tax is consummated at the seller's place of business. An annexed retail center's tax flows to the Sealy/ESD combined-area pool (code 6008609) regardless of where shoppers live.
A63: Residential | C63: A home generates NO sales tax itself. Resident in-store spending is origin-sourced to wherever the store is (leaks out unless they shop in Sealy). Only residents' online/delivery purchases shipped to the Sealy address generate local USE tax for Sealy — captured via the online use-tax line.
A64: Online / Amazon / marketplace | C64: DESTINATION (ship-to address). Marketplace providers (Amazon, eBay, Walmart Mktp, Etsy) and remote sellers source local tax to delivery address — not shipment origin, not manufacturer. Remote sellers may elect a single 1.75% local rate; marketplaces cannot.
A65: Manufacturing / distribution warehouse | C65: Generally LITTLE-TO-NO local sales tax. Manufacturers sell wholesale/for-resale (resale exemption) or ship interstate; a warehouse is explicitly NOT a 'place of business' (94-105), so shipping from it does not originate local tax. These are PROPERTY-TAX plays. Modeled at $0 sales by default; manual override only if a facility truly qualifies as an order-receipt place of business.
A66: Legal-uncertainty flag | C66: The in-state 'where an order is received' sourcing rule (Comptroller Rule 3.334) is under a court injunction (Dec 2024) and not being enforced — another reason to keep the online local-capture factor conservative.
A67: Combined area | C67: Sealy + ESD #2 sit in combined-area code 6008609; the Comptroller holds the rate at 2% and splits it between the two — this is the pool the model allocates.
A69: Peer-study benchmarks & methodology validation: see hidden tab '13_Peer_Benchmarks' (unhide via right-click).

Sheet Scenarios
A1: Scenario Builder — one row per project. Active rows feed model.
A2: # | B2: Project Name | C2: Active? | D2: Development Type | E2: Quantity Type | F2: Quantity | G2: Acres/Unit (lookup) | H2: Manual Acres Override | I2: Final Acres | J2: Start Year | K2: Buildout Years | L2: Capture Rate | M2: Captured Acres | N2: AV basis (lookup) | O2: Manual AV Override | P2: Final AV ($) | Q2: Sales basis (lookup) | R2: Manual Sales Override | S2: Final Annual Taxable Sales ($) | T2: Captured Building SqFt | U2: Captured Residential Units | V2: Captured Residents | W2: LUE Count | X2: Impact Fee/LUE ($) | Y2: Manual Impact Fee Override | Z2: Final Impact Fee ($) | AA2: Manual City Opex Override (annual $) | AB2: Manual ESD Opex Override (annual $) | AC2: Notes / Source | AD2: City Taxable AV ($) | AE2: ESD Taxable AV ($) | AF2: City Industrial Taxable AV ($) | AG2: ESD Industrial Taxable AV ($)
A3: 1 | B3: =INPUTS!$A$54 | C3: =(INPUTS!$B$54="Yes") | D3: =INPUTS!$C$54 | E3: =INPUTS!$D$54 | F3: =INPUTS!$E$54 | G3: =IFERROR(VLOOKUP(D3,'02_Type_Assumptions'!$A$4:$Z$18,3,FALSE()),0) | H3: =IF(INPUTS!$F$54="","",INPUTS!$F$54) | I3: =IF(ISNUMBER(H3),H3,IF(LOWER(E3)="sqft",IFERROR(F3/43560/'00_Inputs_Dashboard'!$B$51,0),IF(LOWER(E3)="acres",IFERROR(F3,0),IFERROR(F3*G3,0)))) | J3: =INPUTS!$G$54 | K3: =INPUTS!$H$54 | L3: =INPUTS!$I$54 | M3: =I3*L3 | N3: =IFERROR(IF(LOWER(E3)="rooms",VLOOKUP(D3,'02_Type_Assumptions'!$A$4:$Z$18,6,FALSE()),IF(LOWER(E3)="acres",VLOOKUP(D3,'02_Type_Assumptions'!$A$4:$Z$18,5,FALSE()),VLOOKUP(D3,'02_Type_Assumptions'!$A$4:$Z$18,4,FALSE()))),0) | P3: =IF(ISNUMBER(O3),O3,IF(LOWER(E3)="rooms",F3*N3*L3,IF(LOWER(E3)="acres",M3*N3,IF(LOWER(E3)="sqft",M3*VLOOKUP(D3,'02_Type_Assumptions'!$A$4:$Z$18,5,FALSE()),F3*N3*L3)))) | Q3: =IFERROR(IF(VLOOKUP(D3,'02_Type_Assumptions'!$A$4:$Z$18,23,FALSE())="per_acre",VLOOKUP(D3,'02_Type_Assumptions'!$A$4:$Z$18,8,FALSE()),0),0) | S3: =IF(ISNUMBER(R3),R3*L3,M3*Q3) | T3: =IF(LOWER(E3)="sqft",F3*L3,M3*IFERROR(VLOOKUP(D3,'02_Type_Assumptions'!$A$4:$Z$18,9,FALSE()),0)) | U3: =IF(OR(LOWER(E3)="lots",LOWER(E3)="units"),F3*L3,0) | V3: =U3*IFERROR(VLOOKUP(D3,'02_Type_Assumptions'!$A$4:$Z$18,21,FALSE()),0) | W3: =IFERROR(IF(OR(LOWER(E3)="lots",LOWER(E3)="units",LOWER(E3)="rooms"),F3*L3*VLOOKUP(D3,'02_Type_Assumptions'!$A$4:$Z$18,10,FALSE()),IF(LOWER(E3)="acres",M3*VLOOKUP(D3,'02_Type_Assumptions'!$A$4:$Z$18,11,FALSE()),IF(LOWER(E3)="sqft",T3/1000*VLOOKUP(D3,'02_Type_Assumptions'!$A$4:$Z$18,12,FALSE()),0))),0) | X3: =INPUTS!$D$50 | Z3: =IF(ISNUMBER(Y3),Y3,W3*X3) | AC3: Active sample row; edit or deactivate as needed. | AD3: =IFERROR($P3*VLOOKUP($D3,'02_Type_Assumptions'!$A$4:$AC$18,28,FALSE()),$P3) | AE3: =IFERROR($P3*VLOOKUP($D3,'02_Type_Assumptions'!$A$4:$AC$18,29,FALSE()),$P3) | AF3: =IF(IFERROR(VLOOKUP($D3,'02_Type_Assumptions'!$A$4:$AC$18,27,FALSE()),"")="Industrial",$AD3,0) | AG3: =IF(IFERROR(VLOOKUP($D3,'02_Type_Assumptions'!$A$4:$AC$18,27,FALSE()),"")="Industrial",$AE3,0)
A4: 2 | B4: =INPUTS!$A$55 | C4: =(INPUTS!$B$55="Yes") | D4: =INPUTS!$C$55 | E4: =INPUTS!$D$55 | F4: =INPUTS!$E$55 | G4: =IFERROR(VLOOKUP(D4,'02_Type_Assumptions'!$A$4:$Z$18,3,FALSE()),0) | H4: =IF(INPUTS!$F$55="","",INPUTS!$F$55) | I4: =IF(ISNUMBER(H4),H4,IF(LOWER(E4)="sqft",IFERROR(F4/43560/'00_Inputs_Dashboard'!$B$51,0),IF(LOWER(E4)="acres",IFERROR(F4,0),IFERROR(F4*G4,0)))) | J4: =INPUTS!$G$55 | K4: =INPUTS!$H$55 | L4: =INPUTS!$I$55 | M4: =I4*L4 | N4: =IFERROR(IF(LOWER(E4)="rooms",VLOOKUP(D4,'02_Type_Assumptions'!$A$4:$Z$18,6,FALSE()),IF(LOWER(E4)="acres",VLOOKUP(D4,'02_Type_Assumptions'!$A$4:$Z$18,5,FALSE()),VLOOKUP(D4,'02_Type_Assumptions'!$A$4:$Z$18,4,FALSE()))),0) | P4: =IF(ISNUMBER(O4),O4,IF(LOWER(E4)="rooms",F4*N4*L4,IF(LOWER(E4)="acres",M4*N4,IF(LOWER(E4)="sqft",M4*VLOOKUP(D4,'02_Type_Assumptions'!$A$4:$Z$18,5,FALSE()),F4*N4*L4)))) | Q4: =IFERROR(IF(VLOOKUP(D4,'02_Type_Assumptions'!$A$4:$Z$18,23,FALSE())="per_acre",VLOOKUP(D4,'02_Type_Assumptions'!$A$4:$Z$18,8,FALSE()),0),0) | S4: =IF(ISNUMBER(R4),R4*L4,M4*Q4) | T4: =IF(LOWER(E4)="sqft",F4*L4,M4*IFERROR(VLOOKUP(D4,'02_Type_Assumptions'!$A$4:$Z$18,9,FALSE()),0)) | U4: =IF(OR(LOWER(E4)="lots",LOWER(E4)="units"),F4*L4,0) | V4: =U4*IFERROR(VLOOKUP(D4,'02_Type_Assumptions'!$A$4:$Z$18,21,FALSE()),0) | W4: =IFERROR(IF(OR(LOWER(E4)="lots",LOWER(E4)="units",LOWER(E4)="rooms"),F4*L4*VLOOKUP(D4,'02_Type_Assumptions'!$A$4:$Z$18,10,FALSE()),IF(LOWER(E4)="acres",M4*VLOOKUP(D4,'02_Type_Assumptions'!$A$4:$Z$18,11,FALSE()),IF(LOWER(E4)="sqft",T4/1000*VLOOKUP(D4,'02_Type_Assumptions'!$A$4:$Z$18,12,FALSE()),0))),0) | X4: =INPUTS!$D$50 | Z4: =IF(ISNUMBER(Y4),Y4,W4*X4) | AC4: Test case — large-scale SF buildout. | AD4: =IFERROR($P4*VLOOKUP($D4,'02_Type_Assumptions'!$A$4:$AC$18,28,FALSE()),$P4) | AE4: =IFERROR($P4*VLOOKUP($D4,'02_Type_Assumptions'!$A$4:$AC$18,29,FALSE()),$P4) | AF4: =IF(IFERROR(VLOOKUP($D4,'02_Type_Assumptions'!$A$4:$AC$18,27,FALSE()),"")="Industrial",$AD4,0) | AG4: =IF(IFERROR(VLOOKUP($D4,'02_Type_Assumptions'!$A$4:$AC$18,27,FALSE()),"")="Industrial",$AE4,0)
A5: 3 | B5: =INPUTS!$A$56 | C5: =(INPUTS!$B$56="Yes") | D5: =INPUTS!$C$56 | E5: =INPUTS!$D$56 | F5: =INPUTS!$E$56 | G5: =IFERROR(VLOOKUP(D5,'02_Type_Assumptions'!$A$4:$Z$18,3,FALSE()),0) | H5: =IF(INPUTS!$F$56="","",INPUTS!$F$56) | I5: =IF(ISNUMBER(H5),H5,IF(LOWER(E5)="sqft",IFERROR(F5/43560/'00_Inputs_Dashboard'!$B$51,0),IF(LOWER(E5)="acres",IFERROR(F5,0),IFERROR(F5*G5,0)))) | J5: =INPUTS!$G$56 | K5: =INPUTS!$H$56 | L5: =INPUTS!$I$56 | M5: =I5*L5 | N5: =IFERROR(IF(LOWER(E5)="rooms",VLOOKUP(D5,'02_Type_Assumptions'!$A$4:$Z$18,6,FALSE()),IF(LOWER(E5)="acres",VLOOKUP(D5,'02_Type_Assumptions'!$A$4:$Z$18,5,FALSE()),VLOOKUP(D5,'02_Type_Assumptions'!$A$4:$Z$18,4,FALSE()))),0) | P5: =IF(ISNUMBER(O5),O5,IF(LOWER(E5)="rooms",F5*N5*L5,IF(LOWER(E5)="acres",M5*N5,IF(LOWER(E5)="sqft",M5*VLOOKUP(D5,'02_Type_Assumptions'!$A$4:$Z$18,5,FALSE()),F5*N5*L5)))) | Q5: =IFERROR(IF(VLOOKUP(D5,'02_Type_Assumptions'!$A$4:$Z$18,23,FALSE())="per_acre",VLOOKUP(D5,'02_Type_Assumptions'!$A$4:$Z$18,8,FALSE()),0),0) | S5: =IF(ISNUMBER(R5),R5*L5,M5*Q5) | T5: =IF(LOWER(E5)="sqft",F5*L5,M5*IFERROR(VLOOKUP(D5,'02_Type_Assumptions'!$A$4:$Z$18,9,FALSE()),0)) | U5: =IF(OR(LOWER(E5)="lots",LOWER(E5)="units"),F5*L5,0) | V5: =U5*IFERROR(VLOOKUP(D5,'02_Type_Assumptions'!$A$4:$Z$18,21,FALSE()),0) | W5: =IFERROR(IF(OR(LOWER(E5)="lots",LOWER(E5)="units",LOWER(E5)="rooms"),F5*L5*VLOOKUP(D5,'02_Type_Assumptions'!$A$4:$Z$18,10,FALSE()),IF(LOWER(E5)="acres",M5*VLOOKUP(D5,'02_Type_Assumptions'!$A$4:$Z$18,11,FALSE()),IF(LOWER(E5)="sqft",T5/1000*VLOOKUP(D5,'02_Type_Assumptions'!$A$4:$Z$18,12,FALSE()),0))),0) | X5: =INPUTS!$D$50 | Z5: =IF(ISNUMBER(Y5),Y5,W5*X5) | AC5: Test case — strip retail anchor. | AD5: =IFERROR($P5*VLOOKUP($D5,'02_Type_Assumptions'!$A$4:$AC$18,28,FALSE()),$P5) | AE5: =IFERROR($P5*VLOOKUP($D5,'02_Type_Assumptions'!$A$4:$AC$18,29,FALSE()),$P5) | AF5: =IF(IFERROR(VLOOKUP($D5,'02_Type_Assumptions'!$A$4:$AC$18,27,FALSE()),"")="Industrial",$AD5,0) | AG5: =IF(IFERROR(VLOOKUP($D5,'02_Type_Assumptions'!$A$4:$AC$18,27,FALSE()),"")="Industrial",$AE5,0)
A6: 4 | B6: =INPUTS!$A$57 | C6: =(INPUTS!$B$57="Yes") | D6: =INPUTS!$C$57 | E6: =INPUTS!$D$57 | F6: =INPUTS!$E$57 | G6: =IFERROR(VLOOKUP(D6,'02_Type_Assumptions'!$A$4:$Z$18,3,FALSE()),0) | H6: =IF(INPUTS!$F$57="","",INPUTS!$F$57) | I6: =IF(ISNUMBER(H6),H6,IF(LOWER(E6)="sqft",IFERROR(F6/43560/'00_Inputs_Dashboard'!$B$51,0),IF(LOWER(E6)="acres",IFERROR(F6,0),IFERROR(F6*G6,0)))) | J6: =INPUTS!$G$57 | K6: =INPUTS!$H$57 | L6: =INPUTS!$I$57 | M6: =I6*L6 | N6: =IFERROR(IF(LOWER(E6)="rooms",VLOOKUP(D6,'02_Type_Assumptions'!$A$4:$Z$18,6,FALSE()),IF(LOWER(E6)="acres",VLOOKUP(D6,'02_Type_Assumptions'!$A$4:$Z$18,5,FALSE()),VLOOKUP(D6,'02_Type_Assumptions'!$A$4:$Z$18,4,FALSE()))),0) | P6: =IF(ISNUMBER(O6),O6,IF(LOWER(E6)="rooms",F6*N6*L6,IF(LOWER(E6)="acres",M6*N6,IF(LOWER(E6)="sqft",M6*VLOOKUP(D6,'02_Type_Assumptions'!$A$4:$Z$18,5,FALSE()),F6*N6*L6)))) | Q6: =IFERROR(IF(VLOOKUP(D6,'02_Type_Assumptions'!$A$4:$Z$18,23,FALSE())="per_acre",VLOOKUP(D6,'02_Type_Assumptions'!$A$4:$Z$18,8,FALSE()),0),0) | S6: =IF(ISNUMBER(R6),R6*L6,M6*Q6) | T6: =IF(LOWER(E6)="sqft",F6*L6,M6*IFERROR(VLOOKUP(D6,'02_Type_Assumptions'!$A$4:$Z$18,9,FALSE()),0)) | U6: =IF(OR(LOWER(E6)="lots",LOWER(E6)="units"),F6*L6,0) | V6: =U6*IFERROR(VLOOKUP(D6,'02_Type_Assumptions'!$A$4:$Z$18,21,FALSE()),0) | W6: =IFERROR(IF(OR(LOWER(E6)="lots",LOWER(E6)="units",LOWER(E6)="rooms"),F6*L6*VLOOKUP(D6,'02_Type_Assumptions'!$A$4:$Z$18,10,FALSE()),IF(LOWER(E6)="acres",M6*VLOOKUP(D6,'02_Type_Assumptions'!$A$4:$Z$18,11,FALSE()),IF(LOWER(E6)="sqft",T6/1000*VLOOKUP(D6,'02_Type_Assumptions'!$A$4:$Z$18,12,FALSE()),0))),0) | X6: =INPUTS!$D$50 | Z6: =IF(ISNUMBER(Y6),Y6,W6*X6) | AC6: Test case — Sika-class manufacturing facility. | AD6: =IFERROR($P6*VLOOKUP($D6,'02_Type_Assumptions'!$A$4:$AC$18,28,FALSE()),$P6) | AE6: =IFERROR($P6*VLOOKUP($D6,'02_Type_Assumptions'!$A$4:$AC$18,29,FALSE()),$P6) | AF6: =IF(IFERROR(VLOOKUP($D6,'02_Type_Assumptions'!$A$4:$AC$18,27,FALSE()),"")="Industrial",$AD6,0) | AG6: =IF(IFERROR(VLOOKUP($D6,'02_Type_Assumptions'!$A$4:$AC$18,27,FALSE()),"")="Industrial",$AE6,0)
A7: 5 | B7: =INPUTS!$A$58 | C7: =(INPUTS!$B$58="Yes") | D7: =INPUTS!$C$58 | E7: =INPUTS!$D$58 | F7: =INPUTS!$E$58 | G7: =IFERROR(VLOOKUP(D7,'02_Type_Assumptions'!$A$4:$Z$18,3,FALSE()),0) | H7: =IF(INPUTS!$F$58="","",INPUTS!$F$58) | I7: =IF(ISNUMBER(H7),H7,IF(LOWER(E7)="sqft",IFERROR(F7/43560/'00_Inputs_Dashboard'!$B$51,0),IF(LOWER(E7)="acres",IFERROR(F7,0),IFERROR(F7*G7,0)))) | J7: =INPUTS!$G$58 | K7: =INPUTS!$H$58 | L7: =INPUTS!$I$58 | M7: =I7*L7 | N7: =IFERROR(IF(LOWER(E7)="rooms",VLOOKUP(D7,'02_Type_Assumptions'!$A$4:$Z$18,6,FALSE()),IF(LOWER(E7)="acres",VLOOKUP(D7,'02_Type_Assumptions'!$A$4:$Z$18,5,FALSE()),VLOOKUP(D7,'02_Type_Assumptions'!$A$4:$Z$18,4,FALSE()))),0) | P7: =IF(ISNUMBER(O7),O7,IF(LOWER(E7)="rooms",F7*N7*L7,IF(LOWER(E7)="acres",M7*N7,IF(LOWER(E7)="sqft",M7*VLOOKUP(D7,'02_Type_Assumptions'!$A$4:$Z$18,5,FALSE()),F7*N7*L7)))) | Q7: =IFERROR(IF(VLOOKUP(D7,'02_Type_Assumptions'!$A$4:$Z$18,23,FALSE())="per_acre",VLOOKUP(D7,'02_Type_Assumptions'!$A$4:$Z$18,8,FALSE()),0),0) | S7: =IF(ISNUMBER(R7),R7*L7,M7*Q7) | T7: =IF(LOWER(E7)="sqft",F7*L7,M7*IFERROR(VLOOKUP(D7,'02_Type_Assumptions'!$A$4:$Z$18,9,FALSE()),0)) | U7: =IF(OR(LOWER(E7)="lots",LOWER(E7)="units"),F7*L7,0) | V7: =U7*IFERROR(VLOOKUP(D7,'02_Type_Assumptions'!$A$4:$Z$18,21,FALSE()),0) | W7: =IFERROR(IF(OR(LOWER(E7)="lots",LOWER(E7)="units",LOWER(E7)="rooms"),F7*L7*VLOOKUP(D7,'02_Type_Assumptions'!$A$4:$Z$18,10,FALSE()),IF(LOWER(E7)="acres",M7*VLOOKUP(D7,'02_Type_Assumptions'!$A$4:$Z$18,11,FALSE()),IF(LOWER(E7)="sqft",T7/1000*VLOOKUP(D7,'02_Type_Assumptions'!$A$4:$Z$18,12,FALSE()),0))),0) | X7: =INPUTS!$D$50 | Z7: =IF(ISNUMBER(Y7),Y7,W7*X7) | AC7: Test case — Walmart DC-class logistics. | AD7: =IFERROR($P7*VLOOKUP($D7,'02_Type_Assumptions'!$A$4:$AC$18,28,FALSE()),$P7) | AE7: =IFERROR($P7*VLOOKUP($D7,'02_Type_Assumptions'!$A$4:$AC$18,29,FALSE()),$P7) | AF7: =IF(IFERROR(VLOOKUP($D7,'02_Type_Assumptions'!$A$4:$AC$18,27,FALSE()),"")="Industrial",$AD7,0) | AG7: =IF(IFERROR(VLOOKUP($D7,'02_Type_Assumptions'!$A$4:$AC$18,27,FALSE()),"")="Industrial",$AE7,0)
A8: 6 | B8: =INPUTS!$A$59 | C8: =(INPUTS!$B$59="Yes") | D8: =INPUTS!$C$59 | E8: =INPUTS!$D$59 | F8: =INPUTS!$E$59 | G8: =IFERROR(VLOOKUP(D8,'02_Type_Assumptions'!$A$4:$Z$18,3,FALSE()),0) | H8: =IF(INPUTS!$F$59="","",INPUTS!$F$59) | I8: =IF(ISNUMBER(H8),H8,IF(LOWER(E8)="sqft",IFERROR(F8/43560/'00_Inputs_Dashboard'!$B$51,0),IF(LOWER(E8)="acres",IFERROR(F8,0),IFERROR(F8*G8,0)))) | J8: =INPUTS!$G$59 | K8: =INPUTS!$H$59 | L8: =INPUTS!$I$59 | M8: =I8*L8 | N8: =IFERROR(IF(LOWER(E8)="rooms",VLOOKUP(D8,'02_Type_Assumptions'!$A$4:$Z$18,6,FALSE()),IF(LOWER(E8)="acres",VLOOKUP(D8,'02_Type_Assumptions'!$A$4:$Z$18,5,FALSE()),VLOOKUP(D8,'02_Type_Assumptions'!$A$4:$Z$18,4,FALSE()))),0) | P8: =IF(ISNUMBER(O8),O8,IF(LOWER(E8)="rooms",F8*N8*L8,IF(LOWER(E8)="acres",M8*N8,IF(LOWER(E8)="sqft",M8*VLOOKUP(D8,'02_Type_Assumptions'!$A$4:$Z$18,5,FALSE()),F8*N8*L8)))) | Q8: =IFERROR(IF(VLOOKUP(D8,'02_Type_Assumptions'!$A$4:$Z$18,23,FALSE())="per_acre",VLOOKUP(D8,'02_Type_Assumptions'!$A$4:$Z$18,8,FALSE()),0),0) | S8: =IF(ISNUMBER(R8),R8*L8,M8*Q8) | T8: =IF(LOWER(E8)="sqft",F8*L8,M8*IFERROR(VLOOKUP(D8,'02_Type_Assumptions'!$A$4:$Z$18,9,FALSE()),0)) | U8: =IF(OR(LOWER(E8)="lots",LOWER(E8)="units"),F8*L8,0) | V8: =U8*IFERROR(VLOOKUP(D8,'02_Type_Assumptions'!$A$4:$Z$18,21,FALSE()),0) | W8: =IFERROR(IF(OR(LOWER(E8)="lots",LOWER(E8)="units",LOWER(E8)="rooms"),F8*L8*VLOOKUP(D8,'02_Type_Assumptions'!$A$4:$Z$18,10,FALSE()),IF(LOWER(E8)="acres",M8*VLOOKUP(D8,'02_Type_Assumptions'!$A$4:$Z$18,11,FALSE()),IF(LOWER(E8)="sqft",T8/1000*VLOOKUP(D8,'02_Type_Assumptions'!$A$4:$Z$18,12,FALSE()),0))),0) | X8: =INPUTS!$D$50 | Z8: =IF(ISNUMBER(Y8),Y8,W8*X8) | AC8: Test case — limited-service hotel. HOT separate. | AD8: =IFERROR($P8*VLOOKUP($D8,'02_Type_Assumptions'!$A$4:$AC$18,28,FALSE()),$P8) | AE8: =IFERROR($P8*VLOOKUP($D8,'02_Type_Assumptions'!$A$4:$AC$18,29,FALSE()),$P8) | AF8: =IF(IFERROR(VLOOKUP($D8,'02_Type_Assumptions'!$A$4:$AC$18,27,FALSE()),"")="Industrial",$AD8,0) | AG8: =IF(IFERROR(VLOOKUP($D8,'02_Type_Assumptions'!$A$4:$AC$18,27,FALSE()),"")="Industrial",$AE8,0)
A9: 7 | B9: =INPUTS!$A$60 | C9: =(INPUTS!$B$60="Yes") | D9: =INPUTS!$C$60 | E9: =INPUTS!$D$60 | F9: =INPUTS!$E$60 | G9: =IFERROR(VLOOKUP(D9,'02_Type_Assumptions'!$A$4:$Z$18,3,FALSE()),0) | H9: =IF(INPUTS!$F$60="","",INPUTS!$F$60) | I9: =IF(ISNUMBER(H9),H9,IF(LOWER(E9)="sqft",IFERROR(F9/43560/'00_Inputs_Dashboard'!$B$51,0),IF(LOWER(E9)="acres",IFERROR(F9,0),IFERROR(F9*G9,0)))) | J9: =INPUTS!$G$60 | K9: =INPUTS!$H$60 | L9: =INPUTS!$I$60 | M9: =I9*L9 | N9: =IFERROR(IF(LOWER(E9)="rooms",VLOOKUP(D9,'02_Type_Assumptions'!$A$4:$Z$18,6,FALSE()),IF(LOWER(E9)="acres",VLOOKUP(D9,'02_Type_Assumptions'!$A$4:$Z$18,5,FALSE()),VLOOKUP(D9,'02_Type_Assumptions'!$A$4:$Z$18,4,FALSE()))),0) | P9: =IF(ISNUMBER(O9),O9,IF(LOWER(E9)="rooms",F9*N9*L9,IF(LOWER(E9)="acres",M9*N9,IF(LOWER(E9)="sqft",M9*VLOOKUP(D9,'02_Type_Assumptions'!$A$4:$Z$18,5,FALSE()),F9*N9*L9)))) | Q9: =IFERROR(IF(VLOOKUP(D9,'02_Type_Assumptions'!$A$4:$Z$18,23,FALSE())="per_acre",VLOOKUP(D9,'02_Type_Assumptions'!$A$4:$Z$18,8,FALSE()),0),0) | S9: =IF(ISNUMBER(R9),R9*L9,M9*Q9) | T9: =IF(LOWER(E9)="sqft",F9*L9,M9*IFERROR(VLOOKUP(D9,'02_Type_Assumptions'!$A$4:$Z$18,9,FALSE()),0)) | U9: =IF(OR(LOWER(E9)="lots",LOWER(E9)="units"),F9*L9,0) | V9: =U9*IFERROR(VLOOKUP(D9,'02_Type_Assumptions'!$A$4:$Z$18,21,FALSE()),0) | W9: =IFERROR(IF(OR(LOWER(E9)="lots",LOWER(E9)="units",LOWER(E9)="rooms"),F9*L9*VLOOKUP(D9,'02_Type_Assumptions'!$A$4:$Z$18,10,FALSE()),IF(LOWER(E9)="acres",M9*VLOOKUP(D9,'02_Type_Assumptions'!$A$4:$Z$18,11,FALSE()),IF(LOWER(E9)="sqft",T9/1000*VLOOKUP(D9,'02_Type_Assumptions'!$A$4:$Z$18,12,FALSE()),0))),0) | X9: =INPUTS!$D$50 | Z9: =IF(ISNUMBER(Y9),Y9,W9*X9) | AD9: =IFERROR($P9*VLOOKUP($D9,'02_Type_Assumptions'!$A$4:$AC$18,28,FALSE()),$P9) | AE9: =IFERROR($P9*VLOOKUP($D9,'02_Type_Assumptions'!$A$4:$AC$18,29,FALSE()),$P9) | AF9: =IF(IFERROR(VLOOKUP($D9,'02_Type_Assumptions'!$A$4:$AC$18,27,FALSE()),"")="Industrial",$AD9,0) | AG9: =IF(IFERROR(VLOOKUP($D9,'02_Type_Assumptions'!$A$4:$AC$18,27,FALSE()),"")="Industrial",$AE9,0)
A10: 8 | B10: =INPUTS!$A$61 | C10: =(INPUTS!$B$61="Yes") | D10: =INPUTS!$C$61 | E10: =INPUTS!$D$61 | F10: =INPUTS!$E$61 | G10: =IFERROR(VLOOKUP(D10,'02_Type_Assumptions'!$A$4:$Z$18,3,FALSE()),0) | H10: =IF(INPUTS!$F$61="","",INPUTS!$F$61) | I10: =IF(ISNUMBER(H10),H10,IF(LOWER(E10)="sqft",IFERROR(F10/43560/'00_Inputs_Dashboard'!$B$51,0),IF(LOWER(E10)="acres",IFERROR(F10,0),IFERROR(F10*G10,0)))) | J10: =INPUTS!$G$61 | K10: =INPUTS!$H$61 | L10: =INPUTS!$I$61 | M10: =I10*L10 | N10: =IFERROR(IF(LOWER(E10)="rooms",VLOOKUP(D10,'02_Type_Assumptions'!$A$4:$Z$18,6,FALSE()),IF(LOWER(E10)="acres",VLOOKUP(D10,'02_Type_Assumptions'!$A$4:$Z$18,5,FALSE()),VLOOKUP(D10,'02_Type_Assumptions'!$A$4:$Z$18,4,FALSE()))),0) | P10: =IF(ISNUMBER(O10),O10,IF(LOWER(E10)="rooms",F10*N10*L10,IF(LOWER(E10)="acres",M10*N10,IF(LOWER(E10)="sqft",M10*VLOOKUP(D10,'02_Type_Assumptions'!$A$4:$Z$18,5,FALSE()),F10*N10*L10)))) | Q10: =IFERROR(IF(VLOOKUP(D10,'02_Type_Assumptions'!$A$4:$Z$18,23,FALSE())="per_acre",VLOOKUP(D10,'02_Type_Assumptions'!$A$4:$Z$18,8,FALSE()),0),0) | S10: =IF(ISNUMBER(R10),R10*L10,M10*Q10) | T10: =IF(LOWER(E10)="sqft",F10*L10,M10*IFERROR(VLOOKUP(D10,'02_Type_Assumptions'!$A$4:$Z$18,9,FALSE()),0)) | U10: =IF(OR(LOWER(E10)="lots",LOWER(E10)="units"),F10*L10,0) | V10: =U10*IFERROR(VLOOKUP(D10,'02_Type_Assumptions'!$A$4:$Z$18,21,FALSE()),0) | W10: =IFERROR(IF(OR(LOWER(E10)="lots",LOWER(E10)="units",LOWER(E10)="rooms"),F10*L10*VLOOKUP(D10,'02_Type_Assumptions'!$A$4:$Z$18,10,FALSE()),IF(LOWER(E10)="acres",M10*VLOOKUP(D10,'02_Type_Assumptions'!$A$4:$Z$18,11,FALSE()),IF(LOWER(E10)="sqft",T10/1000*VLOOKUP(D10,'02_Type_Assumptions'!$A$4:$Z$18,12,FALSE()),0))),0) | X10: =INPUTS!$D$50 | Z10: =IF(ISNUMBER(Y10),Y10,W10*X10) | AD10: =IFERROR($P10*VLOOKUP($D10,'02_Type_Assumptions'!$A$4:$AC$18,28,FALSE()),$P10) | AE10: =IFERROR($P10*VLOOKUP($D10,'02_Type_Assumptions'!$A$4:$AC$18,29,FALSE()),$P10) | AF10: =IF(IFERROR(VLOOKUP($D10,'02_Type_Assumptions'!$A$4:$AC$18,27,FALSE()),"")="Industrial",$AD10,0) | AG10: =IF(IFERROR(VLOOKUP($D10,'02_Type_Assumptions'!$A$4:$AC$18,27,FALSE()),"")="Industrial",$AE10,0)
A11: 9 | B11: =INPUTS!$A$62 | C11: =(INPUTS!$B$62="Yes") | D11: =INPUTS!$C$62 | E11: =INPUTS!$D$62 | F11: =INPUTS!$E$62 | G11: =IFERROR(VLOOKUP(D11,'02_Type_Assumptions'!$A$4:$Z$18,3,FALSE()),0) | H11: =IF(INPUTS!$F$62="","",INPUTS!$F$62) | I11: =IF(ISNUMBER(H11),H11,IF(LOWER(E11)="sqft",IFERROR(F11/43560/'00_Inputs_Dashboard'!$B$51,0),IF(LOWER(E11)="acres",IFERROR(F11,0),IFERROR(F11*G11,0)))) | J11: =INPUTS!$G$62 | K11: =INPUTS!$H$62 | L11: =INPUTS!$I$62 | M11: =I11*L11 | N11: =IFERROR(IF(LOWER(E11)="rooms",VLOOKUP(D11,'02_Type_Assumptions'!$A$4:$Z$18,6,FALSE()),IF(LOWER(E11)="acres",VLOOKUP(D11,'02_Type_Assumptions'!$A$4:$Z$18,5,FALSE()),VLOOKUP(D11,'02_Type_Assumptions'!$A$4:$Z$18,4,FALSE()))),0) | P11: =IF(ISNUMBER(O11),O11,IF(LOWER(E11)="rooms",F11*N11*L11,IF(LOWER(E11)="acres",M11*N11,IF(LOWER(E11)="sqft",M11*VLOOKUP(D11,'02_Type_Assumptions'!$A$4:$Z$18,5,FALSE()),F11*N11*L11)))) | Q11: =IFERROR(IF(VLOOKUP(D11,'02_Type_Assumptions'!$A$4:$Z$18,23,FALSE())="per_acre",VLOOKUP(D11,'02_Type_Assumptions'!$A$4:$Z$18,8,FALSE()),0),0) | S11: =IF(ISNUMBER(R11),R11*L11,M11*Q11) | T11: =IF(LOWER(E11)="sqft",F11*L11,M11*IFERROR(VLOOKUP(D11,'02_Type_Assumptions'!$A$4:$Z$18,9,FALSE()),0)) | U11: =IF(OR(LOWER(E11)="lots",LOWER(E11)="units"),F11*L11,0) | V11: =U11*IFERROR(VLOOKUP(D11,'02_Type_Assumptions'!$A$4:$Z$18,21,FALSE()),0) | W11: =IFERROR(IF(OR(LOWER(E11)="lots",LOWER(E11)="units",LOWER(E11)="rooms"),F11*L11*VLOOKUP(D11,'02_Type_Assumptions'!$A$4:$Z$18,10,FALSE()),IF(LOWER(E11)="acres",M11*VLOOKUP(D11,'02_Type_Assumptions'!$A$4:$Z$18,11,FALSE()),IF(LOWER(E11)="sqft",T11/1000*VLOOKUP(D11,'02_Type_Assumptions'!$A$4:$Z$18,12,FALSE()),0))),0) | X11: =INPUTS!$D$50 | Z11: =IF(ISNUMBER(Y11),Y11,W11*X11) | AD11: =IFERROR($P11*VLOOKUP($D11,'02_Type_Assumptions'!$A$4:$AC$18,28,FALSE()),$P11) | AE11: =IFERROR($P11*VLOOKUP($D11,'02_Type_Assumptions'!$A$4:$AC$18,29,FALSE()),$P11) | AF11: =IF(IFERROR(VLOOKUP($D11,'02_Type_Assumptions'!$A$4:$AC$18,27,FALSE()),"")="Industrial",$AD11,0) | AG11: =IF(IFERROR(VLOOKUP($D11,'02_Type_Assumptions'!$A$4:$AC$18,27,FALSE()),"")="Industrial",$AE11,0)
A12: 10 | B12: =INPUTS!$A$63 | C12: =(INPUTS!$B$63="Yes") | D12: =INPUTS!$C$63 | E12: =INPUTS!$D$63 | F12: =INPUTS!$E$63 | G12: =IFERROR(VLOOKUP(D12,'02_Type_Assumptions'!$A$4:$Z$18,3,FALSE()),0) | H12: =IF(INPUTS!$F$63="","",INPUTS!$F$63) | I12: =IF(ISNUMBER(H12),H12,IF(LOWER(E12)="sqft",IFERROR(F12/43560/'00_Inputs_Dashboard'!$B$51,0),IF(LOWER(E12)="acres",IFERROR(F12,0),IFERROR(F12*G12,0)))) | J12: =INPUTS!$G$63 | K12: =INPUTS!$H$63 | L12: =INPUTS!$I$63 | M12: =I12*L12 | N12: =IFERROR(IF(LOWER(E12)="rooms",VLOOKUP(D12,'02_Type_Assumptions'!$A$4:$Z$18,6,FALSE()),IF(LOWER(E12)="acres",VLOOKUP(D12,'02_Type_Assumptions'!$A$4:$Z$18,5,FALSE()),VLOOKUP(D12,'02_Type_Assumptions'!$A$4:$Z$18,4,FALSE()))),0) | P12: =IF(ISNUMBER(O12),O12,IF(LOWER(E12)="rooms",F12*N12*L12,IF(LOWER(E12)="acres",M12*N12,IF(LOWER(E12)="sqft",M12*VLOOKUP(D12,'02_Type_Assumptions'!$A$4:$Z$18,5,FALSE()),F12*N12*L12)))) | Q12: =IFERROR(IF(VLOOKUP(D12,'02_Type_Assumptions'!$A$4:$Z$18,23,FALSE())="per_acre",VLOOKUP(D12,'02_Type_Assumptions'!$A$4:$Z$18,8,FALSE()),0),0) | S12: =IF(ISNUMBER(R12),R12*L12,M12*Q12) | T12: =IF(LOWER(E12)="sqft",F12*L12,M12*IFERROR(VLOOKUP(D12,'02_Type_Assumptions'!$A$4:$Z$18,9,FALSE()),0)) | U12: =IF(OR(LOWER(E12)="lots",LOWER(E12)="units"),F12*L12,0) | V12: =U12*IFERROR(VLOOKUP(D12,'02_Type_Assumptions'!$A$4:$Z$18,21,FALSE()),0) | W12: =IFERROR(IF(OR(LOWER(E12)="lots",LOWER(E12)="units",LOWER(E12)="rooms"),F12*L12*VLOOKUP(D12,'02_Type_Assumptions'!$A$4:$Z$18,10,FALSE()),IF(LOWER(E12)="acres",M12*VLOOKUP(D12,'02_Type_Assumptions'!$A$4:$Z$18,11,FALSE()),IF(LOWER(E12)="sqft",T12/1000*VLOOKUP(D12,'02_Type_Assumptions'!$A$4:$Z$18,12,FALSE()),0))),0) | X12: =INPUTS!$D$50 | Z12: =IF(ISNUMBER(Y12),Y12,W12*X12) | AD12: =IFERROR($P12*VLOOKUP($D12,'02_Type_Assumptions'!$A$4:$AC$18,28,FALSE()),$P12) | AE12: =IFERROR($P12*VLOOKUP($D12,'02_Type_Assumptions'!$A$4:$AC$18,29,FALSE()),$P12) | AF12: =IF(IFERROR(VLOOKUP($D12,'02_Type_Assumptions'!$A$4:$AC$18,27,FALSE()),"")="Industrial",$AD12,0) | AG12: =IF(IFERROR(VLOOKUP($D12,'02_Type_Assumptions'!$A$4:$AC$18,27,FALSE()),"")="Industrial",$AE12,0)
A13: 11 | B13: =INPUTS!$A$64 | C13: =(INPUTS!$B$64="Yes") | D13: =INPUTS!$C$64 | E13: =INPUTS!$D$64 | F13: =INPUTS!$E$64 | G13: =IFERROR(VLOOKUP(D13,'02_Type_Assumptions'!$A$4:$Z$18,3,FALSE()),0) | H13: =IF(INPUTS!$F$64="","",INPUTS!$F$64) | I13: =IF(ISNUMBER(H13),H13,IF(LOWER(E13)="sqft",IFERROR(F13/43560/'00_Inputs_Dashboard'!$B$51,0),IF(LOWER(E13)="acres",IFERROR(F13,0),IFERROR(F13*G13,0)))) | J13: =INPUTS!$G$64 | K13: =INPUTS!$H$64 | L13: =INPUTS!$I$64 | M13: =I13*L13 | N13: =IFERROR(IF(LOWER(E13)="rooms",VLOOKUP(D13,'02_Type_Assumptions'!$A$4:$Z$18,6,FALSE()),IF(LOWER(E13)="acres",VLOOKUP(D13,'02_Type_Assumptions'!$A$4:$Z$18,5,FALSE()),VLOOKUP(D13,'02_Type_Assumptions'!$A$4:$Z$18,4,FALSE()))),0) | P13: =IF(ISNUMBER(O13),O13,IF(LOWER(E13)="rooms",F13*N13*L13,IF(LOWER(E13)="acres",M13*N13,IF(LOWER(E13)="sqft",M13*VLOOKUP(D13,'02_Type_Assumptions'!$A$4:$Z$18,5,FALSE()),F13*N13*L13)))) | Q13: =IFERROR(IF(VLOOKUP(D13,'02_Type_Assumptions'!$A$4:$Z$18,23,FALSE())="per_acre",VLOOKUP(D13,'02_Type_Assumptions'!$A$4:$Z$18,8,FALSE()),0),0) | S13: =IF(ISNUMBER(R13),R13*L13,M13*Q13) | T13: =IF(LOWER(E13)="sqft",F13*L13,M13*IFERROR(VLOOKUP(D13,'02_Type_Assumptions'!$A$4:$Z$18,9,FALSE()),0)) | U13: =IF(OR(LOWER(E13)="lots",LOWER(E13)="units"),F13*L13,0) | V13: =U13*IFERROR(VLOOKUP(D13,'02_Type_Assumptions'!$A$4:$Z$18,21,FALSE()),0) | W13: =IFERROR(IF(OR(LOWER(E13)="lots",LOWER(E13)="units",LOWER(E13)="rooms"),F13*L13*VLOOKUP(D13,'02_Type_Assumptions'!$A$4:$Z$18,10,FALSE()),IF(LOWER(E13)="acres",M13*VLOOKUP(D13,'02_Type_Assumptions'!$A$4:$Z$18,11,FALSE()),IF(LOWER(E13)="sqft",T13/1000*VLOOKUP(D13,'02_Type_Assumptions'!$A$4:$Z$18,12,FALSE()),0))),0) | X13: =INPUTS!$D$50 | Z13: =IF(ISNUMBER(Y13),Y13,W13*X13) | AD13: =IFERROR($P13*VLOOKUP($D13,'02_Type_Assumptions'!$A$4:$AC$18,28,FALSE()),$P13) | AE13: =IFERROR($P13*VLOOKUP($D13,'02_Type_Assumptions'!$A$4:$AC$18,29,FALSE()),$P13) | AF13: =IF(IFERROR(VLOOKUP($D13,'02_Type_Assumptions'!$A$4:$AC$18,27,FALSE()),"")="Industrial",$AD13,0) | AG13: =IF(IFERROR(VLOOKUP($D13,'02_Type_Assumptions'!$A$4:$AC$18,27,FALSE()),"")="Industrial",$AE13,0)
A14: 12 | B14: =INPUTS!$A$65 | C14: =(INPUTS!$B$65="Yes") | D14: =INPUTS!$C$65 | E14: =INPUTS!$D$65 | F14: =INPUTS!$E$65 | G14: =IFERROR(VLOOKUP(D14,'02_Type_Assumptions'!$A$4:$Z$18,3,FALSE()),0) | H14: =IF(INPUTS!$F$65="","",INPUTS!$F$65) | I14: =IF(ISNUMBER(H14),H14,IF(LOWER(E14)="sqft",IFERROR(F14/43560/'00_Inputs_Dashboard'!$B$51,0),IF(LOWER(E14)="acres",IFERROR(F14,0),IFERROR(F14*G14,0)))) | J14: =INPUTS!$G$65 | K14: =INPUTS!$H$65 | L14: =INPUTS!$I$65 | M14: =I14*L14 | N14: =IFERROR(IF(LOWER(E14)="rooms",VLOOKUP(D14,'02_Type_Assumptions'!$A$4:$Z$18,6,FALSE()),IF(LOWER(E14)="acres",VLOOKUP(D14,'02_Type_Assumptions'!$A$4:$Z$18,5,FALSE()),VLOOKUP(D14,'02_Type_Assumptions'!$A$4:$Z$18,4,FALSE()))),0) | P14: =IF(ISNUMBER(O14),O14,IF(LOWER(E14)="rooms",F14*N14*L14,IF(LOWER(E14)="acres",M14*N14,IF(LOWER(E14)="sqft",M14*VLOOKUP(D14,'02_Type_Assumptions'!$A$4:$Z$18,5,FALSE()),F14*N14*L14)))) | Q14: =IFERROR(IF(VLOOKUP(D14,'02_Type_Assumptions'!$A$4:$Z$18,23,FALSE())="per_acre",VLOOKUP(D14,'02_Type_Assumptions'!$A$4:$Z$18,8,FALSE()),0),0) | S14: =IF(ISNUMBER(R14),R14*L14,M14*Q14) | T14: =IF(LOWER(E14)="sqft",F14*L14,M14*IFERROR(VLOOKUP(D14,'02_Type_Assumptions'!$A$4:$Z$18,9,FALSE()),0)) | U14: =IF(OR(LOWER(E14)="lots",LOWER(E14)="units"),F14*L14,0) | V14: =U14*IFERROR(VLOOKUP(D14,'02_Type_Assumptions'!$A$4:$Z$18,21,FALSE()),0) | W14: =IFERROR(IF(OR(LOWER(E14)="lots",LOWER(E14)="units",LOWER(E14)="rooms"),F14*L14*VLOOKUP(D14,'02_Type_Assumptions'!$A$4:$Z$18,10,FALSE()),IF(LOWER(E14)="acres",M14*VLOOKUP(D14,'02_Type_Assumptions'!$A$4:$Z$18,11,FALSE()),IF(LOWER(E14)="sqft",T14/1000*VLOOKUP(D14,'02_Type_Assumptions'!$A$4:$Z$18,12,FALSE()),0))),0) | X14: =INPUTS!$D$50 | Z14: =IF(ISNUMBER(Y14),Y14,W14*X14) | AD14: =IFERROR($P14*VLOOKUP($D14,'02_Type_Assumptions'!$A$4:$AC$18,28,FALSE()),$P14) | AE14: =IFERROR($P14*VLOOKUP($D14,'02_Type_Assumptions'!$A$4:$AC$18,29,FALSE()),$P14) | AF14: =IF(IFERROR(VLOOKUP($D14,'02_Type_Assumptions'!$A$4:$AC$18,27,FALSE()),"")="Industrial",$AD14,0) | AG14: =IF(IFERROR(VLOOKUP($D14,'02_Type_Assumptions'!$A$4:$AC$18,27,FALSE()),"")="Industrial",$AE14,0)
A15: 13 | C15: =FALSE() | G15: =IFERROR(VLOOKUP(D15,'02_Type_Assumptions'!$A$4:$Z$18,3,FALSE()),0) | I15: =IF(ISNUMBER(H15),H15,IF(LOWER(E15)="sqft",IFERROR(F15/43560/'00_Inputs_Dashboard'!$B$51,0),IF(LOWER(E15)="acres",IFERROR(F15,0),IFERROR(F15*G15,0)))) | J15: 1 | K15: 1 | L15: 0.8 | M15: =I15*L15 | N15: =IFERROR(IF(LOWER(E15)="rooms",VLOOKUP(D15,'02_Type_Assumptions'!$A$4:$Z$18,6,FALSE()),IF(LOWER(E15)="acres",VLOOKUP(D15,'02_Type_Assumptions'!$A$4:$Z$18,5,FALSE()),VLOOKUP(D15,'02_Type_Assumptions'!$A$4:$Z$18,4,FALSE()))),0) | P15: =IF(ISNUMBER(O15),O15,IF(LOWER(E15)="rooms",F15*N15*L15,IF(LOWER(E15)="acres",M15*N15,IF(LOWER(E15)="sqft",M15*VLOOKUP(D15,'02_Type_Assumptions'!$A$4:$Z$18,5,FALSE()),F15*N15*L15)))) | Q15: =IFERROR(IF(VLOOKUP(D15,'02_Type_Assumptions'!$A$4:$Z$18,23,FALSE())="per_acre",VLOOKUP(D15,'02_Type_Assumptions'!$A$4:$Z$18,8,FALSE()),0),0) | S15: =IF(ISNUMBER(R15),R15*L15,M15*Q15) | T15: =IF(LOWER(E15)="sqft",F15*L15,M15*IFERROR(VLOOKUP(D15,'02_Type_Assumptions'!$A$4:$Z$18,9,FALSE()),0)) | U15: =IF(OR(LOWER(E15)="lots",LOWER(E15)="units"),F15*L15,0) | V15: =U15*IFERROR(VLOOKUP(D15,'02_Type_Assumptions'!$A$4:$Z$18,21,FALSE()),0) | W15: =IFERROR(IF(OR(LOWER(E15)="lots",LOWER(E15)="units",LOWER(E15)="rooms"),F15*L15*VLOOKUP(D15,'02_Type_Assumptions'!$A$4:$Z$18,10,FALSE()),IF(LOWER(E15)="acres",M15*VLOOKUP(D15,'02_Type_Assumptions'!$A$4:$Z$18,11,FALSE()),IF(LOWER(E15)="sqft",T15/1000*VLOOKUP(D15,'02_Type_Assumptions'!$A$4:$Z$18,12,FALSE()),0))),0) | X15: =INPUTS!$D$50 | Z15: =IF(ISNUMBER(Y15),Y15,W15*X15) | AD15: =IFERROR($P15*VLOOKUP($D15,'02_Type_Assumptions'!$A$4:$AC$18,28,FALSE()),$P15) | AE15: =IFERROR($P15*VLOOKUP($D15,'02_Type_Assumptions'!$A$4:$AC$18,29,FALSE()),$P15) | AF15: =IF(IFERROR(VLOOKUP($D15,'02_Type_Assumptions'!$A$4:$AC$18,27,FALSE()),"")="Industrial",$AD15,0) | AG15: =IF(IFERROR(VLOOKUP($D15,'02_Type_Assumptions'!$A$4:$AC$18,27,FALSE()),"")="Industrial",$AE15,0)
A16: 14 | C16: =FALSE() | G16: =IFERROR(VLOOKUP(D16,'02_Type_Assumptions'!$A$4:$Z$18,3,FALSE()),0) | I16: =IF(ISNUMBER(H16),H16,IF(LOWER(E16)="sqft",IFERROR(F16/43560/'00_Inputs_Dashboard'!$B$51,0),IF(LOWER(E16)="acres",IFERROR(F16,0),IFERROR(F16*G16,0)))) | J16: 1 | K16: 1 | L16: 0.8 | M16: =I16*L16 | N16: =IFERROR(IF(LOWER(E16)="rooms",VLOOKUP(D16,'02_Type_Assumptions'!$A$4:$Z$18,6,FALSE()),IF(LOWER(E16)="acres",VLOOKUP(D16,'02_Type_Assumptions'!$A$4:$Z$18,5,FALSE()),VLOOKUP(D16,'02_Type_Assumptions'!$A$4:$Z$18,4,FALSE()))),0) | P16: =IF(ISNUMBER(O16),O16,IF(LOWER(E16)="rooms",F16*N16*L16,IF(LOWER(E16)="acres",M16*N16,IF(LOWER(E16)="sqft",M16*VLOOKUP(D16,'02_Type_Assumptions'!$A$4:$Z$18,5,FALSE()),F16*N16*L16)))) | Q16: =IFERROR(IF(VLOOKUP(D16,'02_Type_Assumptions'!$A$4:$Z$18,23,FALSE())="per_acre",VLOOKUP(D16,'02_Type_Assumptions'!$A$4:$Z$18,8,FALSE()),0),0) | S16: =IF(ISNUMBER(R16),R16*L16,M16*Q16) | T16: =IF(LOWER(E16)="sqft",F16*L16,M16*IFERROR(VLOOKUP(D16,'02_Type_Assumptions'!$A$4:$Z$18,9,FALSE()),0)) | U16: =IF(OR(LOWER(E16)="lots",LOWER(E16)="units"),F16*L16,0) | V16: =U16*IFERROR(VLOOKUP(D16,'02_Type_Assumptions'!$A$4:$Z$18,21,FALSE()),0) | W16: =IFERROR(IF(OR(LOWER(E16)="lots",LOWER(E16)="units",LOWER(E16)="rooms"),F16*L16*VLOOKUP(D16,'02_Type_Assumptions'!$A$4:$Z$18,10,FALSE()),IF(LOWER(E16)="acres",M16*VLOOKUP(D16,'02_Type_Assumptions'!$A$4:$Z$18,11,FALSE()),IF(LOWER(E16)="sqft",T16/1000*VLOOKUP(D16,'02_Type_Assumptions'!$A$4:$Z$18,12,FALSE()),0))),0) | X16: =INPUTS!$D$50 | Z16: =IF(ISNUMBER(Y16),Y16,W16*X16) | AD16: =IFERROR($P16*VLOOKUP($D16,'02_Type_Assumptions'!$A$4:$AC$18,28,FALSE()),$P16) | AE16: =IFERROR($P16*VLOOKUP($D16,'02_Type_Assumptions'!$A$4:$AC$18,29,FALSE()),$P16) | AF16: =IF(IFERROR(VLOOKUP($D16,'02_Type_Assumptions'!$A$4:$AC$18,27,FALSE()),"")="Industrial",$AD16,0) | AG16: =IF(IFERROR(VLOOKUP($D16,'02_Type_Assumptions'!$A$4:$AC$18,27,FALSE()),"")="Industrial",$AE16,0)
A17: 15 | C17: =FALSE() | G17: =IFERROR(VLOOKUP(D17,'02_Type_Assumptions'!$A$4:$Z$18,3,FALSE()),0) | I17: =IF(ISNUMBER(H17),H17,IF(LOWER(E17)="sqft",IFERROR(F17/43560/'00_Inputs_Dashboard'!$B$51,0),IF(LOWER(E17)="acres",IFERROR(F17,0),IFERROR(F17*G17,0)))) | J17: 1 | K17: 1 | L17: 0.8 | M17: =I17*L17 | N17: =IFERROR(IF(LOWER(E17)="rooms",VLOOKUP(D17,'02_Type_Assumptions'!$A$4:$Z$18,6,FALSE()),IF(LOWER(E17)="acres",VLOOKUP(D17,'02_Type_Assumptions'!$A$4:$Z$18,5,FALSE()),VLOOKUP(D17,'02_Type_Assumptions'!$A$4:$Z$18,4,FALSE()))),0) | P17: =IF(ISNUMBER(O17),O17,IF(LOWER(E17)="rooms",F17*N17*L17,IF(LOWER(E17)="acres",M17*N17,IF(LOWER(E17)="sqft",M17*VLOOKUP(D17,'02_Type_Assumptions'!$A$4:$Z$18,5,FALSE()),F17*N17*L17)))) | Q17: =IFERROR(IF(VLOOKUP(D17,'02_Type_Assumptions'!$A$4:$Z$18,23,FALSE())="per_acre",VLOOKUP(D17,'02_Type_Assumptions'!$A$4:$Z$18,8,FALSE()),0),0) | S17: =IF(ISNUMBER(R17),R17*L17,M17*Q17) | T17: =IF(LOWER(E17)="sqft",F17*L17,M17*IFERROR(VLOOKUP(D17,'02_Type_Assumptions'!$A$4:$Z$18,9,FALSE()),0)) | U17: =IF(OR(LOWER(E17)="lots",LOWER(E17)="units"),F17*L17,0) | V17: =U17*IFERROR(VLOOKUP(D17,'02_Type_Assumptions'!$A$4:$Z$18,21,FALSE()),0) | W17: =IFERROR(IF(OR(LOWER(E17)="lots",LOWER(E17)="units",LOWER(E17)="rooms"),F17*L17*VLOOKUP(D17,'02_Type_Assumptions'!$A$4:$Z$18,10,FALSE()),IF(LOWER(E17)="acres",M17*VLOOKUP(D17,'02_Type_Assumptions'!$A$4:$Z$18,11,FALSE()),IF(LOWER(E17)="sqft",T17/1000*VLOOKUP(D17,'02_Type_Assumptions'!$A$4:$Z$18,12,FALSE()),0))),0) | X17: =INPUTS!$D$50 | Z17: =IF(ISNUMBER(Y17),Y17,W17*X17) | AD17: =IFERROR($P17*VLOOKUP($D17,'02_Type_Assumptions'!$A$4:$AC$18,28,FALSE()),$P17) | AE17: =IFERROR($P17*VLOOKUP($D17,'02_Type_Assumptions'!$A$4:$AC$18,29,FALSE()),$P17) | AF17: =IF(IFERROR(VLOOKUP($D17,'02_Type_Assumptions'!$A$4:$AC$18,27,FALSE()),"")="Industrial",$AD17,0) | AG17: =IF(IFERROR(VLOOKUP($D17,'02_Type_Assumptions'!$A$4:$AC$18,27,FALSE()),"")="Industrial",$AE17,0)
A18: 16 | C18: =FALSE() | G18: =IFERROR(VLOOKUP(D18,'02_Type_Assumptions'!$A$4:$Z$18,3,FALSE()),0) | I18: =IF(ISNUMBER(H18),H18,IF(LOWER(E18)="sqft",IFERROR(F18/43560/'00_Inputs_Dashboard'!$B$51,0),IF(LOWER(E18)="acres",IFERROR(F18,0),IFERROR(F18*G18,0)))) | J18: 1 | K18: 1 | L18: 0.8 | M18: =I18*L18 | N18: =IFERROR(IF(LOWER(E18)="rooms",VLOOKUP(D18,'02_Type_Assumptions'!$A$4:$Z$18,6,FALSE()),IF(LOWER(E18)="acres",VLOOKUP(D18,'02_Type_Assumptions'!$A$4:$Z$18,5,FALSE()),VLOOKUP(D18,'02_Type_Assumptions'!$A$4:$Z$18,4,FALSE()))),0) | P18: =IF(ISNUMBER(O18),O18,IF(LOWER(E18)="rooms",F18*N18*L18,IF(LOWER(E18)="acres",M18*N18,IF(LOWER(E18)="sqft",M18*VLOOKUP(D18,'02_Type_Assumptions'!$A$4:$Z$18,5,FALSE()),F18*N18*L18)))) | Q18: =IFERROR(IF(VLOOKUP(D18,'02_Type_Assumptions'!$A$4:$Z$18,23,FALSE())="per_acre",VLOOKUP(D18,'02_Type_Assumptions'!$A$4:$Z$18,8,FALSE()),0),0) | S18: =IF(ISNUMBER(R18),R18*L18,M18*Q18) | T18: =IF(LOWER(E18)="sqft",F18*L18,M18*IFERROR(VLOOKUP(D18,'02_Type_Assumptions'!$A$4:$Z$18,9,FALSE()),0)) | U18: =IF(OR(LOWER(E18)="lots",LOWER(E18)="units"),F18*L18,0) | V18: =U18*IFERROR(VLOOKUP(D18,'02_Type_Assumptions'!$A$4:$Z$18,21,FALSE()),0) | W18: =IFERROR(IF(OR(LOWER(E18)="lots",LOWER(E18)="units",LOWER(E18)="rooms"),F18*L18*VLOOKUP(D18,'02_Type_Assumptions'!$A$4:$Z$18,10,FALSE()),IF(LOWER(E18)="acres",M18*VLOOKUP(D18,'02_Type_Assumptions'!$A$4:$Z$18,11,FALSE()),IF(LOWER(E18)="sqft",T18/1000*VLOOKUP(D18,'02_Type_Assumptions'!$A$4:$Z$18,12,FALSE()),0))),0) | X18: =INPUTS!$D$50 | Z18: =IF(ISNUMBER(Y18),Y18,W18*X18) | AD18: =IFERROR($P18*VLOOKUP($D18,'02_Type_Assumptions'!$A$4:$AC$18,28,FALSE()),$P18) | AE18: =IFERROR($P18*VLOOKUP($D18,'02_Type_Assumptions'!$A$4:$AC$18,29,FALSE()),$P18) | AF18: =IF(IFERROR(VLOOKUP($D18,'02_Type_Assumptions'!$A$4:$AC$18,27,FALSE()),"")="Industrial",$AD18,0) | AG18: =IF(IFERROR(VLOOKUP($D18,'02_Type_Assumptions'!$A$4:$AC$18,27,FALSE()),"")="Industrial",$AE18,0)
A19: 17 | C19: =FALSE() | G19: =IFERROR(VLOOKUP(D19,'02_Type_Assumptions'!$A$4:$Z$18,3,FALSE()),0) | I19: =IF(ISNUMBER(H19),H19,IF(LOWER(E19)="sqft",IFERROR(F19/43560/'00_Inputs_Dashboard'!$B$51,0),IF(LOWER(E19)="acres",IFERROR(F19,0),IFERROR(F19*G19,0)))) | J19: 1 | K19: 1 | L19: 0.8 | M19: =I19*L19 | N19: =IFERROR(IF(LOWER(E19)="rooms",VLOOKUP(D19,'02_Type_Assumptions'!$A$4:$Z$18,6,FALSE()),IF(LOWER(E19)="acres",VLOOKUP(D19,'02_Type_Assumptions'!$A$4:$Z$18,5,FALSE()),VLOOKUP(D19,'02_Type_Assumptions'!$A$4:$Z$18,4,FALSE()))),0) | P19: =IF(ISNUMBER(O19),O19,IF(LOWER(E19)="rooms",F19*N19*L19,IF(LOWER(E19)="acres",M19*N19,IF(LOWER(E19)="sqft",M19*VLOOKUP(D19,'02_Type_Assumptions'!$A$4:$Z$18,5,FALSE()),F19*N19*L19)))) | Q19: =IFERROR(IF(VLOOKUP(D19,'02_Type_Assumptions'!$A$4:$Z$18,23,FALSE())="per_acre",VLOOKUP(D19,'02_Type_Assumptions'!$A$4:$Z$18,8,FALSE()),0),0) | S19: =IF(ISNUMBER(R19),R19*L19,M19*Q19) | T19: =IF(LOWER(E19)="sqft",F19*L19,M19*IFERROR(VLOOKUP(D19,'02_Type_Assumptions'!$A$4:$Z$18,9,FALSE()),0)) | U19: =IF(OR(LOWER(E19)="lots",LOWER(E19)="units"),F19*L19,0) | V19: =U19*IFERROR(VLOOKUP(D19,'02_Type_Assumptions'!$A$4:$Z$18,21,FALSE()),0) | W19: =IFERROR(IF(OR(LOWER(E19)="lots",LOWER(E19)="units",LOWER(E19)="rooms"),F19*L19*VLOOKUP(D19,'02_Type_Assumptions'!$A$4:$Z$18,10,FALSE()),IF(LOWER(E19)="acres",M19*VLOOKUP(D19,'02_Type_Assumptions'!$A$4:$Z$18,11,FALSE()),IF(LOWER(E19)="sqft",T19/1000*VLOOKUP(D19,'02_Type_Assumptions'!$A$4:$Z$18,12,FALSE()),0))),0) | X19: =INPUTS!$D$50 | Z19: =IF(ISNUMBER(Y19),Y19,W19*X19) | AD19: =IFERROR($P19*VLOOKUP($D19,'02_Type_Assumptions'!$A$4:$AC$18,28,FALSE()),$P19) | AE19: =IFERROR($P19*VLOOKUP($D19,'02_Type_Assumptions'!$A$4:$AC$18,29,FALSE()),$P19) | AF19: =IF(IFERROR(VLOOKUP($D19,'02_Type_Assumptions'!$A$4:$AC$18,27,FALSE()),"")="Industrial",$AD19,0) | AG19: =IF(IFERROR(VLOOKUP($D19,'02_Type_Assumptions'!$A$4:$AC$18,27,FALSE()),"")="Industrial",$AE19,0)
A20: 18 | C20: =FALSE() | G20: =IFERROR(VLOOKUP(D20,'02_Type_Assumptions'!$A$4:$Z$18,3,FALSE()),0) | I20: =IF(ISNUMBER(H20),H20,IF(LOWER(E20)="sqft",IFERROR(F20/43560/'00_Inputs_Dashboard'!$B$51,0),IF(LOWER(E20)="acres",IFERROR(F20,0),IFERROR(F20*G20,0)))) | J20: 1 | K20: 1 | L20: 0.8 | M20: =I20*L20 | N20: =IFERROR(IF(LOWER(E20)="rooms",VLOOKUP(D20,'02_Type_Assumptions'!$A$4:$Z$18,6,FALSE()),IF(LOWER(E20)="acres",VLOOKUP(D20,'02_Type_Assumptions'!$A$4:$Z$18,5,FALSE()),VLOOKUP(D20,'02_Type_Assumptions'!$A$4:$Z$18,4,FALSE()))),0) | P20: =IF(ISNUMBER(O20),O20,IF(LOWER(E20)="rooms",F20*N20*L20,IF(LOWER(E20)="acres",M20*N20,IF(LOWER(E20)="sqft",M20*VLOOKUP(D20,'02_Type_Assumptions'!$A$4:$Z$18,5,FALSE()),F20*N20*L20)))) | Q20: =IFERROR(IF(VLOOKUP(D20,'02_Type_Assumptions'!$A$4:$Z$18,23,FALSE())="per_acre",VLOOKUP(D20,'02_Type_Assumptions'!$A$4:$Z$18,8,FALSE()),0),0) | S20: =IF(ISNUMBER(R20),R20*L20,M20*Q20) | T20: =IF(LOWER(E20)="sqft",F20*L20,M20*IFERROR(VLOOKUP(D20,'02_Type_Assumptions'!$A$4:$Z$18,9,FALSE()),0)) | U20: =IF(OR(LOWER(E20)="lots",LOWER(E20)="units"),F20*L20,0) | V20: =U20*IFERROR(VLOOKUP(D20,'02_Type_Assumptions'!$A$4:$Z$18,21,FALSE()),0) | W20: =IFERROR(IF(OR(LOWER(E20)="lots",LOWER(E20)="units",LOWER(E20)="rooms"),F20*L20*VLOOKUP(D20,'02_Type_Assumptions'!$A$4:$Z$18,10,FALSE()),IF(LOWER(E20)="acres",M20*VLOOKUP(D20,'02_Type_Assumptions'!$A$4:$Z$18,11,FALSE()),IF(LOWER(E20)="sqft",T20/1000*VLOOKUP(D20,'02_Type_Assumptions'!$A$4:$Z$18,12,FALSE()),0))),0) | X20: =INPUTS!$D$50 | Z20: =IF(ISNUMBER(Y20),Y20,W20*X20) | AD20: =IFERROR($P20*VLOOKUP($D20,'02_Type_Assumptions'!$A$4:$AC$18,28,FALSE()),$P20) | AE20: =IFERROR($P20*VLOOKUP($D20,'02_Type_Assumptions'!$A$4:$AC$18,29,FALSE()),$P20) | AF20: =IF(IFERROR(VLOOKUP($D20,'02_Type_Assumptions'!$A$4:$AC$18,27,FALSE()),"")="Industrial",$AD20,0) | AG20: =IF(IFERROR(VLOOKUP($D20,'02_Type_Assumptions'!$A$4:$AC$18,27,FALSE()),"")="Industrial",$AE20,0)
